Workbook
Name _C1: Crises!$P$5:$X$5
Name _C1Enabled: Crises!$P$7:$X$7
Name _C1Prepared: Crises!$P$8:$X$8
Name _C1Show: Crises!$P$6:$X$6
Name _C1ShowCrisisCard: Crises!$P$9:$X$9
Name _C1Year: Crises!$P$4:$X$4
Name _C2: Crises!$AD$5:$AL$5
Name _C2Enabled: Crises!$AD$7:$AL$7
Name _C2Prepared: Crises!$AD$8:$AL$8
Name _C2Show: Crises!$AD$6:$AL$6
Name _C2ShowCrisisCard: Crises!$AD$9:$AL$9
Name _C2Year: Crises!$AD$4:$AL$4
Name _C3: Crises!$AR$5:$AZ$5
Name _C3Enabled: Crises!$AR$7:$AZ$7
Name _C3Prepared: Crises!$AR$8:$AZ$8
Name _C3Show: Crises!$AR$6:$AZ$6
Name _C3ShowCrisisCard: Crises!$AR$9:$AZ$9
Name _C3Year: Crises!$AR$4:$AZ$4
Name _C4: Crises!$BF$5:$BN$5
Name _C4Enabled: Crises!$BF$7:$BN$7
Name _C4Prepared: Crises!$BF$8:$BN$8
Name _C4Show: Crises!$BF$6:$BN$6
Name _C4ShowCrisisCard: Crises!$BF$9:$BN$9
Name _C4Year: Crises!$BF$4:$BN$4
Name _C5: Crises!$BT$5:$CB$5
Name _C5Enabled: Crises!$BT$7:$CB$7
Name _C5Prepared: Crises!$BT$8:$CB$8
Name _C5Show: Crises!$BT$6:$CB$6
Name _C5ShowCrisisCard: Crises!$BT$9:$CB$9
Name _C5Year: Crises!$BT$4:$CB$4
Name _C6: Crises!$CH$5:$CP$5
Name _C6Enabled: Crises!$CH$7:$CP$7
Name _C6Prepared: Crises!$CH$8:$CP$8
Name _C6Show: Crises!$CH$6:$CP$6
Name _C6ShowCrisisCard: Crises!$CH$9:$CP$9
Name _C6Year: Crises!$CH$4:$CP$4
Name _C7: Crises!$CV$5:$DD$5
Name _C7Enabled: Crises!$CV$7:$DD$7
Name _C7Prepared: Crises!$CV$8:$DD$8
Name _C7Show: Crises!$CV$6:$DD$6
Name _C7ShowCrisisCard: Crises!$CV$9:$DD$9
Name _C7Year: Crises!$CV$4:$DD$4
Name _C8: Crises!$DJ$5:$DR$5
Name _C8Enabled: Crises!$DJ$7:$DR$7
Name _C8Prepared: Crises!$DJ$8:$DR$8
Name _C8Show: Crises!$DJ$6:$DR$6
Name _C8ShowCrisisCard: Crises!$DJ$9:$DR$9
Name _C8Year: Crises!$DJ$4:$DR$4
Name Accountability: Results!$B$69:$J$69
Name AIContributionToGDP: Results!$B$73:$J$73
Name AIContributionToGDPPercOfTargetAchieved: 'Result Targets'!$B$73:$J$73
Name AIContributionToGDPTarget: 'Result Targets'!$B$5:$J$5
Name AIFDIStock: Results!$B$74:$J$74
Name AIFDIStockPercOfTargetAchieved: 'Result Targets'!$B$74:$J$74
Name AIFDIStockTarget: 'Result Targets'!$B$6:$J$6
Name AIFeedbackEnabled: 'Project Variables'!$B$7
Name AILiteracy: Results!$B$102:$J$102
Name AILiteracyPercOfTargetAchieved: 'Result Targets'!$B$102:$J$102
Name AILiteracyTarget: 'Result Targets'!$B$31:$J$31
Name AutonomousSystemsSafteyIndex: Results!$B$94:$J$94

Sheet Project Variables
A1: settingsID | B1: 0
A2: ReadVault | B2: 0
A3: NumYears | B3: 5
A4: GameOver | B4: =IF(Step=NumYears,1,0) -> 0
A6: Misc
A7: AIFeedbackEnabled | B7: 0
A8: IsMultiplayer | B8: 0
A9: SliderReasoningEnabled | B9: 0
A10: TeamName
A12: Enabled Ministries
A13: EcEnabled | B13: 1
A14: EnvEnabled | B14: 1
A15: DefEnabled | B15: 1
A16: EduEnabled | B16: 1
A17: FacEcEnabled | B17: 1
A18: FacEnvEnabled | B18: 1
A19: FacDefEnabled | B19: 1
A20: FacEduEnabled | B20: 1
A21: FacAllowMinistryChoice | B21: 1
A22: MinistriesConfirmed | B22: 0
A24: Role Selection
A25: RoleUser0 | B25: 0
A26: RoleUser1 | B26: 0
A27: RoleUser2 | B27: 0
A28: RoleUser3 | B28: 0
A29: RoleUser4 | B29: 0
A30: RolesConfirmed | B30: 0
D31: Position | E31: 1 | F31: 2 | G31: 3 | H31: 4 | I31: 5 | J31: 6
A32: Values | D32: Weight | E32: 0.25 | F32: 0.25 | G32: 0.15 | H32: 0.15 | I32: 0.1 | J32: 0.1
A33: Value1Position | B33: 1 | D33: Growth & Welbeing | E33: =_xlfn.XLOOKUP(Value1Position,$E$31:$J$31,$E$32:$J$32) -> 0.25
A34: Value2Position | B34: 2 | D34: Human Rights | E34: =_xlfn.XLOOKUP(Value2Position,$E$31:$J$31,$E$32:$J$32) -> 0.25
A35: Value3Position | B35: 3 | D35: Privacy & Data Protection | E35: =_xlfn.XLOOKUP(Value3Position,$E$31:$J$31,$E$32:$J$32) -> 0.15
A36: Value4Position | B36: 4 | D36: Transparency | E36: =_xlfn.XLOOKUP(Value4Position,$E$31:$J$31,$E$32:$J$32) -> 0.15
A37: Value5Position | B37: 5 | D37: Security & Safety | E37: =_xlfn.XLOOKUP(Value5Position,$E$31:$J$31,$E$32:$J$32) -> 0.1
A38: Value6Position | B38: 6 | D38: Accountability | E38: =_xlfn.XLOOKUP(Value6Position,$E$31:$J$31,$E$32:$J$32) -> 0.1
A39: ValuesConfirmed | B39: 0
A41: RoleUser0Value1Position | B41: 1 | D41: Rows Reference
A42: RoleUser0Value2Position | B42: 2 | D42: Governance
A43: RoleUser0Value3Position | B43: 3 | D43: GrowthWellBeing
A44: RoleUser0Value4Position | B44: 4 | D44: HumanRights
A45: RoleUser0Value5Position | B45: 5 | D45: PrivacyDataProtection
A46: RoleUser0Value6Position | B46: 6 | D46: Transparency
A47: RoleUser0ValuesConfirmed | B47: 0 | D47: SecuritySafety
D48: Accountability
A49: RoleUser1Value1Position | B49: 1
A50: RoleUser1Value2Position | B50: 2
A51: RoleUser1Value3Position | B51: 3 | D51: Economy
A52: RoleUser1Value4Position | B52: 4 | D52: AIContributionToGDP
A53: RoleUser1Value5Position | B53: 5 | D53: AIFDIStock
A54: RoleUser1Value6Position | B54: 6 | D54: JobsCreated
A55: RoleUser1ValuesConfirmed | B55: 0 | D55: JobsDisplaced
A57: RoleUser2Value1Position | B57: 1
A58: RoleUser2Value2Position | B58: 2
A59: RoleUser2Value3Position | B59: 3
A60: RoleUser2Value4Position | B60: 4 | D60: Environment
A61: RoleUser2Value5Position | B61: 5
A62: RoleUser2Value6Position | B62: 6
A63: RoleUser2ValuesConfirmed | B63: 0 | D63: RenewableEnergyFactor
D64: WaterCircularityIndex
A65: RoleUser3Value1Position | B65: 1 | D65: EwasteCircularityIndex
A66: RoleUser3Value2Position | B66: 2
A67: RoleUser3Value3Position | B67: 3 | D67: EcosystemIntegrityIndex
A68: RoleUser3Value4Position | B68: 4
A69: RoleUser3Value5Position | B69: 5
A70: RoleUser3Value6Position | B70: 6
A71: RoleUser3ValuesConfirmed | B71: 0 | D71: Defense
D72: CybersecurityIndex
A73: RoleUser4Value1Position | B73: 1 | D73: AutonomousSystemsSafteyIndex
A74: RoleUser4Value2Position | B74: 2 | D74: DefenseExports
A75: RoleUser4Value3Position | B75: 3 | D75: DefenseImports
A76: RoleUser4Value4Position | B76: 4
A77: RoleUser4Value5Position | B77: 5
A78: RoleUser4Value6Position | B78: 6
A79: RoleUser4ValuesConfirmed | B79: 0
D80: Education & Innovation
D81: AILiteracy
D82: InnovationIndex
D83: InstitutionalAdoptionRate

Sheet Target Settings
A1: FacilSetsTargets | B1: 0
A3: Economy | E3: Defaults
A4: F_AIContributionToGDPTarget | B4: =E4 -> 12 | E4: 12
A5: F_AIFDIStockTarget | B5: =E5 -> 2.5 | E5: 2.5
A6: F_NetJobsFromAITarget | B6: =E6 -> 500000 | E6: 500000
A9: Environment
A10: F_RenewableEnergyFactorTarget | B10: =E10 -> 40 | E10: 40
A11: F_CircularityIndexTarget | B11: =E11 -> 60 | E11: 60
A12: F_EcosystemIntegrityIndexTarget | B12: =E12 -> 60 | E12: 60
A15: Defense
A16: F_CybersecurityIndexTarget | B16: =E16 -> 65 | E16: 65
A17: F_AutonomousSystemsSafteyIndexTarget | B17: =E17 -> 75 | E17: 75
A18: F_MilitaryTechnologyTradeBalanceTarget | B18: =E18 -> 2000000000 | E18: 2000000000
A21: Education & Innovation
A22: F_AILiteracyTarget | B22: =E22 -> 60 | E22: 60
A23: F_InnovationIndexTarget | B23: =E23 -> 60 | E23: 60
A24: F_InstitutionalAdoptionRateTarget | B24: =E24 -> 65 | E24: 65

Sheet Results
A1: Public Policy Simulation: AI Governance
A3: Step | B3: 0
A5: Time | B5: 0 | C5: 1 | D5: 2 | E5: 3 | F5: 4 | G5: 5 | H5: 6 | I5: 7 | J5: 8
A6: Year | B6: 1 | C6: 2 | D6: 3 | E6: 4 | F6: 5 | G6: 6 | H6: 7 | I6: 8 | J6: 9
A63: Governance
A64: GrowthWellBeing | B64: 50 | C64: =$B64+'Economy Ministry'!C64+'Environment Ministry'!C64+'Defence Ministry'!C64+'Education Ministry'!C64+Crises!C64+'Breaking News'!C64+Opportunities!C64 -> 50 | D64: =$B64+'Economy Ministry'!D64+'Environment Ministry'!D64+'Defence Ministry'!D64+'Education Ministry'!D64+Crises!D64+'Breaking News'!D64+Opportunities!D64 -> 48.4 | E64: =$B64+'Economy Ministry'!E64+'Environment Ministry'!E64+'Defence Ministry'!E64+'Education Ministry'!E64+Crises!E64+'Breaking News'!E64+Opportunities!E64 -> 48.4 | F64: =$B64+'Economy Ministry'!F64+'Environment Ministry'!F64+'Defence Ministry'!F64+'Education Ministry'!F64+Crises!F64+'Breaking News'!F64+Opportunities!F64 -> 48.4 | G64: =$B64+'Economy Ministry'!G64+'Environment Ministry'!G64+'Defence Ministry'!G64+'Education Ministry'!G64+Crises!G64+'Breaking News'!G64+Opportunities!G64 -> 48.4 | H64: =$B64+'Economy Ministry'!H64+'Environment Ministry'!H64+'Defence Ministry'!H64+'Education Ministry'!H64+Crises!H64+'Breaking News'!H64+Opportunities!H64 -> 48.4 | I64: =$B64+'Economy Ministry'!I64+'Environment Ministry'!I64+'Defence Ministry'!I64+'Education Ministry'!I64+Crises!I64+'Breaking News'!I64+Opportunities!I64 -> 48.4 | J64: =$B64+'Economy Ministry'!J64+'Environment Ministry'!J64+'Defence Ministry'!J64+'Education Ministry'!J64+Crises!J64+'Breaking News'!J64+Opportunities!J64 -> 48.4
A65: HumanRights | B65: 55 | C65: =$B65+'Economy Ministry'!C65+'Environment Ministry'!C65+'Defence Ministry'!C65+'Education Ministry'!C65+Crises!C65+'Breaking News'!C65+Opportunities!C65 -> 55 | D65: =$B65+'Economy Ministry'!D65+'Environment Ministry'!D65+'Defence Ministry'!D65+'Education Ministry'!D65+Crises!D65+'Breaking News'!D65+Opportunities!D65 -> 55 | E65: =$B65+'Economy Ministry'!E65+'Environment Ministry'!E65+'Defence Ministry'!E65+'Education Ministry'!E65+Crises!E65+'Breaking News'!E65+Opportunities!E65 -> 52.6 | F65: =$B65+'Economy Ministry'!F65+'Environment Ministry'!F65+'Defence Ministry'!F65+'Education Ministry'!F65+Crises!F65+'Breaking News'!F65+Opportunities!F65 -> 52.6 | G65: =$B65+'Economy Ministry'!G65+'Environment Ministry'!G65+'Defence Ministry'!G65+'Education Ministry'!G65+Crises!G65+'Breaking News'!G65+Opportunities!G65 -> 52.6 | H65: =$B65+'Economy Ministry'!H65+'Environment Ministry'!H65+'Defence Ministry'!H65+'Education Ministry'!H65+Crises!H65+'Breaking News'!H65+Opportunities!H65 -> 52.6 | I65: =$B65+'Economy Ministry'!I65+'Environment Ministry'!I65+'Defence Ministry'!I65+'Education Ministry'!I65+Crises!I65+'Breaking News'!I65+Opportunities!I65 -> 52.6 | J65: =$B65+'Economy Ministry'!J65+'Environment Ministry'!J65+'Defence Ministry'!J65+'Education Ministry'!J65+Crises!J65+'Breaking News'!J65+Opportunities!J65 -> 52.6
A66: PrivacyDataProtection | B66: 40 | C66: =$B66+'Economy Ministry'!C66+'Environment Ministry'!C66+'Defence Ministry'!C66+'Education Ministry'!C66+Crises!C66+'Breaking News'!C66+Opportunities!C66 -> 40 | D66: =$B66+'Economy Ministry'!D66+'Environment Ministry'!D66+'Defence Ministry'!D66+'Education Ministry'!D66+Crises!D66+'Breaking News'!D66+Opportunities!D66 -> 40 | E66: =$B66+'Economy Ministry'!E66+'Environment Ministry'!E66+'Defence Ministry'!E66+'Education Ministry'!E66+Crises!E66+'Breaking News'!E66+Opportunities!E66 -> 36.8 | F66: =$B66+'Economy Ministry'!F66+'Environment Ministry'!F66+'Defence Ministry'!F66+'Education Ministry'!F66+Crises!F66+'Breaking News'!F66+Opportunities!F66 -> 33.6 | G66: =$B66+'Economy Ministry'!G66+'Environment Ministry'!G66+'Defence Ministry'!G66+'Education Ministry'!G66+Crises!G66+'Breaking News'!G66+Opportunities!G66 -> 30.4 | H66: =$B66+'Economy Ministry'!H66+'Environment Ministry'!H66+'Defence Ministry'!H66+'Education Ministry'!H66+Crises!H66+'Breaking News'!H66+Opportunities!H66 -> 30.4 | I66: =$B66+'Economy Ministry'!I66+'Environment Ministry'!I66+'Defence Ministry'!I66+'Education Ministry'!I66+Crises!I66+'Breaking News'!I66+Opportunities!I66 -> 30.4 | J66: =$B66+'Economy Ministry'!J66+'Environment Ministry'!J66+'Defence Ministry'!J66+'Education Ministry'!J66+Crises!J66+'Breaking News'!J66+Opportunities!J66 -> 30.4
A67: Transparency | B67: 38 | C67: =$B67+'Economy Ministry'!C67+'Environment Ministry'!C67+'Defence Ministry'!C67+'Education Ministry'!C67+Crises!C67+'Breaking News'!C67+Opportunities!C67 -> 38 | D67: =$B67+'Economy Ministry'!D67+'Environment Ministry'!D67+'Defence Ministry'!D67+'Education Ministry'!D67+Crises!D67+'Breaking News'!D67+Opportunities!D67 -> 38 | E67: =$B67+'Economy Ministry'!E67+'Environment Ministry'!E67+'Defence Ministry'!E67+'Education Ministry'!E67+Crises!E67+'Breaking News'!E67+Opportunities!E67 -> 38 | F67: =$B67+'Economy Ministry'!F67+'Environment Ministry'!F67+'Defence Ministry'!F67+'Education Ministry'!F67+Crises!F67+'Breaking News'!F67+Opportunities!F67 -> 38 | G67: =$B67+'Economy Ministry'!G67+'Environment Ministry'!G67+'Defence Ministry'!G67+'Education Ministry'!G67+Crises!G67+'Breaking News'!G67+Opportunities!G67 -> 34.8 | H67: =$B67+'Economy Ministry'!H67+'Environment Ministry'!H67+'Defence Ministry'!H67+'Education Ministry'!H67+Crises!H67+'Breaking News'!H67+Opportunities!H67 -> 34.8 | I67: =$B67+'Economy Ministry'!I67+'Environment Ministry'!I67+'Defence Ministry'!I67+'Education Ministry'!I67+Crises!I67+'Breaking News'!I67+Opportunities!I67 -> 34.8 | J67: =$B67+'Economy Ministry'!J67+'Environment Ministry'!J67+'Defence Ministry'!J67+'Education Ministry'!J67+Crises!J67+'Breaking News'!J67+Opportunities!J67 -> 34.8
A68: SecuritySafety | B68: 45 | C68: =$B68+'Economy Ministry'!C68+'Environment Ministry'!C68+'Defence Ministry'!C68+'Education Ministry'!C68+Crises!C68+'Breaking News'!C68+Opportunities!C68 -> 45 | D68: =$B68+'Economy Ministry'!D68+'Environment Ministry'!D68+'Defence Ministry'!D68+'Education Ministry'!D68+Crises!D68+'Breaking News'!D68+Opportunities!D68 -> 43.4 | E68: =$B68+'Economy Ministry'!E68+'Environment Ministry'!E68+'Defence Ministry'!E68+'Education Ministry'!E68+Crises!E68+'Breaking News'!E68+Opportunities!E68 -> 41.8 | F68: =$B68+'Economy Ministry'!F68+'Environment Ministry'!F68+'Defence Ministry'!F68+'Education Ministry'!F68+Crises!F68+'Breaking News'!F68+Opportunities!F68 -> 38.6 | G68: =$B68+'Economy Ministry'!G68+'Environment Ministry'!G68+'Defence Ministry'!G68+'Education Ministry'!G68+Crises!G68+'Breaking News'!G68+Opportunities!G68 -> 38.6 | H68: =$B68+'Economy Ministry'!H68+'Environment Ministry'!H68+'Defence Ministry'!H68+'Education Ministry'!H68+Crises!H68+'Breaking News'!H68+Opportunities!H68 -> 38.6 | I68: =$B68+'Economy Ministry'!I68+'Environment Ministry'!I68+'Defence Ministry'!I68+'Education Ministry'!I68+Crises!I68+'Breaking News'!I68+Opportunities!I68 -> 38.6 | J68: =$B68+'Economy Ministry'!J68+'Environment Ministry'!J68+'Defence Ministry'!J68+'Education Ministry'!J68+Crises!J68+'Breaking News'!J68+Opportunities!J68 -> 38.6
A69: Accountability | B69: 38 | C69: =$B69+'Economy Ministry'!C69+'Environment Ministry'!C69+'Defence Ministry'!C69+'Education Ministry'!C69+Crises!C69+'Breaking News'!C69+Opportunities!C69 -> 38 | D69: =$B69+'Economy Ministry'!D69+'Environment Ministry'!D69+'Defence Ministry'!D69+'Education Ministry'!D69+Crises!D69+'Breaking News'!D69+Opportunities!D69 -> 38 | E69: =$B69+'Economy Ministry'!E69+'Environment Ministry'!E69+'Defence Ministry'!E69+'Education Ministry'!E69+Crises!E69+'Breaking News'!E69+Opportunities!E69 -> 38 | F69: =$B69+'Economy Ministry'!F69+'Environment Ministry'!F69+'Defence Ministry'!F69+'Education Ministry'!F69+Crises!F69+'Breaking News'!F69+Opportunities!F69 -> 38 | G69: =$B69+'Economy Ministry'!G69+'Environment Ministry'!G69+'Defence Ministry'!G69+'Education Ministry'!G69+Crises!G69+'Breaking News'!G69+Opportunities!G69 -> 34.8 | H69: =$B69+'Economy Ministry'!H69+'Environment Ministry'!H69+'Defence Ministry'!H69+'Education Ministry'!H69+Crises!H69+'Breaking News'!H69+Opportunities!H69 -> 34.8 | I69: =$B69+'Economy Ministry'!I69+'Environment Ministry'!I69+'Defence Ministry'!I69+'Education Ministry'!I69+Crises!I69+'Breaking News'!I69+Opportunities!I69 -> 34.8 | J69: =$B69+'Economy Ministry'!J69+'Environment Ministry'!J69+'Defence Ministry'!J69+'Education Ministry'!J69+Crises!J69+'Breaking News'!J69+Opportunities!J69 -> 34.8
A72: Economy
A73: AIContributionToGDP | B73: 3 | C73: =$B73+'Economy Ministry'!C73+'Environment Ministry'!C73+'Defence Ministry'!C73+'Education Ministry'!C73+Crises!C73+'Breaking News'!C73+Opportunities!C73 -> 2.68 | D73: =$B73+'Economy Ministry'!D73+'Environment Ministry'!D73+'Defence Ministry'!D73+'Education Ministry'!D73+Crises!D73+'Breaking News'!D73+Opportunities!D73 -> 2.68 | E73: =$B73+'Economy Ministry'!E73+'Environment Ministry'!E73+'Defence Ministry'!E73+'Education Ministry'!E73+Crises!E73+'Breaking News'!E73+Opportunities!E73 -> 2.68 | F73: =$B73+'Economy Ministry'!F73+'Environment Ministry'!F73+'Defence Ministry'!F73+'Education Ministry'!F73+Crises!F73+'Breaking News'!F73+Opportunities!F73 -> 2.68 | G73: =$B73+'Economy Ministry'!G73+'Environment Ministry'!G73+'Defence Ministry'!G73+'Education Ministry'!G73+Crises!G73+'Breaking News'!G73+Opportunities!G73 -> 2.68 | H73: =$B73+'Economy Ministry'!H73+'Environment Ministry'!H73+'Defence Ministry'!H73+'Education Ministry'!H73+Crises!H73+'Breaking News'!H73+Opportunities!H73 -> 2.68 | I73: =$B73+'Economy Ministry'!I73+'Environment Ministry'!I73+'Defence Ministry'!I73+'Education Ministry'!I73+Crises!I73+'Breaking News'!I73+Opportunities!I73 -> 2.68 | J73: =$B73+'Economy Ministry'!J73+'Environment Ministry'!J73+'Defence Ministry'!J73+'Education Ministry'!J73+Crises!J73+'Breaking News'!J73+Opportunities!J73 -> 2.68
A74: AIFDIStock | B74: 50000000000 | C74: =$B74+'Economy Ministry'!C74+'Environment Ministry'!C74+'Defence Ministry'!C74+'Education Ministry'!C74+Crises!C74+'Breaking News'!C74+Opportunities!C74 -> 48400000000 | D74: =$B74+'Economy Ministry'!D74+'Environment Ministry'!D74+'Defence Ministry'!D74+'Education Ministry'!D74+Crises!D74+'Breaking News'!D74+Opportunities!D74 -> 48400000000 | E74: =$B74+'Economy Ministry'!E74+'Environment Ministry'!E74+'Defence Ministry'!E74+'Education Ministry'!E74+Crises!E74+'Breaking News'!E74+Opportunities!E74 -> 48400000000 | F74: =$B74+'Economy Ministry'!F74+'Environment Ministry'!F74+'Defence Ministry'!F74+'Education Ministry'!F74+Crises!F74+'Breaking News'!F74+Opportunities!F74 -> 48400000000 | G74: =$B74+'Economy Ministry'!G74+'Environment Ministry'!G74+'Defence Ministry'!G74+'Education Ministry'!G74+Crises!G74+'Breaking News'!G74+Opportunities!G74 -> 48400000000 | H74: =$B74+'Economy Ministry'!H74+'Environment Ministry'!H74+'Defence Ministry'!H74+'Education Ministry'!H74+Crises!H74+'Breaking News'!H74+Opportunities!H74 -> 48400000000 | I74: =$B74+'Economy Ministry'!I74+'Environment Ministry'!I74+'Defence Ministry'!I74+'Education Ministry'!I74+Crises!I74+'Breaking News'!I74+Opportunities!I74 -> 48400000000 | J74: =$B74+'Economy Ministry'!J74+'Environment Ministry'!J74+'Defence Ministry'!J74+'Education Ministry'!J74+Crises!J74+'Breaking News'!J74+Opportunities!J74 -> 48400000000
A75: JobsCreated | B75: 0 | C75: =$B75+'Economy Ministry'!C75+'Environment Ministry'!C75+'Defence Ministry'!C75+'Education Ministry'!C75+Crises!C75+'Breaking News'!C75+Opportunities!C75 -> 0 | D75: =$B75+'Economy Ministry'!D75+'Environment Ministry'!D75+'Defence Ministry'!D75+'Education Ministry'!D75+Crises!D75+'Breaking News'!D75+Opportunities!D75 -> 0 | E75: =$B75+'Economy Ministry'!E75+'Environment Ministry'!E75+'Defence Ministry'!E75+'Education Ministry'!E75+Crises!E75+'Breaking News'!E75+Opportunities!E75 -> 0 | F75: =$B75+'Economy Ministry'!F75+'Environment Ministry'!F75+'Defence Ministry'!F75+'Education Ministry'!F75+Crises!F75+'Breaking News'!F75+Opportunities!F75 -> 0 | G75: =$B75+'Economy Ministry'!G75+'Environment Ministry'!G75+'Defence Ministry'!G75+'Education Ministry'!G75+Crises!G75+'Breaking News'!G75+Opportunities!G75 -> 0 | H75: =$B75+'Economy Ministry'!H75+'Environment Ministry'!H75+'Defence Ministry'!H75+'Education Ministry'!H75+Crises!H75+'Breaking News'!H75+Opportunities!H75 -> 0 | I75: =$B75+'Economy Ministry'!I75+'Environment Ministry'!I75+'Defence Ministry'!I75+'Education Ministry'!I75+Crises!I75+'Breaking News'!I75+Opportunities!I75 -> 0 | J75: =$B75+'Economy Ministry'!J75+'Environment Ministry'!J75+'Defence Ministry'!J75+'Education Ministry'!J75+Crises!J75+'Breaking News'!J75+Opportunities!J75 -> 0
A76: JobsDisplaced | B76: 0 | C76: =$B76+'Economy Ministry'!C76+'Environment Ministry'!C76+'Defence Ministry'!C76+'Education Ministry'!C76+Crises!C76+'Breaking News'!C76+Opportunities!C76 -> 0 | D76: =$B76+'Economy Ministry'!D76+'Environment Ministry'!D76+'Defence Ministry'!D76+'Education Ministry'!D76+Crises!D76+'Breaking News'!D76+Opportunities!D76 -> 0 | E76: =$B76+'Economy Ministry'!E76+'Environment Ministry'!E76+'Defence Ministry'!E76+'Education Ministry'!E76+Crises!E76+'Breaking News'!E76+Opportunities!E76 -> 0 | F76: =$B76+'Economy Ministry'!F76+'Environment Ministry'!F76+'Defence Ministry'!F76+'Education Ministry'!F76+Crises!F76+'Breaking News'!F76+Opportunities!F76 -> 0 | G76: =$B76+'Economy Ministry'!G76+'Environment Ministry'!G76+'Defence Ministry'!G76+'Education Ministry'!G76+Crises!G76+'Breaking News'!G76+Opportunities!G76 -> 0 | H76: =$B76+'Economy Ministry'!H76+'Environment Ministry'!H76+'Defence Ministry'!H76+'Education Ministry'!H76+Crises!H76+'Breaking News'!H76+Opportunities!H76 -> 0 | I76: =$B76+'Economy Ministry'!I76+'Environment Ministry'!I76+'Defence Ministry'!I76+'Education Ministry'!I76+Crises!I76+'Breaking News'!I76+Opportunities!I76 -> 0 | J76: =$B76+'Economy Ministry'!J76+'Environment Ministry'!J76+'Defence Ministry'!J76+'Education Ministry'!J76+Crises!J76+'Breaking News'!J76+Opportunities!J76 -> 0
A77: NetJobsFromAI | B77: =B75-B76 -> 0 | C77: =C75-C76 -> 0 | D77: =D75-D76 -> 0 | E77: =E75-E76 -> 0 | F77: =F75-F76 -> 0 | G77: =G75-G76 -> 0 | H77: =H75-H76 -> 0 | I77: =I75-I76 -> 0 | J77: =J75-J76 -> 0
A78: EconomyScore | B78: ='Result Targets'!B78 -> 25 | C78: ='Result Targets'!C78 -> 23.577778 | D78: ='Result Targets'!D78 -> 23.577778 | E78: ='Result Targets'!E78 -> 23.577778 | F78: ='Result Targets'!F78 -> 23.577778 | G78: ='Result Targets'!G78 -> 23.577778 | H78: ='Result Targets'!H78 -> 23.577778 | I78: ='Result Targets'!I78 -> 23.577778 | J78: ='Result Targets'!J78 -> 23.577778
A81: Environment
A82: EnergyConsumedFromDataCenters | B82: X | C82: X | D82: X | E82: X | F82: X | G82: X | H82: X | I82: X | J82: X
A83: RenewableEnergyFactor | B83: X | C83: X | D83: X | E83: X | F83: X | G83: X | H83: X | I83: X | J83: X
A84: RenewableEnergyFactor | B84: 10 | C84: =$B84+'Economy Ministry'!C84+'Environment Ministry'!C84+'Defence Ministry'!C84+'Education Ministry'!C84+Crises!C84+'Breaking News'!C84+Opportunities!C84 -> 10 | D84: =$B84+'Economy Ministry'!D84+'Environment Ministry'!D84+'Defence Ministry'!D84+'Education Ministry'!D84+Crises!D84+'Breaking News'!D84+Opportunities!D84 -> 10 | E84: =$B84+'Economy Ministry'!E84+'Environment Ministry'!E84+'Defence Ministry'!E84+'Education Ministry'!E84+Crises!E84+'Breaking News'!E84+Opportunities!E84 -> 10 | F84: =$B84+'Economy Ministry'!F84+'Environment Ministry'!F84+'Defence Ministry'!F84+'Education Ministry'!F84+Crises!F84+'Breaking News'!F84+Opportunities!F84 -> 10 | G84: =$B84+'Economy Ministry'!G84+'Environment Ministry'!G84+'Defence Ministry'!G84+'Education Ministry'!G84+Crises!G84+'Breaking News'!G84+Opportunities!G84 -> 10 | H84: =$B84+'Economy Ministry'!H84+'Environment Ministry'!H84+'Defence Ministry'!H84+'Education Ministry'!H84+Crises!H84+'Breaking News'!H84+Opportunities!H84 -> 10 | I84: =$B84+'Economy Ministry'!I84+'Environment Ministry'!I84+'Defence Ministry'!I84+'Education Ministry'!I84+Crises!I84+'Breaking News'!I84+Opportunities!I84 -> 10 | J84: =$B84+'Economy Ministry'!J84+'Environment Ministry'!J84+'Defence Ministry'!J84+'Education Ministry'!J84+Crises!J84+'Breaking News'!J84+Opportunities!J84 -> 10
A85: WaterCircularityIndex | B85: 25 | C85: =$B85+'Economy Ministry'!C85+'Environment Ministry'!C85+'Defence Ministry'!C85+'Education Ministry'!C85+Crises!C85+'Breaking News'!C85+Opportunities!C85 -> 25 | D85: =$B85+'Economy Ministry'!D85+'Environment Ministry'!D85+'Defence Ministry'!D85+'Education Ministry'!D85+Crises!D85+'Breaking News'!D85+Opportunities!D85 -> 23.4 | E85: =$B85+'Economy Ministry'!E85+'Environment Ministry'!E85+'Defence Ministry'!E85+'Education Ministry'!E85+Crises!E85+'Breaking News'!E85+Opportunities!E85 -> 23.4 | F85: =$B85+'Economy Ministry'!F85+'Environment Ministry'!F85+'Defence Ministry'!F85+'Education Ministry'!F85+Crises!F85+'Breaking News'!F85+Opportunities!F85 -> 23.4 | G85: =$B85+'Economy Ministry'!G85+'Environment Ministry'!G85+'Defence Ministry'!G85+'Education Ministry'!G85+Crises!G85+'Breaking News'!G85+Opportunities!G85 -> 23.4 | H85: =$B85+'Economy Ministry'!H85+'Environment Ministry'!H85+'Defence Ministry'!H85+'Education Ministry'!H85+Crises!H85+'Breaking News'!H85+Opportunities!H85 -> 23.4 | I85: =$B85+'Economy Ministry'!I85+'Environment Ministry'!I85+'Defence Ministry'!I85+'Education Ministry'!I85+Crises!I85+'Breaking News'!I85+Opportunities!I85 -> 23.4 | J85: =$B85+'Economy Ministry'!J85+'Environment Ministry'!J85+'Defence Ministry'!J85+'Education Ministry'!J85+Crises!J85+'Breaking News'!J85+Opportunities!J85 -> 23.4
A86: EwasteCircularityIndex | B86: 20 | C86: =$B86+'Economy Ministry'!C86+'Environment Ministry'!C86+'Defence Ministry'!C86+'Education Ministry'!C86+Crises!C86+'Breaking News'!C86+Opportunities!C86 -> 20 | D86: =$B86+'Economy Ministry'!D86+'Environment Ministry'!D86+'Defence Ministry'!D86+'Education Ministry'!D86+Crises!D86+'Breaking News'!D86+Opportunities!D86 -> 20 | E86: =$B86+'Economy Ministry'!E86+'Environment Ministry'!E86+'Defence Ministry'!E86+'Education Ministry'!E86+Crises!E86+'Breaking News'!E86+Opportunities!E86 -> 20 | F86: =$B86+'Economy Ministry'!F86+'Environment Ministry'!F86+'Defence Ministry'!F86+'Education Ministry'!F86+Crises!F86+'Breaking News'!F86+Opportunities!F86 -> 20 | G86: =$B86+'Economy Ministry'!G86+'Environment Ministry'!G86+'Defence Ministry'!G86+'Education Ministry'!G86+Crises!G86+'Breaking News'!G86+Opportunities!G86 -> 20 | H86: =$B86+'Economy Ministry'!H86+'Environment Ministry'!H86+'Defence Ministry'!H86+'Education Ministry'!H86+Crises!H86+'Breaking News'!H86+Opportunities!H86 -> 20 | I86: =$B86+'Economy Ministry'!I86+'Environment Ministry'!I86+'Defence Ministry'!I86+'Education Ministry'!I86+Crises!I86+'Breaking News'!I86+Opportunities!I86 -> 20 | J86: =$B86+'Economy Ministry'!J86+'Environment Ministry'!J86+'Defence Ministry'!J86+'Education Ministry'!J86+Crises!J86+'Breaking News'!J86+Opportunities!J86 -> 20
A87: CircularityIndex | B87: =(B85+B86)/2 -> 22.5 | C87: =(C85+C86)/2 -> 22.5 | D87: =(D85+D86)/2 -> 21.7 | E87: =(E85+E86)/2 -> 21.7 | F87: =(F85+F86)/2 -> 21.7 | G87: =(G85+G86)/2 -> 21.7 | H87: =(H85+H86)/2 -> 21.7 | I87: =(I85+I86)/2 -> 21.7 | J87: =(J85+J86)/2 -> 21.7
A88: EcosystemIntegrityIndex | B88: 25 | C88: =$B88+'Economy Ministry'!C88+'Environment Ministry'!C88+'Defence Ministry'!C88+'Education Ministry'!C88+Crises!C88+'Breaking News'!C88+Opportunities!C88 -> 25 | D88: =$B88+'Economy Ministry'!D88+'Environment Ministry'!D88+'Defence Ministry'!D88+'Education Ministry'!D88+Crises!D88+'Breaking News'!D88+Opportunities!D88 -> 25 | E88: =$B88+'Economy Ministry'!E88+'Environment Ministry'!E88+'Defence Ministry'!E88+'Education Ministry'!E88+Crises!E88+'Breaking News'!E88+Opportunities!E88 -> 25 | F88: =$B88+'Economy Ministry'!F88+'Environment Ministry'!F88+'Defence Ministry'!F88+'Education Ministry'!F88+Crises!F88+'Breaking News'!F88+Opportunities!F88 -> 25 | G88: =$B88+'Economy Ministry'!G88+'Environment Ministry'!G88+'Defence Ministry'!G88+'Education Ministry'!G88+Crises!G88+'Breaking News'!G88+Opportunities!G88 -> 25 | H88: =$B88+'Economy Ministry'!H88+'Environment Ministry'!H88+'Defence Ministry'!H88+'Education Ministry'!H88+Crises!H88+'Breaking News'!H88+Opportunities!H88 -> 25 | I88: =$B88+'Economy Ministry'!I88+'Environment Ministry'!I88+'Defence Ministry'!I88+'Education Ministry'!I88+Crises!I88+'Breaking News'!I88+Opportunities!I88 -> 25 | J88: =$B88+'Economy Ministry'!J88+'Environment Ministry'!J88+'Defence Ministry'!J88+'Education Ministry'!J88+Crises!J88+'Breaking News'!J88+Opportunities!J88 -> 25
A89: EnvironmentScore | B89: ='Result Targets'!B90 -> 34.722222 | C89: ='Result Targets'!C90 -> 34.722222 | D89: ='Result Targets'!D90 -> 34.277778 | E89: ='Result Targets'!E90 -> 34.277778 | F89: ='Result Targets'!F90 -> 34.277778 | G89: ='Result Targets'!G90 -> 34.277778 | H89: ='Result Targets'!H90 -> 34.277778 | I89: ='Result Targets'!I90 -> 34.277778 | J89: ='Result Targets'!J90 -> 34.277778
A92: Defense
A93: CybersecurityIndex | B93: 35 | C93: =$B93+'Economy Ministry'!C93+'Environment Ministry'!C93+'Defence Ministry'!C93+'Education Ministry'!C93+Crises!C93+'Breaking News'!C93+Opportunities!C93 -> 35 | D93: =$B93+'Economy Ministry'!D93+'Environment Ministry'!D93+'Defence Ministry'!D93+'Education Ministry'!D93+Crises!D93+'Breaking News'!D93+Opportunities!D93 -> 35 | E93: =$B93+'Economy Ministry'!E93+'Environment Ministry'!E93+'Defence Ministry'!E93+'Education Ministry'!E93+Crises!E93+'Breaking News'!E93+Opportunities!E93 -> 35 | F93: =$B93+'Economy Ministry'!F93+'Environment Ministry'!F93+'Defence Ministry'!F93+'Education Ministry'!F93+Crises!F93+'Breaking News'!F93+Opportunities!F93 -> 33 | G93: =$B93+'Economy Ministry'!G93+'Environment Ministry'!G93+'Defence Ministry'!G93+'Education Ministry'!G93+Crises!G93+'Breaking News'!G93+Opportunities!G93 -> 33 | H93: =$B93+'Economy Ministry'!H93+'Environment Ministry'!H93+'Defence Ministry'!H93+'Education Ministry'!H93+Crises!H93+'Breaking News'!H93+Opportunities!H93 -> 33 | I93: =$B93+'Economy Ministry'!I93+'Environment Ministry'!I93+'Defence Ministry'!I93+'Education Ministry'!I93+Crises!I93+'Breaking News'!I93+Opportunities!I93 -> 33 | J93: =$B93+'Economy Ministry'!J93+'Environment Ministry'!J93+'Defence Ministry'!J93+'Education Ministry'!J93+Crises!J93+'Breaking News'!J93+Opportunities!J93 -> 33
A94: AutonomousSystemsSafteyIndex | B94: 40 | C94: =$B94+'Economy Ministry'!C94+'Environment Ministry'!C94+'Defence Ministry'!C94+'Education Ministry'!C94+Crises!C94+'Breaking News'!C94+Opportunities!C94 -> 40 | D94: =$B94+'Economy Ministry'!D94+'Environment Ministry'!D94+'Defence Ministry'!D94+'Education Ministry'!D94+Crises!D94+'Breaking News'!D94+Opportunities!D94 -> 40 | E94: =$B94+'Economy Ministry'!E94+'Environment Ministry'!E94+'Defence Ministry'!E94+'Education Ministry'!E94+Crises!E94+'Breaking News'!E94+Opportunities!E94 -> 40 | F94: =$B94+'Economy Ministry'!F94+'Environment Ministry'!F94+'Defence Ministry'!F94+'Education Ministry'!F94+Crises!F94+'Breaking News'!F94+Opportunities!F94 -> 40 | G94: =$B94+'Economy Ministry'!G94+'Environment Ministry'!G94+'Defence Ministry'!G94+'Education Ministry'!G94+Crises!G94+'Breaking News'!G94+Opportunities!G94 -> 40 | H94: =$B94+'Economy Ministry'!H94+'Environment Ministry'!H94+'Defence Ministry'!H94+'Education Ministry'!H94+Crises!H94+'Breaking News'!H94+Opportunities!H94 -> 40 | I94: =$B94+'Economy Ministry'!I94+'Environment Ministry'!I94+'Defence Ministry'!I94+'Education Ministry'!I94+Crises!I94+'Breaking News'!I94+Opportunities!I94 -> 40 | J94: =$B94+'Economy Ministry'!J94+'Environment Ministry'!J94+'Defence Ministry'!J94+'Education Ministry'!J94+Crises!J94+'Breaking News'!J94+Opportunities!J94 -> 40
A95: DefenseExports | B95: 1000000000 | C95: =$B95+'Economy Ministry'!C95+'Environment Ministry'!C95+'Defence Ministry'!C95+'Education Ministry'!C95+Crises!C95+'Breaking News'!C95+Opportunities!C95 -> 1000000000 | D95: =$B95+'Economy Ministry'!D95+'Environment Ministry'!D95+'Defence Ministry'!D95+'Education Ministry'!D95+Crises!D95+'Breaking News'!D95+Opportunities!D95 -> 1000000000 | E95: =$B95+'Economy Ministry'!E95+'Environment Ministry'!E95+'Defence Ministry'!E95+'Education Ministry'!E95+Crises!E95+'Breaking News'!E95+Opportunities!E95 -> 1000000000 | F95: =$B95+'Economy Ministry'!F95+'Environment Ministry'!F95+'Defence Ministry'!F95+'Education Ministry'!F95+Crises!F95+'Breaking News'!F95+Opportunities!F95 -> 1000000000 | G95: =$B95+'Economy Ministry'!G95+'Environment Ministry'!G95+'Defence Ministry'!G95+'Education Ministry'!G95+Crises!G95+'Breaking News'!G95+Opportunities!G95 -> 1000000000 | H95: =$B95+'Economy Ministry'!H95+'Environment Ministry'!H95+'Defence Ministry'!H95+'Education Ministry'!H95+Crises!H95+'Breaking News'!H95+Opportunities!H95 -> 1000000000 | I95: =$B95+'Economy Ministry'!I95+'Environment Ministry'!I95+'Defence Ministry'!I95+'Education Ministry'!I95+Crises!I95+'Breaking News'!I95+Opportunities!I95 -> 1000000000 | J95: =$B95+'Economy Ministry'!J95+'Environment Ministry'!J95+'Defence Ministry'!J95+'Education Ministry'!J95+Crises!J95+'Breaking News'!J95+Opportunities!J95 -> 1000000000
A96: DefenseImports | B96: 1500000000 | C96: =$B96+'Economy Ministry'!C96+'Environment Ministry'!C96+'Defence Ministry'!C96+'Education Ministry'!C96+Crises!C96+'Breaking News'!C96+Opportunities!C96 -> 1500000000 | D96: =$B96+'Economy Ministry'!D96+'Environment Ministry'!D96+'Defence Ministry'!D96+'Education Ministry'!D96+Crises!D96+'Breaking News'!D96+Opportunities!D96 -> 1500000000 | E96: =$B96+'Economy Ministry'!E96+'Environment Ministry'!E96+'Defence Ministry'!E96+'Education Ministry'!E96+Crises!E96+'Breaking News'!E96+Opportunities!E96 -> 1500000000 | F96: =$B96+'Economy Ministry'!F96+'Environment Ministry'!F96+'Defence Ministry'!F96+'Education Ministry'!F96+Crises!F96+'Breaking News'!F96+Opportunities!F96 -> 1500000000 | G96: =$B96+'Economy Ministry'!G96+'Environment Ministry'!G96+'Defence Ministry'!G96+'Education Ministry'!G96+Crises!G96+'Breaking News'!G96+Opportunities!G96 -> 1500000000 | H96: =$B96+'Economy Ministry'!H96+'Environment Ministry'!H96+'Defence Ministry'!H96+'Education Ministry'!H96+Crises!H96+'Breaking News'!H96+Opportunities!H96 -> 1500000000 | I96: =$B96+'Economy Ministry'!I96+'Environment Ministry'!I96+'Defence Ministry'!I96+'Education Ministry'!I96+Crises!I96+'Breaking News'!I96+Opportunities!I96 -> 1500000000 | J96: =$B96+'Economy Ministry'!J96+'Environment Ministry'!J96+'Defence Ministry'!J96+'Education Ministry'!J96+Crises!J96+'Breaking News'!J96+Opportunities!J96 -> 1500000000
A97: MilitaryTechnologyTradeBalance | B97: =B95-B96 -> -500000000 | C97: =C95-C96 -> -500000000 | D97: =D95-D96 -> -500000000 | E97: =E95-E96 -> -500000000 | F97: =F95-F96 -> -500000000 | G97: =G95-G96 -> -500000000 | H97: =H95-H96 -> -500000000 | I97: =I95-I96 -> -500000000 | J97: =J95-J96 -> -500000000
A98: DefenseScore | B98: ='Result Targets'!B98 -> 35.726496 | C98: ='Result Targets'!C98 -> 35.726496 | D98: ='Result Targets'!D98 -> 35.726496 | E98: ='Result Targets'!E98 -> 35.726496 | F98: ='Result Targets'!F98 -> 34.700855 | G98: ='Result Targets'!G98 -> 34.700855 | H98: ='Result Targets'!H98 -> 34.700855 | I98: ='Result Targets'!I98 -> 34.700855 | J98: ='Result Targets'!J98 -> 34.700855
A101: Education & Innovation
A102: AILiteracy | B102: 25 | C102: =$B102+'Economy Ministry'!C102+'Environment Ministry'!C102+'Defence Ministry'!C102+'Education Ministry'!C102+Crises!C102+'Breaking News'!C102+Opportunities!C102 -> 24.2 | D102: =$B102+'Economy Ministry'!D102+'Environment Ministry'!D102+'Defence Ministry'!D102+'Education Ministry'!D102+Crises!D102+'Breaking News'!D102+Opportunities!D102 -> 24.2 | E102: =$B102+'Economy Ministry'!E102+'Environment Ministry'!E102+'Defence Ministry'!E102+'Education Ministry'!E102+Crises!E102+'Breaking News'!E102+Opportunities!E102 -> 24.2 | F102: =$B102+'Economy Ministry'!F102+'Environment Ministry'!F102+'Defence Ministry'!F102+'Education Ministry'!F102+Crises!F102+'Breaking News'!F102+Opportunities!F102 -> 24.2 | G102: =$B102+'Economy Ministry'!G102+'Environment Ministry'!G102+'Defence Ministry'!G102+'Education Ministry'!G102+Crises!G102+'Breaking News'!G102+Opportunities!G102 -> 24.2 | H102: =$B102+'Economy Ministry'!H102+'Environment Ministry'!H102+'Defence Ministry'!H102+'Education Ministry'!H102+Crises!H102+'Breaking News'!H102+Opportunities!H102 -> 24.2 | I102: =$B102+'Economy Ministry'!I102+'Environment Ministry'!I102+'Defence Ministry'!I102+'Education Ministry'!I102+Crises!I102+'Breaking News'!I102+Opportunities!I102 -> 24.2 | J102: =$B102+'Economy Ministry'!J102+'Environment Ministry'!J102+'Defence Ministry'!J102+'Education Ministry'!J102+Crises!J102+'Breaking News'!J102+Opportunities!J102 -> 24.2
A103: InnovationIndex | B103: 30 | C103: =$B103+'Economy Ministry'!C103+'Environment Ministry'!C103+'Defence Ministry'!C103+'Education Ministry'!C103+Crises!C103+'Breaking News'!C103+Opportunities!C103 -> 29.2 | D103: =$B103+'Economy Ministry'!D103+'Environment Ministry'!D103+'Defence Ministry'!D103+'Education Ministry'!D103+Crises!D103+'Breaking News'!D103+Opportunities!D103 -> 29.2 | E103: =$B103+'Economy Ministry'!E103+'Environment Ministry'!E103+'Defence Ministry'!E103+'Education Ministry'!E103+Crises!E103+'Breaking News'!E103+Opportunities!E103 -> 29.2 | F103: =$B103+'Economy Ministry'!F103+'Environment Ministry'!F103+'Defence Ministry'!F103+'Education Ministry'!F103+Crises!F103+'Breaking News'!F103+Opportunities!F103 -> 29.2 | G103: =$B103+'Economy Ministry'!G103+'Environment Ministry'!G103+'Defence Ministry'!G103+'Education Ministry'!G103+Crises!G103+'Breaking News'!G103+Opportunities!G103 -> 29.2 | H103: =$B103+'Economy Ministry'!H103+'Environment Ministry'!H103+'Defence Ministry'!H103+'Education Ministry'!H103+Crises!H103+'Breaking News'!H103+Opportunities!H103 -> 29.2 | I103: =$B103+'Economy Ministry'!I103+'Environment Ministry'!I103+'Defence Ministry'!I103+'Education Ministry'!I103+Crises!I103+'Breaking News'!I103+Opportunities!I103 -> 29.2 | J103: =$B103+'Economy Ministry'!J103+'Environment Ministry'!J103+'Defence Ministry'!J103+'Education Ministry'!J103+Crises!J103+'Breaking News'!J103+Opportunities!J103 -> 29.2
A104: InstitutionalAdoptionRate | B104: 20 | C104: =$B104+'Economy Ministry'!C104+'Environment Ministry'!C104+'Defence Ministry'!C104+'Education Ministry'!C104+Crises!C104+'Breaking News'!C104+Opportunities!C104 -> 20 | D104: =$B104+'Economy Ministry'!D104+'Environment Ministry'!D104+'Defence Ministry'!D104+'Education Ministry'!D104+Crises!D104+'Breaking News'!D104+Opportunities!D104 -> 20 | E104: =$B104+'Economy Ministry'!E104+'Environment Ministry'!E104+'Defence Ministry'!E104+'Education Ministry'!E104+Crises!E104+'Breaking News'!E104+Opportunities!E104 -> 20 | F104: =$B104+'Economy Ministry'!F104+'Environment Ministry'!F104+'Defence Ministry'!F104+'Education Ministry'!F104+Crises!F104+'Breaking News'!F104+Opportunities!F104 -> 20 | G104: =$B104+'Economy Ministry'!G104+'Environment Ministry'!G104+'Defence Ministry'!G104+'Education Ministry'!G104+Crises!G104+'Breaking News'!G104+Opportunities!G104 -> 18.4 | H104: =$B104+'Economy Ministry'!H104+'Environment Ministry'!H104+'Defence Ministry'!H104+'Education Ministry'!H104+Crises!H104+'Breaking News'!H104+Opportunities!H104 -> 18.4 | I104: =$B104+'Economy Ministry'!I104+'Environment Ministry'!I104+'Defence Ministry'!I104+'Education Ministry'!I104+Crises!I104+'Breaking News'!I104+Opportunities!I104 -> 18.4 | J104: =$B104+'Economy Ministry'!J104+'Environment Ministry'!J104+'Defence Ministry'!J104+'Education Ministry'!J104+Crises!J104+'Breaking News'!J104+Opportunities!J104 -> 18.4
A105: EducationScore | B105: ='Result Targets'!B105 -> 40.811966 | C105: ='Result Targets'!C105 -> 39.923077 | D105: ='Result Targets'!D105 -> 39.923077 | E105: ='Result Targets'!E105 -> 39.923077 | F105: ='Result Targets'!F105 -> 39.923077 | G105: ='Result Targets'!G105 -> 39.102564 | H105: ='Result Targets'!H105 -> 39.102564 | I105: ='Result Targets'!I105 -> 39.102564 | J105: ='Result Targets'!J105 -> 39.102564
A108: Weighted Governance
A109: GrowthWellBeing | B109: =B64*'Project Variables'!$E$33 -> 12.5 | C109: =C64*'Project Variables'!$E$33 -> 12.5 | D109: =D64*'Project Variables'!$E$33 -> 12.1 | E109: =E64*'Project Variables'!$E$33 -> 12.1 | F109: =F64*'Project Variables'!$E$33 -> 12.1 | G109: =G64*'Project Variables'!$E$33 -> 12.1 | H109: =H64*'Project Variables'!$E$33 -> 12.1 | I109: =I64*'Project Variables'!$E$33 -> 12.1 | J109: =J64*'Project Variables'!$E$33 -> 12.1
A110: HumanRights | B110: =B65*'Project Variables'!$E$34 -> 13.75 | C110: =C65*'Project Variables'!$E$34 -> 13.75 | D110: =D65*'Project Variables'!$E$34 -> 13.75 | E110: =E65*'Project Variables'!$E$34 -> 13.15 | F110: =F65*'Project Variables'!$E$34 -> 13.15 | G110: =G65*'Project Variables'!$E$34 -> 13.15 | H110: =H65*'Project Variables'!$E$34 -> 13.15 | I110: =I65*'Project Variables'!$E$34 -> 13.15 | J110: =J65*'Project Variables'!$E$34 -> 13.15
A111: PrivacyDataProtection | B111: =B66*'Project Variables'!$E$35 -> 6 | C111: =C66*'Project Variables'!$E$35 -> 6 | D111: =D66*'Project Variables'!$E$35 -> 6 | E111: =E66*'Project Variables'!$E$35 -> 5.52 | F111: =F66*'Project Variables'!$E$35 -> 5.04 | G111: =G66*'Project Variables'!$E$35 -> 4.56 | H111: =H66*'Project Variables'!$E$35 -> 4.56 | I111: =I66*'Project Variables'!$E$35 -> 4.56 | J111: =J66*'Project Variables'!$E$35 -> 4.56
A112: Transparency | B112: =B67*'Project Variables'!$E$36 -> 5.7 | C112: =C67*'Project Variables'!$E$36 -> 5.7 | D112: =D67*'Project Variables'!$E$36 -> 5.7 | E112: =E67*'Project Variables'!$E$36 -> 5.7 | F112: =F67*'Project Variables'!$E$36 -> 5.7 | G112: =G67*'Project Variables'!$E$36 -> 5.22 | H112: =H67*'Project Variables'!$E$36 -> 5.22 | I112: =I67*'Project Variables'!$E$36 -> 5.22 | J112: =J67*'Project Variables'!$E$36 -> 5.22
A113: SecuritySafety | B113: =B68*'Project Variables'!$E$37 -> 4.5 | C113: =C68*'Project Variables'!$E$37 -> 4.5 | D113: =D68*'Project Variables'!$E$37 -> 4.34 | E113: =E68*'Project Variables'!$E$37 -> 4.18 | F113: =F68*'Project Variables'!$E$37 -> 3.86 | G113: =G68*'Project Variables'!$E$37 -> 3.86 | H113: =H68*'Project Variables'!$E$37 -> 3.86 | I113: =I68*'Project Variables'!$E$37 -> 3.86 | J113: =J68*'Project Variables'!$E$37 -> 3.86
A114: Accountability | B114: =B69*'Project Variables'!$E$38 -> 3.8 | C114: =C69*'Project Variables'!$E$38 -> 3.8 | D114: =D69*'Project Variables'!$E$38 -> 3.8 | E114: =E69*'Project Variables'!$E$38 -> 3.8 | F114: =F69*'Project Variables'!$E$38 -> 3.8 | G114: =G69*'Project Variables'!$E$38 -> 3.48 | H114: =H69*'Project Variables'!$E$38 -> 3.48 | I114: =I69*'Project Variables'!$E$38 -> 3.48 | J114: =J69*'Project Variables'!$E$38 -> 3.48
A117: TrustInGovernment | B117: =ROUND(SUM(B109:B114),1) -> 46.3 | C117: =ROUND(SUM(C109:C114),1) -> 46.3 | D117: =ROUND(SUM(D109:D114),1) -> 45.7 | E117: =ROUND(SUM(E109:E114),1) -> 44.5 | F117: =ROUND(SUM(F109:F114),1) -> 43.7 | G117: =ROUND(SUM(G109:G114),1) -> 42.4 | H117: =ROUND(SUM(H109:H114),1) -> 42.4 | I117: =ROUND(SUM(I109:I114),1) -> 42.4 | J117: =ROUND(SUM(J109:J114),1) -> 42.4
A118: AverageMinistryScore | B118: ='Result Targets'!B112 -> 34.065171 | C118: ='Result Targets'!C112 -> 33.487393 | D118: ='Result Targets'!D112 -> 33.376282 | E118: ='Result Targets'!E112 -> 33.376282 | F118: ='Result Targets'!F112 -> 33.119872 | G118: ='Result Targets'!G112 -> 32.914744 | H118: ='Result Targets'!H112 -> 32.914744 | I118: ='Result Targets'!I112 -> 32.914744 | J118: ='Result Targets'!J112 -> 32.914744

Sheet Result Targets
B1: 0 | C1: 1 | D1: 2 | E1: 3 | F1: 4 | G1: 5 | H1: 6 | I1: 7 | J1: 8
A2: Targets
A4: Economy
A5: AIContributionToGDPTarget | B5: =IF(FacilSetsTargets=1,'Target Settings'!B4,'Target Settings'!E4) -> 12 | C5: =B5 -> 12 | D5: =C5 -> 12 | E5: =D5 -> 12 | F5: =E5 -> 12 | G5: =F5 -> 12 | H5: =G5 -> 12 | I5: =H5 -> 12 | J5: =I5 -> 12
A6: AIFDIStockTarget | B6: 100000000000 | C6: =B6 -> 100000000000 | D6: =C6 -> 100000000000 | E6: =D6 -> 100000000000 | F6: =E6 -> 100000000000 | G6: =F6 -> 100000000000 | H6: =G6 -> 100000000000 | I6: =H6 -> 100000000000 | J6: =I6 -> 100000000000
A9: NetJobsFromAITarget | B9: =IF(FacilSetsTargets=1,'Target Settings'!B6,'Target Settings'!E6) -> 500000 | C9: =B9 -> 500000 | D9: =C9 -> 500000 | E9: =D9 -> 500000 | F9: =E9 -> 500000 | G9: =F9 -> 500000 | H9: =G9 -> 500000 | I9: =H9 -> 500000 | J9: =I9 -> 500000
A12: Environment
A15: RenewableEnergyFactorTarget | B15: =IF(FacilSetsTargets=1,'Target Settings'!B10,'Target Settings'!E10) -> 40 | C15: =B15 -> 40 | D15: =C15 -> 40 | E15: =D15 -> 40 | F15: =E15 -> 40 | G15: =F15 -> 40 | H15: =G15 -> 40 | I15: =H15 -> 40 | J15: =I15 -> 40
A18: CircularityIndexTarget | B18: =IF(FacilSetsTargets=1,'Target Settings'!B11,'Target Settings'!E11) -> 60 | C18: =B18 -> 60 | D18: =C18 -> 60 | E18: =D18 -> 60 | F18: =E18 -> 60 | G18: =F18 -> 60 | H18: =G18 -> 60 | I18: =H18 -> 60 | J18: =I18 -> 60
A19: EcosystemIntegrityIndexTarget | B19: =IF(FacilSetsTargets=1,'Target Settings'!B12,'Target Settings'!E12) -> 60 | C19: =B19 -> 60 | D19: =C19 -> 60 | E19: =D19 -> 60 | F19: =E19 -> 60 | G19: =F19 -> 60 | H19: =G19 -> 60 | I19: =H19 -> 60 | J19: =I19 -> 60
A22: Defense
A23: CybersecurityIndexTarget | B23: =IF(FacilSetsTargets=1,'Target Settings'!B16,'Target Settings'!E16) -> 65 | C23: =B23 -> 65 | D23: =C23 -> 65 | E23: =D23 -> 65 | F23: =E23 -> 65 | G23: =F23 -> 65 | H23: =G23 -> 65 | I23: =H23 -> 65 | J23: =I23 -> 65
A24: AutonomousSystemsSafteyIndexTarget | B24: =IF(FacilSetsTargets=1,'Target Settings'!B17,'Target Settings'!E17) -> 75 | C24: =B24 -> 75 | D24: =C24 -> 75 | E24: =D24 -> 75 | F24: =E24 -> 75 | G24: =F24 -> 75 | H24: =G24 -> 75 | I24: =H24 -> 75 | J24: =I24 -> 75
A27: MilitaryTechnologyTradeBalanceTarget | B27: =IF(FacilSetsTargets=1,'Target Settings'!B18,'Target Settings'!E18) -> 2000000000 | C27: =B27 -> 2000000000 | D27: =C27 -> 2000000000 | E27: =D27 -> 2000000000 | F27: =E27 -> 2000000000 | G27: =F27 -> 2000000000 | H27: =G27 -> 2000000000 | I27: =H27 -> 2000000000 | J27: =I27 -> 2000000000
A30: Education & Innovation
A31: AILiteracyTarget | B31: =IF(FacilSetsTargets=1,'Target Settings'!B22,'Target Settings'!E22) -> 60 | C31: =B31 -> 60 | D31: =C31 -> 60 | E31: =D31 -> 60 | F31: =E31 -> 60 | G31: =F31 -> 60 | H31: =G31 -> 60 | I31: =H31 -> 60 | J31: =I31 -> 60
A32: InnovationIndexTarget | B32: =IF(FacilSetsTargets=1,'Target Settings'!B23,'Target Settings'!E23) -> 60 | C32: =B32 -> 60 | D32: =C32 -> 60 | E32: =D32 -> 60 | F32: =E32 -> 60 | G32: =F32 -> 60 | H32: =G32 -> 60 | I32: =H32 -> 60 | J32: =I32 -> 60
A33: InstitutionalAdoptionRateTarget | B33: =IF(FacilSetsTargets=1,'Target Settings'!B24,'Target Settings'!E24) -> 65 | C33: =B33 -> 65 | D33: =C33 -> 65 | E33: =D33 -> 65 | F33: =E33 -> 65 | G33: =F33 -> 65 | H33: =G33 -> 65 | I33: =H33 -> 65 | J33: =I33 -> 65
A70: Percentage of Target Achieved %
A72: Economy
A73: AIContributionToGDPPercOfTargetAchieved | B73: =MAX((Results!B73)/('Result Targets'!B5),0) * 100 -> 25 | C73: =MAX((Results!C73)/('Result Targets'!C5),0) * 100 -> 22.333333 | D73: =MAX((Results!D73)/('Result Targets'!D5),0) * 100 -> 22.333333 | E73: =MAX((Results!E73)/('Result Targets'!E5),0) * 100 -> 22.333333 | F73: =MAX((Results!F73)/('Result Targets'!F5),0) * 100 -> 22.333333 | G73: =MAX((Results!G73)/('Result Targets'!G5),0) * 100 -> 22.333333 | H73: =MAX((Results!H73)/('Result Targets'!H5),0) * 100 -> 22.333333 | I73: =MAX((Results!I73)/('Result Targets'!I5),0) * 100 -> 22.333333 | J73: =MAX((Results!J73)/('Result Targets'!J5),0) * 100 -> 22.333333
A74: AIFDIStockPercOfTargetAchieved | B74: =MAX((Results!B74)/('Result Targets'!B6),0)*100 -> 50 | C74: =MAX((Results!C74)/('Result Targets'!C6),0)*100 -> 48.4 | D74: =MAX((Results!D74)/('Result Targets'!D6),0)*100 -> 48.4 | E74: =MAX((Results!E74)/('Result Targets'!E6),0)*100 -> 48.4 | F74: =MAX((Results!F74)/('Result Targets'!F6),0)*100 -> 48.4 | G74: =MAX((Results!G74)/('Result Targets'!G6),0)*100 -> 48.4 | H74: =MAX((Results!H74)/('Result Targets'!H6),0)*100 -> 48.4 | I74: =MAX((Results!I74)/('Result Targets'!I6),0)*100 -> 48.4 | J74: =MAX((Results!J74)/('Result Targets'!J6),0)*100 -> 48.4
A77: NetJobsFromAIPercOfTargetAchieved | B77: =MAX((Results!B77)/('Result Targets'!B9),0)*100 -> 0 | C77: =MAX((Results!C77)/('Result Targets'!C9),0)*100 -> 0 | D77: =MAX((Results!D77)/('Result Targets'!D9),0)*100 -> 0 | E77: =MAX((Results!E77)/('Result Targets'!E9),0)*100 -> 0 | F77: =MAX((Results!F77)/('Result Targets'!F9),0)*100 -> 0 | G77: =MAX((Results!G77)/('Result Targets'!G9),0)*100 -> 0 | H77: =MAX((Results!H77)/('Result Targets'!H9),0)*100 -> 0 | I77: =MAX((Results!I77)/('Result Targets'!I9),0)*100 -> 0 | J77: =MAX((Results!J77)/('Result Targets'!J9),0)*100 -> 0
A78: EconomyScore | B78: =AVERAGE(MIN(B73,100),MIN(B74,100),MIN(B77,100)) -> 25 | C78: =AVERAGE(MIN(C73,100),MIN(C74,100),MIN(C77,100)) -> 23.577778 | D78: =AVERAGE(MIN(D73,100),MIN(D74,100),MIN(D77,100)) -> 23.577778 | E78: =AVERAGE(MIN(E73,100),MIN(E74,100),MIN(E77,100)) -> 23.577778 | F78: =AVERAGE(MIN(F73,100),MIN(F74,100),MIN(F77,100)) -> 23.577778 | G78: =AVERAGE(MIN(G73,100),MIN(G74,100),MIN(G77,100)) -> 23.577778 | H78: =AVERAGE(MIN(H73,100),MIN(H74,100),MIN(H77,100)) -> 23.577778 | I78: =AVERAGE(MIN(I73,100),MIN(I74,100),MIN(I77,100)) -> 23.577778 | J78: =AVERAGE(MIN(J73,100),MIN(J74,100),MIN(J77,100)) -> 23.577778
A81: Environment
A84: RenewableEnergyFactorPercOfTargetAchieved | B84: =MAX((Results!B84)/('Result Targets'!B15),0) * 100 -> 25 | C84: =MAX((Results!C84)/('Result Targets'!C15),0) * 100 -> 25 | D84: =MAX((Results!D84)/('Result Targets'!D15),0) * 100 -> 25 | E84: =MAX((Results!E84)/('Result Targets'!E15),0) * 100 -> 25 | F84: =MAX((Results!F84)/('Result Targets'!F15),0) * 100 -> 25 | G84: =MAX((Results!G84)/('Result Targets'!G15),0) * 100 -> 25 | H84: =MAX((Results!H84)/('Result Targets'!H15),0) * 100 -> 25 | I84: =MAX((Results!I84)/('Result Targets'!I15),0) * 100 -> 25 | J84: =MAX((Results!J84)/('Result Targets'!J15),0) * 100 -> 25
A87: CircularityIndexPercOfTargetAchieved | B87: =MAX((Results!B87)/('Result Targets'!B18),0) * 100 -> 37.5 | C87: =MAX((Results!C87)/('Result Targets'!C18),0) * 100 -> 37.5 | D87: =MAX((Results!D87)/('Result Targets'!D18),0) * 100 -> 36.166667 | E87: =MAX((Results!E87)/('Result Targets'!E18),0) * 100 -> 36.166667 | F87: =MAX((Results!F87)/('Result Targets'!F18),0) * 100 -> 36.166667 | G87: =MAX((Results!G87)/('Result Targets'!G18),0) * 100 -> 36.166667 | H87: =MAX((Results!H87)/('Result Targets'!H18),0) * 100 -> 36.166667 | I87: =MAX((Results!I87)/('Result Targets'!I18),0) * 100 -> 36.166667 | J87: =MAX((Results!J87)/('Result Targets'!J18),0) * 100 -> 36.166667
A88: EcosystemIntegrityIndexPercOfTargetAchieved | B88: =MAX((Results!B88)/('Result Targets'!B19),0) * 100 -> 41.666667 | C88: =MAX((Results!C88)/('Result Targets'!C19),0) * 100 -> 41.666667 | D88: =MAX((Results!D88)/('Result Targets'!D19),0) * 100 -> 41.666667 | E88: =MAX((Results!E88)/('Result Targets'!E19),0) * 100 -> 41.666667 | F88: =MAX((Results!F88)/('Result Targets'!F19),0) * 100 -> 41.666667 | G88: =MAX((Results!G88)/('Result Targets'!G19),0) * 100 -> 41.666667 | H88: =MAX((Results!H88)/('Result Targets'!H19),0) * 100 -> 41.666667 | I88: =MAX((Results!I88)/('Result Targets'!I19),0) * 100 -> 41.666667 | J88: =MAX((Results!J88)/('Result Targets'!J19),0) * 100 -> 41.666667
A90: EnvironmentScore | B90: =AVERAGE(MIN(B84,100),MIN(B87,100),MIN(B88,100)) -> 34.722222 | C90: =AVERAGE(MIN(C84,100),MIN(C87,100),MIN(C88,100)) -> 34.722222 | D90: =AVERAGE(MIN(D84,100),MIN(D87,100),MIN(D88,100)) -> 34.277778 | E90: =AVERAGE(MIN(E84,100),MIN(E87,100),MIN(E88,100)) -> 34.277778 | F90: =AVERAGE(MIN(F84,100),MIN(F87,100),MIN(F88,100)) -> 34.277778 | G90: =AVERAGE(MIN(G84,100),MIN(G87,100),MIN(G88,100)) -> 34.277778 | H90: =AVERAGE(MIN(H84,100),MIN(H87,100),MIN(H88,100)) -> 34.277778 | I90: =AVERAGE(MIN(I84,100),MIN(I87,100),MIN(I88,100)) -> 34.277778 | J90: =AVERAGE(MIN(J84,100),MIN(J87,100),MIN(J88,100)) -> 34.277778
A92: Defense
A93: CybersecurityIndexPercOfTargetAchieved | B93: =MAX((Results!B93)/('Result Targets'!B23),0)*100 -> 53.846154 | C93: =MAX((Results!C93)/('Result Targets'!C23),0)*100 -> 53.846154 | D93: =MAX((Results!D93)/('Result Targets'!D23),0)*100 -> 53.846154 | E93: =MAX((Results!E93)/('Result Targets'!E23),0)*100 -> 53.846154 | F93: =MAX((Results!F93)/('Result Targets'!F23),0)*100 -> 50.769231 | G93: =MAX((Results!G93)/('Result Targets'!G23),0)*100 -> 50.769231 | H93: =MAX((Results!H93)/('Result Targets'!H23),0)*100 -> 50.769231 | I93: =MAX((Results!I93)/('Result Targets'!I23),0)*100 -> 50.769231 | J93: =MAX((Results!J93)/('Result Targets'!J23),0)*100 -> 50.769231
A94: AutonomousSystemsSafteyIndexPercOfTargetAchieved | B94: =MAX((Results!B94)/('Result Targets'!B24),0)*100 -> 53.333333 | C94: =MAX((Results!C94)/('Result Targets'!C24),0)*100 -> 53.333333 | D94: =MAX((Results!D94)/('Result Targets'!D24),0)*100 -> 53.333333 | E94: =MAX((Results!E94)/('Result Targets'!E24),0)*100 -> 53.333333 | F94: =MAX((Results!F94)/('Result Targets'!F24),0)*100 -> 53.333333 | G94: =MAX((Results!G94)/('Result Targets'!G24),0)*100 -> 53.333333 | H94: =MAX((Results!H94)/('Result Targets'!H24),0)*100 -> 53.333333 | I94: =MAX((Results!I94)/('Result Targets'!I24),0)*100 -> 53.333333 | J94: =MAX((Results!J94)/('Result Targets'!J24),0)*100 -> 53.333333
A97: MilitaryTechnologyTradeBalancePercOfTargetAchieved | B97: =MAX((Results!B97)/('Result Targets'!B27),0)*100 -> 0 | C97: =MAX((Results!C97)/('Result Targets'!C27),0)*100 -> 0 | D97: =MAX((Results!D97)/('Result Targets'!D27),0)*100 -> 0 | E97: =MAX((Results!E97)/('Result Targets'!E27),0)*100 -> 0 | F97: =MAX((Results!F97)/('Result Targets'!F27),0)*100 -> 0 | G97: =MAX((Results!G97)/('Result Targets'!G27),0)*100 -> 0 | H97: =MAX((Results!H97)/('Result Targets'!H27),0)*100 -> 0 | I97: =MAX((Results!I97)/('Result Targets'!I27),0)*100 -> 0 | J97: =MAX((Results!J97)/('Result Targets'!J27),0)*100 -> 0
A98: DefenseScore | B98: =AVERAGE(MIN(B93,100),MIN(B94,100),MIN(B97,100)) -> 35.726496 | C98: =AVERAGE(MIN(C93,100),MIN(C94,100),MIN(C97,100)) -> 35.726496 | D98: =AVERAGE(MIN(D93,100),MIN(D94,100),MIN(D97,100)) -> 35.726496 | E98: =AVERAGE(MIN(E93,100),MIN(E94,100),MIN(E97,100)) -> 35.726496 | F98: =AVERAGE(MIN(F93,100),MIN(F94,100),MIN(F97,100)) -> 34.700855 | G98: =AVERAGE(MIN(G93,100),MIN(G94,100),MIN(G97,100)) -> 34.700855 | H98: =AVERAGE(MIN(H93,100),MIN(H94,100),MIN(H97,100)) -> 34.700855 | I98: =AVERAGE(MIN(I93,100),MIN(I94,100),MIN(I97,100)) -> 34.700855 | J98: =AVERAGE(MIN(J93,100),MIN(J94,100),MIN(J97,100)) -> 34.700855
A101: Education & Innovation
A102: AILiteracyPercOfTargetAchieved | B102: =MAX((Results!B102)/('Result Targets'!B31),0)*100 -> 41.666667 | C102: =MAX((Results!C102)/('Result Targets'!C31),0)*100 -> 40.333333 | D102: =MAX((Results!D102)/('Result Targets'!D31),0)*100 -> 40.333333 | E102: =MAX((Results!E102)/('Result Targets'!E31),0)*100 -> 40.333333 | F102: =MAX((Results!F102)/('Result Targets'!F31),0)*100 -> 40.333333 | G102: =MAX((Results!G102)/('Result Targets'!G31),0)*100 -> 40.333333 | H102: =MAX((Results!H102)/('Result Targets'!H31),0)*100 -> 40.333333 | I102: =MAX((Results!I102)/('Result Targets'!I31),0)*100 -> 40.333333 | J102: =MAX((Results!J102)/('Result Targets'!J31),0)*100 -> 40.333333
A103: InnovationIndexPercOfTargetAchieved | B103: =MAX((Results!B103)/('Result Targets'!B32),0)*100 -> 50 | C103: =MAX((Results!C103)/('Result Targets'!C32),0)*100 -> 48.666667 | D103: =MAX((Results!D103)/('Result Targets'!D32),0)*100 -> 48.666667 | E103: =MAX((Results!E103)/('Result Targets'!E32),0)*100 -> 48.666667 | F103: =MAX((Results!F103)/('Result Targets'!F32),0)*100 -> 48.666667 | G103: =MAX((Results!G103)/('Result Targets'!G32),0)*100 -> 48.666667 | H103: =MAX((Results!H103)/('Result Targets'!H32),0)*100 -> 48.666667 | I103: =MAX((Results!I103)/('Result Targets'!I32),0)*100 -> 48.666667 | J103: =MAX((Results!J103)/('Result Targets'!J32),0)*100 -> 48.666667
A104: InstitutionalAdoptionRatePercOfTargetAchieved | B104: =MAX((Results!B104)/('Result Targets'!B33),0)*100 -> 30.769231 | C104: =MAX((Results!C104)/('Result Targets'!C33),0)*100 -> 30.769231 | D104: =MAX((Results!D104)/('Result Targets'!D33),0)*100 -> 30.769231 | E104: =MAX((Results!E104)/('Result Targets'!E33),0)*100 -> 30.769231 | F104: =MAX((Results!F104)/('Result Targets'!F33),0)*100 -> 30.769231 | G104: =MAX((Results!G104)/('Result Targets'!G33),0)*100 -> 28.307692 | H104: =MAX((Results!H104)/('Result Targets'!H33),0)*100 -> 28.307692 | I104: =MAX((Results!I104)/('Result Targets'!I33),0)*100 -> 28.307692 | J104: =MAX((Results!J104)/('Result Targets'!J33),0)*100 -> 28.307692
A105: EducationScore | B105: =AVERAGE(MIN(B102,100),MIN(B103,100),MIN(B104,100)) -> 40.811966 | C105: =AVERAGE(MIN(C102,100),MIN(C103,100),MIN(C104,100)) -> 39.923077 | D105: =AVERAGE(MIN(D102,100),MIN(D103,100),MIN(D104,100)) -> 39.923077 | E105: =AVERAGE(MIN(E102,100),MIN(E103,100),MIN(E104,100)) -> 39.923077 | F105: =AVERAGE(MIN(F102,100),MIN(F103,100),MIN(F104,100)) -> 39.923077 | G105: =AVERAGE(MIN(G102,100),MIN(G103,100),MIN(G104,100)) -> 39.102564 | H105: =AVERAGE(MIN(H102,100),MIN(H103,100),MIN(H104,100)) -> 39.102564 | I105: =AVERAGE(MIN(I102,100),MIN(I103,100),MIN(I104,100)) -> 39.102564 | J105: =AVERAGE(MIN(J102,100),MIN(J103,100),MIN(J104,100)) -> 39.102564
A108: Numbers
A109: NumTargetsMet | B109: =EcEnabled*COUNTIF(B73:B77,">=100")+EnvEnabled*COUNTIF(B84:B88,">=100")+DefEnabled*COUNTIF(B93:B97,">=100")+EduEnabled*COUNTIF(B102:B104,">=100") -> 0 | C109: =EcEnabled*COUNTIF(C73:C77,">=100")+EnvEnabled*COUNTIF(C84:C88,">=100")+DefEnabled*COUNTIF(C93:C97,">=100")+EduEnabled*COUNTIF(C102:C104,">=100") -> 0 | D109: =EcEnabled*COUNTIF(D73:D77,">=100")+EnvEnabled*COUNTIF(D84:D88,">=100")+DefEnabled*COUNTIF(D93:D97,">=100")+EduEnabled*COUNTIF(D102:D104,">=100") -> 0 | E109: =EcEnabled*COUNTIF(E73:E77,">=100")+EnvEnabled*COUNTIF(E84:E88,">=100")+DefEnabled*COUNTIF(E93:E97,">=100")+EduEnabled*COUNTIF(E102:E104,">=100") -> 0 | F109: =EcEnabled*COUNTIF(F73:F77,">=100")+EnvEnabled*COUNTIF(F84:F88,">=100")+DefEnabled*COUNTIF(F93:F97,">=100")+EduEnabled*COUNTIF(F102:F104,">=100") -> 0 | G109: =EcEnabled*COUNTIF(G73:G77,">=100")+EnvEnabled*COUNTIF(G84:G88,">=100")+DefEnabled*COUNTIF(G93:G97,">=100")+EduEnabled*COUNTIF(G102:G104,">=100") -> 0 | H109: =EcEnabled*COUNTIF(H73:H77,">=100")+EnvEnabled*COUNTIF(H84:H88,">=100")+DefEnabled*COUNTIF(H93:H97,">=100")+EduEnabled*COUNTIF(H102:H104,">=100") -> 0 | I109: =EcEnabled*COUNTIF(I73:I77,">=100")+EnvEnabled*COUNTIF(I84:I88,">=100")+DefEnabled*COUNTIF(I93:I97,">=100")+EduEnabled*COUNTIF(I102:I104,">=100") -> 0 | J109: =EcEnabled*COUNTIF(J73:J77,">=100")+EnvEnabled*COUNTIF(J84:J88,">=100")+DefEnabled*COUNTIF(J93:J97,">=100")+EduEnabled*COUNTIF(J102:J104,">=100") -> 0
A110: NumTargetsAlmostMet | B110: =EcEnabled*COUNTIF(B73:B77,">=80")+EnvEnabled*COUNTIF(B84:B88,">=80")+DefEnabled*COUNTIF(B93:B97,">=80")+EduEnabled*COUNTIF(B102:B104,">=80")-B109 -> 0 | C110: =EcEnabled*COUNTIF(C73:C77,">=80")+EnvEnabled*COUNTIF(C84:C88,">=80")+DefEnabled*COUNTIF(C93:C97,">=80")+EduEnabled*COUNTIF(C102:C104,">=80")-C109 -> 0 | D110: =EcEnabled*COUNTIF(D73:D77,">=80")+EnvEnabled*COUNTIF(D84:D88,">=80")+DefEnabled*COUNTIF(D93:D97,">=80")+EduEnabled*COUNTIF(D102:D104,">=80")-D109 -> 0 | E110: =EcEnabled*COUNTIF(E73:E77,">=80")+EnvEnabled*COUNTIF(E84:E88,">=80")+DefEnabled*COUNTIF(E93:E97,">=80")+EduEnabled*COUNTIF(E102:E104,">=80")-E109 -> 0 | F110: =EcEnabled*COUNTIF(F73:F77,">=80")+EnvEnabled*COUNTIF(F84:F88,">=80")+DefEnabled*COUNTIF(F93:F97,">=80")+EduEnabled*COUNTIF(F102:F104,">=80")-F109 -> 0 | G110: =EcEnabled*COUNTIF(G73:G77,">=80")+EnvEnabled*COUNTIF(G84:G88,">=80")+DefEnabled*COUNTIF(G93:G97,">=80")+EduEnabled*COUNTIF(G102:G104,">=80")-G109 -> 0 | H110: =EcEnabled*COUNTIF(H73:H77,">=80")+EnvEnabled*COUNTIF(H84:H88,">=80")+DefEnabled*COUNTIF(H93:H97,">=80")+EduEnabled*COUNTIF(H102:H104,">=80")-H109 -> 0 | I110: =EcEnabled*COUNTIF(I73:I77,">=80")+EnvEnabled*COUNTIF(I84:I88,">=80")+DefEnabled*COUNTIF(I93:I97,">=80")+EduEnabled*COUNTIF(I102:I104,">=80")-I109 -> 0 | J110: =EcEnabled*COUNTIF(J73:J77,">=80")+EnvEnabled*COUNTIF(J84:J88,">=80")+DefEnabled*COUNTIF(J93:J97,">=80")+EduEnabled*COUNTIF(J102:J104,">=80")-J109 -> 0
A111: NumTargetsNotMet | B111: =EcEnabled*COUNTIF(B73:B77,"<80")+EnvEnabled*COUNTIF(B84:B88,"<80")+DefEnabled*COUNTIF(B93:B97,"<80")+EduEnabled*COUNTIF(B102:B104,"<80") -> 12 | C111: =EcEnabled*COUNTIF(C73:C77,"<80")+EnvEnabled*COUNTIF(C84:C88,"<80")+DefEnabled*COUNTIF(C93:C97,"<80")+EduEnabled*COUNTIF(C102:C104,"<80") -> 12 | D111: =EcEnabled*COUNTIF(D73:D77,"<80")+EnvEnabled*COUNTIF(D84:D88,"<80")+DefEnabled*COUNTIF(D93:D97,"<80")+EduEnabled*COUNTIF(D102:D104,"<80") -> 12 | E111: =EcEnabled*COUNTIF(E73:E77,"<80")+EnvEnabled*COUNTIF(E84:E88,"<80")+DefEnabled*COUNTIF(E93:E97,"<80")+EduEnabled*COUNTIF(E102:E104,"<80") -> 12 | F111: =EcEnabled*COUNTIF(F73:F77,"<80")+EnvEnabled*COUNTIF(F84:F88,"<80")+DefEnabled*COUNTIF(F93:F97,"<80")+EduEnabled*COUNTIF(F102:F104,"<80") -> 12 | G111: =EcEnabled*COUNTIF(G73:G77,"<80")+EnvEnabled*COUNTIF(G84:G88,"<80")+DefEnabled*COUNTIF(G93:G97,"<80")+EduEnabled*COUNTIF(G102:G104,"<80") -> 12 | H111: =EcEnabled*COUNTIF(H73:H77,"<80")+EnvEnabled*COUNTIF(H84:H88,"<80")+DefEnabled*COUNTIF(H93:H97,"<80")+EduEnabled*COUNTIF(H102:H104,"<80") -> 12 | I111: =EcEnabled*COUNTIF(I73:I77,"<80")+EnvEnabled*COUNTIF(I84:I88,"<80")+DefEnabled*COUNTIF(I93:I97,"<80")+EduEnabled*COUNTIF(I102:I104,"<80") -> 12 | J111: =EcEnabled*COUNTIF(J73:J77,"<80")+EnvEnabled*COUNTIF(J84:J88,"<80")+DefEnabled*COUNTIF(J93:J97,"<80")+EduEnabled*COUNTIF(J102:J104,"<80") -> 12
A112: AverageMinistryScore | B112: =(B78*EcEnabled + B90*EnvEnabled + B98*DefEnabled + B105*EduEnabled) / MAX(EcEnabled+EnvEnabled+DefEnabled+EduEnabled, 1) -> 34.065171 | C112: =(C78*EcEnabled + C90*EnvEnabled + C98*DefEnabled + C105*EduEnabled) / MAX(EcEnabled+EnvEnabled+DefEnabled+EduEnabled, 1) -> 33.487393 | D112: =(D78*EcEnabled + D90*EnvEnabled + D98*DefEnabled + D105*EduEnabled) / MAX(EcEnabled+EnvEnabled+DefEnabled+EduEnabled, 1) -> 33.376282 | E112: =(E78*EcEnabled + E90*EnvEnabled + E98*DefEnabled + E105*EduEnabled) / MAX(EcEnabled+EnvEnabled+DefEnabled+EduEnabled, 1) -> 33.376282 | F112: =(F78*EcEnabled + F90*EnvEnabled + F98*DefEnabled + F105*EduEnabled) / MAX(EcEnabled+EnvEnabled+DefEnabled+EduEnabled, 1) -> 33.119872 | G112: =(G78*EcEnabled + G90*EnvEnabled + G98*DefEnabled + G105*EduEnabled) / MAX(EcEnabled+EnvEnabled+DefEnabled+EduEnabled, 1) -> 32.914744 | H112: =(H78*EcEnabled + H90*EnvEnabled + H98*DefEnabled + H105*EduEnabled) / MAX(EcEnabled+EnvEnabled+DefEnabled+EduEnabled, 1) -> 32.914744 | I112: =(I78*EcEnabled + I90*EnvEnabled + I98*DefEnabled + I105*EduEnabled) / MAX(EcEnabled+EnvEnabled+DefEnabled+EduEnabled, 1) -> 32.914744 | J112: =(J78*EcEnabled + J90*EnvEnabled + J98*DefEnabled + J105*EduEnabled) / MAX(EcEnabled+EnvEnabled+DefEnabled+EduEnabled, 1) -> 32.914744 | L112: copied into TotalScore

Sheet KPI Impacts
B1: Policy Impacts | K1: Slider Impacts | S1: Slider Costs
B2: HighNeg | C2: MediumNeg | D2: LowNeg | E2: None | F2: LowPos | G2: MediumPos | H2: HighPos | K2: HighNeg | L2: MediumNeg | M2: LowNeg | N2: None | O2: LowPos | P2: MediumPos | Q2: HighPos | S2: Value | T2: 0 | U2: 1 | V2: 2 | W2: 3
A63: Governance | K63: 0 | L63: 0 | M63: 0 | N63: 0 | O63: 0 | P63: 0 | Q63: 0 | S63: Cost | T63: 0 | U63: 10000000 | V63: 20000000 | W63: 40000000
A64: GrowthWellBeing | B64: =H64*-0.8 -> -2.4 | C64: =G64*-0.8 -> -1.6 | D64: =F64*-0.8 -> -0.8 | E64: 0 | F64: 1 | G64: 2 | H64: 3 | K64: =(Q64*-1)*0.6 -> -0.36 | L64: =(P64*-1)*0.6 -> -0.27 | M64: =(O64*-1)*0.6 -> -0.18 | N64: 0 | O64: 0.3 | P64: 0.45 | Q64: 0.6
A65: HumanRights | B65: =H65*-0.8 -> -2.4 | C65: =G65*-0.8 -> -1.6 | D65: =F65*-0.8 -> -0.8 | E65: 0 | F65: 1 | G65: 2 | H65: 3 | K65: =(Q65*-1)*0.6 -> -0.54 | L65: =(P65*-1)*0.6 -> -0.36 | M65: =(O65*-1)*0.6 -> -0.18 | N65: 0 | O65: 0.3 | P65: 0.6 | Q65: 0.9
A66: PrivacyDataProtection | B66: =H66*-0.8 -> -4.8 | C66: =G66*-0.8 -> -3.2 | D66: =F66*-0.8 -> -1.6 | E66: 0 | F66: 2 | G66: 4 | H66: 6 | K66: =(Q66*-1)*0.6 -> -1.08 | L66: =(P66*-1)*0.6 -> -0.72 | M66: =(O66*-1)*0.6 -> -0.36 | N66: 0 | O66: 0.6 | P66: 1.2 | Q66: 1.8
A67: Transparency | B67: =H67*-0.8 -> -4.8 | C67: =G67*-0.8 -> -3.2 | D67: =F67*-0.8 -> -1.6 | E67: 0 | F67: 2 | G67: 4 | H67: 6 | K67: =(Q67*-1)*0.6 -> -1.08 | L67: =(P67*-1)*0.6 -> -0.72 | M67: =(O67*-1)*0.6 -> -0.36 | N67: 0 | O67: 0.6 | P67: 1.2 | Q67: 1.8
A68: SecuritySafety | B68: =H68*-0.8 -> -4.8 | C68: =G68*-0.8 -> -3.2 | D68: =F68*-0.8 -> -1.6 | E68: 0 | F68: 2 | G68: 4 | H68: 6 | K68: =(Q68*-1)*0.6 -> -0.72 | L68: =(P68*-1)*0.6 -> -0.54 | M68: =(O68*-1)*0.6 -> -0.36 | N68: 0 | O68: 0.6 | P68: 0.9 | Q68: 1.2
A69: Accountability | B69: =H69*-0.8 -> -4.8 | C69: =G69*-0.8 -> -3.2 | D69: =F69*-0.8 -> -1.6 | E69: 0 | F69: 2 | G69: 4 | H69: 6 | K69: =(Q69*-1)*0.6 -> -0.72 | L69: =(P69*-1)*0.6 -> -0.54 | M69: =(O69*-1)*0.6 -> -0.36 | N69: 0 | O69: 0.6 | P69: 0.9 | Q69: 1.2
A72: Economy
A73: AIContributionToGDP | B73: =H73*-0.8 -> -0.8 | C73: =G73*-0.8 -> -0.6 | D73: =F73*-0.8 -> -0.32 | E73: 0 | F73: 0.4 | G73: 0.75 | H73: 1 | K73: =(Q73*-1)*0.6 -> -0.216 | L73: =(P73*-1)*0.6 -> -0.144 | M73: =(O73*-1)*0.6 -> -0.072 | N73: 0 | O73: 0.12 | P73: 0.24 | Q73: 0.36
A74: AIFDIStock | B74: =H74*-0.8 -> -4800000000 | C74: =G74*-0.8 -> -3200000000 | D74: =F74*-0.8 -> -1600000000 | E74: 0 | F74: 2000000000 | G74: 4000000000 | H74: 6000000000 | K74: =(Q74*-1)*0.6 -> -2160000000 | L74: =(P74*-1)*0.6 -> -1440000000 | M74: =(O74*-1)*0.6 -> -720000000 | N74: 0 | O74: 1200000000 | P74: 2400000000 | Q74: 3600000000
A75: JobsCreated | B75: =H75*-0.8 -> -60000 | C75: =G75*-0.8 -> -40000 | D75: =F75*-0.8 -> -20000 | E75: 0 | F75: 25000 | G75: 50000 | H75: 75000 | K75: =(Q75*-1)*0.6 -> -54000 | L75: =(P75*-1)*0.6 -> -54000 | M75: =(O75*-1)*0.6 -> -18000 | N75: 0 | O75: 30000 | P75: 90000 | Q75: 90000
A76: JobsDisplaced | B76: =H76*-0.8 -> -120000 | C76: =G76*-0.8 -> -80000 | D76: =F76*-0.8 -> -40000 | E76: 0 | F76: 50000 | G76: 100000 | H76: 150000 | K76: =(Q76*-1)*0.6 -> -54000 | L76: =(P76*-1)*0.6 -> -36000 | M76: =(O76*-1)*0.6 -> -18000 | N76: 0 | O76: 30000 | P76: 60000 | Q76: 90000
A77: NetJobsFromAI | B77: X | C77: X | D77: X | E77: X | F77: X | G77: X | H77: X | K77: X | L77: X | M77: X | N77: X | O77: X | P77: X | Q77: X
B78: =H78*-1 -> -5 | C78: =G78*-1 -> -3 | D78: =F78*-1 -> -1 | E78: 0 | F78: 1 | G78: 3 | H78: 5 | K78: =(Q78*-1)*0.6 -> -1.8 | L78: =(P78*-1)*0.6 -> -1.08 | M78: =(O78*-1)*0.6 -> -0.36 | N78: 0 | O78: 0.6 | P78: 1.8 | Q78: 3
A81: Environment
A82: EnergyConsumedFromDataCenters | B82: X | C82: X | D82: X | E82: X | F82: X | G82: X | H82: X | K82: X | L82: X | M82: X | N82: X | O82: X | P82: X | Q82: X
A83: CarbonIntensityFromDataCenters | B83: X | C83: X | D83: X | E83: X | F83: X | G83: X | H83: X | K83: X | L83: X | M83: X | N83: X | O83: X | P83: X | Q83: X
A84: RenewableEnergyFactor | B84: =H84*-0.8 -> -3.2 | C84: =G84*-0.8 -> -1.6 | D84: =F84*-0.8 -> -0.8 | E84: 0 | F84: 1 | G84: 2 | H84: 4 | K84: =(Q84*-1)*0.6 -> -1.44 | L84: =(P84*-1)*0.6 -> -0.72 | M84: =(O84*-1)*0.6 -> -0.36 | N84: 0 | O84: 0.6 | P84: 1.2 | Q84: 2.4
A85: WaterCircularityIndex | B85: =H85*-0.8 -> -4.8 | C85: =G85*-0.8 -> -3.2 | D85: =F85*-0.8 -> -1.6 | E85: 0 | F85: 2 | G85: 4 | H85: 6 | K85: =(Q85*-1)*0.6 -> -0.54 | L85: =(P85*-1)*0.6 -> -0.45 | M85: =(O85*-1)*0.6 -> -0.27 | N85: 0 | O85: 0.45 | P85: 0.75 | Q85: 0.9
A86: EwasteCircularityIndex | B86: =H86*-0.8 -> -4.8 | C86: =G86*-0.8 -> -3.2 | D86: =F86*-0.8 -> -1.6 | E86: 0 | F86: 2 | G86: 4 | H86: 6 | K86: =(Q86*-1)*0.6 -> -0.54 | L86: =(P86*-1)*0.6 -> -0.45 | M86: =(O86*-1)*0.6 -> -0.27 | N86: 0 | O86: 0.45 | P86: 0.75 | Q86: 0.9
A87: CircularityIndex | B87: X | C87: X | D87: X | E87: X | F87: X | G87: X | H87: X | K87: X | L87: X | M87: X | N87: X | O87: X | P87: X | Q87: X
A88: EcosystemIntegrityIndex | B88: =H88*-0.8 -> -3.2 | C88: =G88*-0.8 -> -1.6 | D88: =F88*-0.8 -> -0.8 | E88: 0 | F88: 1 | G88: 2 | H88: 4 | K88: =(Q88*-1)*0.6 -> -0.432 | L88: =(P88*-1)*0.6 -> -0.288 | M88: =(O88*-1)*0.6 -> -0.144 | N88: 0 | O88: 0.24 | P88: 0.48 | Q88: 0.72
B89: =H89*-1 -> -5 | C89: =G89*-1 -> -3 | D89: =F89*-1 -> -1 | E89: 0 | F89: 1 | G89: 3 | H89: 5 | K89: =(Q89*-1)*0.6 -> -1.8 | L89: =(P89*-1)*0.6 -> -1.08 | M89: =(O89*-1)*0.6 -> -0.36 | N89: 0 | O89: 0.6 | P89: 1.8 | Q89: 3
A92: Defense
A93: CybersecurityIndex | B93: =H93*-0.8 -> -2 | C93: =G93*-0.8 -> -1.2 | D93: =F93*-0.8 -> -0.8 | E93: 0 | F93: 1 | G93: 1.5 | H93: 2.5 | K93: =(Q93*-1)*0.6 -> -0.54 | L93: =(P93*-1)*0.6 -> -0.36 | M93: =(O93*-1)*0.6 -> -0.18 | N93: 0 | O93: 0.3 | P93: 0.6 | Q93: 0.9
A94: AutonomousSystemsSafteyIndex | B94: =H94*-0.8 -> -2 | C94: =G94*-0.8 -> -1.2 | D94: =F94*-0.8 -> -0.8 | E94: 0 | F94: 1 | G94: 1.5 | H94: 2.5 | K94: =(Q94*-1)*0.6 -> -0.54 | L94: =(P94*-1)*0.6 -> -0.36 | M94: =(O94*-1)*0.6 -> -0.18 | N94: 0 | O94: 0.3 | P94: 0.6 | Q94: 0.9
A95: DefenseExports | B95: =H95*-0.8 -> -1200000000 | C95: =G95*-0.8 -> -800000000 | D95: =F95*-0.8 -> -320000000 | E95: 0 | F95: 400000000 | G95: 1000000000 | H95: 1500000000 | K95: =(Q95*-1)*0.6 -> -270000000 | L95: =(P95*-1)*0.6 -> -144000000 | M95: =(O95*-1)*0.6 -> -54000000 | N95: 0 | O95: 90000000 | P95: 240000000 | Q95: 450000000
A96: DefenseImports | B96: =H96*-0.8 -> -600000000 | C96: =G96*-0.8 -> -320000000 | D96: =F96*-0.8 -> -120000000 | E96: 0 | F96: 150000000 | G96: 400000000 | H96: 750000000 | K96: =(Q96*-1)*0.6 -> -270000000 | L96: =(P96*-1)*0.6 -> -144000000 | M96: =(O96*-1)*0.6 -> -54000000 | N96: 0 | O96: 90000000 | P96: 240000000 | Q96: 450000000
A97: MilitaryTechnologyTradeBalance | B97: X | C97: X | D97: X | E97: X | F97: X | G97: X | H97: X | K97: X | L97: X | M97: X | N97: X | O97: X | P97: X | Q97: X
B98: =H98*-1 -> -5 | C98: =G98*-1 -> -3 | D98: =F98*-1 -> -1 | E98: 0 | F98: 1 | G98: 3 | H98: 5 | K98: =(Q98*-1)*0.6 -> -1.8 | L98: =(P98*-1)*0.6 -> -1.08 | M98: =(O98*-1)*0.6 -> -0.36 | N98: 0 | O98: 0.6 | P98: 1.8 | Q98: 3
A101: Education & Innovation
A102: AILiteracy | B102: =H102*-0.8 -> -3.2 | C102: =G102*-0.8 -> -1.6 | D102: =F102*-0.8 -> -0.8 | E102: 0 | F102: 1 | G102: 2 | H102: 4 | K102: =(Q102*-1)*0.6 -> -1.08 | L102: =(P102*-1)*0.6 -> -0.72 | M102: =(O102*-1)*0.6 -> -0.36 | N102: 0 | O102: 0.6 | P102: 1.2 | Q102: 1.8
A103: InnovationIndex | B103: =H103*-0.8 -> -1.2 | C103: =G103*-0.8 -> -0.8 | D103: =F103*-0.8 -> -0.4 | E103: 0 | F103: 0.5 | G103: 1 | H103: 1.5 | K103: =(Q103*-1)*0.6 -> -0.54 | L103: =(P103*-1)*0.6 -> -0.36 | M103: =(O103*-1)*0.6 -> -0.18 | N103: 0 | O103: 0.3 | P103: 0.6 | Q103: 0.9
A104: InstitutionalAdoptionRate | B104: =H104*-0.8 -> -4.8 | C104: =G104*-0.8 -> -3.2 | D104: =F104*-0.8 -> -1.6 | E104: 0 | F104: 2 | G104: 4 | H104: 6 | K104: =(Q104*-1)*0.6 -> -1.44 | L104: =(P104*-1)*0.6 -> -0.72 | M104: =(O104*-1)*0.6 -> -0.36 | N104: 0 | O104: 0.6 | P104: 1.2 | Q104: 2.4

Sheet Economy Ministry
B1: 0 | C1: 1 | D1: 2 | E1: 3 | F1: 4 | G1: 5 | H1: 6 | I1: 7 | J1: 8 | P1: 0 | Q1: 1 | R1: 2 | S1: 3 | T1: 4 | U1: 5 | V1: 6 | W1: 7 | X1: 8 | Z1: Low | AB1: Medium | AD1: High | AH1: 0 | AI1: 1 | AJ1: 2 | AK1: 3 | AL1: 4 | AM1: 5 | AN1: 6 | AO1: 7 | AP1: 8 | AR1: Low | AT1: Medium | AV1: High | AZ1: 0 | BA1: 1 | BB1: 2 | BC1: 3 | BD1: 4 | BE1: 5 | BF1: 6 | BG1: 7 | BH1: 8 | BJ1: Year 1 | BL1: Year 2 | BP1: 0 | BQ1: 1 | BR1: 2 | BS1: 3 | BT1: 4 | BU1: 5 | BV1: 6 | BW1: 7 | BX1: 8 | BZ1: Year 1 | CB1: Year 2 | CF1: 0 | CG1: 1 | CH1: 2 | CI1: 3 | CJ1: 4 | CK1: 5 | CL1: 6 | CM1: 7 | CN1: 8 | CP1: Year 1 | CR1: Year 2 | CV1: 0 | CW1: 1 | CX1: 2 | CY1: 3 | CZ1: 4 | DA1: 5 | DB1: 6 | DC1: 7 | DD1: 8 | DF1: Year 1 | DH1: Year 2 | DL1: 0 | DM1: 1 | DN1: 2 | DO1: 3 | DP1: 4 | DQ1: 5 | DR1: 6 | DS1: 7 | DT1: 8 | DV1: Year 1 | DX1: Year 2 | EB1: 0 | EC1: 1 | ED1: 2 | EE1: 3 | EF1: 4 | EG1: 5 | EH1: 6 | EI1: 7 | EJ1: 8 | EL1: Year 1 | EN1: Year 2 | ER1: 0 | ES1: 1 | ET1: 2 | EU1: 3 | EV1: 4 | EW1: 5 | EX1: 6 | EY1: 7 | EZ1: 8 | FB1: Year 1 | FD1: Year 2 | FH1: 0 | FI1: 1 | FJ1: 2 | FK1: 3 | FL1: 4 | FM1: 5 | FN1: 6 | FO1: 7 | FP1: 8 | FR1: Year 1 | FT1: Year 2 | FX1: 0 | FY1: 1 | FZ1: 2 | GA1: 3 | GB1: 4 | GC1: 5 | GD1: 6 | GE1: 7 | GF1: 8 | GH1: Year 1 | GJ1: Year 2 | GN1: 0 | GO1: 1 | GP1: 2 | GQ1: 3 | GR1: 4 | GS1: 5 | GT1: 6 | GU1: 7 | GV1: 8 | GX1: Year 1 | GZ1: Year 2 | HD1: 0 | HE1: 1 | HF1: 2 | HG1: 3 | HH1: 4 | HI1: 5 | HJ1: 6 | HK1: 7 | HL1: 8 | HN1: Year 1 | HP1: Year 2 | HT1: 0 | HU1: 1 | HV1: 2 | HW1: 3 | HX1: 4 | HY1: 5 | HZ1: 6 | IA1: 7 | IB1: 8 | ID1: Year 1 | IF1: Year 2 | IJ1: 0 | IK1: 1 | IL1: 2 | IM1: 3 | IN1: 4 | IO1: 5 | IP1: 6 | IQ1: 7 | IR1: 8 | IT1: Year 1 | IV1: Year 2 | IZ1: 0 | JA1: 1 | JB1: 2 | JC1: 3 | JD1: 4 | JE1: 5 | JF1: 6 | JG1: 7 | JH1: 8 | JJ1: Year 1 | JL1: Year 2 | JP1: 0 | JQ1: 1 | JR1: 2 | JS1: 3 | JT1: 4 | JU1: 5 | JV1: 6 | JW1: 7 | JX1: 8 | JZ1: Year 1 | KB1: Year 2 | KF1: 0 | KG1: 1 | KH1: 2 | KI1: 3 | KJ1: 4 | KK1: 5 | KL1: 6 | KM1: 7 | KN1: 8 | KP1: Year 1 | KR1: Year 2 | KV1: 0 | KW1: 1 | KX1: 2 | KY1: 3 | KZ1: 4 | LA1: 5 | LB1: 6 | LC1: 7 | LD1: 8 | LF1: Year 1 | LH1: Year 2 | LL1: 0 | LM1: 1 | LN1: 2 | LO1: 3 | LP1: 4 | LQ1: 5 | LR1: 6 | LS1: 7 | LT1: 8 | LV1: Year 1 | LX1: Year 2 | MB1: 0 | MC1: 1 | MD1: 2 | ME1: 3 | MF1: 4 | MG1: 5 | MH1: 6 | MI1: 7 | MJ1: 8 | ML1: Year 1 | MN1: Year 2 | MR1: 0 | MS1: 1 | MT1: 2 | MU1: 3 | MV1: 4 | MW1: 5 | MX1: 6 | MY1: 7 | MZ1: 8 | NB1: Year 1 | ND1: Year 2 | NH1: 0 | NI1: 1 | NJ1: 2 | NK1: 3 | NL1: 4 | NM1: 5 | NN1: 6 | NO1: 7 | NP1: 8 | NR1: Year 1 | NT1: Year 2 | NX1: 0 | NY1: 1 | NZ1: 2 | OA1: 3 | OB1: 4 | OC1: 5 | OD1: 6 | OE1: 7 | OF1: 8 | OH1: Year 1 | OJ1: Year 2
Z2: Level | AA2: Impact | AB2: Level | AC2: Impact | AD2: Level | AE2: Impact | AR2: Level | AS2: Impact | AT2: Level | AU2: Impact | AV2: Level | AW2: Impact | BJ2: Level | BK2: Impact | BL2: Level | BM2: Impact | BZ2: Level | CA2: Impact | CB2: Level | CC2: Impact | CP2: Level | CQ2: Impact | CR2: Level | CS2: Impact | DF2: Level | DG2: Impact | DH2: Level | DI2: Impact | DV2: Level | DW2: Impact | DX2: Level | DY2: Impact | EL2: Level | EM2: Impact | EN2: Level | EO2: Impact | FB2: Level | FC2: Impact | FD2: Level | FE2: Impact | FR2: Level | FS2: Impact | FT2: Level | FU2: Impact | GH2: Level | GI2: Impact | GJ2: Level | GK2: Impact | GX2: Level | GY2: Impact | GZ2: Level | HA2: Impact | HN2: Level | HO2: Impact | HP2: Level | HQ2: Impact | ID2: Level | IE2: Impact | IF2: Level | IG2: Impact | IT2: Level | IU2: Impact | IV2: Level | IW2: Impact | JJ2: Level | JK2: Impact | JL2: Level | JM2: Impact | JZ2: Level | KA2: Impact | KB2: Level | KC2: Impact | KP2: Level | KQ2: Impact | KR2: Level | KS2: Impact | LF2: Level | LG2: Impact | LH2: Level | LI2: Impact | LV2: Level | LW2: Impact | LX2: Level | LY2: Impact | ML2: Level | MM2: Impact | MN2: Level | MO2: Impact | NB2: Level | NC2: Impact | ND2: Level | NE2: Impact | NR2: Level | NS2: Impact | NT2: Level | NU2: Impact | OH2: Level | OI2: Impact | OJ2: Level | OK2: Impact
O3: Slider 1 | AG3: Slider 2 | AY3: AI Regulatory Sandbox | BO3: Seal for trustworthy AI | CE3: AI talent visa | CU3: AI provisions in trade agreements | DK3: Robot tax | EA3: Train ministry staff | EQ3: Standards for AI Interoperability | FG3: Livelihood Protection Policy | FW3: AI Sovereignty Initiative | GM3: Subsidized GPU Access | HC3: Tax Incentives for AI Adoption | HS3: Initiative 12 | II3: Initiative 13 | IY3: Initiative 14 | JO3: Initiative 15
A4: EcPro | O4: EcSlider1 | P4: 0 | Q4: 0 | R4: 0 | S4: 0 | T4: 0 | U4: 0 | V4: 0 | W4: 0 | X4: 0 | AG4: EcSlider2 | AH4: 0 | AI4: 0 | AJ4: 0 | AK4: 0 | AL4: 0 | AM4: 0 | AN4: 0 | AO4: 0 | AP4: 0 | AY4: EcPro3 | AZ4: 0 | BA4: =+AZ4 -> 0 | BB4: =+BA4 -> 0 | BC4: =+BB4 -> 0 | BD4: =+BC4 -> 0 | BE4: =+BD4 -> 0 | BF4: =+BE4 -> 0 | BG4: =+BF4 -> 0 | BH4: =+BG4 -> 0 | BO4: EcPro4 | BP4: 0 | BQ4: =+BP4 -> 0 | BR4: =+BQ4 -> 0 | BS4: =+BR4 -> 0 | BT4: =+BS4 -> 0 | BU4: =+BT4 -> 0 | BV4: =+BU4 -> 0 | BW4: =+BV4 -> 0 | BX4: =+BW4 -> 0 | CE4: EcPro5 | CF4: 0 | CG4: =+CF4 -> 0 | CH4: =+CG4 -> 0 | CI4: =+CH4 -> 0 | CJ4: =+CI4 -> 0 | CK4: =+CJ4 -> 0 | CL4: =+CK4 -> 0 | CM4: =+CL4 -> 0 | CN4: =+CM4 -> 0 | CU4: EcPro6 | CV4: 0 | CW4: =+CV4 -> 0 | CX4: =+CW4 -> 0 | CY4: =+CX4 -> 0 | CZ4: =+CY4 -> 0 | DA4: =+CZ4 -> 0 | DB4: =+DA4 -> 0 | DC4: =+DB4 -> 0 | DD4: =+DC4 -> 0 | DK4: EcPro7 | DL4: 0 | DM4: =+DL4 -> 0 | DN4: =+DM4 -> 0 | DO4: =+DN4 -> 0 | DP4: =+DO4 -> 0 | DQ4: =+DP4 -> 0 | DR4: =+DQ4 -> 0 | DS4: =+DR4 -> 0 | DT4: =+DS4 -> 0 | EA4: EcPro8 | EB4: 0 | EC4: =+EB4 -> 0 | ED4: =+EC4 -> 0 | EE4: =+ED4 -> 0 | EF4: =+EE4 -> 0 | EG4: =+EF4 -> 0 | EH4: =+EG4 -> 0 | EI4: =+EH4 -> 0 | EJ4: =+EI4 -> 0 | EQ4: EcPro9 | ER4: 0 | ES4: =+ER4 -> 0 | ET4: =+ES4 -> 0 | EU4: =+ET4 -> 0 | EV4: =+EU4 -> 0 | EW4: =+EV4 -> 0 | EX4: =+EW4 -> 0 | EY4: =+EX4 -> 0 | EZ4: =+EY4 -> 0 | FG4: EcPro10 | FH4: 0 | FI4: =+FH4 -> 0 | FJ4: =+FI4 -> 0 | FK4: =+FJ4 -> 0 | FL4: =+FK4 -> 0 | FM4: =+FL4 -> 0 | FN4: =+FM4 -> 0 | FO4: =+FN4 -> 0 | FP4: =+FO4 -> 0 | FW4: EcPro11 | FX4: 0 | FY4: =+FX4 -> 0 | FZ4: =+FY4 -> 0 | GA4: =+FZ4 -> 0 | GB4: =+GA4 -> 0 | GC4: =+GB4 -> 0 | GD4: =+GC4 -> 0 | GE4: =+GD4 -> 0 | GF4: =+GE4 -> 0 | GM4: EcPro12 | GN4: 0 | GO4: =+GN4 -> 0 | GP4: =+GO4 -> 0 | GQ4: =+GP4 -> 0 | GR4: =+GQ4 -> 0 | GS4: =+GR4 -> 0 | GT4: =+GS4 -> 0 | GU4: =+GT4 -> 0 | GV4: =+GU4 -> 0 | HC4: EcPro13 | HD4: 0 | HE4: =+HD4 -> 0 | HF4: =+HE4 -> 0 | HG4: =+HF4 -> 0 | HH4: =+HG4 -> 0 | HI4: =+HH4 -> 0 | HJ4: =+HI4 -> 0 | HK4: =+HJ4 -> 0 | HL4: =+HK4 -> 0 | HS4: EcPro14 | HT4: 0 | HU4: =+HT4 -> 0 | HV4: =+HU4 -> 0 | HW4: =+HV4 -> 0 | HX4: =+HW4 -> 0 | HY4: =+HX4 -> 0 | HZ4: =+HY4 -> 0 | IA4: =+HZ4 -> 0 | IB4: =+IA4 -> 0 | II4: EcPro15 | IJ4: 0 | IK4: =+IJ4 -> 0 | IL4: =+IK4 -> 0 | IM4: =+IL4 -> 0 | IN4: =+IM4 -> 0 | IO4: =+IN4 -> 0 | IP4: =+IO4 -> 0 | IQ4: =+IP4 -> 0 | IR4: =+IQ4 -> 0 | IY4: EcPro16 | IZ4: 0 | JA4: =+IZ4 -> 0 | JB4: =+JA4 -> 0 | JC4: =+JB4 -> 0 | JD4: =+JC4 -> 0 | JE4: =+JD4 -> 0 | JF4: =+JE4 -> 0 | JG4: =+JF4 -> 0 | JH4: =+JG4 -> 0 | JO4: EcPro17 | JP4: 0 | JQ4: =+JP4 -> 0 | JR4: =+JQ4 -> 0 | JS4: =+JR4 -> 0 | JT4: =+JS4 -> 0 | JU4: =+JT4 -> 0 | JV4: =+JU4 -> 0 | JW4: =+JV4 -> 0 | JX4: =+JW4 -> 0 | KE4: EcPro18 | KF4: 0 | KG4: =+KF4 -> 0 | KH4: =+KG4 -> 0 | KI4: =+KH4 -> 0 | KJ4: =+KI4 -> 0 | KK4: =+KJ4 -> 0 | KL4: =+KK4 -> 0 | KM4: =+KL4 -> 0 | KN4: =+KM4 -> 0 | KU4: EcPro19 | KV4: 0 | KW4: =+KV4 -> 0 | KX4: =+KW4 -> 0 | KY4: =+KX4 -> 0 | KZ4: =+KY4 -> 0 | LA4: =+KZ4 -> 0 | LB4: =+LA4 -> 0 | LC4: =+LB4 -> 0 | LD4: =+LC4 -> 0 | LK4: EcPro20 | LL4: 0 | LM4: =+LL4 -> 0 | LN4: =+LM4 -> 0 | LO4: =+LN4 -> 0 | LP4: =+LO4 -> 0 | LQ4: =+LP4 -> 0 | LR4: =+LQ4 -> 0 | LS4: =+LR4 -> 0 | LT4: =+LS4 -> 0 | MA4: EcPro21 | MB4: 0 | MC4: =+MB4 -> 0 | MD4: =+MC4 -> 0 | ME4: =+MD4 -> 0 | MF4: =+ME4 -> 0 | MG4: =+MF4 -> 0 | MH4: =+MG4 -> 0 | MI4: =+MH4 -> 0 | MJ4: =+MI4 -> 0 | MQ4: EcPro22 | MR4: 0 | MS4: =+MR4 -> 0 | MT4: =+MS4 -> 0 | MU4: =+MT4 -> 0 | MV4: =+MU4 -> 0 | MW4: =+MV4 -> 0 | MX4: =+MW4 -> 0 | MY4: =+MX4 -> 0 | MZ4: =+MY4 -> 0 | NG4: EcPro23 | NH4: 0 | NI4: =+NH4 -> 0 | NJ4: =+NI4 -> 0 | NK4: =+NJ4 -> 0 | NL4: =+NK4 -> 0 | NM4: =+NL4 -> 0 | NN4: =+NM4 -> 0 | NO4: =+NN4 -> 0 | NP4: =+NO4 -> 0 | NW4: EcPro24 | NX4: 0 | NY4: =+NX4 -> 0 | NZ4: =+NY4 -> 0 | OA4: =+NZ4 -> 0 | OB4: =+OA4 -> 0 | OC4: =+OB4 -> 0 | OD4: =+OC4 -> 0 | OE4: =+OD4 -> 0 | OF4: =+OE4 -> 0
A5: EcProDone | O5: EcSlider1LastYear | P5: 0 | Q5: =P4 -> 0 | R5: =Q4 -> 0 | S5: =R4 -> 0 | T5: =S4 -> 0 | U5: =T4 -> 0 | V5: =U4 -> 0 | W5: =V4 -> 0 | X5: =W4 -> 0 | AG5: EcSlider2LastYear | AH5: 0 | AI5: =AH4 -> 0 | AJ5: =AI4 -> 0 | AK5: =AJ4 -> 0 | AL5: =AK4 -> 0 | AM5: =AL4 -> 0 | AN5: =AM4 -> 0 | AO5: =AN4 -> 0 | AP5: =AO4 -> 0 | AY5: EcPro3Done | AZ5: =AZ4 -> 0 | BA5: =IF(AZ5=1,1,BA4) -> 0 | BB5: =IF(BA5=1,1,BB4) -> 0 | BC5: =IF(BB5=1,1,BC4) -> 0 | BD5: =IF(BC5=1,1,BD4) -> 0 | BE5: =IF(BD5=1,1,BE4) -> 0 | BF5: =IF(BE5=1,1,BF4) -> 0 | BG5: =IF(BF5=1,1,BG4) -> 0 | BH5: =IF(BG5=1,1,BH4) -> 0 | BO5: EcPro4Done | BP5: =BP4 -> 0 | BQ5: =IF(BP5=1,1,BQ4) -> 0 | BR5: =IF(BQ5=1,1,BR4) -> 0 | BS5: =IF(BR5=1,1,BS4) -> 0 | BT5: =IF(BS5=1,1,BT4) -> 0 | BU5: =IF(BT5=1,1,BU4) -> 0 | BV5: =IF(BU5=1,1,BV4) -> 0 | BW5: =IF(BV5=1,1,BW4) -> 0 | BX5: =IF(BW5=1,1,BX4) -> 0 | CE5: EcPro5Done | CF5: =CF4 -> 0 | CG5: =IF(CF5=1,1,CG4) -> 0 | CH5: =IF(CG5=1,1,CH4) -> 0 | CI5: =IF(CH5=1,1,CI4) -> 0 | CJ5: =IF(CI5=1,1,CJ4) -> 0 | CK5: =IF(CJ5=1,1,CK4) -> 0 | CL5: =IF(CK5=1,1,CL4) -> 0 | CM5: =IF(CL5=1,1,CM4) -> 0 | CN5: =IF(CM5=1,1,CN4) -> 0 | CU5: EcPro6Done | CV5: =CV4 -> 0 | CW5: =IF(CV5=1,1,CW4) -> 0 | CX5: =IF(CW5=1,1,CX4) -> 0 | CY5: =IF(CX5=1,1,CY4) -> 0 | CZ5: =IF(CY5=1,1,CZ4) -> 0 | DA5: =IF(CZ5=1,1,DA4) -> 0 | DB5: =IF(DA5=1,1,DB4) -> 0 | DC5: =IF(DB5=1,1,DC4) -> 0 | DD5: =IF(DC5=1,1,DD4) -> 0 | DK5: EcPro7Done | DL5: =DL4 -> 0 | DM5: =IF(DL5=1,1,DM4) -> 0 | DN5: =IF(DM5=1,1,DN4) -> 0 | DO5: =IF(DN5=1,1,DO4) -> 0 | DP5: =IF(DO5=1,1,DP4) -> 0 | DQ5: =IF(DP5=1,1,DQ4) -> 0 | DR5: =IF(DQ5=1,1,DR4) -> 0 | DS5: =IF(DR5=1,1,DS4) -> 0 | DT5: =IF(DS5=1,1,DT4) -> 0 | EA5: EcPro8Done | EB5: =EB4 -> 0 | EC5: =IF(EB5=1,1,EC4) -> 0 | ED5: =IF(EC5=1,1,ED4) -> 0 | EE5: =IF(ED5=1,1,EE4) -> 0 | EF5: =IF(EE5=1,1,EF4) -> 0 | EG5: =IF(EF5=1,1,EG4) -> 0 | EH5: =IF(EG5=1,1,EH4) -> 0 | EI5: =IF(EH5=1,1,EI4) -> 0 | EJ5: =IF(EI5=1,1,EJ4) -> 0 | EQ5: EcPro9Done | ER5: =ER4 -> 0 | ES5: =IF(ER5=1,1,ES4) -> 0 | ET5: =IF(ES5=1,1,ET4) -> 0 | EU5: =IF(ET5=1,1,EU4) -> 0 | EV5: =IF(EU5=1,1,EV4) -> 0 | EW5: =IF(EV5=1,1,EW4) -> 0 | EX5: =IF(EW5=1,1,EX4) -> 0 | EY5: =IF(EX5=1,1,EY4) -> 0 | EZ5: =IF(EY5=1,1,EZ4) -> 0 | FG5: EcPro10Done | FH5: =FH4 -> 0 | FI5: =IF(FH5=1,1,FI4) -> 0 | FJ5: =IF(FI5=1,1,FJ4) -> 0 | FK5: =IF(FJ5=1,1,FK4) -> 0 | FL5: =IF(FK5=1,1,FL4) -> 0 | FM5: =IF(FL5=1,1,FM4) -> 0 | FN5: =IF(FM5=1,1,FN4) -> 0 | FO5: =IF(FN5=1,1,FO4) -> 0 | FP5: =IF(FO5=1,1,FP4) -> 0 | FW5: EcPro11Done | FX5: =FX4 -> 0 | FY5: =IF(FX5=1,1,FY4) -> 0 | FZ5: =IF(FY5=1,1,FZ4) -> 0 | GA5: =IF(FZ5=1,1,GA4) -> 0 | GB5: =IF(GA5=1,1,GB4) -> 0 | GC5: =IF(GB5=1,1,GC4) -> 0 | GD5: =IF(GC5=1,1,GD4) -> 0 | GE5: =IF(GD5=1,1,GE4) -> 0 | GF5: =IF(GE5=1,1,GF4) -> 0 | GM5: EcPro12Done | GN5: =GN4 -> 0 | GO5: =IF(GN5=1,1,GO4) -> 0 | GP5: =IF(GO5=1,1,GP4) -> 0 | GQ5: =IF(GP5=1,1,GQ4) -> 0 | GR5: =IF(GQ5=1,1,GR4) -> 0 | GS5: =IF(GR5=1,1,GS4) -> 0 | GT5: =IF(GS5=1,1,GT4) -> 0 | GU5: =IF(GT5=1,1,GU4) -> 0 | GV5: =IF(GU5=1,1,GV4) -> 0 | HC5: EcPro13Done | HD5: =HD4 -> 0 | HE5: =IF(HD5=1,1,HE4) -> 0 | HF5: =IF(HE5=1,1,HF4) -> 0 | HG5: =IF(HF5=1,1,HG4) -> 0 | HH5: =IF(HG5=1,1,HH4) -> 0 | HI5: =IF(HH5=1,1,HI4) -> 0 | HJ5: =IF(HI5=1,1,HJ4) -> 0 | HK5: =IF(HJ5=1,1,HK4) -> 0 | HL5: =IF(HK5=1,1,HL4) -> 0 | HS5: EcPro14Done | HT5: =HT4 -> 0 | HU5: =IF(HT5=1,1,HU4) -> 0 | HV5: =IF(HU5=1,1,HV4) -> 0 | HW5: =IF(HV5=1,1,HW4) -> 0 | HX5: =IF(HW5=1,1,HX4) -> 0 | HY5: =IF(HX5=1,1,HY4) -> 0 | HZ5: =IF(HY5=1,1,HZ4) -> 0 | IA5: =IF(HZ5=1,1,IA4) -> 0 | IB5: =IF(IA5=1,1,IB4) -> 0 | II5: EcPro15Done | IJ5: =IJ4 -> 0 | IK5: =IF(IJ5=1,1,IK4) -> 0 | IL5: =IF(IK5=1,1,IL4) -> 0 | IM5: =IF(IL5=1,1,IM4) -> 0 | IN5: =IF(IM5=1,1,IN4) -> 0 | IO5: =IF(IN5=1,1,IO4) -> 0 | IP5: =IF(IO5=1,1,IP4) -> 0 | IQ5: =IF(IP5=1,1,IQ4) -> 0 | IR5: =IF(IQ5=1,1,IR4) -> 0 | IY5: EcPro16Done | IZ5: =IZ4 -> 0 | JA5: =IF(IZ5=1,1,JA4) -> 0 | JB5: =IF(JA5=1,1,JB4) -> 0 | JC5: =IF(JB5=1,1,JC4) -> 0 | JD5: =IF(JC5=1,1,JD4) -> 0 | JE5: =IF(JD5=1,1,JE4) -> 0 | JF5: =IF(JE5=1,1,JF4) -> 0 | JG5: =IF(JF5=1,1,JG4) -> 0 | JH5: =IF(JG5=1,1,JH4) -> 0 | JO5: EcPro17Done | JP5: =JP4 -> 0 | JQ5: =IF(JP5=1,1,JQ4) -> 0 | JR5: =IF(JQ5=1,1,JR4) -> 0 | JS5: =IF(JR5=1,1,JS4) -> 0 | JT5: =IF(JS5=1,1,JT4) -> 0 | JU5: =IF(JT5=1,1,JU4) -> 0 | JV5: =IF(JU5=1,1,JV4) -> 0 | JW5: =IF(JV5=1,1,JW4) -> 0 | JX5: =IF(JW5=1,1,JX4) -> 0 | KE5: EcPro18Done | KF5: =KF4 -> 0 | KG5: =IF(KF5=1,1,KG4) -> 0 | KH5: =IF(KG5=1,1,KH4) -> 0 | KI5: =IF(KH5=1,1,KI4) -> 0 | KJ5: =IF(KI5=1,1,KJ4) -> 0 | KK5: =IF(KJ5=1,1,KK4) -> 0 | KL5: =IF(KK5=1,1,KL4) -> 0 | KM5: =IF(KL5=1,1,KM4) -> 0 | KN5: =IF(KM5=1,1,KN4) -> 0 | KU5: EcPro19Done | KV5: =KV4 -> 0 | KW5: =IF(KV5=1,1,KW4) -> 0 | KX5: =IF(KW5=1,1,KX4) -> 0 | KY5: =IF(KX5=1,1,KY4) -> 0 | KZ5: =IF(KY5=1,1,KZ4) -> 0 | LA5: =IF(KZ5=1,1,LA4) -> 0 | LB5: =IF(LA5=1,1,LB4) -> 0 | LC5: =IF(LB5=1,1,LC4) -> 0 | LD5: =IF(LC5=1,1,LD4) -> 0 | LK5: EcPro20Done | LL5: =LL4 -> 0 | LM5: =IF(LL5=1,1,LM4) -> 0 | LN5: =IF(LM5=1,1,LN4) -> 0 | LO5: =IF(LN5=1,1,LO4) -> 0 | LP5: =IF(LO5=1,1,LP4) -> 0 | LQ5: =IF(LP5=1,1,LQ4) -> 0 | LR5: =IF(LQ5=1,1,LR4) -> 0 | LS5: =IF(LR5=1,1,LS4) -> 0 | LT5: =IF(LS5=1,1,LT4) -> 0 | MA5: EcPro21Done | MB5: =MB4 -> 0 | MC5: =IF(MB5=1,1,MC4) -> 0 | MD5: =IF(MC5=1,1,MD4) -> 0 | ME5: =IF(MD5=1,1,ME4) -> 0 | MF5: =IF(ME5=1,1,MF4) -> 0 | MG5: =IF(MF5=1,1,MG4) -> 0 | MH5: =IF(MG5=1,1,MH4) -> 0 | MI5: =IF(MH5=1,1,MI4) -> 0 | MJ5: =IF(MI5=1,1,MJ4) -> 0 | MQ5: EcPro22Done | MR5: =MR4 -> 0 | MS5: =IF(MR5=1,1,MS4) -> 0 | MT5: =IF(MS5=1,1,MT4) -> 0 | MU5: =IF(MT5=1,1,MU4) -> 0 | MV5: =IF(MU5=1,1,MV4) -> 0 | MW5: =IF(MV5=1,1,MW4) -> 0 | MX5: =IF(MW5=1,1,MX4) -> 0 | MY5: =IF(MX5=1,1,MY4) -> 0 | MZ5: =IF(MY5=1,1,MZ4) -> 0 | NG5: EcPro23Done | NH5: =NH4 -> 0 | NI5: =IF(NH5=1,1,NI4) -> 0 | NJ5: =IF(NI5=1,1,NJ4) -> 0 | NK5: =IF(NJ5=1,1,NK4) -> 0 | NL5: =IF(NK5=1,1,NL4) -> 0 | NM5: =IF(NL5=1,1,NM4) -> 0 | NN5: =IF(NM5=1,1,NN4) -> 0 | NO5: =IF(NN5=1,1,NO4) -> 0 | NP5: =IF(NO5=1,1,NP4) -> 0 | NW5: EcPro24Done | NX5: =NX4 -> 0 | NY5: =IF(NX5=1,1,NY4) -> 0 | NZ5: =IF(NY5=1,1,NZ4) -> 0 | OA5: =IF(NZ5=1,1,OA4) -> 0 | OB5: =IF(OA5=1,1,OB4) -> 0 | OC5: =IF(OB5=1,1,OC4) -> 0 | OD5: =IF(OC5=1,1,OD4) -> 0 | OE5: =IF(OD5=1,1,OE4) -> 0 | OF5: =IF(OE5=1,1,OF4) -> 0
A6: EcProShow | O6: EcSlider1Cost | P6: =_xlfn.XLOOKUP(P4,'KPI Impacts'!$T$2:$W$2,'KPI Impacts'!$T$63:$W$63) -> 0 | Q6: =_xlfn.XLOOKUP(Q4,'KPI Impacts'!$T$2:$W$2,'KPI Impacts'!$T$63:$W$63) -> 0 | R6: =_xlfn.XLOOKUP(R4,'KPI Impacts'!$T$2:$W$2,'KPI Impacts'!$T$63:$W$63) -> 0 | S6: =_xlfn.XLOOKUP(S4,'KPI Impacts'!$T$2:$W$2,'KPI Impacts'!$T$63:$W$63) -> 0 | T6: =_xlfn.XLOOKUP(T4,'KPI Impacts'!$T$2:$W$2,'KPI Impacts'!$T$63:$W$63) -> 0 | U6: =_xlfn.XLOOKUP(U4,'KPI Impacts'!$T$2:$W$2,'KPI Impacts'!$T$63:$W$63) -> 0 | V6: =_xlfn.XLOOKUP(V4,'KPI Impacts'!$T$2:$W$2,'KPI Impacts'!$T$63:$W$63) -> 0 | W6: =_xlfn.XLOOKUP(W4,'KPI Impacts'!$T$2:$W$2,'KPI Impacts'!$T$63:$W$63) -> 0 | X6: =_xlfn.XLOOKUP(X4,'KPI Impacts'!$T$2:$W$2,'KPI Impacts'!$T$63:$W$63) -> 0 | AG6: EcSlider2Cost | AH6: =_xlfn.XLOOKUP(AH4,'KPI Impacts'!$T$2:$W$2,'KPI Impacts'!$T$63:$W$63) -> 0 | AI6: =_xlfn.XLOOKUP(AI4,'KPI Impacts'!$T$2:$W$2,'KPI Impacts'!$T$63:$W$63) -> 0 | AJ6: =_xlfn.XLOOKUP(AJ4,'KPI Impacts'!$T$2:$W$2,'KPI Impacts'!$T$63:$W$63) -> 0 | AK6: =_xlfn.XLOOKUP(AK4,'KPI Impacts'!$T$2:$W$2,'KPI Impacts'!$T$63:$W$63) -> 0 | AL6: =_xlfn.XLOOKUP(AL4,'KPI Impacts'!$T$2:$W$2,'KPI Impacts'!$T$63:$W$63) -> 0 | AM6: =_xlfn.XLOOKUP(AM4,'KPI Impacts'!$T$2:$W$2,'KPI Impacts'!$T$63:$W$63) -> 0 | AN6: =_xlfn.XLOOKUP(AN4,'KPI Impacts'!$T$2:$W$2,'KPI Impacts'!$T$63:$W$63) -> 0 | AO6: =_xlfn.XLOOKUP(AO4,'KPI Impacts'!$T$2:$W$2,'KPI Impacts'!$T$63:$W$63) -> 0 | AP6: =_xlfn.XLOOKUP(AP4,'KPI Impacts'!$T$2:$W$2,'KPI Impacts'!$T$63:$W$63) -> 0 | AY6: EcPro3Show | AZ6: 0 | BA6: =IF(AND(AZ4=1,AZ5=1),1,IF(AND(AZ4=0,AZ5=1),3,0)) -> 0 | BB6: =IF(AND(BA4=1,BA5=1),1,IF(AND(BA4=0,BA5=1),3,0)) -> 0 | BC6: =IF(AND(BB4=1,BB5=1),1,IF(AND(BB4=0,BB5=1),3,0)) -> 0 | BD6: =IF(AND(BC4=1,BC5=1),1,IF(AND(BC4=0,BC5=1),3,0)) -> 0 | BE6: =IF(AND(BD4=1,BD5=1),1,IF(AND(BD4=0,BD5=1),3,0)) -> 0 | BF6: =IF(AND(BE4=1,BE5=1),1,IF(AND(BE4=0,BE5=1),3,0)) -> 0 | BG6: =IF(AND(BF4=1,BF5=1),1,IF(AND(BF4=0,BF5=1),3,0)) -> 0 | BH6: =IF(AND(BG4=1,BG5=1),1,IF(AND(BG4=0,BG5=1),3,0)) -> 0 | BO6: EcPro4Show | BP6: 0 | BQ6: =IF(AND(BP4=1,BP5=1),1,IF(AND(BP4=0,BP5=1),3,0)) -> 0 | BR6: =IF(AND(BQ4=1,BQ5=1),1,IF(AND(BQ4=0,BQ5=1),3,0)) -> 0 | BS6: =IF(AND(BR4=1,BR5=1),1,IF(AND(BR4=0,BR5=1),3,0)) -> 0 | BT6: =IF(AND(BS4=1,BS5=1),1,IF(AND(BS4=0,BS5=1),3,0)) -> 0 | BU6: =IF(AND(BT4=1,BT5=1),1,IF(AND(BT4=0,BT5=1),3,0)) -> 0 | BV6: =IF(AND(BU4=1,BU5=1),1,IF(AND(BU4=0,BU5=1),3,0)) -> 0 | BW6: =IF(AND(BV4=1,BV5=1),1,IF(AND(BV4=0,BV5=1),3,0)) -> 0 | BX6: =IF(AND(BW4=1,BW5=1),1,IF(AND(BW4=0,BW5=1),3,0)) -> 0 | CE6: EcPro5Show | CF6: 0 | CG6: =IF(AND(CF4=1,CF5=1),1,IF(AND(CF4=0,CF5=1),3,0)) -> 0 | CH6: =IF(AND(CG4=1,CG5=1),1,IF(AND(CG4=0,CG5=1),3,0)) -> 0 | CI6: =IF(AND(CH4=1,CH5=1),1,IF(AND(CH4=0,CH5=1),3,0)) -> 0 | CJ6: =IF(AND(CI4=1,CI5=1),1,IF(AND(CI4=0,CI5=1),3,0)) -> 0 | CK6: =IF(AND(CJ4=1,CJ5=1),1,IF(AND(CJ4=0,CJ5=1),3,0)) -> 0 | CL6: =IF(AND(CK4=1,CK5=1),1,IF(AND(CK4=0,CK5=1),3,0)) -> 0 | CM6: =IF(AND(CL4=1,CL5=1),1,IF(AND(CL4=0,CL5=1),3,0)) -> 0 | CN6: =IF(AND(CM4=1,CM5=1),1,IF(AND(CM4=0,CM5=1),3,0)) -> 0 | CU6: EcPro6Show | CV6: 0 | CW6: =IF(AND(CV4=1,CV5=1),1,IF(AND(CV4=0,CV5=1),3,0)) -> 0 | CX6: =IF(AND(CW4=1,CW5=1),1,IF(AND(CW4=0,CW5=1),3,0)) -> 0 | CY6: =IF(AND(CX4=1,CX5=1),1,IF(AND(CX4=0,CX5=1),3,0)) -> 0 | CZ6: =IF(AND(CY4=1,CY5=1),1,IF(AND(CY4=0,CY5=1),3,0)) -> 0 | DA6: =IF(AND(CZ4=1,CZ5=1),1,IF(AND(CZ4=0,CZ5=1),3,0)) -> 0 | DB6: =IF(AND(DA4=1,DA5=1),1,IF(AND(DA4=0,DA5=1),3,0)) -> 0 | DC6: =IF(AND(DB4=1,DB5=1),1,IF(AND(DB4=0,DB5=1),3,0)) -> 0 | DD6: =IF(AND(DC4=1,DC5=1),1,IF(AND(DC4=0,DC5=1),3,0)) -> 0 | DK6: EcPro7Show | DL6: 2 | DM6: 2 | DN6: =IF(AND(DM4=1,DM5=1),1,IF(AND(DM4=0,DM5=1),3,0)) -> 0 | DO6: =IF(AND(DN4=1,DN5=1),1,IF(AND(DN4=0,DN5=1),3,0)) -> 0 | DP6: =IF(AND(DO4=1,DO5=1),1,IF(AND(DO4=0,DO5=1),3,0)) -> 0 | DQ6: =IF(AND(DP4=1,DP5=1),1,IF(AND(DP4=0,DP5=1),3,0)) -> 0 | DR6: =IF(AND(DQ4=1,DQ5=1),1,IF(AND(DQ4=0,DQ5=1),3,0)) -> 0 | DS6: =IF(AND(DR4=1,DR5=1),1,IF(AND(DR4=0,DR5=1),3,0)) -> 0 | DT6: =IF(AND(DS4=1,DS5=1),1,IF(AND(DS4=0,DS5=1),3,0)) -> 0 | EA6: EcPro8Show | EB6: 2 | EC6: 2 | ED6: =IF(AND(EC4=1,EC5=1),1,IF(AND(EC4=0,EC5=1),3,0)) -> 0 | EE6: =IF(AND(ED4=1,ED5=1),1,IF(AND(ED4=0,ED5=1),3,0)) -> 0 | EF6: =IF(AND(EE4=1,EE5=1),1,IF(AND(EE4=0,EE5=1),3,0)) -> 0 | EG6: =IF(AND(EF4=1,EF5=1),1,IF(AND(EF4=0,EF5=1),3,0)) -> 0 | EH6: =IF(AND(EG4=1,EG5=1),1,IF(AND(EG4=0,EG5=1),3,0)) -> 0 | EI6: =IF(AND(EH4=1,EH5=1),1,IF(AND(EH4=0,EH5=1),3,0)) -> 0 | EJ6: =IF(AND(EI4=1,EI5=1),1,IF(AND(EI4=0,EI5=1),3,0)) -> 0 | EQ6: EcPro9Show | ER6: 2 | ES6: 2 | ET6: 2 | EU6: =IF(AND(ET4=1,ET5=1),1,IF(AND(ET4=0,ET5=1),3,0)) -> 0 | EV6: =IF(AND(EU4=1,EU5=1),1,IF(AND(EU4=0,EU5=1),3,0)) -> 0 | EW6: =IF(AND(EV4=1,EV5=1),1,IF(AND(EV4=0,EV5=1),3,0)) -> 0 | EX6: =IF(AND(EW4=1,EW5=1),1,IF(AND(EW4=0,EW5=1),3,0)) -> 0 | EY6: =IF(AND(EX4=1,EX5=1),1,IF(AND(EX4=0,EX5=1),3,0)) -> 0 | EZ6: =IF(AND(EY4=1,EY5=1),1,IF(AND(EY4=0,EY5=1),3,0)) -> 0 | FG6: EcPro10Show | FH6: 2 | FI6: 2 | FJ6: 2 | FK6: =IF(AND(FJ4=1,FJ5=1),1,IF(AND(FJ4=0,FJ5=1),3,0)) -> 0 | FL6: =IF(AND(FK4=1,FK5=1),1,IF(AND(FK4=0,FK5=1),3,0)) -> 0 | FM6: =IF(AND(FL4=1,FL5=1),1,IF(AND(FL4=0,FL5=1),3,0)) -> 0 | FN6: =IF(AND(FM4=1,FM5=1),1,IF(AND(FM4=0,FM5=1),3,0)) -> 0 | FO6: =IF(AND(FN4=1,FN5=1),1,IF(AND(FN4=0,FN5=1),3,0)) -> 0 | FP6: =IF(AND(FO4=1,FO5=1),1,IF(AND(FO4=0,FO5=1),3,0)) -> 0 | FW6: EcPro11Show | FX6: 2 | FY6: 2 | FZ6: 2 | GA6: 2 | GB6: =IF(AND(GA4=1,GA5=1),1,IF(AND(GA4=0,GA5=1),3,0)) -> 0 | GC6: =IF(AND(GB4=1,GB5=1),1,IF(AND(GB4=0,GB5=1),3,0)) -> 0 | GD6: =IF(AND(GC4=1,GC5=1),1,IF(AND(GC4=0,GC5=1),3,0)) -> 0 | GE6: =IF(AND(GD4=1,GD5=1),1,IF(AND(GD4=0,GD5=1),3,0)) -> 0 | GF6: =IF(AND(GE4=1,GE5=1),1,IF(AND(GE4=0,GE5=1),3,0)) -> 0 | GM6: EcPro12Show | GN6: 2 | GO6: 2 | GP6: 2 | GQ6: 2 | GR6: =IF(AND(GQ4=1,GQ5=1),1,IF(AND(GQ4=0,GQ5=1),3,0)) -> 0 | GS6: =IF(AND(GR4=1,GR5=1),1,IF(AND(GR4=0,GR5=1),3,0)) -> 0 | GT6: =IF(AND(GS4=1,GS5=1),1,IF(AND(GS4=0,GS5=1),3,0)) -> 0 | GU6: =IF(AND(GT4=1,GT5=1),1,IF(AND(GT4=0,GT5=1),3,0)) -> 0 | GV6: =IF(AND(GU4=1,GU5=1),1,IF(AND(GU4=0,GU5=1),3,0)) -> 0 | HC6: EcPro13Show | HD6: 2 | HE6: 2 | HF6: 2 | HG6: 2 | HH6: 2 | HI6: =IF(AND(HH4=1,HH5=1),1,IF(AND(HH4=0,HH5=1),3,0)) -> 0 | HJ6: =IF(AND(HI4=1,HI5=1),1,IF(AND(HI4=0,HI5=1),3,0)) -> 0 | HK6: =IF(AND(HJ4=1,HJ5=1),1,IF(AND(HJ4=0,HJ5=1),3,0)) -> 0 | HL6: =IF(AND(HK4=1,HK5=1),1,IF(AND(HK4=0,HK5=1),3,0)) -> 0 | HS6: EcPro14Show | HT6: 2 | HU6: 2 | HV6: 2 | HW6: =IF(AND(HV4=1,HV5=1),1,IF(AND(HV4=0,HV5=1),3,0)) -> 0 | HX6: =IF(AND(HW4=1,HW5=1),1,IF(AND(HW4=0,HW5=1),3,0)) -> 0 | HY6: =IF(AND(HX4=1,HX5=1),1,IF(AND(HX4=0,HX5=1),3,0)) -> 0 | HZ6: =IF(AND(HY4=1,HY5=1),1,IF(AND(HY4=0,HY5=1),3,0)) -> 0 | IA6: =IF(AND(HZ4=1,HZ5=1),1,IF(AND(HZ4=0,HZ5=1),3,0)) -> 0 | IB6: =IF(AND(IA4=1,IA5=1),1,IF(AND(IA4=0,IA5=1),3,0)) -> 0 | II6: EcPro15Show | IJ6: 2 | IK6: 2 | IL6: 2 | IM6: =IF(AND(IL4=1,IL5=1),1,IF(AND(IL4=0,IL5=1),3,0)) -> 0 | IN6: =IF(AND(IM4=1,IM5=1),1,IF(AND(IM4=0,IM5=1),3,0)) -> 0 | IO6: =IF(AND(IN4=1,IN5=1),1,IF(AND(IN4=0,IN5=1),3,0)) -> 0 | IP6: =IF(AND(IO4=1,IO5=1),1,IF(AND(IO4=0,IO5=1),3,0)) -> 0 | IQ6: =IF(AND(IP4=1,IP5=1),1,IF(AND(IP4=0,IP5=1),3,0)) -> 0 | IR6: =IF(AND(IQ4=1,IQ5=1),1,IF(AND(IQ4=0,IQ5=1),3,0)) -> 0 | IY6: EcPro16Show | IZ6: 2 | JA6: 2 | JB6: 2 | JC6: 2 | JD6: =IF(AND(JC4=1,JC5=1),1,IF(AND(JC4=0,JC5=1),3,0)) -> 0 | JE6: =IF(AND(JD4=1,JD5=1),1,IF(AND(JD4=0,JD5=1),3,0)) -> 0 | JF6: =IF(AND(JE4=1,JE5=1),1,IF(AND(JE4=0,JE5=1),3,0)) -> 0 | JG6: =IF(AND(JF4=1,JF5=1),1,IF(AND(JF4=0,JF5=1),3,0)) -> 0 | JH6: =IF(AND(JG4=1,JG5=1),1,IF(AND(JG4=0,JG5=1),3,0)) -> 0 | JO6: EcPro17Show | JP6: 2 | JQ6: 2 | JR6: 2 | JS6: 2 | JT6: =IF(AND(JS4=1,JS5=1),1,IF(AND(JS4=0,JS5=1),3,0)) -> 0 | JU6: =IF(AND(JT4=1,JT5=1),1,IF(AND(JT4=0,JT5=1),3,0)) -> 0 | JV6: =IF(AND(JU4=1,JU5=1),1,IF(AND(JU4=0,JU5=1),3,0)) -> 0 | JW6: =IF(AND(JV4=1,JV5=1),1,IF(AND(JV4=0,JV5=1),3,0)) -> 0 | JX6: =IF(AND(JW4=1,JW5=1),1,IF(AND(JW4=0,JW5=1),3,0)) -> 0 | KE6: EcPro18Show | KF6: 0 | KG6: =IF(AND(KF4=1,KF5=1),1,IF(AND(KF4=0,KF5=1),3,0)) -> 0 | KH6: =IF(AND(KG4=1,KG5=1),1,IF(AND(KG4=0,KG5=1),3,0)) -> 0 | KI6: =IF(AND(KH4=1,KH5=1),1,IF(AND(KH4=0,KH5=1),3,0)) -> 0 | KJ6: =IF(AND(KI4=1,KI5=1),1,IF(AND(KI4=0,KI5=1),3,0)) -> 0 | KK6: =IF(AND(KJ4=1,KJ5=1),1,IF(AND(KJ4=0,KJ5=1),3,0)) -> 0 | KL6: =IF(AND(KK4=1,KK5=1),1,IF(AND(KK4=0,KK5=1),3,0)) -> 0 | KM6: =IF(AND(KL4=1,KL5=1),1,IF(AND(KL4=0,KL5=1),3,0)) -> 0 | KN6: =IF(AND(KM4=1,KM5=1),1,IF(AND(KM4=0,KM5=1),3,0)) -> 0 | KU6: EcPro19Show | KV6: 0 | KW6: =IF(AND(KV4=1,KV5=1),1,IF(AND(KV4=0,KV5=1),3,0)) -> 0 | KX6: =IF(AND(KW4=1,KW5=1),1,IF(AND(KW4=0,KW5=1),3,0)) -> 0 | KY6: =IF(AND(KX4=1,KX5=1),1,IF(AND(KX4=0,KX5=1),3,0)) -> 0 | KZ6: =IF(AND(KY4=1,KY5=1),1,IF(AND(KY4=0,KY5=1),3,0)) -> 0 | LA6: =IF(AND(KZ4=1,KZ5=1),1,IF(AND(KZ4=0,KZ5=1),3,0)) -> 0 | LB6: =IF(AND(LA4=1,LA5=1),1,IF(AND(LA4=0,LA5=1),3,0)) -> 0 | LC6: =IF(AND(LB4=1,LB5=1),1,IF(AND(LB4=0,LB5=1),3,0)) -> 0 | LD6: =IF(AND(LC4=1,LC5=1),1,IF(AND(LC4=0,LC5=1),3,0)) -> 0 | LK6: EcPro20Show | LL6: 0 | LM6: =IF(AND(LL4=1,LL5=1),1,IF(AND(LL4=0,LL5=1),3,0)) -> 0 | LN6: =IF(AND(LM4=1,LM5=1),1,IF(AND(LM4=0,LM5=1),3,0)) -> 0 | LO6: =IF(AND(LN4=1,LN5=1),1,IF(AND(LN4=0,LN5=1),3,0)) -> 0 | LP6: =IF(AND(LO4=1,LO5=1),1,IF(AND(LO4=0,LO5=1),3,0)) -> 0 | LQ6: =IF(AND(LP4=1,LP5=1),1,IF(AND(LP4=0,LP5=1),3,0)) -> 0 | LR6: =IF(AND(LQ4=1,LQ5=1),1,IF(AND(LQ4=0,LQ5=1),3,0)) -> 0 | LS6: =IF(AND(LR4=1,LR5=1),1,IF(AND(LR4=0,LR5=1),3,0)) -> 0 | LT6: =IF(AND(LS4=1,LS5=1),1,IF(AND(LS4=0,LS5=1),3,0)) -> 0 | MA6: EcPro21Show | MB6: 0 | MC6: =IF(AND(MB4=1,MB5=1),1,IF(AND(MB4=0,MB5=1),3,0)) -> 0 | MD6: =IF(AND(MC4=1,MC5=1),1,IF(AND(MC4=0,MC5=1),3,0)) -> 0 | ME6: =IF(AND(MD4=1,MD5=1),1,IF(AND(MD4=0,MD5=1),3,0)) -> 0 | MF6: =IF(AND(ME4=1,ME5=1),1,IF(AND(ME4=0,ME5=1),3,0)) -> 0 | MG6: =IF(AND(MF4=1,MF5=1),1,IF(AND(MF4=0,MF5=1),3,0)) -> 0 | MH6: =IF(AND(MG4=1,MG5=1),1,IF(AND(MG4=0,MG5=1),3,0)) -> 0 | MI6: =IF(AND(MH4=1,MH5=1),1,IF(AND(MH4=0,MH5=1),3,0)) -> 0 | MJ6: =IF(AND(MI4=1,MI5=1),1,IF(AND(MI4=0,MI5=1),3,0)) -> 0 | MQ6: EcPro22Show | MR6: 0 | MS6: =IF(AND(MR4=1,MR5=1),1,IF(AND(MR4=0,MR5=1),3,0)) -> 0 | MT6: =IF(AND(MS4=1,MS5=1),1,IF(AND(MS4=0,MS5=1),3,0)) -> 0 | MU6: =IF(AND(MT4=1,MT5=1),1,IF(AND(MT4=0,MT5=1),3,0)) -> 0 | MV6: =IF(AND(MU4=1,MU5=1),1,IF(AND(MU4=0,MU5=1),3,0)) -> 0 | MW6: =IF(AND(MV4=1,MV5=1),1,IF(AND(MV4=0,MV5=1),3,0)) -> 0 | MX6: =IF(AND(MW4=1,MW5=1),1,IF(AND(MW4=0,MW5=1),3,0)) -> 0 | MY6: =IF(AND(MX4=1,MX5=1),1,IF(AND(MX4=0,MX5=1),3,0)) -> 0 | MZ6: =IF(AND(MY4=1,MY5=1),1,IF(AND(MY4=0,MY5=1),3,0)) -> 0 | NG6: EcPro23Show | NH6: 0 | NI6: =IF(AND(NH4=1,NH5=1),1,IF(AND(NH4=0,NH5=1),3,0)) -> 0 | NJ6: =IF(AND(NI4=1,NI5=1),1,IF(AND(NI4=0,NI5=1),3,0)) -> 0 | NK6: =IF(AND(NJ4=1,NJ5=1),1,IF(AND(NJ4=0,NJ5=1),3,0)) -> 0 | NL6: =IF(AND(NK4=1,NK5=1),1,IF(AND(NK4=0,NK5=1),3,0)) -> 0 | NM6: =IF(AND(NL4=1,NL5=1),1,IF(AND(NL4=0,NL5=1),3,0)) -> 0 | NN6: =IF(AND(NM4=1,NM5=1),1,IF(AND(NM4=0,NM5=1),3,0)) -> 0 | NO6: =IF(AND(NN4=1,NN5=1),1,IF(AND(NN4=0,NN5=1),3,0)) -> 0 | NP6: =IF(AND(NO4=1,NO5=1),1,IF(AND(NO4=0,NO5=1),3,0)) -> 0 | NW6: EcPro24Show | NX6: 0 | NY6: =IF(AND(NX4=1,NX5=1),1,IF(AND(NX4=0,NX5=1),3,0)) -> 0 | NZ6: =IF(AND(NY4=1,NY5=1),1,IF(AND(NY4=0,NY5=1),3,0)) -> 0 | OA6: =IF(AND(NZ4=1,NZ5=1),1,IF(AND(NZ4=0,NZ5=1),3,0)) -> 0 | OB6: =IF(AND(OA4=1,OA5=1),1,IF(AND(OA4=0,OA5=1),3,0)) -> 0 | OC6: =IF(AND(OB4=1,OB5=1),1,IF(AND(OB4=0,OB5=1),3,0)) -> 0 | OD6: =IF(AND(OC4=1,OC5=1),1,IF(AND(OC4=0,OC5=1),3,0)) -> 0 | OE6: =IF(AND(OD4=1,OD5=1),1,IF(AND(OD4=0,OD5=1),3,0)) -> 0 | OF6: =IF(AND(OE4=1,OE5=1),1,IF(AND(OE4=0,OE5=1),3,0)) -> 0
A7: EcProNew | AY7: EcPro3New | AZ7: 0 | BA7: =IF(AND(AZ6=2,BA6<>2),1,0) -> 0 | BB7: =IF(AND(BA6=2,BB6<>2),1,0) -> 0 | BC7: =IF(AND(BB6=2,BC6<>2),1,0) -> 0 | BD7: =IF(AND(BC6=2,BD6<>2),1,0) -> 0 | BE7: =IF(AND(BD6=2,BE6<>2),1,0) -> 0 | BF7: =IF(AND(BE6=2,BF6<>2),1,0) -> 0 | BG7: =IF(AND(BF6=2,BG6<>2),1,0) -> 0 | BH7: =IF(AND(BG6=2,BH6<>2),1,0) -> 0 | BO7: EcPro4New | BP7: 0 | BQ7: =IF(AND(BP6=2,BQ6<>2),1,0) -> 0 | BR7: =IF(AND(BQ6=2,BR6<>2),1,0) -> 0 | BS7: =IF(AND(BR6=2,BS6<>2),1,0) -> 0 | BT7: =IF(AND(BS6=2,BT6<>2),1,0) -> 0 | BU7: =IF(AND(BT6=2,BU6<>2),1,0) -> 0 | BV7: =IF(AND(BU6=2,BV6<>2),1,0) -> 0 | BW7: =IF(AND(BV6=2,BW6<>2),1,0) -> 0 | BX7: =IF(AND(BW6=2,BX6<>2),1,0) -> 0 | CE7: EcPro5New | CF7: 0 | CG7: =IF(AND(CF6=2,CG6<>2),1,0) -> 0 | CH7: =IF(AND(CG6=2,CH6<>2),1,0) -> 0 | CI7: =IF(AND(CH6=2,CI6<>2),1,0) -> 0 | CJ7: =IF(AND(CI6=2,CJ6<>2),1,0) -> 0 | CK7: =IF(AND(CJ6=2,CK6<>2),1,0) -> 0 | CL7: =IF(AND(CK6=2,CL6<>2),1,0) -> 0 | CM7: =IF(AND(CL6=2,CM6<>2),1,0) -> 0 | CN7: =IF(AND(CM6=2,CN6<>2),1,0) -> 0 | CU7: EcPro6New | CV7: 0 | CW7: =IF(AND(CV6=2,CW6<>2),1,0) -> 0 | CX7: =IF(AND(CW6=2,CX6<>2),1,0) -> 0 | CY7: =IF(AND(CX6=2,CY6<>2),1,0) -> 0 | CZ7: =IF(AND(CY6=2,CZ6<>2),1,0) -> 0 | DA7: =IF(AND(CZ6=2,DA6<>2),1,0) -> 0 | DB7: =IF(AND(DA6=2,DB6<>2),1,0) -> 0 | DC7: =IF(AND(DB6=2,DC6<>2),1,0) -> 0 | DD7: =IF(AND(DC6=2,DD6<>2),1,0) -> 0 | DK7: EcPro7New | DL7: 0 | DM7: =IF(AND(DL6=2,DM6<>2),1,0) -> 0 | DN7: =IF(AND(DM6=2,DN6<>2),1,0) -> 1 | DO7: =IF(AND(DN6=2,DO6<>2),1,0) -> 0 | DP7: =IF(AND(DO6=2,DP6<>2),1,0) -> 0 | DQ7: =IF(AND(DP6=2,DQ6<>2),1,0) -> 0 | DR7: =IF(AND(DQ6=2,DR6<>2),1,0) -> 0 | DS7: =IF(AND(DR6=2,DS6<>2),1,0) -> 0 | DT7: =IF(AND(DS6=2,DT6<>2),1,0) -> 0 | EA7: EcPro8New | EB7: 0 | EC7: =IF(AND(EB6=2,EC6<>2),1,0) -> 0 | ED7: =IF(AND(EC6=2,ED6<>2),1,0) -> 1 | EE7: =IF(AND(ED6=2,EE6<>2),1,0) -> 0 | EF7: =IF(AND(EE6=2,EF6<>2),1,0) -> 0 | EG7: =IF(AND(EF6=2,EG6<>2),1,0) -> 0 | EH7: =IF(AND(EG6=2,EH6<>2),1,0) -> 0 | EI7: =IF(AND(EH6=2,EI6<>2),1,0) -> 0 | EJ7: =IF(AND(EI6=2,EJ6<>2),1,0) -> 0 | EQ7: EcPro9New | ER7: 0 | ES7: =IF(AND(ER6=2,ES6<>2),1,0) -> 0 | ET7: =IF(AND(ES6=2,ET6<>2),1,0) -> 0 | EU7: =IF(AND(ET6=2,EU6<>2),1,0) -> 1 | EV7: =IF(AND(EU6=2,EV6<>2),1,0) -> 0 | EW7: =IF(AND(EV6=2,EW6<>2),1,0) -> 0 | EX7: =IF(AND(EW6=2,EX6<>2),1,0) -> 0 | EY7: =IF(AND(EX6=2,EY6<>2),1,0) -> 0 | EZ7: =IF(AND(EY6=2,EZ6<>2),1,0) -> 0 | FG7: EcPro10New | FH7: 0 | FI7: =IF(AND(FH6=2,FI6<>2),1,0) -> 0 | FJ7: =IF(AND(FI6=2,FJ6<>2),1,0) -> 0 | FK7: =IF(AND(FJ6=2,FK6<>2),1,0) -> 1 | FL7: =IF(AND(FK6=2,FL6<>2),1,0) -> 0 | FM7: =IF(AND(FL6=2,FM6<>2),1,0) -> 0 | FN7: =IF(AND(FM6=2,FN6<>2),1,0) -> 0 | FO7: =IF(AND(FN6=2,FO6<>2),1,0) -> 0 | FP7: =IF(AND(FO6=2,FP6<>2),1,0) -> 0 | FW7: EcPro11New | FX7: 0 | FY7: =IF(AND(FX6=2,FY6<>2),1,0) -> 0 | FZ7: =IF(AND(FY6=2,FZ6<>2),1,0) -> 0 | GA7: =IF(AND(FZ6=2,GA6<>2),1,0) -> 0 | GB7: =IF(AND(GA6=2,GB6<>2),1,0) -> 1 | GC7: =IF(AND(GB6=2,GC6<>2),1,0) -> 0 | GD7: =IF(AND(GC6=2,GD6<>2),1,0) -> 0 | GE7: =IF(AND(GD6=2,GE6<>2),1,0) -> 0 | GF7: =IF(AND(GE6=2,GF6<>2),1,0) -> 0 | GM7: EcPro12New | GN7: 0 | GO7: =IF(AND(GN6=2,GO6<>2),1,0) -> 0 | GP7: =IF(AND(GO6=2,GP6<>2),1,0) -> 0 | GQ7: =IF(AND(GP6=2,GQ6<>2),1,0) -> 0 | GR7: =IF(AND(GQ6=2,GR6<>2),1,0) -> 1 | GS7: =IF(AND(GR6=2,GS6<>2),1,0) -> 0 | GT7: =IF(AND(GS6=2,GT6<>2),1,0) -> 0 | GU7: =IF(AND(GT6=2,GU6<>2),1,0) -> 0 | GV7: =IF(AND(GU6=2,GV6<>2),1,0) -> 0 | HC7: EcPro13New | HD7: 0 | HE7: =IF(AND(HD6=2,HE6<>2),1,0) -> 0 | HF7: =IF(AND(HE6=2,HF6<>2),1,0) -> 0 | HG7: =IF(AND(HF6=2,HG6<>2),1,0) -> 0 | HH7: =IF(AND(HG6=2,HH6<>2),1,0) -> 0 | HI7: =IF(AND(HH6=2,HI6<>2),1,0) -> 1 | HJ7: =IF(AND(HI6=2,HJ6<>2),1,0) -> 0 | HK7: =IF(AND(HJ6=2,HK6<>2),1,0) -> 0 | HL7: =IF(AND(HK6=2,HL6<>2),1,0) -> 0 | HS7: EcPro14New | HT7: 0 | HU7: =IF(AND(HT6=2,HU6<>2),1,0) -> 0 | HV7: =IF(AND(HU6=2,HV6<>2),1,0) -> 0 | HW7: =IF(AND(HV6=2,HW6<>2),1,0) -> 1 | HX7: =IF(AND(HW6=2,HX6<>2),1,0) -> 0 | HY7: =IF(AND(HX6=2,HY6<>2),1,0) -> 0 | HZ7: =IF(AND(HY6=2,HZ6<>2),1,0) -> 0 | IA7: =IF(AND(HZ6=2,IA6<>2),1,0) -> 0 | IB7: =IF(AND(IA6=2,IB6<>2),1,0) -> 0 | II7: EcPro15New | IJ7: 0 | IK7: =IF(AND(IJ6=2,IK6<>2),1,0) -> 0 | IL7: =IF(AND(IK6=2,IL6<>2),1,0) -> 0 | IM7: =IF(AND(IL6=2,IM6<>2),1,0) -> 1 | IN7: =IF(AND(IM6=2,IN6<>2),1,0) -> 0 | IO7: =IF(AND(IN6=2,IO6<>2),1,0) -> 0 | IP7: =IF(AND(IO6=2,IP6<>2),1,0) -> 0 | IQ7: =IF(AND(IP6=2,IQ6<>2),1,0) -> 0 | IR7: =IF(AND(IQ6=2,IR6<>2),1,0) -> 0 | IY7: EcPro16New | IZ7: 0 | JA7: =IF(AND(IZ6=2,JA6<>2),1,0) -> 0 | JB7: =IF(AND(JA6=2,JB6<>2),1,0) -> 0 | JC7: =IF(AND(JB6=2,JC6<>2),1,0) -> 0 | JD7: =IF(AND(JC6=2,JD6<>2),1,0) -> 1 | JE7: =IF(AND(JD6=2,JE6<>2),1,0) -> 0 | JF7: =IF(AND(JE6=2,JF6<>2),1,0) -> 0 | JG7: =IF(AND(JF6=2,JG6<>2),1,0) -> 0 | JH7: =IF(AND(JG6=2,JH6<>2),1,0) -> 0 | JO7: EcPro17New | JP7: 0 | JQ7: =IF(AND(JP6=2,JQ6<>2),1,0) -> 0 | JR7: =IF(AND(JQ6=2,JR6<>2),1,0) -> 0 | JS7: =IF(AND(JR6=2,JS6<>2),1,0) -> 0 | JT7: =IF(AND(JS6=2,JT6<>2),1,0) -> 1 | JU7: =IF(AND(JT6=2,JU6<>2),1,0) -> 0 | JV7: =IF(AND(JU6=2,JV6<>2),1,0) -> 0 | JW7: =IF(AND(JV6=2,JW6<>2),1,0) -> 0 | JX7: =IF(AND(JW6=2,JX6<>2),1,0) -> 0 | KE7: EcPro18New | KF7: 0 | KG7: =IF(AND(KF6=2,KG6<>2),1,0) -> 0 | KH7: =IF(AND(KG6=2,KH6<>2),1,0) -> 0 | KI7: =IF(AND(KH6=2,KI6<>2),1,0) -> 0 | KJ7: =IF(AND(KI6=2,KJ6<>2),1,0) -> 0 | KK7: =IF(AND(KJ6=2,KK6<>2),1,0) -> 0 | KL7: =IF(AND(KK6=2,KL6<>2),1,0) -> 0 | KM7: =IF(AND(KL6=2,KM6<>2),1,0) -> 0 | KN7: =IF(AND(KM6=2,KN6<>2),1,0) -> 0 | KU7: EcPro19New | KV7: 0 | KW7: =IF(AND(KV6=2,KW6<>2),1,0) -> 0 | KX7: =IF(AND(KW6=2,KX6<>2),1,0) -> 0 | KY7: =IF(AND(KX6=2,KY6<>2),1,0) -> 0 | KZ7: =IF(AND(KY6=2,KZ6<>2),1,0) -> 0 | LA7: =IF(AND(KZ6=2,LA6<>2),1,0) -> 0 | LB7: =IF(AND(LA6=2,LB6<>2),1,0) -> 0 | LC7: =IF(AND(LB6=2,LC6<>2),1,0) -> 0 | LD7: =IF(AND(LC6=2,LD6<>2),1,0) -> 0 | LK7: EcPro20New | LL7: 0 | LM7: =IF(AND(LL6=2,LM6<>2),1,0) -> 0 | LN7: =IF(AND(LM6=2,LN6<>2),1,0) -> 0 | LO7: =IF(AND(LN6=2,LO6<>2),1,0) -> 0 | LP7: =IF(AND(LO6=2,LP6<>2),1,0) -> 0 | LQ7: =IF(AND(LP6=2,LQ6<>2),1,0) -> 0 | LR7: =IF(AND(LQ6=2,LR6<>2),1,0) -> 0 | LS7: =IF(AND(LR6=2,LS6<>2),1,0) -> 0 | LT7: =IF(AND(LS6=2,LT6<>2),1,0) -> 0 | MA7: EcPro21New | MB7: 0 | MC7: =IF(AND(MB6=2,MC6<>2),1,0) -> 0 | MD7: =IF(AND(MC6=2,MD6<>2),1,0) -> 0 | ME7: =IF(AND(MD6=2,ME6<>2),1,0) -> 0 | MF7: =IF(AND(ME6=2,MF6<>2),1,0) -> 0 | MG7: =IF(AND(MF6=2,MG6<>2),1,0) -> 0 | MH7: =IF(AND(MG6=2,MH6<>2),1,0) -> 0 | MI7: =IF(AND(MH6=2,MI6<>2),1,0) -> 0 | MJ7: =IF(AND(MI6=2,MJ6<>2),1,0) -> 0 | MQ7: EcPro22New | MR7: 0 | MS7: =IF(AND(MR6=2,MS6<>2),1,0) -> 0 | MT7: =IF(AND(MS6=2,MT6<>2),1,0) -> 0 | MU7: =IF(AND(MT6=2,MU6<>2),1,0) -> 0 | MV7: =IF(AND(MU6=2,MV6<>2),1,0) -> 0 | MW7: =IF(AND(MV6=2,MW6<>2),1,0) -> 0 | MX7: =IF(AND(MW6=2,MX6<>2),1,0) -> 0 | MY7: =IF(AND(MX6=2,MY6<>2),1,0) -> 0 | MZ7: =IF(AND(MY6=2,MZ6<>2),1,0) -> 0 | NG7: EcPro23New | NH7: 0 | NI7: =IF(AND(NH6=2,NI6<>2),1,0) -> 0 | NJ7: =IF(AND(NI6=2,NJ6<>2),1,0) -> 0 | NK7: =IF(AND(NJ6=2,NK6<>2),1,0) -> 0 | NL7: =IF(AND(NK6=2,NL6<>2),1,0) -> 0 | NM7: =IF(AND(NL6=2,NM6<>2),1,0) -> 0 | NN7: =IF(AND(NM6=2,NN6<>2),1,0) -> 0 | NO7: =IF(AND(NN6=2,NO6<>2),1,0) -> 0 | NP7: =IF(AND(NO6=2,NP6<>2),1,0) -> 0 | NW7: EcPro24New | NX7: 0 | NY7: =IF(AND(NX6=2,NY6<>2),1,0) -> 0 | NZ7: =IF(AND(NY6=2,NZ6<>2),1,0) -> 0 | OA7: =IF(AND(NZ6=2,OA6<>2),1,0) -> 0 | OB7: =IF(AND(OA6=2,OB6<>2),1,0) -> 0 | OC7: =IF(AND(OB6=2,OC6<>2),1,0) -> 0 | OD7: =IF(AND(OC6=2,OD6<>2),1,0) -> 0 | OE7: =IF(AND(OD6=2,OE6<>2),1,0) -> 0 | OF7: =IF(AND(OE6=2,OF6<>2),1,0) -> 0
A8: EcProSort | AY8: EcPro3Sort | AZ8: 0 | BA8: =IF(BA7=1,Results!C5+1,AZ8) -> 0 | BB8: =IF(BB7=1,Results!D5+1,BA8) -> 0 | BC8: =IF(BC7=1,Results!E5+1,BB8) -> 0 | BD8: =IF(BD7=1,Results!F5+1,BC8) -> 0 | BE8: =IF(BE7=1,Results!G5+1,BD8) -> 0 | BF8: =IF(BF7=1,Results!H5+1,BE8) -> 0 | BG8: =IF(BG7=1,Results!I5+1,BF8) -> 0 | BH8: =IF(BH7=1,Results!J5+1,BG8) -> 0 | BO8: EcPro4Sort | BP8: 0 | BQ8: =IF(BQ7=1,Results!C5+1,BP8) -> 0 | BR8: =IF(BR7=1,Results!D5+1,BQ8) -> 0 | BS8: =IF(BS7=1,Results!E5+1,BR8) -> 0 | BT8: =IF(BT7=1,Results!F5+1,BS8) -> 0 | BU8: =IF(BU7=1,Results!G5+1,BT8) -> 0 | BV8: =IF(BV7=1,Results!H5+1,BU8) -> 0 | BW8: =IF(BW7=1,Results!I5+1,BV8) -> 0 | BX8: =IF(BX7=1,Results!J5+1,BW8) -> 0 | CE8: EcPro5Sort | CF8: 0 | CG8: =IF(CG7=1,Results!C5+1,CF8) -> 0 | CH8: =IF(CH7=1,Results!D5+1,CG8) -> 0 | CI8: =IF(CI7=1,Results!E5+1,CH8) -> 0 | CJ8: =IF(CJ7=1,Results!F5+1,CI8) -> 0 | CK8: =IF(CK7=1,Results!G5+1,CJ8) -> 0 | CL8: =IF(CL7=1,Results!H5+1,CK8) -> 0 | CM8: =IF(CM7=1,Results!I5+1,CL8) -> 0 | CN8: =IF(CN7=1,Results!J5+1,CM8) -> 0 | CU8: EcPro6Sort | CV8: 0 | CW8: =IF(CW7=1,Results!C5+1,CV8) -> 0 | CX8: =IF(CX7=1,Results!D5+1,CW8) -> 0 | CY8: =IF(CY7=1,Results!E5+1,CX8) -> 0 | CZ8: =IF(CZ7=1,Results!F5+1,CY8) -> 0 | DA8: =IF(DA7=1,Results!G5+1,CZ8) -> 0 | DB8: =IF(DB7=1,Results!H5+1,DA8) -> 0 | DC8: =IF(DC7=1,Results!I5+1,DB8) -> 0 | DD8: =IF(DD7=1,Results!J5+1,DC8) -> 0 | DK8: EcPro7Sort | DL8: 0 | DM8: =IF(DM7=1,Results!C5+1,DL8) -> 0 | DN8: =IF(DN7=1,Results!D5+1,DM8) -> 3 | DO8: =IF(DO7=1,Results!E5+1,DN8) -> 3 | DP8: =IF(DP7=1,Results!F5+1,DO8) -> 3 | DQ8: =IF(DQ7=1,Results!G5+1,DP8) -> 3 | DR8: =IF(DR7=1,Results!H5+1,DQ8) -> 3 | DS8: =IF(DS7=1,Results!I5+1,DR8) -> 3 | DT8: =IF(DT7=1,Results!J5+1,DS8) -> 3 | EA8: EcPro8Sort | EB8: 0 | EC8: =IF(EC7=1,Results!C5+1,EB8) -> 0 | ED8: =IF(ED7=1,Results!D5+1,EC8) -> 3 | EE8: =IF(EE7=1,Results!E5+1,ED8) -> 3 | EF8: =IF(EF7=1,Results!F5+1,EE8) -> 3 | EG8: =IF(EG7=1,Results!G5+1,EF8) -> 3 | EH8: =IF(EH7=1,Results!H5+1,EG8) -> 3 | EI8: =IF(EI7=1,Results!I5+1,EH8) -> 3 | EJ8: =IF(EJ7=1,Results!J5+1,EI8) -> 3 | EQ8: EcPro9Sort | ER8: 0 | ES8: =IF(ES7=1,Results!C5+1,ER8) -> 0 | ET8: =IF(ET7=1,Results!D5+1,ES8) -> 0 | EU8: =IF(EU7=1,Results!E5+1,ET8) -> 4 | EV8: =IF(EV7=1,Results!F5+1,EU8) -> 4 | EW8: =IF(EW7=1,Results!G5+1,EV8) -> 4 | EX8: =IF(EX7=1,Results!H5+1,EW8) -> 4 | EY8: =IF(EY7=1,Results!I5+1,EX8) -> 4 | EZ8: =IF(EZ7=1,Results!J5+1,EY8) -> 4 | FG8: EcPro10Sort | FH8: 0 | FI8: =IF(FI7=1,Results!C5+1,FH8) -> 0 | FJ8: =IF(FJ7=1,Results!D5+1,FI8) -> 0 | FK8: =IF(FK7=1,Results!E5+1,FJ8) -> 4 | FL8: =IF(FL7=1,Results!F5+1,FK8) -> 4 | FM8: =IF(FM7=1,Results!G5+1,FL8) -> 4 | FN8: =IF(FN7=1,Results!H5+1,FM8) -> 4 | FO8: =IF(FO7=1,Results!I5+1,FN8) -> 4 | FP8: =IF(FP7=1,Results!J5+1,FO8) -> 4 | FW8: EcPro11Sort | FX8: 0 | FY8: =IF(FY7=1,Results!C5+1,FX8) -> 0 | FZ8: =IF(FZ7=1,Results!D5+1,FY8) -> 0 | GA8: =IF(GA7=1,Results!E5+1,FZ8) -> 0 | GB8: =IF(GB7=1,Results!F5+1,GA8) -> 5 | GC8: =IF(GC7=1,Results!G5+1,GB8) -> 5 | GD8: =IF(GD7=1,Results!H5+1,GC8) -> 5 | GE8: =IF(GE7=1,Results!I5+1,GD8) -> 5 | GF8: =IF(GF7=1,Results!J5+1,GE8) -> 5 | GM8: EcPro12Sort | GN8: 0 | GO8: =IF(GO7=1,Results!C5+1,GN8) -> 0 | GP8: =IF(GP7=1,Results!D5+1,GO8) -> 0 | GQ8: =IF(GQ7=1,Results!E5+1,GP8) -> 0 | GR8: =IF(GR7=1,Results!F5+1,GQ8) -> 5 | GS8: =IF(GS7=1,Results!G5+1,GR8) -> 5 | GT8: =IF(GT7=1,Results!H5+1,GS8) -> 5 | GU8: =IF(GU7=1,Results!I5+1,GT8) -> 5 | GV8: =IF(GV7=1,Results!J5+1,GU8) -> 5 | HC8: EcPro13Sort | HD8: 0 | HE8: =IF(HE7=1,Results!C5+1,HD8) -> 0 | HF8: =IF(HF7=1,Results!D5+1,HE8) -> 0 | HG8: =IF(HG7=1,Results!E5+1,HF8) -> 0 | HH8: =IF(HH7=1,Results!F5+1,HG8) -> 0 | HI8: =IF(HI7=1,Results!G5+1,HH8) -> 6 | HJ8: =IF(HJ7=1,Results!H5+1,HI8) -> 6 | HK8: =IF(HK7=1,Results!I5+1,HJ8) -> 6 | HL8: =IF(HL7=1,Results!J5+1,HK8) -> 6 | HS8: EcPro14Sort | HT8: 0 | HU8: =IF(HU7=1,Results!C5+1,HT8) -> 0 | HV8: =IF(HV7=1,Results!D5+1,HU8) -> 0 | HW8: =IF(HW7=1,Results!E5+1,HV8) -> 4 | HX8: =IF(HX7=1,Results!F5+1,HW8) -> 4 | HY8: =IF(HY7=1,Results!G5+1,HX8) -> 4 | HZ8: =IF(HZ7=1,Results!H5+1,HY8) -> 4 | IA8: =IF(IA7=1,Results!I5+1,HZ8) -> 4 | IB8: =IF(IB7=1,Results!J5+1,IA8) -> 4 | II8: EcPro15Sort | IJ8: 0 | IK8: =IF(IK7=1,Results!$C5+1,IJ8) -> 0 | IL8: =IF(IL7=1,Results!$D5+1,IK8) -> 0 | IM8: =IF(IM7=1,Results!$E5+1,IL8) -> 4 | IN8: =IF(IN7=1,Results!$F5+1,IM8) -> 4 | IO8: =IF(IO7=1,Results!$G5+1,IN8) -> 4 | IP8: =IF(IP7=1,Results!$H5+1,IO8) -> 4 | IQ8: =IF(IQ7=1,Results!$I5+1,IP8) -> 4 | IR8: =IF(IR7=1,Results!$J5+1,IQ8) -> 4 | IY8: EcPro16Sort | IZ8: 0 | JA8: =IF(JA7=1,Results!$C5+1,IZ8) -> 0 | JB8: =IF(JB7=1,Results!$D5+1,JA8) -> 0 | JC8: =IF(JC7=1,Results!$E5+1,JB8) -> 0 | JD8: =IF(JD7=1,Results!$F5+1,JC8) -> 5 | JE8: =IF(JE7=1,Results!$G5+1,JD8) -> 5 | JF8: =IF(JF7=1,Results!$H5+1,JE8) -> 5 | JG8: =IF(JG7=1,Results!$I5+1,JF8) -> 5 | JH8: =IF(JH7=1,Results!$J5+1,JG8) -> 5 | JO8: EcPro17Sort | JP8: 0 | JQ8: =IF(JQ7=1,Results!$C5+1,JP8) -> 0 | JR8: =IF(JR7=1,Results!$D5+1,JQ8) -> 0 | JS8: =IF(JS7=1,Results!$E5+1,JR8) -> 0 | JT8: =IF(JT7=1,Results!$F5+1,JS8) -> 5 | JU8: =IF(JU7=1,Results!$G5+1,JT8) -> 5 | JV8: =IF(JV7=1,Results!$H5+1,JU8) -> 5 | JW8: =IF(JW7=1,Results!$I5+1,JV8) -> 5 | JX8: =IF(JX7=1,Results!$J5+1,JW8) -> 5 | KE8: EcPro18Sort | KF8: 0 | KG8: =IF(KG7=1,Results!C5+1,KF8) -> 0 | KH8: =IF(KH7=1,Results!D5+1,KG8) -> 0 | KI8: =IF(KI7=1,Results!E5+1,KH8) -> 0 | KJ8: =IF(KJ7=1,Results!F5+1,KI8) -> 0 | KK8: =IF(KK7=1,Results!G5+1,KJ8) -> 0 | KL8: =IF(KL7=1,Results!H5+1,KK8) -> 0 | KM8: =IF(KM7=1,Results!I5+1,KL8) -> 0 | KN8: =IF(KN7=1,Results!J5+1,KM8) -> 0 | KU8: EcPro19Sort | KV8: 0 | KW8: =IF(KW7=1,Results!C5+1,KV8) -> 0 | KX8: =IF(KX7=1,Results!D5+1,KW8) -> 0 | KY8: =IF(KY7=1,Results!E5+1,KX8) -> 0 | KZ8: =IF(KZ7=1,Results!F5+1,KY8) -> 0 | LA8: =IF(LA7=1,Results!G5+1,KZ8) -> 0 | LB8: =IF(LB7=1,Results!H5+1,LA8) -> 0 | LC8: =IF(LC7=1,Results!I5+1,LB8) -> 0 | LD8: =IF(LD7=1,Results!J5+1,LC8) -> 0 | LK8: EcPro20Sort | LL8: 0 | LM8: =IF(LM7=1,Results!C5+1,LL8) -> 0 | LN8: =IF(LN7=1,Results!D5+1,LM8) -> 0 | LO8: =IF(LO7=1,Results!E5+1,LN8) -> 0 | LP8: =IF(LP7=1,Results!F5+1,LO8) -> 0 | LQ8: =IF(LQ7=1,Results!G5+1,LP8) -> 0 | LR8: =IF(LR7=1,Results!H5+1,LQ8) -> 0 | LS8: =IF(LS7=1,Results!I5+1,LR8) -> 0 | LT8: =IF(LT7=1,Results!J5+1,LS8) -> 0 | MA8: EcPro21Sort | MB8: 0 | MC8: =IF(MC7=1,Results!C5+1,MB8) -> 0 | MD8: =IF(MD7=1,Results!D5+1,MC8) -> 0 | ME8: =IF(ME7=1,Results!E5+1,MD8) -> 0 | MF8: =IF(MF7=1,Results!F5+1,ME8) -> 0 | MG8: =IF(MG7=1,Results!G5+1,MF8) -> 0 | MH8: =IF(MH7=1,Results!H5+1,MG8) -> 0 | MI8: =IF(MI7=1,Results!I5+1,MH8) -> 0 | MJ8: =IF(MJ7=1,Results!J5+1,MI8) -> 0 | MQ8: EcPro22Sort | MR8: 0 | MS8: =IF(MS7=1,Results!C5+1,MR8) -> 0 | MT8: =IF(MT7=1,Results!D5+1,MS8) -> 0 | MU8: =IF(MU7=1,Results!E5+1,MT8) -> 0 | MV8: =IF(MV7=1,Results!F5+1,MU8) -> 0 | MW8: =IF(MW7=1,Results!G5+1,MV8) -> 0 | MX8: =IF(MX7=1,Results!H5+1,MW8) -> 0 | MY8: =IF(MY7=1,Results!I5+1,MX8) -> 0 | MZ8: =IF(MZ7=1,Results!J5+1,MY8) -> 0 | NG8: EcPro23Sort | NH8: 0 | NI8: =IF(NI7=1,Results!C5+1,NH8) -> 0 | NJ8: =IF(NJ7=1,Results!D5+1,NI8) -> 0 | NK8: =IF(NK7=1,Results!E5+1,NJ8) -> 0 | NL8: =IF(NL7=1,Results!F5+1,NK8) -> 0 | NM8: =IF(NM7=1,Results!G5+1,NL8) -> 0 | NN8: =IF(NN7=1,Results!H5+1,NM8) -> 0 | NO8: =IF(NO7=1,Results!I5+1,NN8) -> 0 | NP8: =IF(NP7=1,Results!J5+1,NO8) -> 0 | NW8: EcPro24Sort | NX8: 0 | NY8: =IF(NY7=1,Results!C5+1,NX8) -> 0 | NZ8: =IF(NZ7=1,Results!D5+1,NY8) -> 0 | OA8: =IF(OA7=1,Results!E5+1,NZ8) -> 0 | OB8: =IF(OB7=1,Results!F5+1,OA8) -> 0 | OC8: =IF(OC7=1,Results!G5+1,OB8) -> 0 | OD8: =IF(OD7=1,Results!H5+1,OC8) -> 0 | OE8: =IF(OE7=1,Results!I5+1,OD8) -> 0 | OF8: =IF(OF7=1,Results!J5+1,OE8) -> 0
A9: EcProDecidedlastyr | AY9: EcPro3Decidedlastyr | AZ9: 0 | BA9: =+AZ4 -> 0 | BB9: =+BA4-AZ4 -> 0 | BC9: =+BB4-BA4 -> 0 | BD9: =+BC4-BB4 -> 0 | BE9: =+BD4-BC4 -> 0 | BF9: =+BE4-BD4 -> 0 | BG9: =+BF4-BE4 -> 0 | BH9: =+BG4-BF4 -> 0 | BO9: EcPro4Decidedlastyr | BP9: 0 | BQ9: =+BP4 -> 0 | BR9: =+BQ4-BP4 -> 0 | BS9: =+BR4-BQ4 -> 0 | BT9: =+BS4-BR4 -> 0 | BU9: =+BT4-BS4 -> 0 | BV9: =+BU4-BT4 -> 0 | BW9: =+BV4-BU4 -> 0 | BX9: =+BW4-BV4 -> 0 | CE9: EcPro5Decidedlastyr | CF9: 0 | CG9: =+CF4 -> 0 | CH9: =+CG4-CF4 -> 0 | CI9: =+CH4-CG4 -> 0 | CJ9: =+CI4-CH4 -> 0 | CK9: =+CJ4-CI4 -> 0 | CL9: =+CK4-CJ4 -> 0 | CM9: =+CL4-CK4 -> 0 | CN9: =+CM4-CL4 -> 0 | CU9: EcPro6Decidedlastyr | CV9: 0 | CW9: =+CV4 -> 0 | CX9: =+CW4-CV4 -> 0 | CY9: =+CX4-CW4 -> 0 | CZ9: =+CY4-CX4 -> 0 | DA9: =+CZ4-CY4 -> 0 | DB9: =+DA4-CZ4 -> 0 | DC9: =+DB4-DA4 -> 0 | DD9: =+DC4-DB4 -> 0 | DK9: EcPro7Decidedlastyr | DL9: 0 | DM9: =+DL4 -> 0 | DN9: =+DM4-DL4 -> 0 | DO9: =+DN4-DM4 -> 0 | DP9: =+DO4-DN4 -> 0 | DQ9: =+DP4-DO4 -> 0 | DR9: =+DQ4-DP4 -> 0 | DS9: =+DR4-DQ4 -> 0 | DT9: =+DS4-DR4 -> 0 | EA9: EcPro8Decidedlastyr | EB9: 0 | EC9: =+EB4 -> 0 | ED9: =+EC4-EB4 -> 0 | EE9: =+ED4-EC4 -> 0 | EF9: =+EE4-ED4 -> 0 | EG9: =+EF4-EE4 -> 0 | EH9: =+EG4-EF4 -> 0 | EI9: =+EH4-EG4 -> 0 | EJ9: =+EI4-EH4 -> 0 | EQ9: EcPro9Decidedlastyr | ER9: 0 | ES9: =+ER4 -> 0 | ET9: =+ES4-ER4 -> 0 | EU9: =+ET4-ES4 -> 0 | EV9: =+EU4-ET4 -> 0 | EW9: =+EV4-EU4 -> 0 | EX9: =+EW4-EV4 -> 0 | EY9: =+EX4-EW4 -> 0 | EZ9: =+EY4-EX4 -> 0 | FG9: EcPro10Decidedlastyr | FH9: 0 | FI9: =+FH4 -> 0 | FJ9: =+FI4-FH4 -> 0 | FK9: =+FJ4-FI4 -> 0 | FL9: =+FK4-FJ4 -> 0 | FM9: =+FL4-FK4 -> 0 | FN9: =+FM4-FL4 -> 0 | FO9: =+FN4-FM4 -> 0 | FP9: =+FO4-FN4 -> 0 | FW9: EcPro11Decidedlastyr | FX9: 0 | FY9: =+FX4 -> 0 | FZ9: =+FY4-FX4 -> 0 | GA9: =+FZ4-FY4 -> 0 | GB9: =+GA4-FZ4 -> 0 | GC9: =+GB4-GA4 -> 0 | GD9: =+GC4-GB4 -> 0 | GE9: =+GD4-GC4 -> 0 | GF9: =+GE4-GD4 -> 0 | GM9: EcPro12Decidedlastyr | GN9: 0 | GO9: =+GN4 -> 0 | GP9: =+GO4-GN4 -> 0 | GQ9: =+GP4-GO4 -> 0 | GR9: =+GQ4-GP4 -> 0 | GS9: =+GR4-GQ4 -> 0 | GT9: =+GS4-GR4 -> 0 | GU9: =+GT4-GS4 -> 0 | GV9: =+GU4-GT4 -> 0 | HC9: EcPro13Decidedlastyr | HD9: 0 | HE9: =+HD4 -> 0 | HF9: =+HE4-HD4 -> 0 | HG9: =+HF4-HE4 -> 0 | HH9: =+HG4-HF4 -> 0 | HI9: =+HH4-HG4 -> 0 | HJ9: =+HI4-HH4 -> 0 | HK9: =+HJ4-HI4 -> 0 | HL9: =+HK4-HJ4 -> 0 | HS9: EcPro14Decidedlastyr | HT9: 0 | HU9: =+HT4 -> 0 | HV9: =+HU4-HT4 -> 0 | HW9: =+HV4-HU4 -> 0 | HX9: =+HW4-HV4 -> 0 | HY9: =+HX4-HW4 -> 0 | HZ9: =+HY4-HX4 -> 0 | IA9: =+HZ4-HY4 -> 0 | IB9: =+IA4-HZ4 -> 0 | II9: EcPro15Decidedlastyr | IJ9: 0 | IK9: =+IJ4 -> 0 | IL9: =+IK4-IJ4 -> 0 | IM9: =+IL4-IK4 -> 0 | IN9: =+IM4-IL4 -> 0 | IO9: =+IN4-IM4 -> 0 | IP9: =+IO4-IN4 -> 0 | IQ9: =+IP4-IO4 -> 0 | IR9: =+IQ4-IP4 -> 0 | IY9: EcPro16Decidedlastyr | IZ9: 0 | JA9: =+IZ4 -> 0 | JB9: =+JA4-IZ4 -> 0 | JC9: =+JB4-JA4 -> 0 | JD9: =+JC4-JB4 -> 0 | JE9: =+JD4-JC4 -> 0 | JF9: =+JE4-JD4 -> 0 | JG9: =+JF4-JE4 -> 0 | JH9: =+JG4-JF4 -> 0 | JO9: EcPro17Decidedlastyr | JP9: 0 | JQ9: =+JP4 -> 0 | JR9: =+JQ4-JP4 -> 0 | JS9: =+JR4-JQ4 -> 0 | JT9: =+JS4-JR4 -> 0 | JU9: =+JT4-JS4 -> 0 | JV9: =+JU4-JT4 -> 0 | JW9: =+JV4-JU4 -> 0 | JX9: =+JW4-JV4 -> 0 | KE9: EcPro18Decidedlastyr | KF9: 0 | KG9: =+KF4 -> 0 | KH9: =+KG4-KF4 -> 0 | KI9: =+KH4-KG4 -> 0 | KJ9: =+KI4-KH4 -> 0 | KK9: =+KJ4-KI4 -> 0 | KL9: =+KK4-KJ4 -> 0 | KM9: =+KL4-KK4 -> 0 | KN9: =+KM4-KL4 -> 0 | KU9: EcPro19Decidedlastyr | KV9: 0 | KW9: =+KV4 -> 0 | KX9: =+KW4-KV4 -> 0 | KY9: =+KX4-KW4 -> 0 | KZ9: =+KY4-KX4 -> 0 | LA9: =+KZ4-KY4 -> 0 | LB9: =+LA4-KZ4 -> 0 | LC9: =+LB4-LA4 -> 0 | LD9: =+LC4-LB4 -> 0 | LK9: EcPro20Decidedlastyr | LL9: 0 | LM9: =+LL4 -> 0 | LN9: =+LM4-LL4 -> 0 | LO9: =+LN4-LM4 -> 0 | LP9: =+LO4-LN4 -> 0 | LQ9: =+LP4-LO4 -> 0 | LR9: =+LQ4-LP4 -> 0 | LS9: =+LR4-LQ4 -> 0 | LT9: =+LS4-LR4 -> 0 | MA9: EcPro21Decidedlastyr | MB9: 0 | MC9: =+MB4 -> 0 | MD9: =+MC4-MB4 -> 0 | ME9: =+MD4-MC4 -> 0 | MF9: =+ME4-MD4 -> 0 | MG9: =+MF4-ME4 -> 0 | MH9: =+MG4-MF4 -> 0 | MI9: =+MH4-MG4 -> 0 | MJ9: =+MI4-MH4 -> 0 | MQ9: EcPro22Decidedlastyr | MR9: 0 | MS9: =+MR4 -> 0 | MT9: =+MS4-MR4 -> 0 | MU9: =+MT4-MS4 -> 0 | MV9: =+MU4-MT4 -> 0 | MW9: =+MV4-MU4 -> 0 | MX9: =+MW4-MV4 -> 0 | MY9: =+MX4-MW4 -> 0 | MZ9: =+MY4-MX4 -> 0 | NG9: EcPro23Decidedlastyr | NH9: 0 | NI9: =+NH4 -> 0 | NJ9: =+NI4-NH4 -> 0 | NK9: =+NJ4-NI4 -> 0 | NL9: =+NK4-NJ4 -> 0 | NM9: =+NL4-NK4 -> 0 | NN9: =+NM4-NL4 -> 0 | NO9: =+NN4-NM4 -> 0 | NP9: =+NO4-NN4 -> 0 | NW9: EcPro24Decidedlastyr | NX9: 0 | NY9: =+NX4 -> 0 | NZ9: =+NY4-NX4 -> 0 | OA9: =+NZ4-NY4 -> 0 | OB9: =+OA4-NZ4 -> 0 | OC9: =+OB4-OA4 -> 0 | OD9: =+OC4-OB4 -> 0 | OE9: =+OD4-OC4 -> 0 | OF9: =+OE4-OD4 -> 0
A10: EcProDecided2yrsago | AY10: EcPro3Decided2yrsago | AZ10: 0 | BA10: =AZ9 -> 0 | BB10: =BA9 -> 0 | BC10: =BB9 -> 0 | BD10: =BC9 -> 0 | BE10: =BD9 -> 0 | BF10: =BE9 -> 0 | BG10: =BF9 -> 0 | BH10: =BG9 -> 0 | BO10: EcPro4Decided2yrsago | BP10: 0 | BQ10: =BP9 -> 0 | BR10: =BQ9 -> 0 | BS10: =BR9 -> 0 | BT10: =BS9 -> 0 | BU10: =BT9 -> 0 | BV10: =BU9 -> 0 | BW10: =BV9 -> 0 | BX10: =BW9 -> 0 | CE10: EcPro5Decided2yrsago | CF10: 0 | CG10: =CF9 -> 0 | CH10: =CG9 -> 0 | CI10: =CH9 -> 0 | CJ10: =CI9 -> 0 | CK10: =CJ9 -> 0 | CL10: =CK9 -> 0 | CM10: =CL9 -> 0 | CN10: =CM9 -> 0 | CU10: EcPro6Decided2yrsago | CV10: 0 | CW10: =CV9 -> 0 | CX10: =CW9 -> 0 | CY10: =CX9 -> 0 | CZ10: =CY9 -> 0 | DA10: =CZ9 -> 0 | DB10: =DA9 -> 0 | DC10: =DB9 -> 0 | DD10: =DC9 -> 0 | DK10: EcPro7Decided2yrsago | DL10: 0 | DM10: =DL9 -> 0 | DN10: =DM9 -> 0 | DO10: =DN9 -> 0 | DP10: =DO9 -> 0 | DQ10: =DP9 -> 0 | DR10: =DQ9 -> 0 | DS10: =DR9 -> 0 | DT10: =DS9 -> 0 | EA10: EcPro8Decided2yrsago | EB10: 0 | EC10: =EB9 -> 0 | ED10: =EC9 -> 0 | EE10: =ED9 -> 0 | EF10: =EE9 -> 0 | EG10: =EF9 -> 0 | EH10: =EG9 -> 0 | EI10: =EH9 -> 0 | EJ10: =EI9 -> 0 | EQ10: EcPro9Decided2yrsago | ER10: 0 | ES10: =ER9 -> 0 | ET10: =ES9 -> 0 | EU10: =ET9 -> 0 | EV10: =EU9 -> 0 | EW10: =EV9 -> 0 | EX10: =EW9 -> 0 | EY10: =EX9 -> 0 | EZ10: =EY9 -> 0 | FG10: EcPro10Decided2yrsago | FH10: 0 | FI10: =FH9 -> 0 | FJ10: =FI9 -> 0 | FK10: =FJ9 -> 0 | FL10: =FK9 -> 0 | FM10: =FL9 -> 0 | FN10: =FM9 -> 0 | FO10: =FN9 -> 0 | FP10: =FO9 -> 0 | FW10: EcPro11Decided2yrsago | FX10: 0 | FY10: =FX9 -> 0 | FZ10: =FY9 -> 0 | GA10: =FZ9 -> 0 | GB10: =GA9 -> 0 | GC10: =GB9 -> 0 | GD10: =GC9 -> 0 | GE10: =GD9 -> 0 | GF10: =GE9 -> 0 | GM10: EcPro12Decided2yrsago | GN10: 0 | GO10: =GN9 -> 0 | GP10: =GO9 -> 0 | GQ10: =GP9 -> 0 | GR10: =GQ9 -> 0 | GS10: =GR9 -> 0 | GT10: =GS9 -> 0 | GU10: =GT9 -> 0 | GV10: =GU9 -> 0 | HC10: EcPro13Decided2yrsago | HD10: 0 | HE10: =HD9 -> 0 | HF10: =HE9 -> 0 | HG10: =HF9 -> 0 | HH10: =HG9 -> 0 | HI10: =HH9 -> 0 | HJ10: =HI9 -> 0 | HK10: =HJ9 -> 0 | HL10: =HK9 -> 0 | HS10: EcPro14Decided2yrsago | HT10: 0 | HU10: =HT9 -> 0 | HV10: =HU9 -> 0 | HW10: =HV9 -> 0 | HX10: =HW9 -> 0 | HY10: =HX9 -> 0 | HZ10: =HY9 -> 0 | IA10: =HZ9 -> 0 | IB10: =IA9 -> 0 | II10: EcPro15Decided2yrsago | IJ10: 0 | IK10: =IJ9 -> 0 | IL10: =IK9 -> 0 | IM10: =IL9 -> 0 | IN10: =IM9 -> 0 | IO10: =IN9 -> 0 | IP10: =IO9 -> 0 | IQ10: =IP9 -> 0 | IR10: =IQ9 -> 0 | IY10: EcPro16Decided2yrsago | IZ10: 0 | JA10: =IZ9 -> 0 | JB10: =JA9 -> 0 | JC10: =JB9 -> 0 | JD10: =JC9 -> 0 | JE10: =JD9 -> 0 | JF10: =JE9 -> 0 | JG10: =JF9 -> 0 | JH10: =JG9 -> 0 | JO10: EcPro17Decided2yrsago | JP10: 0 | JQ10: =JP9 -> 0 | JR10: =JQ9 -> 0 | JS10: =JR9 -> 0 | JT10: =JS9 -> 0 | JU10: =JT9 -> 0 | JV10: =JU9 -> 0 | JW10: =JV9 -> 0 | JX10: =JW9 -> 0 | KE10: EcPro18Decided2yrsago | KF10: 0 | KG10: =KF9 -> 0 | KH10: =KG9 -> 0 | KI10: =KH9 -> 0 | KJ10: =KI9 -> 0 | KK10: =KJ9 -> 0 | KL10: =KK9 -> 0 | KM10: =KL9 -> 0 | KN10: =KM9 -> 0 | KU10: EcPro19Decided2yrsago | KV10: 0 | KW10: =KV9 -> 0 | KX10: =KW9 -> 0 | KY10: =KX9 -> 0 | KZ10: =KY9 -> 0 | LA10: =KZ9 -> 0 | LB10: =LA9 -> 0 | LC10: =LB9 -> 0 | LD10: =LC9 -> 0 | LK10: EcPro20Decided2yrsago | LL10: 0 | LM10: =LL9 -> 0 | LN10: =LM9 -> 0 | LO10: =LN9 -> 0 | LP10: =LO9 -> 0 | LQ10: =LP9 -> 0 | LR10: =LQ9 -> 0 | LS10: =LR9 -> 0 | LT10: =LS9 -> 0 | MA10: EcPro21Decided2yrsago | MB10: 0 | MC10: =MB9 -> 0 | MD10: =MC9 -> 0 | ME10: =MD9 -> 0 | MF10: =ME9 -> 0 | MG10: =MF9 -> 0 | MH10: =MG9 -> 0 | MI10: =MH9 -> 0 | MJ10: =MI9 -> 0 | MQ10: EcPro22Decided2yrsago | MR10: 0 | MS10: =MR9 -> 0 | MT10: =MS9 -> 0 | MU10: =MT9 -> 0 | MV10: =MU9 -> 0 | MW10: =MV9 -> 0 | MX10: =MW9 -> 0 | MY10: =MX9 -> 0 | MZ10: =MY9 -> 0 | NG10: EcPro23Decided2yrsago | NH10: 0 | NI10: =NH9 -> 0 | NJ10: =NI9 -> 0 | NK10: =NJ9 -> 0 | NL10: =NK9 -> 0 | NM10: =NL9 -> 0 | NN10: =NM9 -> 0 | NO10: =NN9 -> 0 | NP10: =NO9 -> 0 | NW10: EcPro24Decided2yrsago | NX10: 0 | NY10: =NX9 -> 0 | NZ10: =NY9 -> 0 | OA10: =NZ9 -> 0 | OB10: =OA9 -> 0 | OC10: =OB9 -> 0 | OD10: =OC9 -> 0 | OE10: =OD9 -> 0 | OF10: =OE9 -> 0
A11: EcProCost | AY11: EcPro3Cost | AZ11: =IF(AZ18=1,MAX((AZ4-AZ6)*AZ12,0),MAX((AZ4-AZ6),0)) -> 0 | BA11: =IF(AZ18=1,MAX((BA4-BA6)*AZ12,0),MAX((BA4-BA6),0)) -> 0 | BB11: =IF(AZ18=1,MAX((BB4-BB6)*AZ12,0),MAX((BB4-BB6),0)) -> 0 | BC11: =IF(AZ18=1,MAX((BC4-BC6)*AZ12,0),MAX((BC4-BC6),0)) -> 0 | BD11: =IF(AZ18=1,MAX((BD4-BD6)*AZ12,0),MAX((BD4-BD6),0)) -> 0 | BE11: =IF(AZ18=1,MAX((BE4-BE6)*AZ12,0),MAX((BE4-BE6),0)) -> 0 | BF11: =IF(AZ18=1,MAX((BF4-BF6)*AZ12,0),MAX((BF4-BF6),0)) -> 0 | BG11: =IF(AZ18=1,MAX((BG4-BG6)*AZ12,0),MAX((BG4-BG6),0)) -> 0 | BH11: =IF(AZ18=1,MAX((BH4-BH6)*AZ12,0),MAX((BH4-BH6),0)) -> 0 | BO11: EcPro4Cost | BP11: =IF(BP18=1,MAX((BP4-BP6)*BP12,0),MAX((BP4-BP6),0)) -> 0 | BQ11: =IF(BP18=1,MAX((BQ4-BQ6)*BP12,0),MAX((BQ4-BQ6),0)) -> 0 | BR11: =IF(BP18=1,MAX((BR4-BR6)*BP12,0),MAX((BR4-BR6),0)) -> 0 | BS11: =IF(BP18=1,MAX((BS4-BS6)*BP12,0),MAX((BS4-BS6),0)) -> 0 | BT11: =IF(BP18=1,MAX((BT4-BT6)*BP12,0),MAX((BT4-BT6),0)) -> 0 | BU11: =IF(BP18=1,MAX((BU4-BU6)*BP12,0),MAX((BU4-BU6),0)) -> 0 | BV11: =IF(BP18=1,MAX((BV4-BV6)*BP12,0),MAX((BV4-BV6),0)) -> 0 | BW11: =IF(BP18=1,MAX((BW4-BW6)*BP12,0),MAX((BW4-BW6),0)) -> 0 | BX11: =IF(BP18=1,MAX((BX4-BX6)*BP12,0),MAX((BX4-BX6),0)) -> 0 | CE11: EcPro5Cost | CF11: =IF(CF18=1,MAX((CF4-CF6)*CF12,0),MAX((CF4-CF6),0)) -> 0 | CG11: =IF(CF18=1,MAX((CG4-CG6)*CF12,0),MAX((CG4-CG6),0)) -> 0 | CH11: =IF(CF18=1,MAX((CH4-CH6)*CF12,0),MAX((CH4-CH6),0)) -> 0 | CI11: =IF(CF18=1,MAX((CI4-CI6)*CF12,0),MAX((CI4-CI6),0)) -> 0 | CJ11: =IF(CF18=1,MAX((CJ4-CJ6)*CF12,0),MAX((CJ4-CJ6),0)) -> 0 | CK11: =IF(CF18=1,MAX((CK4-CK6)*CF12,0),MAX((CK4-CK6),0)) -> 0 | CL11: =IF(CF18=1,MAX((CL4-CL6)*CF12,0),MAX((CL4-CL6),0)) -> 0 | CM11: =IF(CF18=1,MAX((CM4-CM6)*CF12,0),MAX((CM4-CM6),0)) -> 0 | CN11: =IF(CF18=1,MAX((CN4-CN6)*CF12,0),MAX((CN4-CN6),0)) -> 0 | CU11: EcPro6Cost | CV11: =IF(CV18=1,MAX((CV4-CV6)*CV12,0),MAX((CV4-CV6),0)) -> 0 | CW11: =IF(CV18=1,MAX((CW4-CW6)*CV12,0),MAX((CW4-CW6),0)) -> 0 | CX11: =IF(CV18=1,MAX((CX4-CX6)*CV12,0),MAX((CX4-CX6),0)) -> 0 | CY11: =IF(CV18=1,MAX((CY4-CY6)*CV12,0),MAX((CY4-CY6),0)) -> 0 | CZ11: =IF(CV18=1,MAX((CZ4-CZ6)*CV12,0),MAX((CZ4-CZ6),0)) -> 0 | DA11: =IF(CV18=1,MAX((DA4-DA6)*CV12,0),MAX((DA4-DA6),0)) -> 0 | DB11: =IF(CV18=1,MAX((DB4-DB6)*CV12,0),MAX((DB4-DB6),0)) -> 0 | DC11: =IF(CV18=1,MAX((DC4-DC6)*CV12,0),MAX((DC4-DC6),0)) -> 0 | DD11: =IF(CV18=1,MAX((DD4-DD6)*CV12,0),MAX((DD4-DD6),0)) -> 0 | DK11: EcPro7Cost | DL11: =IF(DL18=1,MAX((DL4-DL6)*DL12,0),MAX((DL4-DL6),0)) -> 0 | DM11: =IF(DL18=1,MAX((DM4-DM6)*DL12,0),MAX((DM4-DM6),0)) -> 0 | DN11: =IF(DL18=1,MAX((DN4-DN6)*DL12,0),MAX((DN4-DN6),0)) -> 0 | DO11: =IF(DL18=1,MAX((DO4-DO6)*DL12,0),MAX((DO4-DO6),0)) -> 0 | DP11: =IF(DL18=1,MAX((DP4-DP6)*DL12,0),MAX((DP4-DP6),0)) -> 0 | DQ11: =IF(DL18=1,MAX((DQ4-DQ6)*DL12,0),MAX((DQ4-DQ6),0)) -> 0 | DR11: =IF(DL18=1,MAX((DR4-DR6)*DL12,0),MAX((DR4-DR6),0)) -> 0 | DS11: =IF(DL18=1,MAX((DS4-DS6)*DL12,0),MAX((DS4-DS6),0)) -> 0 | DT11: =IF(DL18=1,MAX((DT4-DT6)*DL12,0),MAX((DT4-DT6),0)) -> 0 | EA11: EcPro8Cost | EB11: =IF(EB18=1,MAX((EB4-EB6)*EB12,0),MAX((EB4-EB6),0)) -> 0 | EC11: =IF(EB18=1,MAX((EC4-EC6)*EB12,0),MAX((EC4-EC6),0)) -> 0 | ED11: =IF(EB18=1,MAX((ED4-ED6)*EB12,0),MAX((ED4-ED6),0)) -> 0 | EE11: =IF(EB18=1,MAX((EE4-EE6)*EB12,0),MAX((EE4-EE6),0)) -> 0 | EF11: =IF(EB18=1,MAX((EF4-EF6)*EB12,0),MAX((EF4-EF6),0)) -> 0 | EG11: =IF(EB18=1,MAX((EG4-EG6)*EB12,0),MAX((EG4-EG6),0)) -> 0 | EH11: =IF(EB18=1,MAX((EH4-EH6)*EB12,0),MAX((EH4-EH6),0)) -> 0 | EI11: =IF(EB18=1,MAX((EI4-EI6)*EB12,0),MAX((EI4-EI6),0)) -> 0 | EJ11: =IF(EB18=1,MAX((EJ4-EJ6)*EB12,0),MAX((EJ4-EJ6),0)) -> 0 | EQ11: EcPro9Cost | ER11: =IF(ER18=1,MAX((ER4-ER6)*ER12,0),MAX((ER4-ER6),0)) -> 0 | ES11: =IF(ER18=1,MAX((ES4-ES6)*ER12,0),MAX((ES4-ES6),0)) -> 0 | ET11: =IF(ER18=1,MAX((ET4-ET6)*ER12,0),MAX((ET4-ET6),0)) -> 0 | EU11: =IF(ER18=1,MAX((EU4-EU6)*ER12,0),MAX((EU4-EU6),0)) -> 0 | EV11: =IF(ER18=1,MAX((EV4-EV6)*ER12,0),MAX((EV4-EV6),0)) -> 0 | EW11: =IF(ER18=1,MAX((EW4-EW6)*ER12,0),MAX((EW4-EW6),0)) -> 0 | EX11: =IF(ER18=1,MAX((EX4-EX6)*ER12,0),MAX((EX4-EX6),0)) -> 0 | EY11: =IF(ER18=1,MAX((EY4-EY6)*ER12,0),MAX((EY4-EY6),0)) -> 0 | EZ11: =IF(ER18=1,MAX((EZ4-EZ6)*ER12,0),MAX((EZ4-EZ6),0)) -> 0 | FG11: EcPro10Cost | FH11: =IF(FH18=1,MAX((FH4-FH6)*FH12,0),MAX((FH4-FH6),0)) -> 0 | FI11: =IF(FH18=1,MAX((FI4-FI6)*FH12,0),MAX((FI4-FI6),0)) -> 0 | FJ11: =IF(FH18=1,MAX((FJ4-FJ6)*FH12,0),MAX((FJ4-FJ6),0)) -> 0 | FK11: =IF(FH18=1,MAX((FK4-FK6)*FH12,0),MAX((FK4-FK6),0)) -> 0 | FL11: =IF(FH18=1,MAX((FL4-FL6)*FH12,0),MAX((FL4-FL6),0)) -> 0 | FM11: =IF(FH18=1,MAX((FM4-FM6)*FH12,0),MAX((FM4-FM6),0)) -> 0 | FN11: =IF(FH18=1,MAX((FN4-FN6)*FH12,0),MAX((FN4-FN6),0)) -> 0 | FO11: =IF(FH18=1,MAX((FO4-FO6)*FH12,0),MAX((FO4-FO6),0)) -> 0 | FP11: =IF(FH18=1,MAX((FP4-FP6)*FH12,0),MAX((FP4-FP6),0)) -> 0 | FW11: EcPro11Cost | FX11: =IF(FX18=1,MAX((FX4-FX6)*FX12,0),MAX((FX4-FX6),0)) -> 0 | FY11: =IF(FX18=1,MAX((FY4-FY6)*FX12,0),MAX((FY4-FY6),0)) -> 0 | FZ11: =IF(FX18=1,MAX((FZ4-FZ6)*FX12,0),MAX((FZ4-FZ6),0)) -> 0 | GA11: =IF(FX18=1,MAX((GA4-GA6)*FX12,0),MAX((GA4-GA6),0)) -> 0 | GB11: =IF(FX18=1,MAX((GB4-GB6)*FX12,0),MAX((GB4-GB6),0)) -> 0 | GC11: =IF(FX18=1,MAX((GC4-GC6)*FX12,0),MAX((GC4-GC6),0)) -> 0 | GD11: =IF(FX18=1,MAX((GD4-GD6)*FX12,0),MAX((GD4-GD6),0)) -> 0 | GE11: =IF(FX18=1,MAX((GE4-GE6)*FX12,0),MAX((GE4-GE6),0)) -> 0 | GF11: =IF(FX18=1,MAX((GF4-GF6)*FX12,0),MAX((GF4-GF6),0)) -> 0 | GM11: EcPro12Cost | GN11: =IF(GN18=1,MAX((GN4-GN6)*GN12,0),MAX((GN4-GN6),0)) -> 0 | GO11: =IF(GN18=1,MAX((GO4-GO6)*GN12,0),MAX((GO4-GO6),0)) -> 0 | GP11: =IF(GN18=1,MAX((GP4-GP6)*GN12,0),MAX((GP4-GP6),0)) -> 0 | GQ11: =IF(GN18=1,MAX((GQ4-GQ6)*GN12,0),MAX((GQ4-GQ6),0)) -> 0 | GR11: =IF(GN18=1,MAX((GR4-GR6)*GN12,0),MAX((GR4-GR6),0)) -> 0 | GS11: =IF(GN18=1,MAX((GS4-GS6)*GN12,0),MAX((GS4-GS6),0)) -> 0 | GT11: =IF(GN18=1,MAX((GT4-GT6)*GN12,0),MAX((GT4-GT6),0)) -> 0 | GU11: =IF(GN18=1,MAX((GU4-GU6)*GN12,0),MAX((GU4-GU6),0)) -> 0 | GV11: =IF(GN18=1,MAX((GV4-GV6)*GN12,0),MAX((GV4-GV6),0)) -> 0 | HC11: EcPro13Cost | HD11: =IF(HD18=1,MAX((HD4-HD6)*HD12,0),MAX((HD4-HD6),0)) -> 0 | HE11: =IF(HD18=1,MAX((HE4-HE6)*HD12,0),MAX((HE4-HE6),0)) -> 0 | HF11: =IF(HD18=1,MAX((HF4-HF6)*HD12,0),MAX((HF4-HF6),0)) -> 0 | HG11: =IF(HD18=1,MAX((HG4-HG6)*HD12,0),MAX((HG4-HG6),0)) -> 0 | HH11: =IF(HD18=1,MAX((HH4-HH6)*HD12,0),MAX((HH4-HH6),0)) -> 0 | HI11: =IF(HD18=1,MAX((HI4-HI6)*HD12,0),MAX((HI4-HI6),0)) -> 0 | HJ11: =IF(HD18=1,MAX((HJ4-HJ6)*HD12,0),MAX((HJ4-HJ6),0)) -> 0 | HK11: =IF(HD18=1,MAX((HK4-HK6)*HD12,0),MAX((HK4-HK6),0)) -> 0 | HL11: =IF(HD18=1,MAX((HL4-HL6)*HD12,0),MAX((HL4-HL6),0)) -> 0 | HS11: EcPro14Cost | HT11: =IF(HT18=1,MAX((HT4-HT6)*HT12,0),MAX((HT4-HT6),0)) -> 0 | HU11: =IF(HT18=1,MAX((HU4-HU6)*HT12,0),MAX((HU4-HU6),0)) -> 0 | HV11: =IF(HT18=1,MAX((HV4-HV6)*HT12,0),MAX((HV4-HV6),0)) -> 0 | HW11: =IF(HT18=1,MAX((HW4-HW6)*HT12,0),MAX((HW4-HW6),0)) -> 0 | HX11: =IF(HT18=1,MAX((HX4-HX6)*HT12,0),MAX((HX4-HX6),0)) -> 0 | HY11: =IF(HT18=1,MAX((HY4-HY6)*HT12,0),MAX((HY4-HY6),0)) -> 0 | HZ11: =IF(HT18=1,MAX((HZ4-HZ6)*HT12,0),MAX((HZ4-HZ6),0)) -> 0 | IA11: =IF(HT18=1,MAX((IA4-IA6)*HT12,0),MAX((IA4-IA6),0)) -> 0 | IB11: =IF(HT18=1,MAX((IB4-IB6)*HT12,0),MAX((IB4-IB6),0)) -> 0 | II11: EcPro15Cost | IJ11: =IF(IJ18=1,MAX((IJ4-IJ6)*IJ12,0),MAX((IJ4-IJ6),0)) -> 0 | IK11: =IF(IJ18=1,MAX((IK4-IK6)*IJ12,0),MAX((IK4-IK6),0)) -> 0 | IL11: =IF(IJ18=1,MAX((IL4-IL6)*IJ12,0),MAX((IL4-IL6),0)) -> 0 | IM11: =IF(IJ18=1,MAX((IM4-IM6)*IJ12,0),MAX((IM4-IM6),0)) -> 0 | IN11: =IF(IJ18=1,MAX((IN4-IN6)*IJ12,0),MAX((IN4-IN6),0)) -> 0 | IO11: =IF(IJ18=1,MAX((IO4-IO6)*IJ12,0),MAX((IO4-IO6),0)) -> 0 | IP11: =IF(IJ18=1,MAX((IP4-IP6)*IJ12,0),MAX((IP4-IP6),0)) -> 0 | IQ11: =IF(IJ18=1,MAX((IQ4-IQ6)*IJ12,0),MAX((IQ4-IQ6),0)) -> 0 | IR11: =IF(IJ18=1,MAX((IR4-IR6)*IJ12,0),MAX((IR4-IR6),0)) -> 0 | IY11: EcPro16Cost | IZ11: =IF(IZ18=1,MAX((IZ4-IZ6)*IZ12,0),MAX((IZ4-IZ6),0)) -> 0 | JA11: =IF(IZ18=1,MAX((JA4-JA6)*IZ12,0),MAX((JA4-JA6),0)) -> 0 | JB11: =IF(IZ18=1,MAX((JB4-JB6)*IZ12,0),MAX((JB4-JB6),0)) -> 0 | JC11: =IF(IZ18=1,MAX((JC4-JC6)*IZ12,0),MAX((JC4-JC6),0)) -> 0 | JD11: =IF(IZ18=1,MAX((JD4-JD6)*IZ12,0),MAX((JD4-JD6),0)) -> 0 | JE11: =IF(IZ18=1,MAX((JE4-JE6)*IZ12,0),MAX((JE4-JE6),0)) -> 0 | JF11: =IF(IZ18=1,MAX((JF4-JF6)*IZ12,0),MAX((JF4-JF6),0)) -> 0 | JG11: =IF(IZ18=1,MAX((JG4-JG6)*IZ12,0),MAX((JG4-JG6),0)) -> 0 | JH11: =IF(IZ18=1,MAX((JH4-JH6)*IZ12,0),MAX((JH4-JH6),0)) -> 0 | JO11: EcPro17Cost | JP11: =IF(JP18=1,MAX((JP4-JP6)*JP12,0),MAX((JP4-JP6),0)) -> 0 | JQ11: =IF(JP18=1,MAX((JQ4-JQ6)*JP12,0),MAX((JQ4-JQ6),0)) -> 0 | JR11: =IF(JP18=1,MAX((JR4-JR6)*JP12,0),MAX((JR4-JR6),0)) -> 0 | JS11: =IF(JP18=1,MAX((JS4-JS6)*JP12,0),MAX((JS4-JS6),0)) -> 0 | JT11: =IF(JP18=1,MAX((JT4-JT6)*JP12,0),MAX((JT4-JT6),0)) -> 0 | JU11: =IF(JP18=1,MAX((JU4-JU6)*JP12,0),MAX((JU4-JU6),0)) -> 0 | JV11: =IF(JP18=1,MAX((JV4-JV6)*JP12,0),MAX((JV4-JV6),0)) -> 0 | JW11: =IF(JP18=1,MAX((JW4-JW6)*JP12,0),MAX((JW4-JW6),0)) -> 0 | JX11: =IF(JP18=1,MAX((JX4-JX6)*JP12,0),MAX((JX4-JX6),0)) -> 0 | KE11: EcPro18Cost | KF11: =+MAX((KF4-KF6)*$KF12,0) -> 0 | KG11: =+MAX((KG4-KG6)*$KF12,0) -> 0 | KH11: =+MAX((KH4-KH6)*$KF12,0) -> 0 | KI11: =+MAX((KI4-KI6)*$KF12,0) -> 0 | KJ11: =+MAX((KJ4-KJ6)*$KF12,0) -> 0 | KK11: =+MAX((KK4-KK6)*$KF12,0) -> 0 | KL11: =+MAX((KL4-KL6)*$KF12,0) -> 0 | KM11: =+MAX((KM4-KM6)*$KF12,0) -> 0 | KN11: =+MAX((KN4-KN6)*$KF12,0) -> 0 | KU11: EcPro19Cost | KV11: =+MAX((KV4-KV6)*$KV12,0) -> 0 | KW11: =+MAX((KW4-KW6)*$KV12,0) -> 0 | KX11: =+MAX((KX4-KX6)*$KV12,0) -> 0 | KY11: =+MAX((KY4-KY6)*$KV12,0) -> 0 | KZ11: =+MAX((KZ4-KZ6)*$KV12,0) -> 0 | LA11: =+MAX((LA4-LA6)*$KV12,0) -> 0 | LB11: =+MAX((LB4-LB6)*$KV12,0) -> 0 | LC11: =+MAX((LC4-LC6)*$KV12,0) -> 0 | LD11: =+MAX((LD4-LD6)*$KV12,0) -> 0 | LK11: EcPro20Cost | LL11: =+MAX((LL4-LL6)*$LL12,0) -> 0 | LM11: =+MAX((LM4-LM6)*$LL12,0) -> 0 | LN11: =+MAX((LN4-LN6)*$LL12,0) -> 0 | LO11: =+MAX((LO4-LO6)*$LL12,0) -> 0 | LP11: =+MAX((LP4-LP6)*$LL12,0) -> 0 | LQ11: =+MAX((LQ4-LQ6)*$LL12,0) -> 0 | LR11: =+MAX((LR4-LR6)*$LL12,0) -> 0 | LS11: =+MAX((LS4-LS6)*$LL12,0) -> 0 | LT11: =+MAX((LT4-LT6)*$LL12,0) -> 0 | MA11: EcPro21Cost | MB11: =+MAX((MB4-MB6)*$MB12,0) -> 0 | MC11: =+MAX((MC4-MC6)*$MB12,0) -> 0 | MD11: =+MAX((MD4-MD6)*$MB12,0) -> 0 | ME11: =+MAX((ME4-ME6)*$MB12,0) -> 0 | MF11: =+MAX((MF4-MF6)*$MB12,0) -> 0 | MG11: =+MAX((MG4-MG6)*$MB12,0) -> 0 | MH11: =+MAX((MH4-MH6)*$MB12,0) -> 0 | MI11: =+MAX((MI4-MI6)*$MB12,0) -> 0 | MJ11: =+MAX((MJ4-MJ6)*$MB12,0) -> 0 | MQ11: EcPro22Cost | MR11: =+MAX((MR4-MR6)*$MR12,0) -> 0 | MS11: =+MAX((MS4-MS6)*$MR12,0) -> 0 | MT11: =+MAX((MT4-MT6)*$MR12,0) -> 0 | MU11: =+MAX((MU4-MU6)*$MR12,0) -> 0 | MV11: =+MAX((MV4-MV6)*$MR12,0) -> 0 | MW11: =+MAX((MW4-MW6)*$MR12,0) -> 0 | MX11: =+MAX((MX4-MX6)*$MR12,0) -> 0 | MY11: =+MAX((MY4-MY6)*$MR12,0) -> 0 | MZ11: =+MAX((MZ4-MZ6)*$MR12,0) -> 0 | NG11: EcPro23Cost | NH11: =+MAX((NH4-NH6)*$NH12,0) -> 0 | NI11: =+MAX((NI4-NI6)*$NH12,0) -> 0 | NJ11: =+MAX((NJ4-NJ6)*$NH12,0) -> 0 | NK11: =+MAX((NK4-NK6)*$NH12,0) -> 0 | NL11: =+MAX((NL4-NL6)*$NH12,0) -> 0 | NM11: =+MAX((NM4-NM6)*$NH12,0) -> 0 | NN11: =+MAX((NN4-NN6)*$NH12,0) -> 0 | NO11: =+MAX((NO4-NO6)*$NH12,0) -> 0 | NP11: =+MAX((NP4-NP6)*$NH12,0) -> 0 | NW11: EcPro24Cost | NX11: =+MAX((NX4-NX6)*$NX12,0) -> 0 | NY11: =+MAX((NY4-NY6)*$NX12,0) -> 0 | NZ11: =+MAX((NZ4-NZ6)*$NX12,0) -> 0 | OA11: =+MAX((OA4-OA6)*$NX12,0) -> 0 | OB11: =+MAX((OB4-OB6)*$NX12,0) -> 0 | OC11: =+MAX((OC4-OC6)*$NX12,0) -> 0 | OD11: =+MAX((OD4-OD6)*$NX12,0) -> 0 | OE11: =+MAX((OE4-OE6)*$NX12,0) -> 0 | OF11: =+MAX((OF4-OF6)*$NX12,0) -> 0
A12: EcProCostInitial | AY12: EcPro3CostValue | AZ12: 20000000 | BO12: EcPro4CostValue | BP12: 10000000 | CE12: EcPro5CostValue | CF12: 20000000 | CU12: EcPro6CostValue | CV12: 40000000 | DK12: EcPro7CostValue | DL12: 20000000 | EA12: EcPro8CostValue | EB12: 20000000 | EQ12: EcPro9CostValue | ER12: 40000000 | FG12: EcPro10CostValue | FH12: 10000000 | FW12: EcPro11CostValue | FX12: 10000000 | GM12: EcPro12CostValue | GN12: 40000000 | HC12: EcPro13CostValue | HD12: 40000000 | HS12: EcPro14CostValue | HT12: 20000000 | II12: EcPro15CostValue | IJ12: 20000000 | IY12: EcPro16CostValue | IZ12: 20000000 | JO12: EcPro17CostValue | JP12: 20000000 | KE12: EcPro18CostValue | KF12: 20000000 | KU12: EcPro19CostValue | KV12: 20000000 | LK12: EcPro20CostValue | LL12: 20000000 | MA12: EcPro21CostValue | MB12: 20000000 | MQ12: EcPro22CostValue | MR12: 20000000 | NG12: EcPro23CostValue | NH12: 20000000 | NW12: EcPro24CostValue | NX12: 20000000
A13: EcProCostRecurring | AY13: EcPro3CostRecurring | AZ13: =IF(AND(AZ6=1,AZ4=1),$AZ$14,0) -> 0 | BA13: =IF(AND(BA6=1,BA4=1),$AZ$14,0) -> 0 | BB13: =IF(AND(BB6=1,BB4=1),$AZ$14,0) -> 0 | BC13: =IF(AND(BC6=1,BC4=1),$AZ$14,0) -> 0 | BD13: =IF(AND(BD6=1,BD4=1),$AZ$14,0) -> 0 | BE13: =IF(AND(BE6=1,BE4=1),$AZ$14,0) -> 0 | BF13: =IF(AND(BF6=1,BF4=1),$AZ$14,0) -> 0 | BG13: =IF(AND(BG6=1,BG4=1),$AZ$14,0) -> 0 | BH13: =IF(AND(BH6=1,BH4=1),$AZ$14,0) -> 0 | BO13: EcPro4CostRecurring | BP13: =IF(AND(BP6=1,BP4=1),$BP$14,0) -> 0 | BQ13: =IF(AND(BQ6=1,BQ4=1),$BP$14,0) -> 0 | BR13: =IF(AND(BR6=1,BR4=1),$BP$14,0) -> 0 | BS13: =IF(AND(BS6=1,BS4=1),$BP$14,0) -> 0 | BT13: =IF(AND(BT6=1,BT4=1),$BP$14,0) -> 0 | BU13: =IF(AND(BU6=1,BU4=1),$BP$14,0) -> 0 | BV13: =IF(AND(BV6=1,BV4=1),$BP$14,0) -> 0 | BW13: =IF(AND(BW6=1,BW4=1),$BP$14,0) -> 0 | BX13: =IF(AND(BX6=1,BX4=1),$BP$14,0) -> 0 | CE13: EcPro5CostRecurring | CF13: =IF(AND(CF6=1,CF4=1),$CF$14,0) -> 0 | CG13: =IF(AND(CG6=1,CG4=1),$CF$14,0) -> 0 | CH13: =IF(AND(CH6=1,CH4=1),$CF$14,0) -> 0 | CI13: =IF(AND(CI6=1,CI4=1),$CF$14,0) -> 0 | CJ13: =IF(AND(CJ6=1,CJ4=1),$CF$14,0) -> 0 | CK13: =IF(AND(CK6=1,CK4=1),$CF$14,0) -> 0 | CL13: =IF(AND(CL6=1,CL4=1),$CF$14,0) -> 0 | CM13: =IF(AND(CM6=1,CM4=1),$CF$14,0) -> 0 | CN13: =IF(AND(CN6=1,CN4=1),$CF$14,0) -> 0 | CU13: EcPro6CostRecurring | CV13: =IF(AND(CV6=1,CV4=1),$CV$14,0) -> 0 | CW13: =IF(AND(CW6=1,CW4=1),$CV$14,0) -> 0 | CX13: =IF(AND(CX6=1,CX4=1),$CV$14,0) -> 0 | CY13: =IF(AND(CY6=1,CY4=1),$CV$14,0) -> 0 | CZ13: =IF(AND(CZ6=1,CZ4=1),$CV$14,0) -> 0 | DA13: =IF(AND(DA6=1,DA4=1),$CV$14,0) -> 0 | DB13: =IF(AND(DB6=1,DB4=1),$CV$14,0) -> 0 | DC13: =IF(AND(DC6=1,DC4=1),$CV$14,0) -> 0 | DD13: =IF(AND(DD6=1,DD4=1),$CV$14,0) -> 0 | DK13: EcPro7CostRecurring | DL13: =IF(AND(DL6=1,DL4=1),$DL$14,0) -> 0 | DM13: =IF(AND(DM6=1,DM4=1),$DL$14,0) -> 0 | DN13: =IF(AND(DN6=1,DN4=1),$DL$14,0) -> 0 | DO13: =IF(AND(DO6=1,DO4=1),$DL$14,0) -> 0 | DP13: =IF(AND(DP6=1,DP4=1),$DL$14,0) -> 0 | DQ13: =IF(AND(DQ6=1,DQ4=1),$DL$14,0) -> 0 | DR13: =IF(AND(DR6=1,DR4=1),$DL$14,0) -> 0 | DS13: =IF(AND(DS6=1,DS4=1),$DL$14,0) -> 0 | DT13: =IF(AND(DT6=1,DT4=1),$DL$14,0) -> 0 | EA13: EcPro8CostRecurring | EB13: =IF(AND(EB6=1,EB4=1),$EB$14,0) -> 0 | EC13: =IF(AND(EC6=1,EC4=1),$EB$14,0) -> 0 | ED13: =IF(AND(ED6=1,ED4=1),$EB$14,0) -> 0 | EE13: =IF(AND(EE6=1,EE4=1),$EB$14,0) -> 0 | EF13: =IF(AND(EF6=1,EF4=1),$EB$14,0) -> 0 | EG13: =IF(AND(EG6=1,EG4=1),$EB$14,0) -> 0 | EH13: =IF(AND(EH6=1,EH4=1),$EB$14,0) -> 0 | EI13: =IF(AND(EI6=1,EI4=1),$EB$14,0) -> 0 | EJ13: =IF(AND(EJ6=1,EJ4=1),$EB$14,0) -> 0 | EQ13: EcPro9CostRecurring | ER13: =IF(AND(ER6=1,ER4=1),$ER$14,0) -> 0 | ES13: =IF(AND(ES6=1,ES4=1),$ER$14,0) -> 0 | ET13: =IF(AND(ET6=1,ET4=1),$ER$14,0) -> 0 | EU13: =IF(AND(EU6=1,EU4=1),$ER$14,0) -> 0 | EV13: =IF(AND(EV6=1,EV4=1),$ER$14,0) -> 0 | EW13: =IF(AND(EW6=1,EW4=1),$ER$14,0) -> 0 | EX13: =IF(AND(EX6=1,EX4=1),$ER$14,0) -> 0 | EY13: =IF(AND(EY6=1,EY4=1),$ER$14,0) -> 0 | EZ13: =IF(AND(EZ6=1,EZ4=1),$ER$14,0) -> 0 | FG13: EcPro10CostRecurring | FH13: =IF(AND(FH6=1,FH4=1),$FH$14,0) -> 0 | FI13: =IF(AND(FI6=1,FI4=1),$FH$14,0) -> 0 | FJ13: =IF(AND(FJ6=1,FJ4=1),$FH$14,0) -> 0 | FK13: =IF(AND(FK6=1,FK4=1),$FH$14,0) -> 0 | FL13: =IF(AND(FL6=1,FL4=1),$FH$14,0) -> 0 | FM13: =IF(AND(FM6=1,FM4=1),$FH$14,0) -> 0 | FN13: =IF(AND(FN6=1,FN4=1),$FH$14,0) -> 0 | FO13: =IF(AND(FO6=1,FO4=1),$FH$14,0) -> 0 | FP13: =IF(AND(FP6=1,FP4=1),$FH$14,0) -> 0 | FW13: EcPro11CostRecurring | FX13: =IF(AND(FX6=1,FX4=1),$FX$14,0) -> 0 | FY13: =IF(AND(FY6=1,FY4=1),$FX$14,0) -> 0 | FZ13: =IF(AND(FZ6=1,FZ4=1),$FX$14,0) -> 0 | GA13: =IF(AND(GA6=1,GA4=1),$FX$14,0) -> 0 | GB13: =IF(AND(GB6=1,GB4=1),$FX$14,0) -> 0 | GC13: =IF(AND(GC6=1,GC4=1),$FX$14,0) -> 0 | GD13: =IF(AND(GD6=1,GD4=1),$FX$14,0) -> 0 | GE13: =IF(AND(GE6=1,GE4=1),$FX$14,0) -> 0 | GF13: =IF(AND(GF6=1,GF4=1),$FX$14,0) -> 0 | GM13: EcPro12CostRecurring | GN13: =IF(AND(GN6=1,GN4=1),$GN$14,0) -> 0 | GO13: =IF(AND(GO6=1,GO4=1),$GN$14,0) -> 0 | GP13: =IF(AND(GP6=1,GP4=1),$GN$14,0) -> 0 | GQ13: =IF(AND(GQ6=1,GQ4=1),$GN$14,0) -> 0 | GR13: =IF(AND(GR6=1,GR4=1),$GN$14,0) -> 0 | GS13: =IF(AND(GS6=1,GS4=1),$GN$14,0) -> 0 | GT13: =IF(AND(GT6=1,GT4=1),$GN$14,0) -> 0 | GU13: =IF(AND(GU6=1,GU4=1),$GN$14,0) -> 0 | GV13: =IF(AND(GV6=1,GV4=1),$GN$14,0) -> 0 | HC13: EcPro13CostRecurring | HD13: =IF(AND(HD6=1,HD4=1),$HD$14,0) -> 0 | HE13: =IF(AND(HE6=1,HE4=1),$HD$14,0) -> 0 | HF13: =IF(AND(HF6=1,HF4=1),$HD$14,0) -> 0 | HG13: =IF(AND(HG6=1,HG4=1),$HD$14,0) -> 0 | HH13: =IF(AND(HH6=1,HH4=1),$HD$14,0) -> 0 | HI13: =IF(AND(HI6=1,HI4=1),$HD$14,0) -> 0 | HJ13: =IF(AND(HJ6=1,HJ4=1),$HD$14,0) -> 0 | HK13: =IF(AND(HK6=1,HK4=1),$HD$14,0) -> 0 | HL13: =IF(AND(HL6=1,HL4=1),$HD$14,0) -> 0 | HS13: EcPro14CostRecurring | HT13: =IF(AND(HT6=1,HT4=1),$HT$14,0) -> 0 | HU13: =IF(AND(HU6=1,HU4=1),$HT$14,0) -> 0 | HV13: =IF(AND(HV6=1,HV4=1),$HT$14,0) -> 0 | HW13: =IF(AND(HW6=1,HW4=1),$HT$14,0) -> 0 | HX13: =IF(AND(HX6=1,HX4=1),$HT$14,0) -> 0 | HY13: =IF(AND(HY6=1,HY4=1),$HT$14,0) -> 0 | HZ13: =IF(AND(HZ6=1,HZ4=1),$HT$14,0) -> 0 | IA13: =IF(AND(IA6=1,IA4=1),$HT$14,0) -> 0 | IB13: =IF(AND(IB6=1,IB4=1),$HT$14,0) -> 0 | II13: EcPro15CostRecurring | IJ13: =IF(AND(IJ6=1,IJ4=1),$IJ$14,0) -> 0 | IK13: =IF(AND(IK6=1,IK4=1),$IJ$14,0) -> 0 | IL13: =IF(AND(IL6=1,IL4=1),$IJ$14,0) -> 0 | IM13: =IF(AND(IM6=1,IM4=1),$IJ$14,0) -> 0 | IN13: =IF(AND(IN6=1,IN4=1),$IJ$14,0) -> 0 | IO13: =IF(AND(IO6=1,IO4=1),$IJ$14,0) -> 0 | IP13: =IF(AND(IP6=1,IP4=1),$IJ$14,0) -> 0 | IQ13: =IF(AND(IQ6=1,IQ4=1),$IJ$14,0) -> 0 | IR13: =IF(AND(IR6=1,IR4=1),$IJ$14,0) -> 0 | IY13: EcPro16CostRecurring | IZ13: =IF(AND(IZ6=1,IZ4=1),$IZ$14,0) -> 0 | JA13: =IF(AND(JA6=1,JA4=1),$IZ$14,0) -> 0 | JB13: =IF(AND(JB6=1,JB4=1),$IZ$14,0) -> 0 | JC13: =IF(AND(JC6=1,JC4=1),$IZ$14,0) -> 0 | JD13: =IF(AND(JD6=1,JD4=1),$IZ$14,0) -> 0 | JE13: =IF(AND(JE6=1,JE4=1),$IZ$14,0) -> 0 | JF13: =IF(AND(JF6=1,JF4=1),$IZ$14,0) -> 0 | JG13: =IF(AND(JG6=1,JG4=1),$IZ$14,0) -> 0 | JH13: =IF(AND(JH6=1,JH4=1),$IZ$14,0) -> 0 | JO13: EcPro17CostRecurring | JP13: =IF(AND(JP6=1,JP4=1),$JP$14,0) -> 0 | JQ13: =IF(AND(JQ6=1,JQ4=1),$JP$14,0) -> 0 | JR13: =IF(AND(JR6=1,JR4=1),$JP$14,0) -> 0 | JS13: =IF(AND(JS6=1,JS4=1),$JP$14,0) -> 0 | JT13: =IF(AND(JT6=1,JT4=1),$JP$14,0) -> 0 | JU13: =IF(AND(JU6=1,JU4=1),$JP$14,0) -> 0 | JV13: =IF(AND(JV6=1,JV4=1),$JP$14,0) -> 0 | JW13: =IF(AND(JW6=1,JW4=1),$JP$14,0) -> 0 | JX13: =IF(AND(JX6=1,JX4=1),$JP$14,0) -> 0 | KE13: EcPro18CostRecurring | KF13: =IF(AND(KF6=1,KF4=1),$KF$14,0) -> 0 | KG13: =IF(AND(KG6=1,KG4=1),$KF$14,0) -> 0 | KH13: =IF(AND(KH6=1,KH4=1),$KF$14,0) -> 0 | KI13: =IF(AND(KI6=1,KI4=1),$KF$14,0) -> 0 | KJ13: =IF(AND(KJ6=1,KJ4=1),$KF$14,0) -> 0 | KK13: =IF(AND(KK6=1,KK4=1),$KF$14,0) -> 0 | KL13: =IF(AND(KL6=1,KL4=1),$KF$14,0) -> 0 | KM13: =IF(AND(KM6=1,KM4=1),$KF$14,0) -> 0 | KN13: =IF(AND(KN6=1,KN4=1),$KF$14,0) -> 0 | KU13: EcPro19CostRecurring | KV13: =IF(AND(KV6=1,KV4=1),$KV$14,0) -> 0 | KW13: =IF(AND(KW6=1,KW4=1),$KV$14,0) -> 0 | KX13: =IF(AND(KX6=1,KX4=1),$KV$14,0) -> 0 | KY13: =IF(AND(KY6=1,KY4=1),$KV$14,0) -> 0 | KZ13: =IF(AND(KZ6=1,KZ4=1),$KV$14,0) -> 0 | LA13: =IF(AND(LA6=1,LA4=1),$KV$14,0) -> 0 | LB13: =IF(AND(LB6=1,LB4=1),$KV$14,0) -> 0 | LC13: =IF(AND(LC6=1,LC4=1),$KV$14,0) -> 0 | LD13: =IF(AND(LD6=1,LD4=1),$KV$14,0) -> 0 | LK13: EcPro20CostRecurring | LL13: =IF(AND(LL6=1,LL4=1),$LL$14,0) -> 0 | LM13: =IF(AND(LM6=1,LM4=1),$LL$14,0) -> 0 | LN13: =IF(AND(LN6=1,LN4=1),$LL$14,0) -> 0 | LO13: =IF(AND(LO6=1,LO4=1),$LL$14,0) -> 0 | LP13: =IF(AND(LP6=1,LP4=1),$LL$14,0) -> 0 | LQ13: =IF(AND(LQ6=1,LQ4=1),$LL$14,0) -> 0 | LR13: =IF(AND(LR6=1,LR4=1),$LL$14,0) -> 0 | LS13: =IF(AND(LS6=1,LS4=1),$LL$14,0) -> 0 | LT13: =IF(AND(LT6=1,LT4=1),$LL$14,0) -> 0 | MA13: EcPro21CostRecurring | MB13: =IF(AND(MB6=1,MB4=1),$MB$14,0) -> 0 | MC13: =IF(AND(MC6=1,MC4=1),$MB$14,0) -> 0 | MD13: =IF(AND(MD6=1,MD4=1),$MB$14,0) -> 0 | ME13: =IF(AND(ME6=1,ME4=1),$MB$14,0) -> 0 | MF13: =IF(AND(MF6=1,MF4=1),$MB$14,0) -> 0 | MG13: =IF(AND(MG6=1,MG4=1),$MB$14,0) -> 0 | MH13: =IF(AND(MH6=1,MH4=1),$MB$14,0) -> 0 | MI13: =IF(AND(MI6=1,MI4=1),$MB$14,0) -> 0 | MJ13: =IF(AND(MJ6=1,MJ4=1),$MB$14,0) -> 0 | MQ13: EcPro22CostRecurring | MR13: =IF(AND(MR6=1,MR4=1),$MR$14,0) -> 0 | MS13: =IF(AND(MS6=1,MS4=1),$MR$14,0) -> 0 | MT13: =IF(AND(MT6=1,MT4=1),$MR$14,0) -> 0 | MU13: =IF(AND(MU6=1,MU4=1),$MR$14,0) -> 0 | MV13: =IF(AND(MV6=1,MV4=1),$MR$14,0) -> 0 | MW13: =IF(AND(MW6=1,MW4=1),$MR$14,0) -> 0 | MX13: =IF(AND(MX6=1,MX4=1),$MR$14,0) -> 0 | MY13: =IF(AND(MY6=1,MY4=1),$MR$14,0) -> 0 | MZ13: =IF(AND(MZ6=1,MZ4=1),$MR$14,0) -> 0 | NG13: EcPro23CostRecurring | NH13: =IF(AND(NH6=1,NH4=1),$NH$14,0) -> 0 | NI13: =IF(AND(NI6=1,NI4=1),$NH$14,0) -> 0 | NJ13: =IF(AND(NJ6=1,NJ4=1),$NH$14,0) -> 0 | NK13: =IF(AND(NK6=1,NK4=1),$NH$14,0) -> 0 | NL13: =IF(AND(NL6=1,NL4=1),$NH$14,0) -> 0 | NM13: =IF(AND(NM6=1,NM4=1),$NH$14,0) -> 0 | NN13: =IF(AND(NN6=1,NN4=1),$NH$14,0) -> 0 | NO13: =IF(AND(NO6=1,NO4=1),$NH$14,0) -> 0 | NP13: =IF(AND(NP6=1,NP4=1),$NH$14,0) -> 0 | NW13: EcPro24CostRecurring | NX13: =IF(AND(NX6=1,NX4=1),$NX$14,0) -> 0 | NY13: =IF(AND(NY6=1,NY4=1),$NX$14,0) -> 0 | NZ13: =IF(AND(NZ6=1,NZ4=1),$NX$14,0) -> 0 | OA13: =IF(AND(OA6=1,OA4=1),$NX$14,0) -> 0 | OB13: =IF(AND(OB6=1,OB4=1),$NX$14,0) -> 0 | OC13: =IF(AND(OC6=1,OC4=1),$NX$14,0) -> 0 | OD13: =IF(AND(OD6=1,OD4=1),$NX$14,0) -> 0 | OE13: =IF(AND(OE6=1,OE4=1),$NX$14,0) -> 0 | OF13: =IF(AND(OF6=1,OF4=1),$NX$14,0) -> 0
A14: EcProCostRecurringValue | AY14: EcPro3CostRecurringValue | AZ14: =AZ12/5 -> 4000000 | BO14: EcPro4CostRecurringValue | BP14: =BP12/5 -> 2000000 | CE14: EcPro5CostRecurringValue | CF14: =CF12/5 -> 4000000 | CU14: EcPro6CostRecurringValue | CV14: =CV12/5 -> 8000000 | DK14: EcPro7CostRecurringValue | DL14: =DL12/5 -> 4000000 | EA14: EcPro8CostRecurringValue | EB14: =EB12/5 -> 4000000 | EQ14: EcPro9CostRecurringValue | ER14: =ER12/5 -> 8000000 | FG14: EcPro10CostRecurringValue | FH14: =FH12/5 -> 2000000 | FW14: EcPro11CostRecurringValue | FX14: =FX12/5 -> 2000000 | GM14: EcPro12CostRecurringValue | GN14: =GN12/5 -> 8000000 | HC14: EcPro13CostRecurringValue | HD14: =HD12/5 -> 8000000 | HS14: EcPro14CostRecurringValue | HT14: =HT12/5 -> 4000000 | II14: EcPro15CostRecurringValue | IJ14: =IJ12/5 -> 4000000 | IY14: EcPro16CostRecurringValue | IZ14: =IZ12/5 -> 4000000 | JO14: EcPro17CostRecurringValue | JP14: =JP12/5 -> 4000000 | KE14: EcPro18CostRecurringValue | KF14: =KF12/5 -> 4000000 | KU14: EcPro19CostRecurringValue | KV14: =KV12/5 -> 4000000 | LK14: EcPro20CostRecurringValue | LL14: =LL12/5 -> 4000000 | MA14: EcPro21CostRecurringValue | MB14: =MB12/5 -> 4000000 | MQ14: EcPro22CostRecurringValue | MR14: =MR12/5 -> 4000000 | NG14: EcPro23CostRecurringValue | NH14: =NH12/5 -> 4000000 | NW14: EcPro24CostRecurringValue | NX14: =NX12/5 -> 4000000
A15: EcProReasoning | AY15: EcPro3Reasoning | BO15: EcPro4Reasoning | CE15: EcPro5Reasoning | CU15: EcPro6Reasoning | DK15: EcPro7Reasoning | EA15: EcPro8Reasoning | EQ15: EcPro9Reasoning | FG15: EcPro10Reasoning | FW15: EcPro11Reasoning | GM15: EcPro12Reasoning | HC15: EcPro13Reasoning | HS15: EcPro14Reasoning | II15: EcPro15Reasoning | IY15: EcPro16Reasoning | JO15: EcPro17Reasoning | KE15: EcPro18Reasoning | KU15: EcPro19Reasoning | LK15: EcPro20Reasoning | MA15: EcPro21Reasoning | MQ15: EcPro22Reasoning | NG15: EcPro23Reasoning | NW15: EcPro24Reasoning
A16: EcProResponse | AY16: EcPro3Response | BO16: EcPro4Response | CE16: EcPro5Response | CU16: EcPro6Response | DK16: EcPro7Response | EA16: EcPro8Response | EQ16: EcPro9Response | FG16: EcPro10Response | FW16: EcPro11Response | GM16: EcPro12Response | HC16: EcPro13Response | HS16: EcPro14Response | II16: EcPro15Response | IY16: EcPro16Response | JO16: EcPro17Response | KE16: EcPro18Response | KU16: EcPro19Response | LK16: EcPro20Response | MA16: EcPro21Response | MQ16: EcPro22Response | NG16: EcPro23Response | NW16: EcPro24Response
A17: EcProYearSelected | AY17: EcPro3YearSelected | AZ17: =IF(AZ4=1,1,IF(AND(AZ4=0,BA4=1),2,IF(AND(BA4=0,BB4=1),3,IF(AND(BB4=0,BC4=1),4,IF(AND(BC4=0,BD4=1),5,IF(AND(BD4=0,BE4=1),6,IF(AND(BE4=0,BF4=1),7,IF(AND(BF4=0,BG4=1),8,-1)))))))) -> -1 | BO17: EcPro4YearSelected | BP17: =IF(BP4=1,1,IF(AND(BP4=0,BQ4=1),2,IF(AND(BQ4=0,BR4=1),3,IF(AND(BR4=0,BS4=1),4,IF(AND(BS4=0,BT4=1),5,IF(AND(BT4=0,BU4=1),6,IF(AND(BU4=0,BV4=1),7,IF(AND(BV4=0,BW4=1),8,-1)))))))) -> -1 | CE17: EcPro5YearSelected | CF17: =IF(CF4=1,1,IF(AND(CF4=0,CG4=1),2,IF(AND(CG4=0,CH4=1),3,IF(AND(CH4=0,CI4=1),4,IF(AND(CI4=0,CJ4=1),5,IF(AND(CJ4=0,CK4=1),6,IF(AND(CK4=0,CL4=1),7,IF(AND(CL4=0,CM4=1),8,-1)))))))) -> -1 | CU17: EcPro6YearSelected | CV17: =IF(CV4=1,1,IF(AND(CV4=0,CW4=1),2,IF(AND(CW4=0,CX4=1),3,IF(AND(CX4=0,CY4=1),4,IF(AND(CY4=0,CZ4=1),5,IF(AND(CZ4=0,DA4=1),6,IF(AND(DA4=0,DB4=1),7,IF(AND(DB4=0,DC4=1),8,-1)))))))) -> -1 | DK17: EcPro7YearSelected | DL17: =IF(DL4=1,1,IF(AND(DL4=0,DM4=1),2,IF(AND(DM4=0,DN4=1),3,IF(AND(DN4=0,DO4=1),4,IF(AND(DO4=0,DP4=1),5,IF(AND(DP4=0,DQ4=1),6,IF(AND(DQ4=0,DR4=1),7,IF(AND(DR4=0,DS4=1),8,-1)))))))) -> -1 | EA17: EcPro8YearSelected | EB17: =IF(EB4=1,1,IF(AND(EB4=0,EC4=1),2,IF(AND(EC4=0,ED4=1),3,IF(AND(ED4=0,EE4=1),4,IF(AND(EE4=0,EF4=1),5,IF(AND(EF4=0,EG4=1),6,IF(AND(EG4=0,EH4=1),7,IF(AND(EH4=0,EI4=1),8,-1)))))))) -> -1 | EQ17: EcPro9YearSelected | ER17: =IF(ER4=1,1,IF(AND(ER4=0,ES4=1),2,IF(AND(ES4=0,ET4=1),3,IF(AND(ET4=0,EU4=1),4,IF(AND(EU4=0,EV4=1),5,IF(AND(EV4=0,EW4=1),6,IF(AND(EW4=0,EX4=1),7,IF(AND(EX4=0,EY4=1),8,-1)))))))) -> -1 | FG17: EcPro10YearSelected | FH17: =IF(FH4=1,1,IF(AND(FH4=0,FI4=1),2,IF(AND(FI4=0,FJ4=1),3,IF(AND(FJ4=0,FK4=1),4,IF(AND(FK4=0,FL4=1),5,IF(AND(FL4=0,FM4=1),6,IF(AND(FM4=0,FN4=1),7,IF(AND(FN4=0,FO4=1),8,-1)))))))) -> -1 | FW17: EcPro11YearSelected | FX17: =IF(FX4=1,1,IF(AND(FX4=0,FY4=1),2,IF(AND(FY4=0,FZ4=1),3,IF(AND(FZ4=0,GA4=1),4,IF(AND(GA4=0,GB4=1),5,IF(AND(GB4=0,GC4=1),6,IF(AND(GC4=0,GD4=1),7,IF(AND(GD4=0,GE4=1),8,-1)))))))) -> -1 | GM17: EcPro12YearSelected | GN17: =IF(GN4=1,1,IF(AND(GN4=0,GO4=1),2,IF(AND(GO4=0,GP4=1),3,IF(AND(GP4=0,GQ4=1),4,IF(AND(GQ4=0,GR4=1),5,IF(AND(GR4=0,GS4=1),6,IF(AND(GS4=0,GT4=1),7,IF(AND(GT4=0,GU4=1),8,-1)))))))) -> -1 | HC17: EcPro13YearSelected | HD17: =IF(HD4=1,1,IF(AND(HD4=0,HE4=1),2,IF(AND(HE4=0,HF4=1),3,IF(AND(HF4=0,HG4=1),4,IF(AND(HG4=0,HH4=1),5,IF(AND(HH4=0,HI4=1),6,IF(AND(HI4=0,HJ4=1),7,IF(AND(HJ4=0,HK4=1),8,-1)))))))) -> -1 | HS17: EcPro14YearSelected | HT17: =IF(HT4=1,1,IF(AND(HT4=0,HU4=1),2,IF(AND(HU4=0,HV4=1),3,IF(AND(HV4=0,HW4=1),4,IF(AND(HW4=0,HX4=1),5,IF(AND(HX4=0,HY4=1),6,IF(AND(HY4=0,HZ4=1),7,IF(AND(HZ4=0,IA4=1),8,-1)))))))) -> -1 | II17: EcPro15YearSelected | IJ17: =IF(IJ4=1,1,IF(AND(IJ4=0,IK4=1),2,IF(AND(IK4=0,IL4=1),3,IF(AND(IL4=0,IM4=1),4,IF(AND(IM4=0,IN4=1),5,IF(AND(IN4=0,IO4=1),6,IF(AND(IO4=0,IP4=1),7,IF(AND(IP4=0,IQ4=1),8,-1)))))))) -> -1 | IY17: EcPro16YearSelected | IZ17: =IF(IZ4=1,1,IF(AND(IZ4=0,JA4=1),2,IF(AND(JA4=0,JB4=1),3,IF(AND(JB4=0,JC4=1),4,IF(AND(JC4=0,JD4=1),5,IF(AND(JD4=0,JE4=1),6,IF(AND(JE4=0,JF4=1),7,IF(AND(JF4=0,JG4=1),8,-1)))))))) -> -1 | JO17: EcPro17YearSelected | JP17: =IF(JP4=1,1,IF(AND(JP4=0,JQ4=1),2,IF(AND(JQ4=0,JR4=1),3,IF(AND(JR4=0,JS4=1),4,IF(AND(JS4=0,JT4=1),5,IF(AND(JT4=0,JU4=1),6,IF(AND(JU4=0,JV4=1),7,IF(AND(JV4=0,JW4=1),8,-1)))))))) -> -1 | KE17: EcPro18YearSelected | KF17: =IF(KF4=1,1,IF(AND(KF4=0,KG4=1),2,IF(AND(KG4=0,KH4=1),3,IF(AND(KH4=0,KI4=1),4,IF(AND(KI4=0,KJ4=1),5,IF(AND(KJ4=0,KK4=1),6,IF(AND(KK4=0,KL4=1),7,IF(AND(KL4=0,KM4=1),8,-1)))))))) -> -1 | KU17: EcPro19YearSelected | KV17: =IF(KV4=1,1,IF(AND(KV4=0,KW4=1),2,IF(AND(KW4=0,KX4=1),3,IF(AND(KX4=0,KY4=1),4,IF(AND(KY4=0,KZ4=1),5,IF(AND(KZ4=0,LA4=1),6,IF(AND(LA4=0,LB4=1),7,IF(AND(LB4=0,LC4=1),8,-1)))))))) -> -1 | LK17: EcPro20YearSelected | LL17: =IF(LL4=1,1,IF(AND(LL4=0,LM4=1),2,IF(AND(LM4=0,LN4=1),3,IF(AND(LN4=0,LO4=1),4,IF(AND(LO4=0,LP4=1),5,IF(AND(LP4=0,LQ4=1),6,IF(AND(LQ4=0,LR4=1),7,IF(AND(LR4=0,LS4=1),8,-1)))))))) -> -1 | MA17: EcPro21YearSelected | MB17: =IF(MB4=1,1,IF(AND(MB4=0,MC4=1),2,IF(AND(MC4=0,MD4=1),3,IF(AND(MD4=0,ME4=1),4,IF(AND(ME4=0,MF4=1),5,IF(AND(MF4=0,MG4=1),6,IF(AND(MG4=0,MH4=1),7,IF(AND(MH4=0,MI4=1),8,-1)))))))) -> -1 | MQ17: EcPro22YearSelected | MR17: =IF(MR4=1,1,IF(AND(MR4=0,MS4=1),2,IF(AND(MS4=0,MT4=1),3,IF(AND(MT4=0,MU4=1),4,IF(AND(MU4=0,MV4=1),5,IF(AND(MV4=0,MW4=1),6,IF(AND(MW4=0,MX4=1),7,IF(AND(MX4=0,MY4=1),8,-1)))))))) -> -1 | NG17: EcPro23YearSelected | NH17: =IF(NH4=1,1,IF(AND(NH4=0,NI4=1),2,IF(AND(NI4=0,NJ4=1),3,IF(AND(NJ4=0,NK4=1),4,IF(AND(NK4=0,NL4=1),5,IF(AND(NL4=0,NM4=1),6,IF(AND(NM4=0,NN4=1),7,IF(AND(NN4=0,NO4=1),8,-1)))))))) -> -1 | NW17: EcPro24YearSelected | NX17: =IF(NX4=1,1,IF(AND(NX4=0,NY4=1),2,IF(AND(NY4=0,NZ4=1),3,IF(AND(NZ4=0,OA4=1),4,IF(AND(OA4=0,OB4=1),5,IF(AND(OB4=0,OC4=1),6,IF(AND(OC4=0,OD4=1),7,IF(AND(OD4=0,OE4=1),8,-1)))))))) -> -1
A18: EcProType | AY18: EcPro3Type | AZ18: 1 | BO18: EcPro4Type | BP18: 1 | CE18: EcPro5Type | CF18: 1 | CU18: EcPro6Type | CV18: 1 | DK18: EcPro7Type | DL18: 1 | EA18: EcPro8Type | EB18: 1 | EQ18: EcPro9Type | ER18: 1 | FG18: EcPro10Type | FH18: 1 | FW18: EcPro11Type | FX18: 1 | GM18: EcPro12Type | GN18: 1 | HC18: EcPro13Type | HD18: 1 | HS18: EcPro14Type | HT18: 1 | II18: EcPro15Type | IJ18: 1 | IY18: EcPro16Type | IZ18: 1 | JO18: EcPro17Type | JP18: 1
A19: EcProCanCancel | AY19: EcPro3CanCancel | AZ19: 1 | BO19: EcPro4CanCancel | BP19: 1 | CE19: EcPro5CanCancel | CF19: 1 | CU19: EcPro6CanCancel | CV19: 0 | DK19: EcPro7CanCancel | DL19: 1 | EA19: EcPro8CanCancel | EB19: 1 | EQ19: EcPro9CanCancel | ER19: 1 | FG19: EcPro10CanCancel | FH19: 1 | FW19: EcPro11CanCancel | FX19: 1 | GM19: EcPro12CanCancel | GN19: 0 | HC19: EcPro13CanCancel | HD19: 1 | HS19: EcPro14CanCancel | HT19: 0 | II19: EcPro15CanCancel | IJ19: 1 | IY19: EcPro16CanCancel | IZ19: 0 | JO19: EcPro17CanCancel | JP19: 1 | KE19: EcPro18CanCancel | KF19: 1 | KU19: EcPro19CanCancel | KV19: 1 | LK19: EcPro20CanCancel | LL19: 1 | MA19: EcPro21CanCancel | MB19: 1 | MQ19: EcPro22CanCancel | MR19: 1 | NG19: EcPro23CanCancel | NH19: 1 | NW19: EcPro24CanCancel | NX19: 1
A20: EcProYear2Impact | AY20: EcPro3Year2Impact | AZ20: 0 | BO20: EcPro4Year2Impact | BP20: 0 | CE20: EcPro5Year2Impact | CF20: 0 | CU20: EcPro6Year2Impact | CV20: 0 | DK20: EcPro7Year2Impact | DL20: 0 | EA20: EcPro8Year2Impact | EB20: 0 | EQ20: EcPro9Year2Impact | ER20: 0 | FG20: EcPro10Year2Impact | FH20: 0 | FW20: EcPro11Year2Impact | FX20: 0 | GM20: EcPro12Year2Impact | GN20: 0 | HC20: EcPro13Year2Impact | HD20: 0 | HS20: EcPro14Year2Impact | HT20: 0 | II20: EcPro15Year2Impact | IJ20: 0 | IY20: EcPro16Year2Impact | IZ20: 0 | JO20: EcPro17Year2Impact | JP20: 0 | KE20: EcPro18Year2Impact | KF20: 0 | KU20: EcPro19Year2Impact | KV20: 0 | LK20: EcPro20Year2Impact | LL20: 0 | MA20: EcPro21Year2Impact | MB20: 0 | MQ20: EcPro22Year2Impact | MR20: 0 | NG20: EcPro23Year2Impact | NH20: 0 | NW20: EcPro24Year2Impact | NX20: 0
A63: Governance
A64: GrowthWellBeing | B64: =P64+AH64+AZ64+BP64+CF64+CV64+DL64+EB64+ER64+FH64+FX64+GN64+HD64+HT64+IJ64+IZ64+JP64+KF64+KV64+LL64+MB64+MR64+NH64+NX64 -> 0 | C64: =Q64+AI64+BA64+BQ64+CG64+CW64+DM64+EC64+ES64+FI64+FY64+GO64+HE64+HU64+IK64+JA64+JQ64+KG64+KW64+LM64+MC64+MS64+NI64+NY64 -> 0 | D64: =R64+AJ64+BB64+BR64+CH64+CX64+DN64+ED64+ET64+FJ64+FZ64+GP64+HF64+HV64+IL64+JB64+JR64+KH64+KX64+LN64+MD64+MT64+NJ64+NZ64 -> 0 | E64: =S64+AK64+BC64+BS64+CI64+CY64+DO64+EE64+EU64+FK64+GA64+GQ64+HG64+HW64+IM64+JC64+JS64+KI64+KY64+LO64+ME64+MU64+NK64+OA64 -> 0 | F64: =T64+AL64+BD64+BT64+CJ64+CZ64+DP64+EF64+EV64+FL64+GB64+GR64+HH64+HX64+IN64+JD64+JT64+KJ64+KZ64+LP64+MF64+MV64+NL64+OB64 -> 0 | G64: =U64+AM64+BE64+BU64+CK64+DA64+DQ64+EG64+EW64+FM64+GC64+GS64+HI64+HY64+IO64+JE64+JU64+KK64+LA64+LQ64+MG64+MW64+NM64+OC64 -> 0 | H64: =V64+AN64+BF64+BV64+CL64+DB64+DR64+EH64+EX64+FN64+GD64+GT64+HJ64+HZ64+IP64+JF64+JV64+KL64+LB64+LR64+MH64+MX64+NN64+OD64 -> 0 | I64: =W64+AO64+BG64+BW64+CM64+DC64+DS64+EI64+EY64+FO64+GE64+GU64+HK64+IA64+IQ64+JG64+JW64+KM64+LC64+LS64+MI64+MY64+NO64+OE64 -> 0 | J64: =X64+AP64+BH64+BX64+CN64+DD64+DT64+EJ64+EZ64+FP64+GF64+GV64+HL64+IB64+IR64+JH64+JX64+KN64+LD64+LT64+MJ64+MZ64+NP64+OF64 -> 0 | P64: {=_xlfn.SWITCH(P$4, 0,0, 1, AA64,2,AC64,3,AE64,0)} -> 0 | Q64: {=_xlfn.SWITCH(Q$4, 0,0, 1, AA64,2,AC64,3,AE64,0)+P64} -> 0 | R64: {=_xlfn.SWITCH(R$4, 0,0, 1, AA64,2,AC64,3,AE64,0)+Q64} -> 0 | S64: {=_xlfn.SWITCH(S$4, 0,0, 1, AA64,2,AC64,3,AE64,0)+R64} -> 0 | T64: {=_xlfn.SWITCH(T$4, 0,0, 1, AA64,2,AC64,3,AE64,0)+S64} -> 0 | U64: {=_xlfn.SWITCH(U$4, 0,0, 1, AA64,2,AC64,3,AE64,0)+T64} -> 0 | V64: {=_xlfn.SWITCH(V$4, 0,0, 1, AA64,2,AC64,3,AE64,0)+U64} -> 0 | W64: {=_xlfn.SWITCH(W$4, 0,0, 1, AA64,2,AC64,3,AE64,0)+V64} -> 0 | X64: {=_xlfn.SWITCH(X$4, 0,0, 1, AA64,2,AC64,3,AE64,0)+W64} -> 0 | Z64: None | AA64: =_xlfn.XLOOKUP(Z64,'KPI Impacts'!$K$2:$Q$2,'KPI Impacts'!$K64:$Q64) -> 0 | AB64: None | AC64: =_xlfn.XLOOKUP(AB64,'KPI Impacts'!$K$2:$Q$2,'KPI Impacts'!$K64:$Q64) -> 0 | AD64: None | AE64: =_xlfn.XLOOKUP(AD64,'KPI Impacts'!$K$2:$Q$2,'KPI Impacts'!$K64:$Q64) -> 0 | AH64: {=_xlfn.SWITCH(AH$4, 0,0, 1, AS64,2,AU64,3,AW64,0)} -> 0 | AI64: {=_xlfn.SWITCH(AI$4, 0,0, 1, AS64,2,AU64,3,AW64,0)+AH64} -> 0 | AJ64: {=_xlfn.SWITCH(AJ$4, 0,0, 1, AS64,2,AU64,3,AW64,0)+AI64} -> 0 | AK64: {=_xlfn.SWITCH(AK$4, 0,0, 1, AS64,2,AU64,3,AW64,0)+AJ64} -> 0 | AL64: {=_xlfn.SWITCH(AL$4, 0,0, 1, AS64,2,AU64,3,AW64,0)+AK64} -> 0 | AM64: {=_xlfn.SWITCH(AM$4, 0,0, 1, AS64,2,AU64,3,AW64,0)+AL64} -> 0 | AN64: {=_xlfn.SWITCH(AN$4, 0,0, 1, AS64,2,AU64,3,AW64,0)+AM64} -> 0 | AO64: {=_xlfn.SWITCH(AO$4, 0,0, 1, AS64,2,AU64,3,AW64,0)+AN64} -> 0 | AP64: {=_xlfn.SWITCH(AP$4, 0,0, 1, AS64,2,AU64,3,AW64,0)+AO64} -> 0 | AR64: LowPos | AS64: =_xlfn.XLOOKUP(AR64,'KPI Impacts'!$K$2:$Q$2,'KPI Impacts'!$K64:$Q64) -> 0.3 | AT64: MediumPos | AU64: =_xlfn.XLOOKUP(AT64,'KPI Impacts'!$K$2:$Q$2,'KPI Impacts'!$K64:$Q64) -> 0.45 | AV64: HighPos | AW64: =_xlfn.XLOOKUP(AV64,'KPI Impacts'!$K$2:$Q$2,'KPI Impacts'!$K64:$Q64) -> 0.6 | AZ64: =AZ$4*BK64 -> 0 | BA64: =BA$4 * IF(AND(AZ$4=1,AZ$20=1), BM64, BK64) -> 0 | BB64: =BB$4 * IF(AND(BA$4=1,AZ$20=1), BM64, BK64) -> 0 | BC64: =BC$4 * IF(AND(BB$4=1,AZ$20=1), BM64, BK64) -> 0 | BD64: =BD$4 * IF(AND(BC$4=1,AZ$20=1), BM64, BK64) -> 0 | BE64: =BE$4 * IF(AND(BD$4=1,AZ$20=1), BM64, BK64) -> 0 | BF64: =BF$4 * IF(AND(BE$4=1,AZ$20=1), BM64, BK64) -> 0 | BG64: =BG$4 * IF(AND(BF$4=1,AZ$20=1), BM64, BK64) -> 0 | BH64: =BH$4 * IF(AND(BG$4=1,AZ$20=1), BM64, BK64) -> 0 | BJ64: None | BK64: =_xlfn.XLOOKUP(BJ64,'KPI Impacts'!$B$2:$H$2,'KPI Impacts'!$B64:$H64) -> 0 | BL64: None | BM64: =_xlfn.XLOOKUP(BL64,'KPI Impacts'!$B$2:$H$2,'KPI Impacts'!$B64:$H64) -> 0 | BP64: =BP$4*CA64 -> 0 | BQ64: =BQ$4 * IF(AND(BP$4=1,BP$20=1), CC64, CA64) -> 0 | BR64: =BR$4 * IF(AND(BQ$4=1,BP$20=1), CC64, CA64) -> 0 | BS64: =BS$4 * IF(AND(BR$4=1,BP$20=1), CC64, CA64) -> 0 | BT64: =BT$4 * IF(AND(BS$4=1,BP$20=1), CC64, CA64) -> 0 | BU64: =BU$4 * IF(AND(BT$4=1,BP$20=1), CC64, CA64) -> 0 | BV64: =BV$4 * IF(AND(BU$4=1,BP$20=1), CC64, CA64) -> 0 | BW64: =BW$4 * IF(AND(BV$4=1,BP$20=1), CC64, CA64) -> 0 | BX64: =BX$4 * IF(AND(BW$4=1,BP$20=1), CC64, CA64) -> 0 | BZ64: None | CA64: =_xlfn.XLOOKUP(BZ64,'KPI Impacts'!$B$2:$H$2,'KPI Impacts'!$B64:$H64) -> 0 | CB64: None | CC64: =_xlfn.XLOOKUP(CB64,'KPI Impacts'!$B$2:$H$2,'KPI Impacts'!$B64:$H64) -> 0 | CF64: =CF$4*CQ64 -> 0 | CG64: =CG$4 * IF(AND(CF$4=1,CF$20=1), CS64, CQ64) -> 0 | CH64: =CH$4 * IF(AND(CG$4=1,CF$20=1), CS64, CQ64) -> 0 | CI64: =CI$4 * IF(AND(CH$4=1,CF$20=1), CS64, CQ64) -> 0 | CJ64: =CJ$4 * IF(AND(CI$4=1,CF$20=1), CS64, CQ64) -> 0 | CK64: =CK$4 * IF(AND(CJ$4=1,CF$20=1), CS64, CQ64) -> 0 | CL64: =CL$4 * IF(AND(CK$4=1,CF$20=1), CS64, CQ64) -> 0 | CM64: =CM$4 * IF(AND(CL$4=1,CF$20=1), CS64, CQ64) -> 0 | CN64: =CN$4 * IF(AND(CM$4=1,CF$20=1), CS64, CQ64) -> 0 | CP64: LowPos | CQ64: =_xlfn.XLOOKUP(CP64,'KPI Impacts'!$B$2:$H$2,'KPI Impacts'!$B64:$H64) -> 1 | CR64: None | CS64: =_xlfn.XLOOKUP(CR64,'KPI Impacts'!$B$2:$H$2,'KPI Impacts'!$B64:$H64) -> 0 | CV64: =CV$4*DG64 -> 0 | CW64: =CW$4 * IF(AND(CV$4=1,CV$20=1), DI64, DG64) -> 0 | CX64: =CX$4 * IF(AND(CW$4=1,CV$20=1), DI64, DG64) -> 0 | CY64: =CY$4 * IF(AND(CX$4=1,CV$20=1), DI64, DG64) -> 0 | CZ64: =CZ$4 * IF(AND(CY$4=1,CV$20=1), DI64, DG64) -> 0 | DA64: =DA$4 * IF(AND(CZ$4=1,CV$20=1), DI64, DG64) -> 0 | DB64: =DB$4 * IF(AND(DA$4=1,CV$20=1), DI64, DG64) -> 0 | DC64: =DC$4 * IF(AND(DB$4=1,CV$20=1), DI64, DG64) -> 0 | DD64: =DD$4 * IF(AND(DC$4=1,CV$20=1), DI64, DG64) -> 0 | DF64: LowPos | DG64: =_xlfn.XLOOKUP(DF64,'KPI Impacts'!$B$2:$H$2,'KPI Impacts'!$B64:$H64) -> 1 | DH64: None | DI64: =_xlfn.XLOOKUP(DH64,'KPI Impacts'!$B$2:$H$2,'KPI Impacts'!$B64:$H64) -> 0 | DL64: =DL$4*DW64 -> 0 | DM64: =DM$4 * IF(AND(DL$4=1,DL$20=1), DY64, DW64) -> 0 | DN64: =DN$4 * IF(AND(DM$4=1,DL$20=1), DY64, DW64) -> 0 | DO64: =DO$4 * IF(AND(DN$4=1,DL$20=1), DY64, DW64) -> 0 | DP64: =DP$4 * IF(AND(DO$4=1,DL$20=1), DY64, DW64) -> 0 | DQ64: =DQ$4 * IF(AND(DP$4=1,DL$20=1), DY64, DW64) -> 0 | DR64: =DR$4 * IF(AND(DQ$4=1,DL$20=1), DY64, DW64) -> 0 | DS64: =DS$4 * IF(AND(DR$4=1,DL$20=1), DY64, DW64) -> 0 | DT64: =DT$4 * IF(AND(DS$4=1,DL$20=1), DY64, DW64) -> 0 | DV64: MediumPos | DW64: =_xlfn.XLOOKUP(DV64,'KPI Impacts'!$B$2:$H$2,'KPI Impacts'!$B64:$H64) -> 2 | DX64: None | DY64: =_xlfn.XLOOKUP(DX64,'KPI Impacts'!$B$2:$H$2,'KPI Impacts'!$B64:$H64) -> 0 | EB64: =EB$4*EM64 -> 0 | EC64: =EC$4 * IF(AND(EB$4=1,EB$20=1), EO64, EM64) -> 0 | ED64: =ED$4 * IF(AND(EC$4=1,EB$20=1), EO64, EM64) -> 0 | EE64: =EE$4 * IF(AND(ED$4=1,EB$20=1), EO64, EM64) -> 0 | EF64: =EF$4 * IF(AND(EE$4=1,EB$20=1), EO64, EM64) -> 0 | EG64: =EG$4 * IF(AND(EF$4=1,EB$20=1), EO64, EM64) -> 0 | EH64: =EH$4 * IF(AND(EG$4=1,EB$20=1), EO64, EM64) -> 0 | EI64: =EI$4 * IF(AND(EH$4=1,EB$20=1), EO64, EM64) -> 0 | EJ64: =EJ$4 * IF(AND(EI$4=1,EB$20=1), EO64, EM64) -> 0 | EL64: LowPos | EM64: =_xlfn.XLOOKUP(EL64,'KPI Impacts'!$B$2:$H$2,'KPI Impacts'!$B64:$H64) -> 1 | EN64: None | EO64: =_xlfn.XLOOKUP(EN64,'KPI Impacts'!$B$2:$H$2,'KPI Impacts'!$B64:$H64) -> 0 | ER64: =ER$4*FC64 -> 0 | ES64: =ES$4 * IF(AND(ER$4=1,ER$20=1), FE64, FC64) -> 0 | ET64: =ET$4 * IF(AND(ES$4=1,ER$20=1), FE64, FC64) -> 0 | EU64: =EU$4 * IF(AND(ET$4=1,ER$20=1), FE64, FC64) -> 0 | EV64: =EV$4 * IF(AND(EU$4=1,ER$20=1), FE64, FC64) -> 0 | EW64: =EW$4 * IF(AND(EV$4=1,ER$20=1), FE64, FC64) -> 0 | EX64: =EX$4 * IF(AND(EW$4=1,ER$20=1), FE64, FC64) -> 0 | EY64: =EY$4 * IF(AND(EX$4=1,ER$20=1), FE64, FC64) -> 0 | EZ64: =EZ$4 * IF(AND(EY$4=1,ER$20=1), FE64, FC64) -> 0 | FB64: LowPos | FC64: =_xlfn.XLOOKUP(FB64,'KPI Impacts'!$B$2:$H$2,'KPI Impacts'!$B64:$H64) -> 1 | FD64: None | FE64: =_xlfn.XLOOKUP(FD64,'KPI Impacts'!$B$2:$H$2,'KPI Impacts'!$B64:$H64) -> 0 | FH64: =FH$4*FS64 -> 0 | FI64: =FI$4 * IF(AND(FH$4=1,FH$20=1), FU64, FS64) -> 0 | FJ64: =FJ$4 * IF(AND(FI$4=1,FH$20=1), FU64, FS64) -> 0 | FK64: =FK$4 * IF(AND(FJ$4=1,FH$20=1), FU64, FS64) -> 0 | FL64: =FL$4 * IF(AND(FK$4=1,FH$20=1), FU64, FS64) -> 0 | FM64: =FM$4 * IF(AND(FL$4=1,FH$20=1), FU64, FS64) -> 0 | FN64: =FN$4 * IF(AND(FM$4=1,FH$20=1), FU64, FS64) -> 0 | FO64: =FO$4 * IF(AND(FN$4=1,FH$20=1), FU64, FS64) -> 0 | FP64: =FP$4 * IF(AND(FO$4=1,FH$20=1), FU64, FS64) -> 0 | FR64: HighPos | FS64: =_xlfn.XLOOKUP(FR64,'KPI Impacts'!$B$2:$H$2,'KPI Impacts'!$B64:$H64) -> 3 | FT64: None | FU64: =_xlfn.XLOOKUP(FT64,'KPI Impacts'!$B$2:$H$2,'KPI Impacts'!$B64:$H64) -> 0 | FX64: =FX$4*GI64 -> 0 | FY64: =FY$4 * IF(AND(FX$4=1,FX$20=1), GK64, GI64) -> 0 | FZ64: =FZ$4 * IF(AND(FY$4=1,FX$20=1), GK64, GI64) -> 0 | GA64: =GA$4 * IF(AND(FZ$4=1,FX$20=1), GK64, GI64) -> 0 | GB64: =GB$4 * IF(AND(GA$4=1,FX$20=1), GK64, GI64) -> 0 | GC64: =GC$4 * IF(AND(GB$4=1,FX$20=1), GK64, GI64) -> 0 | GD64: =GD$4 * IF(AND(GC$4=1,FX$20=1), GK64, GI64) -> 0 | GE64: =GE$4 * IF(AND(GD$4=1,FX$20=1), GK64, GI64) -> 0 | GF64: =GF$4 * IF(AND(GE$4=1,FX$20=1), GK64, GI64) -> 0 | GH64: MediumPos | GI64: =_xlfn.XLOOKUP(GH64,'KPI Impacts'!$B$2:$H$2,'KPI Impacts'!$B64:$H64) -> 2 | GJ64: None | GK64: =_xlfn.XLOOKUP(GJ64,'KPI Impacts'!$B$2:$H$2,'KPI Impacts'!$B64:$H64) -> 0 | GN64: =GN$4*GY64 -> 0 | GO64: =GO$4 * IF(AND(GN$4=1,GN$20=1), HA64, GY64) -> 0 | GP64: =GP$4 * IF(AND(GO$4=1,GN$20=1), HA64, GY64) -> 0 | GQ64: =GQ$4 * IF(AND(GP$4=1,GN$20=1), HA64, GY64) -> 0 | GR64: =GR$4 * IF(AND(GQ$4=1,GN$20=1), HA64, GY64) -> 0 | GS64: =GS$4 * IF(AND(GR$4=1,GN$20=1), HA64, GY64) -> 0 | GT64: =GT$4 * IF(AND(GS$4=1,GN$20=1), HA64, GY64) -> 0 | GU64: =GU$4 * IF(AND(GT$4=1,GN$20=1), HA64, GY64) -> 0 | GV64: =GV$4 * IF(AND(GU$4=1,GN$20=1), HA64, GY64) -> 0 | GX64: LowPos | GY64: =_xlfn.XLOOKUP(GX64,'KPI Impacts'!$B$2:$H$2,'KPI Impacts'!$B64:$H64) -> 1 | GZ64: None | HA64: =_xlfn.XLOOKUP(GZ64,'KPI Impacts'!$B$2:$H$2,'KPI Impacts'!$B64:$H64) -> 0 | HD64: =HD$4*HO64 -> 0 | HE64: =HE$4 * IF(AND(HD$4=1,HD$20=1), HQ64, HO64) -> 0 | HF64: =HF$4 * IF(AND(HE$4=1,HD$20=1), HQ64, HO64) -> 0 | HG64: =HG$4 * IF(AND(HF$4=1,HD$20=1), HQ64, HO64) -> 0 | HH64: =HH$4 * IF(AND(HG$4=1,HD$20=1), HQ64, HO64) -> 0 | HI64: =HI$4 * IF(AND(HH$4=1,HD$20=1), HQ64, HO64) -> 0 | HJ64: =HJ$4 * IF(AND(HI$4=1,HD$20=1), HQ64, HO64) -> 0 | HK64: =HK$4 * IF(AND(HJ$4=1,HD$20=1), HQ64, HO64) -> 0 | HL64: =HL$4 * IF(AND(HK$4=1,HD$20=1), HQ64, HO64) -> 0 | HN64: None | HO64: =_xlfn.XLOOKUP(HN64,'KPI Impacts'!$B$2:$H$2,'KPI Impacts'!$B64:$H64) -> 0 | HP64: None | HQ64: =_xlfn.XLOOKUP(HP64,'KPI Impacts'!$B$2:$H$2,'KPI Impacts'!$B64:$H64) -> 0 | HT64: =HT$4*IE64 -> 0 | HU64: =HU$4 * IF(AND(HT$4=1,HT$20=1), IG64, IE64) -> 0 | HV64: =HV$4 * IF(AND(HU$4=1,HT$20=1), IG64, IE64) -> 0 | HW64: =HW$4 * IF(AND(HV$4=1,HT$20=1), IG64, IE64) -> 0 | HX64: =HX$4 * IF(AND(HW$4=1,HT$20=1), IG64, IE64) -> 0 | HY64: =HY$4 * IF(AND(HX$4=1,HT$20=1), IG64, IE64) -> 0 | HZ64: =HZ$4 * IF(AND(HY$4=1,HT$20=1), IG64, IE64) -> 0 | IA64: =IA$4 * IF(AND(HZ$4=1,HT$20=1), IG64, IE64) -> 0 | IB64: =IB$4 * IF(AND(IA$4=1,HT$20=1), IG64, IE64) -> 0 | ID64: None | IE64: =_xlfn.XLOOKUP(ID64,'KPI Impacts'!$B$2:$H$2,'KPI Impacts'!$B64:$H64) -> 0 | IF64: None | IG64: =_xlfn.XLOOKUP(IF64,'KPI Impacts'!$B$2:$H$2,'KPI Impacts'!$B64:$H64) -> 0 | IJ64: =IJ$4*IU64 -> 0 | IK64: =IK$4 * IF(AND(IJ$4=1,IJ$20=1), IW64, IU64) -> 0 | IL64: =IL$4 * IF(AND(IK$4=1,IJ$20=1), IW64, IU64) -> 0 | IM64: =IM$4 * IF(AND(IL$4=1,IJ$20=1), IW64, IU64) -> 0 | IN64: =IN$4 * IF(AND(IM$4=1,IJ$20=1), IW64, IU64) -> 0 | IO64: =IO$4 * IF(AND(IN$4=1,IJ$20=1), IW64, IU64) -> 0 | IP64: =IP$4 * IF(AND(IO$4=1,IJ$20=1), IW64, IU64) -> 0 | IQ64: =IQ$4 * IF(AND(IP$4=1,IJ$20=1), IW64, IU64) -> 0 | IR64: =IR$4 * IF(AND(IQ$4=1,IJ$20=1), IW64, IU64) -> 0 | IT64: None | IU64: =_xlfn.XLOOKUP(IT64,'KPI Impacts'!$B$2:$H$2,'KPI Impacts'!$B64:$H64) -> 0 | IV64: None | IW64: =_xlfn.XLOOKUP(IV64,'KPI Impacts'!$B$2:$H$2,'KPI Impacts'!$B64:$H64) -> 0 | IZ64: =IZ$4*JK64 -> 0 | JA64: =JA$4 * IF(AND(IZ$4=1,IZ$20=1), JM64, JK64) -> 0 | JB64: =JB$4 * IF(AND(JA$4=1,IZ$20=1), JM64, JK64) -> 0 | JC64: =JC$4 * IF(AND(JB$4=1,IZ$20=1), JM64, JK64) -> 0 | JD64: =JD$4 * IF(AND(JC$4=1,IZ$20=1), JM64, JK64) -> 0 | JE64: =JE$4 * IF(AND(JD$4=1,IZ$20=1), JM64, JK64) -> 0 | JF64: =JF$4 * IF(AND(JE$4=1,IZ$20=1), JM64, JK64) -> 0 | JG64: =JG$4 * IF(AND(JF$4=1,IZ$20=1), JM64, JK64) -> 0 | JH64: =JH$4 * IF(AND(JG$4=1,IZ$20=1), JM64, JK64) -> 0 | JJ64: None | JK64: =_xlfn.XLOOKUP(JJ64,'KPI Impacts'!$B$2:$H$2,'KPI Impacts'!$B64:$H64) -> 0 | JL64: None | JM64: =_xlfn.XLOOKUP(JL64,'KPI Impacts'!$B$2:$H$2,'KPI Impacts'!$B64:$H64) -> 0 | JP64: =JP$4*KA64 -> 0 | JQ64: =JQ$4 * IF(AND(JP$4=1,JP$20=1), KC64, KA64) -> 0 | JR64: =JR$4 * IF(AND(JQ$4=1,JP$20=1), KC64, KA64) -> 0 | JS64: =JS$4 * IF(AND(JR$4=1,JP$20=1), KC64, KA64) -> 0 | JT64: =JT$4 * IF(AND(JS$4=1,JP$20=1), KC64, KA64) -> 0 | JU64: =JU$4 * IF(AND(JT$4=1,JP$20=1), KC64, KA64) -> 0 | JV64: =JV$4 * IF(AND(JU$4=1,JP$20=1), KC64, KA64) -> 0 | JW64: =JW$4 * IF(AND(JV$4=1,JP$20=1), KC64, KA64) -> 0 | JX64: =JX$4 * IF(AND(JW$4=1,JP$20=1), KC64, KA64) -> 0 | JZ64: None | KA64: =_xlfn.XLOOKUP(JZ64,'KPI Impacts'!$B$2:$H$2,'KPI Impacts'!$B64:$H64) -> 0 | KB64: None | KC64: =_xlfn.XLOOKUP(KB64,'KPI Impacts'!$B$2:$H$2,'KPI Impacts'!$B64:$H64) -> 0 | KF64: =KF$4*KQ64 -> 0 | KG64: =KG$4 * IF(AND(KF$4=1,KF$20=1), KS64, KQ64) -> 0 | KH64: =KH$4 * IF(AND(KG$4=1,KF$20=1), KS64, KQ64) -> 0 | KI64: =KI$4 * IF(AND(KH$4=1,KF$20=1), KS64, KQ64) -> 0 | KJ64: =KJ$4 * IF(AND(KI$4=1,KF$20=1), KS64, KQ64) -> 0 | KK64: =KK$4 * IF(AND(KJ$4=1,KF$20=1), KS64, KQ64) -> 0 | KL64: =KL$4 * IF(AND(KK$4=1,KF$20=1), KS64, KQ64) -> 0 | KM64: =KM$4 * IF(AND(KL$4=1,KF$20=1), KS64, KQ64) -> 0 | KN64: =KN$4 * IF(AND(KM$4=1,KF$20=1), KS64, KQ64) -> 0 | KP64: None | KQ64: =_xlfn.XLOOKUP(KP64,'KPI Impacts'!$B$2:$H$2,'KPI Impacts'!$B64:$H64) -> 0 | KR64: None | KS64: =_xlfn.XLOOKUP(KR64,'KPI Impacts'!$B$2:$H$2,'KPI Impacts'!$B64:$H64) -> 0 | KV64: =KV$4*LG64 -> 0 | KW64: =KW$4 * IF(AND(KV$4=1,KV$20=1), LI64, LG64) -> 0 | KX64: =KX$4 * IF(AND(KW$4=1,KV$20=1), LI64, LG64) -> 0 | KY64: =KY$4 * IF(AND(KX$4=1,KV$20=1), LI64, LG64) -> 0 | KZ64: =KZ$4 * IF(AND(KY$4=1,KV$20=1), LI64, LG64) -> 0 | LA64: =LA$4 * IF(AND(KZ$4=1,KV$20=1), LI64, LG64) -> 0 | LB64: =LB$4 * IF(AND(LA$4=1,KV$20=1), LI64, LG64) -> 0 | LC64: =LC$4 * IF(AND(LB$4=1,KV$20=1), LI64, LG64) -> 0 | LD64: =LD$4 * IF(AND(LC$4=1,KV$20=1), LI64, LG64) -> 0 | LF64: None | LG64: =_xlfn.XLOOKUP(LF64,'KPI Impacts'!$B$2:$H$2,'KPI Impacts'!$B64:$H64) -> 0 | LH64: None | LI64: =_xlfn.XLOOKUP(LH64,'KPI Impacts'!$B$2:$H$2,'KPI Impacts'!$B64:$H64) -> 0 | LL64: =LL$4*LW64 -> 0 | LM64: =LM$4 * IF(AND(LL$4=1,LL$20=1), LY64, LW64) -> 0 | LN64: =LN$4 * IF(AND(LM$4=1,LL$20=1), LY64, LW64) -> 0 | LO64: =LO$4 * IF(AND(LN$4=1,LL$20=1), LY64, LW64) -> 0 | LP64: =LP$4 * IF(AND(LO$4=1,LL$20=1), LY64, LW64) -> 0 | LQ64: =LQ$4 * IF(AND(LP$4=1,LL$20=1), LY64, LW64) -> 0 | LR64: =LR$4 * IF(AND(LQ$4=1,LL$20=1), LY64, LW64) -> 0 | LS64: =LS$4 * IF(AND(LR$4=1,LL$20=1), LY64, LW64) -> 0 | LT64: =LT$4 * IF(AND(LS$4=1,LL$20=1), LY64, LW64) -> 0 | LV64: None | LW64: =_xlfn.XLOOKUP(LV64,'KPI Impacts'!$B$2:$H$2,'KPI Impacts'!$B64:$H64) -> 0 | LX64: None | LY64: =_xlfn.XLOOKUP(LX64,'KPI Impacts'!$B$2:$H$2,'KPI Impacts'!$B64:$H64) -> 0 | MB64: =MB$4*MM64 -> 0 | MC64: =MC$4 * IF(AND(MB$4=1,MB$20=1), MO64, MM64) -> 0 | MD64: =MD$4 * IF(AND(MC$4=1,MB$20=1), MO64, MM64) -> 0 | ME64: =ME$4 * IF(AND(MD$4=1,MB$20=1), MO64, MM64) -> 0 | MF64: =MF$4 * IF(AND(ME$4=1,MB$20=1), MO64, MM64) -> 0 | MG64: =MG$4 * IF(AND(MF$4=1,MB$20=1), MO64, MM64) -> 0 | MH64: =MH$4 * IF(AND(MG$4=1,MB$20=1), MO64, MM64) -> 0 | MI64: =MI$4 * IF(AND(MH$4=1,MB$20=1), MO64, MM64) -> 0 | MJ64: =MJ$4 * IF(AND(MI$4=1,MB$20=1), MO64, MM64) -> 0 | ML64: None | MM64: =_xlfn.XLOOKUP(ML64,'KPI Impacts'!$B$2:$H$2,'KPI Impacts'!$B64:$H64) -> 0 | MN64: None | MO64: =_xlfn.XLOOKUP(MN64,'KPI Impacts'!$B$2:$H$2,'KPI Impacts'!$B64:$H64) -> 0 | MR64: =MR$4*NC64 -> 0 | MS64: =MS$4 * IF(AND(MR$4=1,MR$20=1), NE64, NC64) -> 0 | MT64: =MT$4 * IF(AND(MS$4=1,MR$20=1), NE64, NC64) -> 0 | MU64: =MU$4 * IF(AND(MT$4=1,MR$20=1), NE64, NC64) -> 0 | MV64: =MV$4 * IF(AND(MU$4=1,MR$20=1), NE64, NC64) -> 0 | MW64: =MW$4 * IF(AND(MV$4=1,MR$20=1), NE64, NC64) -> 0 | MX64: =MX$4 * IF(AND(MW$4=1,MR$20=1), NE64, NC64) -> 0 | MY64: =MY$4 * IF(AND(MX$4=1,MR$20=1), NE64, NC64) -> 0 | MZ64: =MZ$4 * IF(AND(MY$4=1,MR$20=1), NE64, NC64) -> 0 | NB64: None | NC64: =_xlfn.XLOOKUP(NB64,'KPI Impacts'!$B$2:$H$2,'KPI Impacts'!$B64:$H64) -> 0 | ND64: None | NE64: =_xlfn.XLOOKUP(ND64,'KPI Impacts'!$B$2:$H$2,'KPI Impacts'!$B64:$H64) -> 0 | NH64: =NH$4*NS64 -> 0 | NI64: =NI$4 * IF(AND(NH$4=1,NH$20=1), NU64, NS64) -> 0 | NJ64: =NJ$4 * IF(AND(NI$4=1,NH$20=1), NU64, NS64) -> 0 | NK64: =NK$4 * IF(AND(NJ$4=1,NH$20=1), NU64, NS64) -> 0 | NL64: =NL$4 * IF(AND(NK$4=1,NH$20=1), NU64, NS64) -> 0 | NM64: =NM$4 * IF(AND(NL$4=1,NH$20=1), NU64, NS64) -> 0 | NN64: =NN$4 * IF(AND(NM$4=1,NH$20=1), NU64, NS64) -> 0 | NO64: =NO$4 * IF(AND(NN$4=1,NH$20=1), NU64, NS64) -> 0 | NP64: =NP$4 * IF(AND(NO$4=1,NH$20=1), NU64, NS64) -> 0 | NR64: None | NS64: =_xlfn.XLOOKUP(NR64,'KPI Impacts'!$B$2:$H$2,'KPI Impacts'!$B64:$H64) -> 0 | NT64: None | NU64: =_xlfn.XLOOKUP(NT64,'KPI Impacts'!$B$2:$H$2,'KPI Impacts'!$B64:$H64) -> 0 | NX64: =NX$4*OI64 -> 0 | NY64: =NY$4 * IF(AND(NX$4=1,NX$20=1), OK64, OI64) -> 0 | NZ64: =NZ$4 * IF(AND(NY$4=1,NX$20=1), OK64, OI64) -> 0 | OA64: =OA$4 * IF(AND(NZ$4=1,NX$20=1), OK64, OI64) -> 0 | OB64: =OB$4 * IF(AND(OA$4=1,NX$20=1), OK64, OI64) -> 0 | OC64: =OC$4 * IF(AND(OB$4=1,NX$20=1), OK64, OI64) -> 0 | OD64: =OD$4 * IF(AND(OC$4=1,NX$20=1), OK64, OI64) -> 0 | OE64: =OE$4 * IF(AND(OD$4=1,NX$20=1), OK64, OI64) -> 0 | OF64: =OF$4 * IF(AND(OE$4=1,NX$20=1), OK64, OI64) -> 0 | OH64: None | OI64: =_xlfn.XLOOKUP(OH64,'KPI Impacts'!$B$2:$H$2,'KPI Impacts'!$B64:$H64) -> 0 | OJ64: None | OK64: =_xlfn.XLOOKUP(OJ64,'KPI Impacts'!$B$2:$H$2,'KPI Impacts'!$B64:$H64) -> 0
A65: HumanRights | B65: =P65+AH65+AZ65+BP65+CF65+CV65+DL65+EB65+ER65+FH65+FX65+GN65+HD65+HT65+IJ65+IZ65+JP65+KF65+KV65+LL65+MB65+MR65+NH65+NX65 -> 0 | C65: =Q65+AI65+BA65+BQ65+CG65+CW65+DM65+EC65+ES65+FI65+FY65+GO65+HE65+HU65+IK65+JA65+JQ65+KG65+KW65+LM65+MC65+MS65+NI65+NY65 -> 0 | D65: =R65+AJ65+BB65+BR65+CH65+CX65+DN65+ED65+ET65+FJ65+FZ65+GP65+HF65+HV65+IL65+JB65+JR65+KH65+KX65+LN65+MD65+MT65+NJ65+NZ65 -> 0 | E65: =S65+AK65+BC65+BS65+CI65+CY65+DO65+EE65+EU65+FK65+GA65+GQ65+HG65+HW65+IM65+JC65+JS65+KI65+KY65+LO65+ME65+MU65+NK65+OA65 -> 0 | F65: =T65+AL65+BD65+BT65+CJ65+CZ65+DP65+EF65+EV65+FL65+GB65+GR65+HH65+HX65+IN65+JD65+JT65+KJ65+KZ65+LP65+MF65+MV65+NL65+OB65 -> 0 | G65: =U65+AM65+BE65+BU65+CK65+DA65+DQ65+EG65+EW65+FM65+GC65+GS65+HI65+HY65+IO65+JE65+JU65+KK65+LA65+LQ65+MG65+MW65+NM65+OC65 -> 0 | H65: =V65+AN65+BF65+BV65+CL65+DB65+DR65+EH65+EX65+FN65+GD65+GT65+HJ65+HZ65+IP65+JF65+JV65+KL65+LB65+LR65+MH65+MX65+NN65+OD65 -> 0 | I65: =W65+AO65+BG65+BW65+CM65+DC65+DS65+EI65+EY65+FO65+GE65+GU65+HK65+IA65+IQ65+JG65+JW65+KM65+LC65+LS65+MI65+MY65+NO65+OE65 -> 0 | J65: =X65+AP65+BH65+BX65+CN65+DD65+DT65+EJ65+EZ65+FP65+GF65+GV65+HL65+IB65+IR65+JH65+JX65+KN65+LD65+LT65+MJ65+MZ65+NP65+OF65 -> 0 | P65: {=_xlfn.SWITCH(P$4, 0,0, 1, AA65,2,AC65,3,AE65,0)} -> 0 | Q65: {=_xlfn.SWITCH(Q$4, 0,0, 1, AA65,2,AC65,3,AE65,0)+P65} -> 0 | R65: {=_xlfn.SWITCH(R$4, 0,0, 1, AA65,2,AC65,3,AE65,0)+Q65} -> 0 | S65: {=_xlfn.SWITCH(S$4, 0,0, 1, AA65,2,AC65,3,AE65,0)+R65} -> 0 | T65: {=_xlfn.SWITCH(T$4, 0,0, 1, AA65,2,AC65,3,AE65,0)+S65} -> 0 | U65: {=_xlfn.SWITCH(U$4, 0,0, 1, AA65,2,AC65,3,AE65,0)+T65} -> 0 | V65: {=_xlfn.SWITCH(V$4, 0,0, 1, AA65,2,AC65,3,AE65,0)+U65} -> 0 | W65: {=_xlfn.SWITCH(W$4, 0,0, 1, AA65,2,AC65,3,AE65,0)+V65} -> 0 | X65: {=_xlfn.SWITCH(X$4, 0,0, 1, AA65,2,AC65,3,AE65,0)+W65} -> 0 | Z65: None | AA65: =_xlfn.XLOOKUP(Z65,'KPI Impacts'!$K$2:$Q$2,'KPI Impacts'!$K65:$Q65) -> 0 | AB65: None | AC65: =_xlfn.XLOOKUP(AB65,'KPI Impacts'!$K$2:$Q$2,'KPI Impacts'!$K65:$Q65) -> 0 | AD65: None | AE65: =_xlfn.XLOOKUP(AD65,'KPI Impacts'!$K$2:$Q$2,'KPI Impacts'!$K65:$Q65) -> 0 | AH65: {=_xlfn.SWITCH(AH$4, 0,0, 1, AS65,2,AU65,3,AW65,0)} -> 0 | AI65: {=_xlfn.SWITCH(AI$4, 0,0, 1, AS65,2,AU65,3,AW65,0)+AH65} -> 0 | AJ65: {=_xlfn.SWITCH(AJ$4, 0,0, 1, AS65,2,AU65,3,AW65,0)+AI65} -> 0 | AK65: {=_xlfn.SWITCH(AK$4, 0,0, 1, AS65,2,AU65,3,AW65,0)+AJ65} -> 0 | AL65: {=_xlfn.SWITCH(AL$4, 0,0, 1, AS65,2,AU65,3,AW65,0)+AK65} -> 0 | AM65: {=_xlfn.SWITCH(AM$4, 0,0, 1, AS65,2,AU65,3,AW65,0)+AL65} -> 0 | AN65: {=_xlfn.SWITCH(AN$4, 0,0, 1, AS65,2,AU65,3,AW65,0)+AM65} -> 0 | AO65: {=_xlfn.SWITCH(AO$4, 0,0, 1, AS65,2,AU65,3,AW65,0)+AN65} -> 0 | AP65: {=_xlfn.SWITCH(AP$4, 0,0, 1, AS65,2,AU65,3,AW65,0)+AO65} -> 0 | AR65: None | AS65: =_xlfn.XLOOKUP(AR65,'KPI Impacts'!$K$2:$Q$2,'KPI Impacts'!$K65:$Q65) -> 0 | AT65: None | AU65: =_xlfn.XLOOKUP(AT65,'KPI Impacts'!$K$2:$Q$2,'KPI Impacts'!$K65:$Q65) -> 0 | AV65: None | AW65: =_xlfn.XLOOKUP(AV65,'KPI Impacts'!$K$2:$Q$2,'KPI Impacts'!$K65:$Q65) -> 0 | AZ65: =AZ$4*BK65 -> 0 | BA65: =BA$4 * IF(AND(AZ$4=1,AZ$20=1), BM65, BK65) -> 0 | BB65: =BB$4 * IF(AND(BA$4=1,AZ$20=1), BM65, BK65) -> 0 | BC65: =BC$4 * IF(AND(BB$4=1,AZ$20=1), BM65, BK65) -> 0 | BD65: =BD$4 * IF(AND(BC$4=1,AZ$20=1), BM65, BK65) -> 0 | BE65: =BE$4 * IF(AND(BD$4=1,AZ$20=1), BM65, BK65) -> 0 | BF65: =BF$4 * IF(AND(BE$4=1,AZ$20=1), BM65, BK65) -> 0 | BG65: =BG$4 * IF(AND(BF$4=1,AZ$20=1), BM65, BK65) -> 0 | BH65: =BH$4 * IF(AND(BG$4=1,AZ$20=1), BM65, BK65) -> 0 | BJ65: None | BK65: =_xlfn.XLOOKUP(BJ65,'KPI Impacts'!$B$2:$H$2,'KPI Impacts'!$B65:$H65) -> 0 | BL65: None | BM65: =_xlfn.XLOOKUP(BL65,'KPI Impacts'!$B$2:$H$2,'KPI Impacts'!$B65:$H65) -> 0 | BP65: =BP$4*CA65 -> 0 | BQ65: =BQ$4 * IF(AND(BP$4=1,BP$20=1), CC65, CA65) -> 0 | BR65: =BR$4 * IF(AND(BQ$4=1,BP$20=1), CC65, CA65) -> 0 | BS65: =BS$4 * IF(AND(BR$4=1,BP$20=1), CC65, CA65) -> 0 | BT65: =BT$4 * IF(AND(BS$4=1,BP$20=1), CC65, CA65) -> 0 | BU65: =BU$4 * IF(AND(BT$4=1,BP$20=1), CC65, CA65) -> 0 | BV65: =BV$4 * IF(AND(BU$4=1,BP$20=1), CC65, CA65) -> 0 | BW65: =BW$4 * IF(AND(BV$4=1,BP$20=1), CC65, CA65) -> 0 | BX65: =BX$4 * IF(AND(BW$4=1,BP$20=1), CC65, CA65) -> 0 | BZ65: None | CA65: =_xlfn.XLOOKUP(BZ65,'KPI Impacts'!$B$2:$H$2,'KPI Impacts'!$B65:$H65) -> 0 | CB65: None | CC65: =_xlfn.XLOOKUP(CB65,'KPI Impacts'!$B$2:$H$2,'KPI Impacts'!$B65:$H65) -> 0 | CF65: =CF$4*CQ65 -> 0 | CG65: =CG$4 * IF(AND(CF$4=1,CF$20=1), CS65, CQ65) -> 0 | CH65: =CH$4 * IF(AND(CG$4=1,CF$20=1), CS65, CQ65) -> 0 | CI65: =CI$4 * IF(AND(CH$4=1,CF$20=1), CS65, CQ65) -> 0 | CJ65: =CJ$4 * IF(AND(CI$4=1,CF$20=1), CS65, CQ65) -> 0 | CK65: =CK$4 * IF(AND(CJ$4=1,CF$20=1), CS65, CQ65) -> 0 | CL65: =CL$4 * IF(AND(CK$4=1,CF$20=1), CS65, CQ65) -> 0 | CM65: =CM$4 * IF(AND(CL$4=1,CF$20=1), CS65, CQ65) -> 0 | CN65: =CN$4 * IF(AND(CM$4=1,CF$20=1), CS65, CQ65) -> 0 | CP65: None | CQ65: =_xlfn.XLOOKUP(CP65,'KPI Impacts'!$B$2:$H$2,'KPI Impacts'!$B65:$H65) -> 0 | CR65: None | CS65: =_xlfn.XLOOKUP(CR65,'KPI Impacts'!$B$2:$H$2,'KPI Impacts'!$B65:$H65) -> 0 | CV65: =CV$4*DG65 -> 0 | CW65: =CW$4 * IF(AND(CV$4=1,CV$20=1), DI65, DG65) -> 0 | CX65: =CX$4 * IF(AND(CW$4=1,CV$20=1), DI65, DG65) -> 0 | CY65: =CY$4 * IF(AND(CX$4=1,CV$20=1), DI65, DG65) -> 0 | CZ65: =CZ$4 * IF(AND(CY$4=1,CV$20=1), DI65, DG65) -> 0 | DA65: =DA$4 * IF(AND(CZ$4=1,CV$20=1), DI65, DG65) -> 0 | DB65: =DB$4 * IF(AND(DA$4=1,CV$20=1), DI65, DG65) -> 0 | DC65: =DC$4 * IF(AND(DB$4=1,CV$20=1), DI65, DG65) -> 0 | DD65: =DD$4 * IF(AND(DC$4=1,CV$20=1), DI65, DG65) -> 0 | DF65: None | DG65: =_xlfn.XLOOKUP(DF65,'KPI Impacts'!$B$2:$H$2,'KPI Impacts'!$B65:$H65) -> 0 | DH65: None | DI65: =_xlfn.XLOOKUP(DH65,'KPI Impacts'!$B$2:$H$2,'KPI Impacts'!$B65:$H65) -> 0 | DL65: =DL$4*DW65 -> 0 | DM65: =DM$4 * IF(AND(DL$4=1,DL$20=1), DY65, DW65) -> 0 | DN65: =DN$4 * IF(AND(DM$4=1,DL$20=1), DY65, DW65) -> 0 | DO65: =DO$4 * IF(AND(DN$4=1,DL$20=1), DY65, DW65) -> 0 | DP65: =DP$4 * IF(AND(DO$4=1,DL$20=1), DY65, DW65) -> 0 | DQ65: =DQ$4 * IF(AND(DP$4=1,DL$20=1), DY65, DW65) -> 0 | DR65: =DR$4 * IF(AND(DQ$4=1,DL$20=1), DY65, DW65) -> 0 | DS65: =DS$4 * IF(AND(DR$4=1,DL$20=1), DY65, DW65) -> 0 | DT65: =DT$4 * IF(AND(DS$4=1,DL$20=1), DY65, DW65) -> 0 | DV65: LowPos | DW65: =_xlfn.XLOOKUP(DV65,'KPI Impacts'!$B$2:$H$2,'KPI Impacts'!$B65:$H65) -> 1 | DX65: None | DY65: =_xlfn.XLOOKUP(DX65,'KPI Impacts'!$B$2:$H$2,'KPI Impacts'!$B65:$H65) -> 0 | EB65: =EB$4*EM65 -> 0 | EC65: =EC$4 * IF(AND(EB$4=1,EB$20=1), EO65, EM65) -> 0 | ED65: =ED$4 * IF(AND(EC$4=1,EB$20=1), EO65, EM65) -> 0 | EE65: =EE$4 * IF(AND(ED$4=1,EB$20=1), EO65, EM65) -> 0 | EF65: =EF$4 * IF(AND(EE$4=1,EB$20=1), EO65, EM65) -> 0 | EG65: =EG$4 * IF(AND(EF$4=1,EB$20=1), EO65, EM65) -> 0 | EH65: =EH$4 * IF(AND(EG$4=1,EB$20=1), EO65, EM65) -> 0 | EI65: =EI$4 * IF(AND(EH$4=1,EB$20=1), EO65, EM65) -> 0 | EJ65: =EJ$4 * IF(AND(EI$4=1,EB$20=1), EO65, EM65) -> 0 | EL65: None | EM65: =_xlfn.XLOOKUP(EL65,'KPI Impacts'!$B$2:$H$2,'KPI Impacts'!$B65:$H65) -> 0 | EN65: None | EO65: =_xlfn.XLOOKUP(EN65,'KPI Impacts'!$B$2:$H$2,'KPI Impacts'!$B65:$H65) -> 0 | ER65: =ER$4*FC65 -> 0 | ES65: =ES$4 * IF(AND(ER$4=1,ER$20=1), FE65, FC65) -> 0 | ET65: =ET$4 * IF(AND(ES$4=1,ER$20=1), FE65, FC65) -> 0 | EU65: =EU$4 * IF(AND(ET$4=1,ER$20=1), FE65, FC65) -> 0 | EV65: =EV$4 * IF(AND(EU$4=1,ER$20=1), FE65, FC65) -> 0 | EW65: =EW$4 * IF(AND(EV$4=1,ER$20=1), FE65, FC65) -> 0 | EX65: =EX$4 * IF(AND(EW$4=1,ER$20=1), FE65, FC65) -> 0 | EY65: =EY$4 * IF(AND(EX$4=1,ER$20=1), FE65, FC65) -> 0 | EZ65: =EZ$4 * IF(AND(EY$4=1,ER$20=1), FE65, FC65) -> 0 | FB65: None | FC65: =_xlfn.XLOOKUP(FB65,'KPI Impacts'!$B$2:$H$2,'KPI Impacts'!$B65:$H65) -> 0 | FD65: None | FE65: =_xlfn.XLOOKUP(FD65,'KPI Impacts'!$B$2:$H$2,'KPI Impacts'!$B65:$H65) -> 0 | FH65: =FH$4*FS65 -> 0 | FI65: =FI$4 * IF(AND(FH$4=1,FH$20=1), FU65, FS65) -> 0 | FJ65: =FJ$4 * IF(AND(FI$4=1,FH$20=1), FU65, FS65) -> 0 | FK65: =FK$4 * IF(AND(FJ$4=1,FH$20=1), FU65, FS65) -> 0 | FL65: =FL$4 * IF(AND(FK$4=1,FH$20=1), FU65, FS65) -> 0 | FM65: =FM$4 * IF(AND(FL$4=1,FH$20=1), FU65, FS65) -> 0 | FN65: =FN$4 * IF(AND(FM$4=1,FH$20=1), FU65, FS65) -> 0 | FO65: =FO$4 * IF(AND(FN$4=1,FH$20=1), FU65, FS65) -> 0 | FP65: =FP$4 * IF(AND(FO$4=1,FH$20=1), FU65, FS65) -> 0 | FR65: MediumPos | FS65: =_xlfn.XLOOKUP(FR65,'KPI Impacts'!$B$2:$H$2,'KPI Impacts'!$B65:$H65) -> 2 | FT65: None | FU65: =_xlfn.XLOOKUP(FT65,'KPI Impacts'!$B$2:$H$2,'KPI Impacts'!$B65:$H65) -> 0 | FX65: =FX$4*GI65 -> 0 | FY65: =FY$4 * IF(AND(FX$4=1,FX$20=1), GK65, GI65) -> 0 | FZ65: =FZ$4 * IF(AND(FY$4=1,FX$20=1), GK65, GI65) -> 0 | GA65: =GA$4 * IF(AND(FZ$4=1,FX$20=1), GK65, GI65) -> 0 | GB65: =GB$4 * IF(AND(GA$4=1,FX$20=1), GK65, GI65) -> 0 | GC65: =GC$4 * IF(AND(GB$4=1,FX$20=1), GK65, GI65) -> 0 | GD65: =GD$4 * IF(AND(GC$4=1,FX$20=1), GK65, GI65) -> 0 | GE65: =GE$4 * IF(AND(GD$4=1,FX$20=1), GK65, GI65) -> 0 | GF65: =GF$4 * IF(AND(GE$4=1,FX$20=1), GK65, GI65) -> 0 | GH65: None | GI65: =_xlfn.XLOOKUP(GH65,'KPI Impacts'!$B$2:$H$2,'KPI Impacts'!$B65:$H65) -> 0 | GJ65: None | GK65: =_xlfn.XLOOKUP(GJ65,'KPI Impacts'!$B$2:$H$2,'KPI Impacts'!$B65:$H65) -> 0 | GN65: =GN$4*GY65 -> 0 | GO65: =GO$4 * IF(AND(GN$4=1,GN$20=1), HA65, GY65) -> 0 | GP65: =GP$4 * IF(AND(GO$4=1,GN$20=1), HA65, GY65) -> 0 | GQ65: =GQ$4 * IF(AND(GP$4=1,GN$20=1), HA65, GY65) -> 0 | GR65: =GR$4 * IF(AND(GQ$4=1,GN$20=1), HA65, GY65) -> 0 | GS65: =GS$4 * IF(AND(GR$4=1,GN$20=1), HA65, GY65) -> 0 | GT65: =GT$4 * IF(AND(GS$4=1,GN$20=1), HA65, GY65) -> 0 | GU65: =GU$4 * IF(AND(GT$4=1,GN$20=1), HA65, GY65) -> 0 | GV65: =GV$4 * IF(AND(GU$4=1,GN$20=1), HA65, GY65) -> 0 | GX65: None | GY65: =_xlfn.XLOOKUP(GX65,'KPI Impacts'!$B$2:$H$2,'KPI Impacts'!$B65:$H65) -> 0 | GZ65: None | HA65: =_xlfn.XLOOKUP(GZ65,'KPI Impacts'!$B$2:$H$2,'KPI Impacts'!$B65:$H65) -> 0 | HD65: =HD$4*HO65 -> 0 | HE65: =HE$4 * IF(AND(HD$4=1,HD$20=1), HQ65, HO65) -> 0 | HF65: =HF$4 * IF(AND(HE$4=1,HD$20=1), HQ65, HO65) -> 0 | HG65: =HG$4 * IF(AND(HF$4=1,HD$20=1), HQ65, HO65) -> 0 | HH65: =HH$4 * IF(AND(HG$4=1,HD$20=1), HQ65, HO65) -> 0 | HI65: =HI$4 * IF(AND(HH$4=1,HD$20=1), HQ65, HO65) -> 0 | HJ65: =HJ$4 * IF(AND(HI$4=1,HD$20=1), HQ65, HO65) -> 0 | HK65: =HK$4 * IF(AND(HJ$4=1,HD$20=1), HQ65, HO65) -> 0 | HL65: =HL$4 * IF(AND(HK$4=1,HD$20=1), HQ65, HO65) -> 0 | HN65: None | HO65: =_xlfn.XLOOKUP(HN65,'KPI Impacts'!$B$2:$H$2,'KPI Impacts'!$B65:$H65) -> 0 | HP65: None | HQ65: =_xlfn.XLOOKUP(HP65,'KPI Impacts'!$B$2:$H$2,'KPI Impacts'!$B65:$H65) -> 0 | HT65: =HT$4*IE65 -> 0 | HU65: =HU$4 * IF(AND(HT$4=1,HT$20=1), IG65, IE65) -> 0 | HV65: =HV$4 * IF(AND(HU$4=1,HT$20=1), IG65, IE65) -> 0 | HW65: =HW$4 * IF(AND(HV$4=1,HT$20=1), IG65, IE65) -> 0 | HX65: =HX$4 * IF(AND(HW$4=1,HT$20=1), IG65, IE65) -> 0 | HY65: =HY$4 * IF(AND(HX$4=1,HT$20=1), IG65, IE65) -> 0 | HZ65: =HZ$4 * IF(AND(HY$4=1,HT$20=1), IG65, IE65) -> 0 | IA65: =IA$4 * IF(AND(HZ$4=1,HT$20=1), IG65, IE65) -> 0 | IB65: =IB$4 * IF(AND(IA$4=1,HT$20=1), IG65, IE65) -> 0 | ID65: None | IE65: =_xlfn.XLOOKUP(ID65,'KPI Impacts'!$B$2:$H$2,'KPI Impacts'!$B65:$H65) -> 0 | IF65: None | IG65: =_xlfn.XLOOKUP(IF65,'KPI Impacts'!$B$2:$H$2,'KPI Impacts'!$B65:$H65) -> 0 | IJ65: =IJ$4*IU65 -> 0 | IK65: =IK$4 * IF(AND(IJ$4=1,IJ$20=1), IW65, IU65) -> 0 | IL65: =IL$4 * IF(AND(IK$4=1,IJ$20=1), IW65, IU65) -> 0 | IM65: =IM$4 * IF(AND(IL$4=1,IJ$20=1), IW65, IU65) -> 0 | IN65: =IN$4 * IF(AND(IM$4=1,IJ$20=1), IW65, IU65) -> 0 | IO65: =IO$4 * IF(AND(IN$4=1,IJ$20=1), IW65, IU65) -> 0 | IP65: =IP$4 * IF(AND(IO$4=1,IJ$20=1), IW65, IU65) -> 0 | IQ65: =IQ$4 * IF(AND(IP$4=1,IJ$20=1), IW65, IU65) -> 0 | IR65: =IR$4 * IF(AND(IQ$4=1,IJ$20=1), IW65, IU65) -> 0 | IT65: None | IU65: =_xlfn.XLOOKUP(IT65,'KPI Impacts'!$B$2:$H$2,'KPI Impacts'!$B65:$H65) -> 0 | IV65: None | IW65: =_xlfn.XLOOKUP(IV65,'KPI Impacts'!$B$2:$H$2,'KPI Impacts'!$B65:$H65) -> 0 | IZ65: =IZ$4*JK65 -> 0 | JA65: =JA$4 * IF(AND(IZ$4=1,IZ$20=1), JM65, JK65) -> 0 | JB65: =JB$4 * IF(AND(JA$4=1,IZ$20=1), JM65, JK65) -> 0 | JC65: =JC$4 * IF(AND(JB$4=1,IZ$20=1), JM65, JK65) -> 0 | JD65: =JD$4 * IF(AND(JC$4=1,IZ$20=1), JM65, JK65) -> 0 | JE65: =JE$4 * IF(AND(JD$4=1,IZ$20=1), JM65, JK65) -> 0 | JF65: =JF$4 * IF(AND(JE$4=1,IZ$20=1), JM65, JK65) -> 0 | JG65: =JG$4 * IF(AND(JF$4=1,IZ$20=1), JM65, JK65) -> 0 | JH65: =JH$4 * IF(AND(JG$4=1,IZ$20=1), JM65, JK65) -> 0 | JJ65: None | JK65: =_xlfn.XLOOKUP(JJ65,'KPI Impacts'!$B$2:$H$2,'KPI Impacts'!$B65:$H65) -> 0 | JL65: None | JM65: =_xlfn.XLOOKUP(JL65,'KPI Impacts'!$B$2:$H$2,'KPI Impacts'!$B65:$H65) -> 0 | JP65: =JP$4*KA65 -> 0 | JQ65: =JQ$4 * IF(AND(JP$4=1,JP$20=1), KC65, KA65) -> 0 | JR65: =JR$4 * IF(AND(JQ$4=1,JP$20=1), KC65, KA65) -> 0 | JS65: =JS$4 * IF(AND(JR$4=1,JP$20=1), KC65, KA65) -> 0 | JT65: =JT$4 * IF(AND(JS$4=1,JP$20=1), KC65, KA65) -> 0 | JU65: =JU$4 * IF(AND(JT$4=1,JP$20=1), KC65, KA65) -> 0 | JV65: =JV$4 * IF(AND(JU$4=1,JP$20=1), KC65, KA65) -> 0 | JW65: =JW$4 * IF(AND(JV$4=1,JP$20=1), KC65, KA65) -> 0 | JX65: =JX$4 * IF(AND(JW$4=1,JP$20=1), KC65, KA65) -> 0 | JZ65: None | KA65: =_xlfn.XLOOKUP(JZ65,'KPI Impacts'!$B$2:$H$2,'KPI Impacts'!$B65:$H65) -> 0 | KB65: None | KC65: =_xlfn.XLOOKUP(KB65,'KPI Impacts'!$B$2:$H$2,'KPI Impacts'!$B65:$H65) -> 0 | KF65: =KF$4*KQ65 -> 0 | KG65: =KG$4 * IF(AND(KF$4=1,KF$20=1), KS65, KQ65) -> 0 | KH65: =KH$4 * IF(AND(KG$4=1,KF$20=1), KS65, KQ65) -> 0 | KI65: =KI$4 * IF(AND(KH$4=1,KF$20=1), KS65, KQ65) -> 0 | KJ65: =KJ$4 * IF(AND(KI$4=1,KF$20=1), KS65, KQ65) -> 0 | KK65: =KK$4 * IF(AND(KJ$4=1,KF$20=1), KS65, KQ65) -> 0 | KL65: =KL$4 * IF(AND(KK$4=1,KF$20=1), KS65, KQ65) -> 0 | KM65: =KM$4 * IF(AND(KL$4=1,KF$20=1), KS65, KQ65) -> 0 | KN65: =KN$4 * IF(AND(KM$4=1,KF$20=1), KS65, KQ65) -> 0 | KP65: None | KQ65: =_xlfn.XLOOKUP(KP65,'KPI Impacts'!$B$2:$H$2,'KPI Impacts'!$B65:$H65) -> 0 | KR65: None | KS65: =_xlfn.XLOOKUP(KR65,'KPI Impacts'!$B$2:$H$2,'KPI Impacts'!$B65:$H65) -> 0 | KV65: =KV$4*LG65 -> 0 | KW65: =KW$4 * IF(AND(KV$4=1,KV$20=1), LI65, LG65) -> 0 | KX65: =KX$4 * IF(AND(KW$4=1,KV$20=1), LI65, LG65) -> 0 | KY65: =KY$4 * IF(AND(KX$4=1,KV$20=1), LI65, LG65) -> 0 | KZ65: =KZ$4 * IF(AND(KY$4=1,KV$20=1), LI65, LG65) -> 0 | LA65: =LA$4 * IF(AND(KZ$4=1,KV$20=1), LI65, LG65) -> 0 | LB65: =LB$4 * IF(AND(LA$4=1,KV$20=1), LI65, LG65) -> 0 | LC65: =LC$4 * IF(AND(LB$4=1,KV$20=1), LI65, LG65) -> 0 | LD65: =LD$4 * IF(AND(LC$4=1,KV$20=1), LI65, LG65) -> 0 | LF65: None | LG65: =_xlfn.XLOOKUP(LF65,'KPI Impacts'!$B$2:$H$2,'KPI Impacts'!$B65:$H65) -> 0 | LH65: None | LI65: =_xlfn.XLOOKUP(LH65,'KPI Impacts'!$B$2:$H$2,'KPI Impacts'!$B65:$H65) -> 0 | LL65: =LL$4*LW65 -> 0 | LM65: =LM$4 * IF(AND(LL$4=1,LL$20=1), LY65, LW65) -> 0 | LN65: =LN$4 * IF(AND(LM$4=1,LL$20=1), LY65, LW65) -> 0 | LO65: =LO$4 * IF(AND(LN$4=1,LL$20=1), LY65, LW65) -> 0 | LP65: =LP$4 * IF(AND(LO$4=1,LL$20=1), LY65, LW65) -> 0 | LQ65: =LQ$4 * IF(AND(LP$4=1,LL$20=1), LY65, LW65) -> 0 | LR65: =LR$4 * IF(AND(LQ$4=1,LL$20=1), LY65, LW65) -> 0 | LS65: =LS$4 * IF(AND(LR$4=1,LL$20=1), LY65, LW65) -> 0 | LT65: =LT$4 * IF(AND(LS$4=1,LL$20=1), LY65, LW65) -> 0 | LV65: None | LW65: =_xlfn.XLOOKUP(LV65,'KPI Impacts'!$B$2:$H$2,'KPI Impacts'!$B65:$H65) -> 0 | LX65: None | LY65: =_xlfn.XLOOKUP(LX65,'KPI Impacts'!$B$2:$H$2,'KPI Impacts'!$B65:$H65) -> 0 | MB65: =MB$4*MM65 -> 0 | MC65: =MC$4 * IF(AND(MB$4=1,MB$20=1), MO65, MM65) -> 0 | MD65: =MD$4 * IF(AND(MC$4=1,MB$20=1), MO65, MM65) -> 0 | ME65: =ME$4 * IF(AND(MD$4=1,MB$20=1), MO65, MM65) -> 0 | MF65: =MF$4 * IF(AND(ME$4=1,MB$20=1), MO65, MM65) -> 0 | MG65: =MG$4 * IF(AND(MF$4=1,MB$20=1), MO65, MM65) -> 0 | MH65: =MH$4 * IF(AND(MG$4=1,MB$20=1), MO65, MM65) -> 0 | MI65: =MI$4 * IF(AND(MH$4=1,MB$20=1), MO65, MM65) -> 0 | MJ65: =MJ$4 * IF(AND(MI$4=1,MB$20=1), MO65, MM65) -> 0 | ML65: None | MM65: =_xlfn.XLOOKUP(ML65,'KPI Impacts'!$B$2:$H$2,'KPI Impacts'!$B65:$H65) -> 0 | MN65: None | MO65: =_xlfn.XLOOKUP(MN65,'KPI Impacts'!$B$2:$H$2,'KPI Impacts'!$B65:$H65) -> 0 | MR65: =MR$4*NC65 -> 0 | MS65: =MS$4 * IF(AND(MR$4=1,MR$20=1), NE65, NC65) -> 0 | MT65: =MT$4 * IF(AND(MS$4=1,MR$20=1), NE65, NC65) -> 0 | MU65: =MU$4 * IF(AND(MT$4=1,MR$20=1), NE65, NC65) -> 0 | MV65: =MV$4 * IF(AND(MU$4=1,MR$20=1), NE65, NC65) -> 0 | MW65: =MW$4 * IF(AND(MV$4=1,MR$20=1), NE65, NC65) -> 0 | MX65: =MX$4 * IF(AND(MW$4=1,MR$20=1), NE65, NC65) -> 0 | MY65: =MY$4 * IF(AND(MX$4=1,MR$20=1), NE65, NC65) -> 0 | MZ65: =MZ$4 * IF(AND(MY$4=1,MR$20=1), NE65, NC65) -> 0 | NB65: None | NC65: =_xlfn.XLOOKUP(NB65,'KPI Impacts'!$B$2:$H$2,'KPI Impacts'!$B65:$H65) -> 0 | ND65: None | NE65: =_xlfn.XLOOKUP(ND65,'KPI Impacts'!$B$2:$H$2,'KPI Impacts'!$B65:$H65) -> 0 | NH65: =NH$4*NS65 -> 0 | NI65: =NI$4 * IF(AND(NH$4=1,NH$20=1), NU65, NS65) -> 0 | NJ65: =NJ$4 * IF(AND(NI$4=1,NH$20=1), NU65, NS65) -> 0 | NK65: =NK$4 * IF(AND(NJ$4=1,NH$20=1), NU65, NS65) -> 0 | NL65: =NL$4 * IF(AND(NK$4=1,NH$20=1), NU65, NS65) -> 0 | NM65: =NM$4 * IF(AND(NL$4=1,NH$20=1), NU65, NS65) -> 0 | NN65: =NN$4 * IF(AND(NM$4=1,NH$20=1), NU65, NS65) -> 0 | NO65: =NO$4 * IF(AND(NN$4=1,NH$20=1), NU65, NS65) -> 0 | NP65: =NP$4 * IF(AND(NO$4=1,NH$20=1), NU65, NS65) -> 0 | NR65: None | NS65: =_xlfn.XLOOKUP(NR65,'KPI Impacts'!$B$2:$H$2,'KPI Impacts'!$B65:$H65) -> 0 | NT65: None | NU65: =_xlfn.XLOOKUP(NT65,'KPI Impacts'!$B$2:$H$2,'KPI Impacts'!$B65:$H65) -> 0 | NX65: =NX$4*OI65 -> 0 | NY65: =NY$4 * IF(AND(NX$4=1,NX$20=1), OK65, OI65) -> 0 | NZ65: =NZ$4 * IF(AND(NY$4=1,NX$20=1), OK65, OI65) -> 0 | OA65: =OA$4 * IF(AND(NZ$4=1,NX$20=1), OK65, OI65) -> 0 | OB65: =OB$4 * IF(AND(OA$4=1,NX$20=1), OK65, OI65) -> 0 | OC65: =OC$4 * IF(AND(OB$4=1,NX$20=1), OK65, OI65) -> 0 | OD65: =OD$4 * IF(AND(OC$4=1,NX$20=1), OK65, OI65) -> 0 | OE65: =OE$4 * IF(AND(OD$4=1,NX$20=1), OK65, OI65) -> 0 | OF65: =OF$4 * IF(AND(OE$4=1,NX$20=1), OK65, OI65) -> 0 | OH65: None | OI65: =_xlfn.XLOOKUP(OH65,'KPI Impacts'!$B$2:$H$2,'KPI Impacts'!$B65:$H65) -> 0 | OJ65: None | OK65: =_xlfn.XLOOKUP(OJ65,'KPI Impacts'!$B$2:$H$2,'KPI Impacts'!$B65:$H65) -> 0
