Workbook
Name _C1: Crises!$P$5:$X$5
Name _C1Enabled: Crises!$P$7:$X$7
Name _C1Prepared: Crises!$P$8:$X$8
Name _C1Show: Crises!$P$6:$X$6
Name _C1ShowCrisisCard: Crises!$P$9:$X$9
Name _C1Year: Crises!$P$4:$X$4
Name _C2: Crises!$AD$5:$AL$5
Name _C2Enabled: Crises!$AD$7:$AL$7
Name _C2Prepared: Crises!$AD$8:$AL$8
Name _C2Show: Crises!$AD$6:$AL$6
Name _C2ShowCrisisCard: Crises!$AD$9:$AL$9
Name _C2Year: Crises!$AD$4:$AL$4
Name _C3: Crises!$AR$5:$AZ$5
Name _C3Enabled: Crises!$AR$7:$AZ$7
Name _C3Prepared: Crises!$AR$8:$AZ$8
Name _C3Show: Crises!$AR$6:$AZ$6
Name _C3ShowCrisisCard: Crises!$AR$9:$AZ$9
Name _C3Year: Crises!$AR$4:$AZ$4
Name _C4: Crises!$BF$5:$BN$5
Name _C4Enabled: Crises!$BF$7:$BN$7
Name _C4Prepared: Crises!$BF$8:$BN$8
Name _C4Show: Crises!$BF$6:$BN$6
Name _C4ShowCrisisCard: Crises!$BF$9:$BN$9
Name _C4Year: Crises!$BF$4:$BN$4
Name _C5: Crises!$BT$5:$CB$5
Name _C5Enabled: Crises!$BT$7:$CB$7
Name _C5Prepared: Crises!$BT$8:$CB$8
Name _C5Show: Crises!$BT$6:$CB$6
Name _C5ShowCrisisCard: Crises!$BT$9:$CB$9
Name _C5Year: Crises!$BT$4:$CB$4
Name _C6: Crises!$CH$5:$CP$5
Name _C6Enabled: Crises!$CH$7:$CP$7
Name _C6Prepared: Crises!$CH$8:$CP$8
Name _C6Show: Crises!$CH$6:$CP$6
Name _C6ShowCrisisCard: Crises!$CH$9:$CP$9
Name _C6Year: Crises!$CH$4:$CP$4
Name Accountability: Results!$B$69:$J$69
Name AIContributionToGDP: Results!$B$73:$J$73
Name AIContributionToGDPPercOfTargetAchieved: 'Result Targets'!$B$73:$J$73
Name AIContributionToGDPTarget: 'Result Targets'!$B$5:$J$5
Name AIFDIStock: Results!$B$74:$J$74
Name AIFDIStockPercOfTargetAchieved: 'Result Targets'!$B$74:$J$74
Name AIFDIStockTarget: 'Result Targets'!$B$6:$J$6
Name AIFeedbackEnabled: 'Project Variables'!$B$8
Name AILiteracy: Results!$B$102:$J$102
Name AILiteracyPercOfTargetAchieved: 'Result Targets'!$B$102:$J$102
Name AILiteracyTarget: 'Result Targets'!$B$31:$J$31
Name AutonomousSystemsSafteyIndex: Results!$B$94:$J$94
Name AutonomousSystemsSafteyIndexPercOfTargetAchieved: 'Result Targets'!$B$94:$J$94
Name AutonomousSystemsSafteyIndexTarget: 'Result Targets'!$B$24:$J$24
Name AverageMinistryScore: Results!$B$118:$J$118
Name CarbonIntensityFromDataCenters: Results!$B$83:$J$83
Name CircularityIndex: Results!$B$87:$J$87
Name CircularityIndexPercOfTargetAchieved: 'Result Targets'!$B$87:$J$87
Name CircularityIndexTarget: 'Result Targets'!$B$18:$J$18
Name CumulativeStartupImpactYear: Startups!$B$6:$H$6
Name CybersecurityIndex: Results!$B$93:$J$93
Name CybersecurityIndexPercOfTargetAchieved: 'Result Targets'!$B$93:$J$93
Name CybersecurityIndexTarget: 'Result Targets'!$B$23:$J$23
Name DefAvaialbleToAllocate: 'Defence Ministry'!$B$111:$J$111

Sheet Project Variables
A1: ModelKitID | B1: aigov
A2: settingsID | B2: 0
A3: ReadVault | B3: 0
A4: NumYears | B4: 5
A5: GameOver | B5: =IF(Step=NumYears,1,0) -> 0
A7: Misc
A8: AIFeedbackEnabled | B8: 0
A9: IsMultiplayer | B9: 0
A10: SliderReasoningEnabled | B10: 0
A11: TeamName
A13: Confirmed / Ready
A14: EcConfirmed | B14: 0
A15: EnvConfirmed | B15: 0
A16: DefConfirmed | B16: 0
A17: EduConfirmed | B17: 0
A19: Enabled Ministries
A20: EcEnabled | B20: 1
A21: EnvEnabled | B21: 1
A22: DefEnabled | B22: 1
A23: EduEnabled | B23: 1
A24: FacEcEnabled | B24: 1
A25: FacEnvEnabled | B25: 1
A26: FacDefEnabled | B26: 1
A27: FacEduEnabled | B27: 1
A28: FacAllowMinistryChoice | B28: 1
A29: MinistriesConfirmed | B29: 0
A31: Role Selection
A32: RoleUser0 | B32: 0
A33: RoleUser1 | B33: 0
A34: RoleUser2 | B34: 0
A35: RoleUser3 | B35: 0
A36: RoleUser4 | B36: 0
A37: RolesConfirmed | B37: 0
D38: Position | E38: 1 | F38: 2 | G38: 3 | H38: 4 | I38: 5 | J38: 6
A39: Values | D39: Weight | E39: 0.25 | F39: 0.25 | G39: 0.15 | H39: 0.15 | I39: 0.1 | J39: 0.1
A40: Value1Position | B40: 1 | D40: Growth & Welbeing | E40: =_xlfn.XLOOKUP(Value1Position,$E$38:$J$38,$E$39:$J$39) -> 0.25
A41: Value2Position | B41: 2 | D41: Human Rights | E41: =_xlfn.XLOOKUP(Value2Position,$E$38:$J$38,$E$39:$J$39) -> 0.25
A42: Value3Position | B42: 3 | D42: Privacy & Data Protection | E42: =_xlfn.XLOOKUP(Value3Position,$E$38:$J$38,$E$39:$J$39) -> 0.15
A43: Value4Position | B43: 4 | D43: Transparency | E43: =_xlfn.XLOOKUP(Value4Position,$E$38:$J$38,$E$39:$J$39) -> 0.15
A44: Value5Position | B44: 5 | D44: Security & Safety | E44: =_xlfn.XLOOKUP(Value5Position,$E$38:$J$38,$E$39:$J$39) -> 0.1
A45: Value6Position | B45: 6 | D45: Accountability | E45: =_xlfn.XLOOKUP(Value6Position,$E$38:$J$38,$E$39:$J$39) -> 0.1
A46: ValuesConfirmed | B46: 0
A48: RoleUser0Value1Position | B48: 1 | D48: Rows Reference
A49: RoleUser0Value2Position | B49: 2 | D49: Governance
A50: RoleUser0Value3Position | B50: 3 | D50: GrowthWellBeing
A51: RoleUser0Value4Position | B51: 4 | D51: HumanRights
A52: RoleUser0Value5Position | B52: 5 | D52: PrivacyDataProtection
A53: RoleUser0Value6Position | B53: 6 | D53: Transparency
A54: RoleUser0ValuesConfirmed | B54: 0 | D54: SecuritySafety
D55: Accountability
A56: RoleUser1Value1Position | B56: 1
A57: RoleUser1Value2Position | B57: 2
A58: RoleUser1Value3Position | B58: 3 | D58: Economy
A59: RoleUser1Value4Position | B59: 4 | D59: AIContributionToGDP
A60: RoleUser1Value5Position | B60: 5 | D60: AIFDIStock
A61: RoleUser1Value6Position | B61: 6 | D61: JobsCreated
A62: RoleUser1ValuesConfirmed | B62: 0 | D62: JobsDisplaced
A64: RoleUser2Value1Position | B64: 1
A65: RoleUser2Value2Position | B65: 2
A66: RoleUser2Value3Position | B66: 3
A67: RoleUser2Value4Position | B67: 4 | D67: Environment
A68: RoleUser2Value5Position | B68: 5
A69: RoleUser2Value6Position | B69: 6
A70: RoleUser2ValuesConfirmed | B70: 0 | D70: RenewableEnergyFactor
D71: WaterCircularityIndex
A72: RoleUser3Value1Position | B72: 1 | D72: EwasteCircularityIndex
A73: RoleUser3Value2Position | B73: 2
A74: RoleUser3Value3Position | B74: 3 | D74: EcosystemIntegrityIndex
A75: RoleUser3Value4Position | B75: 4
A76: RoleUser3Value5Position | B76: 5
A77: RoleUser3Value6Position | B77: 6
A78: RoleUser3ValuesConfirmed | B78: 0 | D78: Defense
D79: CybersecurityIndex
A80: RoleUser4Value1Position | B80: 1 | D80: AutonomousSystemsSafteyIndex
A81: RoleUser4Value2Position | B81: 2 | D81: DefenseExports
A82: RoleUser4Value3Position | B82: 3 | D82: DefenseImports
A83: RoleUser4Value4Position | B83: 4
A84: RoleUser4Value5Position | B84: 5
A85: RoleUser4Value6Position | B85: 6
A86: RoleUser4ValuesConfirmed | B86: 0
D87: Education & Innovation
D88: AILiteracy
D89: InnovationIndex
D90: InstitutionalAdoptionRate

Sheet Target Settings
A1: FacilSetsTargets | B1: 0
A3: Economy | E3: Defaults
A4: F_AIContributionToGDPTarget | B4: =E4 -> 12 | E4: 12
A5: F_AIFDIStockTarget | B5: =E5 -> 2.5 | E5: 2.5
A6: F_NetJobsFromAITarget | B6: =E6 -> 500000 | E6: 500000
A9: Environment
A10: F_RenewableEnergyFactorTarget | B10: =E10 -> 40 | E10: 40
A11: F_CircularityIndexTarget | B11: =E11 -> 60 | E11: 60
A12: F_EcosystemIntegrityIndexTarget | B12: =E12 -> 60 | E12: 60
A15: Defense
A16: F_CybersecurityIndexTarget | B16: =E16 -> 65 | E16: 65
A17: F_AutonomousSystemsSafteyIndexTarget | B17: =E17 -> 75 | E17: 75
A18: F_MilitaryTechnologyTradeBalanceTarget | B18: =E18 -> 2000000000 | E18: 2000000000
A21: Education & Innovation
A22: F_AILiteracyTarget | B22: =E22 -> 60 | E22: 60
A23: F_InnovationIndexTarget | B23: =E23 -> 60 | E23: 60
A24: F_InstitutionalAdoptionRateTarget | B24: =E24 -> 65 | E24: 65

Sheet Results
A1: Public Policy Simulation: AI Governance
A3: Step | B3: 0
A5: Time | B5: 0 | C5: 1 | D5: 2 | E5: 3 | F5: 4 | G5: 5 | H5: 6 | I5: 7 | J5: 8
A6: Year | B6: 1 | C6: 2 | D6: 3 | E6: 4 | F6: 5 | G6: 6 | H6: 7 | I6: 8 | J6: 9
A63: Governance
A64: GrowthWellBeing | B64: 50 | C64: =$B64+'Economy Ministry'!C64*EcEnabled+'Environment Ministry'!C64*EnvEnabled+'Defence Ministry'!C64*DefEnabled+'Education Ministry'!C64*EduEnabled+Crises!C64+'Breaking News'!C64+Dilemmas!C64+Startups!C64 -> 50 | D64: =$B64+'Economy Ministry'!D64*EcEnabled+'Environment Ministry'!D64*EnvEnabled+'Defence Ministry'!D64*DefEnabled+'Education Ministry'!D64*EduEnabled+Crises!D64+'Breaking News'!D64+Dilemmas!D64+Startups!D64 -> 50 | E64: =$B64+'Economy Ministry'!E64*EcEnabled+'Environment Ministry'!E64*EnvEnabled+'Defence Ministry'!E64*DefEnabled+'Education Ministry'!E64*EduEnabled+Crises!E64+'Breaking News'!E64+Dilemmas!E64+Startups!E64 -> 50 | F64: =$B64+'Economy Ministry'!F64*EcEnabled+'Environment Ministry'!F64*EnvEnabled+'Defence Ministry'!F64*DefEnabled+'Education Ministry'!F64*EduEnabled+Crises!F64+'Breaking News'!F64+Dilemmas!F64+Startups!F64 -> 50 | G64: =$B64+'Economy Ministry'!G64*EcEnabled+'Environment Ministry'!G64*EnvEnabled+'Defence Ministry'!G64*DefEnabled+'Education Ministry'!G64*EduEnabled+Crises!G64+'Breaking News'!G64+Dilemmas!G64+Startups!G64 -> 50 | H64: =$B64+'Economy Ministry'!H64*EcEnabled+'Environment Ministry'!H64*EnvEnabled+'Defence Ministry'!H64*DefEnabled+'Education Ministry'!H64*EduEnabled+Crises!H64+'Breaking News'!H64+Dilemmas!H64+Startups!H64 -> 50 | I64: =$B64+'Economy Ministry'!I64*EcEnabled+'Environment Ministry'!I64*EnvEnabled+'Defence Ministry'!I64*DefEnabled+'Education Ministry'!I64*EduEnabled+Crises!I64+'Breaking News'!I64+Dilemmas!I64 -> 50 | J64: =$B64+'Economy Ministry'!J64*EcEnabled+'Environment Ministry'!J64*EnvEnabled+'Defence Ministry'!J64*DefEnabled+'Education Ministry'!J64*EduEnabled+Crises!J64+'Breaking News'!J64+Dilemmas!J64 -> 50
A65: HumanRights | B65: 55 | C65: =$B65+'Economy Ministry'!C65*EcEnabled+'Environment Ministry'!C65*EnvEnabled+'Defence Ministry'!C65*DefEnabled+'Education Ministry'!C65*EduEnabled+Crises!C65+'Breaking News'!C65+Dilemmas!C65+Startups!C65 -> 55 | D65: =$B65+'Economy Ministry'!D65*EcEnabled+'Environment Ministry'!D65*EnvEnabled+'Defence Ministry'!D65*DefEnabled+'Education Ministry'!D65*EduEnabled+Crises!D65+'Breaking News'!D65+Dilemmas!D65+Startups!D65 -> 53.4 | E65: =$B65+'Economy Ministry'!E65*EcEnabled+'Environment Ministry'!E65*EnvEnabled+'Defence Ministry'!E65*DefEnabled+'Education Ministry'!E65*EduEnabled+Crises!E65+'Breaking News'!E65+Dilemmas!E65+Startups!E65 -> 53.4 | F65: =$B65+'Economy Ministry'!F65*EcEnabled+'Environment Ministry'!F65*EnvEnabled+'Defence Ministry'!F65*DefEnabled+'Education Ministry'!F65*EduEnabled+Crises!F65+'Breaking News'!F65+Dilemmas!F65+Startups!F65 -> 53.4 | G65: =$B65+'Economy Ministry'!G65*EcEnabled+'Environment Ministry'!G65*EnvEnabled+'Defence Ministry'!G65*DefEnabled+'Education Ministry'!G65*EduEnabled+Crises!G65+'Breaking News'!G65+Dilemmas!G65+Startups!G65 -> 53.4 | H65: =$B65+'Economy Ministry'!H65*EcEnabled+'Environment Ministry'!H65*EnvEnabled+'Defence Ministry'!H65*DefEnabled+'Education Ministry'!H65*EduEnabled+Crises!H65+'Breaking News'!H65+Dilemmas!H65+Startups!H65 -> 53.4 | I65: =$B65+'Economy Ministry'!I65*EcEnabled+'Environment Ministry'!I65*EnvEnabled+'Defence Ministry'!I65*DefEnabled+'Education Ministry'!I65*EduEnabled+Crises!I65+'Breaking News'!I65+Dilemmas!I65 -> 53.4 | J65: =$B65+'Economy Ministry'!J65*EcEnabled+'Environment Ministry'!J65*EnvEnabled+'Defence Ministry'!J65*DefEnabled+'Education Ministry'!J65*EduEnabled+Crises!J65+'Breaking News'!J65+Dilemmas!J65 -> 53.4
A66: PrivacyDataProtection | B66: 40 | C66: =$B66+'Economy Ministry'!C66*EcEnabled+'Environment Ministry'!C66*EnvEnabled+'Defence Ministry'!C66*DefEnabled+'Education Ministry'!C66*EduEnabled+Crises!C66+'Breaking News'!C66+Dilemmas!C66+Startups!C66 -> 40 | D66: =$B66+'Economy Ministry'!D66*EcEnabled+'Environment Ministry'!D66*EnvEnabled+'Defence Ministry'!D66*DefEnabled+'Education Ministry'!D66*EduEnabled+Crises!D66+'Breaking News'!D66+Dilemmas!D66+Startups!D66 -> 40 | E66: =$B66+'Economy Ministry'!E66*EcEnabled+'Environment Ministry'!E66*EnvEnabled+'Defence Ministry'!E66*DefEnabled+'Education Ministry'!E66*EduEnabled+Crises!E66+'Breaking News'!E66+Dilemmas!E66+Startups!E66 -> 40 | F66: =$B66+'Economy Ministry'!F66*EcEnabled+'Environment Ministry'!F66*EnvEnabled+'Defence Ministry'!F66*DefEnabled+'Education Ministry'!F66*EduEnabled+Crises!F66+'Breaking News'!F66+Dilemmas!F66+Startups!F66 -> 40 | G66: =$B66+'Economy Ministry'!G66*EcEnabled+'Environment Ministry'!G66*EnvEnabled+'Defence Ministry'!G66*DefEnabled+'Education Ministry'!G66*EduEnabled+Crises!G66+'Breaking News'!G66+Dilemmas!G66+Startups!G66 -> 40 | H66: =$B66+'Economy Ministry'!H66*EcEnabled+'Environment Ministry'!H66*EnvEnabled+'Defence Ministry'!H66*DefEnabled+'Education Ministry'!H66*EduEnabled+Crises!H66+'Breaking News'!H66+Dilemmas!H66+Startups!H66 -> 40 | I66: =$B66+'Economy Ministry'!I66*EcEnabled+'Environment Ministry'!I66*EnvEnabled+'Defence Ministry'!I66*DefEnabled+'Education Ministry'!I66*EduEnabled+Crises!I66+'Breaking News'!I66+Dilemmas!I66 -> 40 | J66: =$B66+'Economy Ministry'!J66*EcEnabled+'Environment Ministry'!J66*EnvEnabled+'Defence Ministry'!J66*DefEnabled+'Education Ministry'!J66*EduEnabled+Crises!J66+'Breaking News'!J66+Dilemmas!J66 -> 40
A67: Transparency | B67: 38 | C67: =$B67+'Economy Ministry'!C67*EcEnabled+'Environment Ministry'!C67*EnvEnabled+'Defence Ministry'!C67*DefEnabled+'Education Ministry'!C67*EduEnabled+Crises!C67+'Breaking News'!C67+Dilemmas!C67+Startups!C67 -> 38 | D67: =$B67+'Economy Ministry'!D67*EcEnabled+'Environment Ministry'!D67*EnvEnabled+'Defence Ministry'!D67*DefEnabled+'Education Ministry'!D67*EduEnabled+Crises!D67+'Breaking News'!D67+Dilemmas!D67+Startups!D67 -> 36.4 | E67: =$B67+'Economy Ministry'!E67*EcEnabled+'Environment Ministry'!E67*EnvEnabled+'Defence Ministry'!E67*DefEnabled+'Education Ministry'!E67*EduEnabled+Crises!E67+'Breaking News'!E67+Dilemmas!E67+Startups!E67 -> 36.4 | F67: =$B67+'Economy Ministry'!F67*EcEnabled+'Environment Ministry'!F67*EnvEnabled+'Defence Ministry'!F67*DefEnabled+'Education Ministry'!F67*EduEnabled+Crises!F67+'Breaking News'!F67+Dilemmas!F67+Startups!F67 -> 36.4 | G67: =$B67+'Economy Ministry'!G67*EcEnabled+'Environment Ministry'!G67*EnvEnabled+'Defence Ministry'!G67*DefEnabled+'Education Ministry'!G67*EduEnabled+Crises!G67+'Breaking News'!G67+Dilemmas!G67+Startups!G67 -> 36.4 | H67: =$B67+'Economy Ministry'!H67*EcEnabled+'Environment Ministry'!H67*EnvEnabled+'Defence Ministry'!H67*DefEnabled+'Education Ministry'!H67*EduEnabled+Crises!H67+'Breaking News'!H67+Dilemmas!H67+Startups!H67 -> 34.8 | I67: =$B67+'Economy Ministry'!I67*EcEnabled+'Environment Ministry'!I67*EnvEnabled+'Defence Ministry'!I67*DefEnabled+'Education Ministry'!I67*EduEnabled+Crises!I67+'Breaking News'!I67+Dilemmas!I67 -> 34.8 | J67: =$B67+'Economy Ministry'!J67*EcEnabled+'Environment Ministry'!J67*EnvEnabled+'Defence Ministry'!J67*DefEnabled+'Education Ministry'!J67*EduEnabled+Crises!J67+'Breaking News'!J67+Dilemmas!J67 -> 34.8
A68: SecuritySafety | B68: 45 | C68: =$B68+'Economy Ministry'!C68*EcEnabled+'Environment Ministry'!C68*EnvEnabled+'Defence Ministry'!C68*DefEnabled+'Education Ministry'!C68*EduEnabled+Crises!C68+'Breaking News'!C68+Dilemmas!C68+Startups!C68 -> 45 | D68: =$B68+'Economy Ministry'!D68*EcEnabled+'Environment Ministry'!D68*EnvEnabled+'Defence Ministry'!D68*DefEnabled+'Education Ministry'!D68*EduEnabled+Crises!D68+'Breaking News'!D68+Dilemmas!D68+Startups!D68 -> 45 | E68: =$B68+'Economy Ministry'!E68*EcEnabled+'Environment Ministry'!E68*EnvEnabled+'Defence Ministry'!E68*DefEnabled+'Education Ministry'!E68*EduEnabled+Crises!E68+'Breaking News'!E68+Dilemmas!E68+Startups!E68 -> 45 | F68: =$B68+'Economy Ministry'!F68*EcEnabled+'Environment Ministry'!F68*EnvEnabled+'Defence Ministry'!F68*DefEnabled+'Education Ministry'!F68*EduEnabled+Crises!F68+'Breaking News'!F68+Dilemmas!F68+Startups!F68 -> 45 | G68: =$B68+'Economy Ministry'!G68*EcEnabled+'Environment Ministry'!G68*EnvEnabled+'Defence Ministry'!G68*DefEnabled+'Education Ministry'!G68*EduEnabled+Crises!G68+'Breaking News'!G68+Dilemmas!G68+Startups!G68 -> 45 | H68: =$B68+'Economy Ministry'!H68*EcEnabled+'Environment Ministry'!H68*EnvEnabled+'Defence Ministry'!H68*DefEnabled+'Education Ministry'!H68*EduEnabled+Crises!H68+'Breaking News'!H68+Dilemmas!H68+Startups!H68 -> 45 | I68: =$B68+'Economy Ministry'!I68*EcEnabled+'Environment Ministry'!I68*EnvEnabled+'Defence Ministry'!I68*DefEnabled+'Education Ministry'!I68*EduEnabled+Crises!I68+'Breaking News'!I68+Dilemmas!I68 -> 45 | J68: =$B68+'Economy Ministry'!J68*EcEnabled+'Environment Ministry'!J68*EnvEnabled+'Defence Ministry'!J68*DefEnabled+'Education Ministry'!J68*EduEnabled+Crises!J68+'Breaking News'!J68+Dilemmas!J68 -> 45
A69: Accountability | B69: 38 | C69: =$B69+'Economy Ministry'!C69*EcEnabled+'Environment Ministry'!C69*EnvEnabled+'Defence Ministry'!C69*DefEnabled+'Education Ministry'!C69*EduEnabled+Crises!C69+'Breaking News'!C69+Dilemmas!C69+Startups!C69 -> 38 | D69: =$B69+'Economy Ministry'!D69*EcEnabled+'Environment Ministry'!D69*EnvEnabled+'Defence Ministry'!D69*DefEnabled+'Education Ministry'!D69*EduEnabled+Crises!D69+'Breaking News'!D69+Dilemmas!D69+Startups!D69 -> 34.8 | E69: =$B69+'Economy Ministry'!E69*EcEnabled+'Environment Ministry'!E69*EnvEnabled+'Defence Ministry'!E69*DefEnabled+'Education Ministry'!E69*EduEnabled+Crises!E69+'Breaking News'!E69+Dilemmas!E69+Startups!E69 -> 34.8 | F69: =$B69+'Economy Ministry'!F69*EcEnabled+'Environment Ministry'!F69*EnvEnabled+'Defence Ministry'!F69*DefEnabled+'Education Ministry'!F69*EduEnabled+Crises!F69+'Breaking News'!F69+Dilemmas!F69+Startups!F69 -> 34.8 | G69: =$B69+'Economy Ministry'!G69*EcEnabled+'Environment Ministry'!G69*EnvEnabled+'Defence Ministry'!G69*DefEnabled+'Education Ministry'!G69*EduEnabled+Crises!G69+'Breaking News'!G69+Dilemmas!G69+Startups!G69 -> 34.8 | H69: =$B69+'Economy Ministry'!H69*EcEnabled+'Environment Ministry'!H69*EnvEnabled+'Defence Ministry'!H69*DefEnabled+'Education Ministry'!H69*EduEnabled+Crises!H69+'Breaking News'!H69+Dilemmas!H69+Startups!H69 -> 31.6 | I69: =$B69+'Economy Ministry'!I69*EcEnabled+'Environment Ministry'!I69*EnvEnabled+'Defence Ministry'!I69*DefEnabled+'Education Ministry'!I69*EduEnabled+Crises!I69+'Breaking News'!I69+Dilemmas!I69 -> 31.6 | J69: =$B69+'Economy Ministry'!J69*EcEnabled+'Environment Ministry'!J69*EnvEnabled+'Defence Ministry'!J69*DefEnabled+'Education Ministry'!J69*EduEnabled+Crises!J69+'Breaking News'!J69+Dilemmas!J69 -> 31.6
A72: Economy
A73: AIContributionToGDP | B73: 3 | C73: =$B73+'Economy Ministry'!C73*EcEnabled+'Environment Ministry'!C73*EnvEnabled+'Defence Ministry'!C73*DefEnabled+'Education Ministry'!C73*EduEnabled+Crises!C73+'Breaking News'!C73+Dilemmas!C73+Startups!C73 -> 2.68 | D73: =$B73+'Economy Ministry'!D73*EcEnabled+'Environment Ministry'!D73*EnvEnabled+'Defence Ministry'!D73*DefEnabled+'Education Ministry'!D73*EduEnabled+Crises!D73+'Breaking News'!D73+Dilemmas!D73+Startups!D73 -> 2.68 | E73: =$B73+'Economy Ministry'!E73*EcEnabled+'Environment Ministry'!E73*EnvEnabled+'Defence Ministry'!E73*DefEnabled+'Education Ministry'!E73*EduEnabled+Crises!E73+'Breaking News'!E73+Dilemmas!E73+Startups!E73 -> 2.68 | F73: =$B73+'Economy Ministry'!F73*EcEnabled+'Environment Ministry'!F73*EnvEnabled+'Defence Ministry'!F73*DefEnabled+'Education Ministry'!F73*EduEnabled+Crises!F73+'Breaking News'!F73+Dilemmas!F73+Startups!F73 -> 2.68 | G73: =$B73+'Economy Ministry'!G73*EcEnabled+'Environment Ministry'!G73*EnvEnabled+'Defence Ministry'!G73*DefEnabled+'Education Ministry'!G73*EduEnabled+Crises!G73+'Breaking News'!G73+Dilemmas!G73+Startups!G73 -> 2.68 | H73: =$B73+'Economy Ministry'!H73*EcEnabled+'Environment Ministry'!H73*EnvEnabled+'Defence Ministry'!H73*DefEnabled+'Education Ministry'!H73*EduEnabled+Crises!H73+'Breaking News'!H73+Dilemmas!H73+Startups!H73 -> 3.08 | I73: =$B73+'Economy Ministry'!I73*EcEnabled+'Environment Ministry'!I73*EnvEnabled+'Defence Ministry'!I73*DefEnabled+'Education Ministry'!I73*EduEnabled+Crises!I73+'Breaking News'!I73+Dilemmas!I73 -> 3.08 | J73: =$B73+'Economy Ministry'!J73*EcEnabled+'Environment Ministry'!J73*EnvEnabled+'Defence Ministry'!J73*DefEnabled+'Education Ministry'!J73*EduEnabled+Crises!J73+'Breaking News'!J73+Dilemmas!J73 -> 3.08
A74: AIFDIStock | B74: 50000000000 | C74: =$B74+'Economy Ministry'!C74*EcEnabled+'Environment Ministry'!C74*EnvEnabled+'Defence Ministry'!C74*DefEnabled+'Education Ministry'!C74*EduEnabled+Crises!C74+'Breaking News'!C74+Dilemmas!C74+Startups!C74 -> 46800000000 | D74: =$B74+'Economy Ministry'!D74*EcEnabled+'Environment Ministry'!D74*EnvEnabled+'Defence Ministry'!D74*DefEnabled+'Education Ministry'!D74*EduEnabled+Crises!D74+'Breaking News'!D74+Dilemmas!D74+Startups!D74 -> 46800000000 | E74: =$B74+'Economy Ministry'!E74*EcEnabled+'Environment Ministry'!E74*EnvEnabled+'Defence Ministry'!E74*DefEnabled+'Education Ministry'!E74*EduEnabled+Crises!E74+'Breaking News'!E74+Dilemmas!E74+Startups!E74 -> 45200000000 | F74: =$B74+'Economy Ministry'!F74*EcEnabled+'Environment Ministry'!F74*EnvEnabled+'Defence Ministry'!F74*DefEnabled+'Education Ministry'!F74*EduEnabled+Crises!F74+'Breaking News'!F74+Dilemmas!F74+Startups!F74 -> 45200000000 | G74: =$B74+'Economy Ministry'!G74*EcEnabled+'Environment Ministry'!G74*EnvEnabled+'Defence Ministry'!G74*DefEnabled+'Education Ministry'!G74*EduEnabled+Crises!G74+'Breaking News'!G74+Dilemmas!G74+Startups!G74 -> 42000000000 | H74: =$B74+'Economy Ministry'!H74*EcEnabled+'Environment Ministry'!H74*EnvEnabled+'Defence Ministry'!H74*DefEnabled+'Education Ministry'!H74*EduEnabled+Crises!H74+'Breaking News'!H74+Dilemmas!H74+Startups!H74 -> 42000000000 | I74: =$B74+'Economy Ministry'!I74*EcEnabled+'Environment Ministry'!I74*EnvEnabled+'Defence Ministry'!I74*DefEnabled+'Education Ministry'!I74*EduEnabled+Crises!I74+'Breaking News'!I74+Dilemmas!I74 -> 42000000000 | J74: =$B74+'Economy Ministry'!J74*EcEnabled+'Environment Ministry'!J74*EnvEnabled+'Defence Ministry'!J74*DefEnabled+'Education Ministry'!J74*EduEnabled+Crises!J74+'Breaking News'!J74+Dilemmas!J74 -> 42000000000
A75: JobsCreated | B75: 0 | C75: =$B75+'Economy Ministry'!C75*EcEnabled+'Environment Ministry'!C75*EnvEnabled+'Defence Ministry'!C75*DefEnabled+'Education Ministry'!C75*EduEnabled+Crises!C75+'Breaking News'!C75+Dilemmas!C75+Startups!C75 -> 0 | D75: =$B75+'Economy Ministry'!D75*EcEnabled+'Environment Ministry'!D75*EnvEnabled+'Defence Ministry'!D75*DefEnabled+'Education Ministry'!D75*EduEnabled+Crises!D75+'Breaking News'!D75+Dilemmas!D75+Startups!D75 -> 0 | E75: =$B75+'Economy Ministry'!E75*EcEnabled+'Environment Ministry'!E75*EnvEnabled+'Defence Ministry'!E75*DefEnabled+'Education Ministry'!E75*EduEnabled+Crises!E75+'Breaking News'!E75+Dilemmas!E75+Startups!E75 -> 0 | F75: =$B75+'Economy Ministry'!F75*EcEnabled+'Environment Ministry'!F75*EnvEnabled+'Defence Ministry'!F75*DefEnabled+'Education Ministry'!F75*EduEnabled+Crises!F75+'Breaking News'!F75+Dilemmas!F75+Startups!F75 -> 0 | G75: =$B75+'Economy Ministry'!G75*EcEnabled+'Environment Ministry'!G75*EnvEnabled+'Defence Ministry'!G75*DefEnabled+'Education Ministry'!G75*EduEnabled+Crises!G75+'Breaking News'!G75+Dilemmas!G75+Startups!G75 -> 0 | H75: =$B75+'Economy Ministry'!H75*EcEnabled+'Environment Ministry'!H75*EnvEnabled+'Defence Ministry'!H75*DefEnabled+'Education Ministry'!H75*EduEnabled+Crises!H75+'Breaking News'!H75+Dilemmas!H75+Startups!H75 -> 0 | I75: =$B75+'Economy Ministry'!I75*EcEnabled+'Environment Ministry'!I75*EnvEnabled+'Defence Ministry'!I75*DefEnabled+'Education Ministry'!I75*EduEnabled+Crises!I75+'Breaking News'!I75+Dilemmas!I75 -> 0 | J75: =$B75+'Economy Ministry'!J75*EcEnabled+'Environment Ministry'!J75*EnvEnabled+'Defence Ministry'!J75*DefEnabled+'Education Ministry'!J75*EduEnabled+Crises!J75+'Breaking News'!J75+Dilemmas!J75 -> 0
A76: JobsDisplaced | B76: 0 | C76: =$B76+'Economy Ministry'!C76*EcEnabled+'Environment Ministry'!C76*EnvEnabled+'Defence Ministry'!C76*DefEnabled+'Education Ministry'!C76*EduEnabled+Crises!C76+'Breaking News'!C76+Dilemmas!C76+Startups!C76 -> 0 | D76: =$B76+'Economy Ministry'!D76*EcEnabled+'Environment Ministry'!D76*EnvEnabled+'Defence Ministry'!D76*DefEnabled+'Education Ministry'!D76*EduEnabled+Crises!D76+'Breaking News'!D76+Dilemmas!D76+Startups!D76 -> 0 | E76: =$B76+'Economy Ministry'!E76*EcEnabled+'Environment Ministry'!E76*EnvEnabled+'Defence Ministry'!E76*DefEnabled+'Education Ministry'!E76*EduEnabled+Crises!E76+'Breaking News'!E76+Dilemmas!E76+Startups!E76 -> 0 | F76: =$B76+'Economy Ministry'!F76*EcEnabled+'Environment Ministry'!F76*EnvEnabled+'Defence Ministry'!F76*DefEnabled+'Education Ministry'!F76*EduEnabled+Crises!F76+'Breaking News'!F76+Dilemmas!F76+Startups!F76 -> 0 | G76: =$B76+'Economy Ministry'!G76*EcEnabled+'Environment Ministry'!G76*EnvEnabled+'Defence Ministry'!G76*DefEnabled+'Education Ministry'!G76*EduEnabled+Crises!G76+'Breaking News'!G76+Dilemmas!G76+Startups!G76 -> 0 | H76: =$B76+'Economy Ministry'!H76*EcEnabled+'Environment Ministry'!H76*EnvEnabled+'Defence Ministry'!H76*DefEnabled+'Education Ministry'!H76*EduEnabled+Crises!H76+'Breaking News'!H76+Dilemmas!H76+Startups!H76 -> 0 | I76: =$B76+'Economy Ministry'!I76*EcEnabled+'Environment Ministry'!I76*EnvEnabled+'Defence Ministry'!I76*DefEnabled+'Education Ministry'!I76*EduEnabled+Crises!I76+'Breaking News'!I76+Dilemmas!I76 -> 0 | J76: =$B76+'Economy Ministry'!J76*EcEnabled+'Environment Ministry'!J76*EnvEnabled+'Defence Ministry'!J76*DefEnabled+'Education Ministry'!J76*EduEnabled+Crises!J76+'Breaking News'!J76+Dilemmas!J76 -> 0
A77: NetJobsFromAI | B77: =B75-B76 -> 0 | C77: =C75-C76 -> 0 | D77: =D75-D76 -> 0 | E77: =E75-E76 -> 0 | F77: =F75-F76 -> 0 | G77: =G75-G76 -> 0 | H77: =H75-H76 -> 0 | I77: =I75-I76 -> 0 | J77: =J75-J76 -> 0
A78: EconomyScore | B78: ='Result Targets'!B78 -> 25 | C78: ='Result Targets'!C78 -> 23.044444 | D78: ='Result Targets'!D78 -> 23.044444 | E78: ='Result Targets'!E78 -> 22.511111 | F78: ='Result Targets'!F78 -> 22.511111 | G78: ='Result Targets'!G78 -> 21.444444 | H78: ='Result Targets'!H78 -> 22.555556 | I78: ='Result Targets'!I78 -> 22.555556 | J78: ='Result Targets'!J78 -> 22.555556
A81: Environment
A82: EnergyConsumedFromDataCenters | B82: X | C82: X | D82: X | E82: X | F82: X | G82: X | H82: X | I82: X | J82: X
A83: RenewableEnergyFactor | B83: X | C83: X | D83: X | E83: X | F83: X | G83: X | H83: X | I83: X | J83: X
A84: RenewableEnergyFactor | B84: 10 | C84: =$B84+'Economy Ministry'!C84*EcEnabled+'Environment Ministry'!C84*EnvEnabled+'Defence Ministry'!C84*DefEnabled+'Education Ministry'!C84*EduEnabled+Crises!C84+'Breaking News'!C84+Dilemmas!C84+Startups!C84 -> 10 | D84: =$B84+'Economy Ministry'!D84*EcEnabled+'Environment Ministry'!D84*EnvEnabled+'Defence Ministry'!D84*DefEnabled+'Education Ministry'!D84*EduEnabled+Crises!D84+'Breaking News'!D84+Dilemmas!D84+Startups!D84 -> 10 | E84: =$B84+'Economy Ministry'!E84*EcEnabled+'Environment Ministry'!E84*EnvEnabled+'Defence Ministry'!E84*DefEnabled+'Education Ministry'!E84*EduEnabled+Crises!E84+'Breaking News'!E84+Dilemmas!E84+Startups!E84 -> 10 | F84: =$B84+'Economy Ministry'!F84*EcEnabled+'Environment Ministry'!F84*EnvEnabled+'Defence Ministry'!F84*DefEnabled+'Education Ministry'!F84*EduEnabled+Crises!F84+'Breaking News'!F84+Dilemmas!F84+Startups!F84 -> 10 | G84: =$B84+'Economy Ministry'!G84*EcEnabled+'Environment Ministry'!G84*EnvEnabled+'Defence Ministry'!G84*DefEnabled+'Education Ministry'!G84*EduEnabled+Crises!G84+'Breaking News'!G84+Dilemmas!G84+Startups!G84 -> 10 | H84: =$B84+'Economy Ministry'!H84*EcEnabled+'Environment Ministry'!H84*EnvEnabled+'Defence Ministry'!H84*DefEnabled+'Education Ministry'!H84*EduEnabled+Crises!H84+'Breaking News'!H84+Dilemmas!H84+Startups!H84 -> 10 | I84: =$B84+'Economy Ministry'!I84*EcEnabled+'Environment Ministry'!I84*EnvEnabled+'Defence Ministry'!I84*DefEnabled+'Education Ministry'!I84*EduEnabled+Crises!I84+'Breaking News'!I84+Dilemmas!I84 -> 10 | J84: =$B84+'Economy Ministry'!J84*EcEnabled+'Environment Ministry'!J84*EnvEnabled+'Defence Ministry'!J84*DefEnabled+'Education Ministry'!J84*EduEnabled+Crises!J84+'Breaking News'!J84+Dilemmas!J84 -> 10
A85: WaterCircularityIndex | B85: 25 | C85: =$B85+'Economy Ministry'!C85*EcEnabled+'Environment Ministry'!C85*EnvEnabled+'Defence Ministry'!C85*DefEnabled+'Education Ministry'!C85*EduEnabled+Crises!C85+'Breaking News'!C85+Dilemmas!C85+Startups!C85 -> 25 | D85: =$B85+'Economy Ministry'!D85*EcEnabled+'Environment Ministry'!D85*EnvEnabled+'Defence Ministry'!D85*DefEnabled+'Education Ministry'!D85*EduEnabled+Crises!D85+'Breaking News'!D85+Dilemmas!D85+Startups!D85 -> 25 | E85: =$B85+'Economy Ministry'!E85*EcEnabled+'Environment Ministry'!E85*EnvEnabled+'Defence Ministry'!E85*DefEnabled+'Education Ministry'!E85*EduEnabled+Crises!E85+'Breaking News'!E85+Dilemmas!E85+Startups!E85 -> 25 | F85: =$B85+'Economy Ministry'!F85*EcEnabled+'Environment Ministry'!F85*EnvEnabled+'Defence Ministry'!F85*DefEnabled+'Education Ministry'!F85*EduEnabled+Crises!F85+'Breaking News'!F85+Dilemmas!F85+Startups!F85 -> 25 | G85: =$B85+'Economy Ministry'!G85*EcEnabled+'Environment Ministry'!G85*EnvEnabled+'Defence Ministry'!G85*DefEnabled+'Education Ministry'!G85*EduEnabled+Crises!G85+'Breaking News'!G85+Dilemmas!G85+Startups!G85 -> 25 | H85: =$B85+'Economy Ministry'!H85*EcEnabled+'Environment Ministry'!H85*EnvEnabled+'Defence Ministry'!H85*DefEnabled+'Education Ministry'!H85*EduEnabled+Crises!H85+'Breaking News'!H85+Dilemmas!H85+Startups!H85 -> 25 | I85: =$B85+'Economy Ministry'!I85*EcEnabled+'Environment Ministry'!I85*EnvEnabled+'Defence Ministry'!I85*DefEnabled+'Education Ministry'!I85*EduEnabled+Crises!I85+'Breaking News'!I85+Dilemmas!I85 -> 25 | J85: =$B85+'Economy Ministry'!J85*EcEnabled+'Environment Ministry'!J85*EnvEnabled+'Defence Ministry'!J85*DefEnabled+'Education Ministry'!J85*EduEnabled+Crises!J85+'Breaking News'!J85+Dilemmas!J85 -> 25
A86: EwasteCircularityIndex | B86: 20 | C86: =$B86+'Economy Ministry'!C86*EcEnabled+'Environment Ministry'!C86*EnvEnabled+'Defence Ministry'!C86*DefEnabled+'Education Ministry'!C86*EduEnabled+Crises!C86+'Breaking News'!C86+Dilemmas!C86+Startups!C86 -> 20 | D86: =$B86+'Economy Ministry'!D86*EcEnabled+'Environment Ministry'!D86*EnvEnabled+'Defence Ministry'!D86*DefEnabled+'Education Ministry'!D86*EduEnabled+Crises!D86+'Breaking News'!D86+Dilemmas!D86+Startups!D86 -> 20 | E86: =$B86+'Economy Ministry'!E86*EcEnabled+'Environment Ministry'!E86*EnvEnabled+'Defence Ministry'!E86*DefEnabled+'Education Ministry'!E86*EduEnabled+Crises!E86+'Breaking News'!E86+Dilemmas!E86+Startups!E86 -> 20 | F86: =$B86+'Economy Ministry'!F86*EcEnabled+'Environment Ministry'!F86*EnvEnabled+'Defence Ministry'!F86*DefEnabled+'Education Ministry'!F86*EduEnabled+Crises!F86+'Breaking News'!F86+Dilemmas!F86+Startups!F86 -> 20 | G86: =$B86+'Economy Ministry'!G86*EcEnabled+'Environment Ministry'!G86*EnvEnabled+'Defence Ministry'!G86*DefEnabled+'Education Ministry'!G86*EduEnabled+Crises!G86+'Breaking News'!G86+Dilemmas!G86+Startups!G86 -> 20 | H86: =$B86+'Economy Ministry'!H86*EcEnabled+'Environment Ministry'!H86*EnvEnabled+'Defence Ministry'!H86*DefEnabled+'Education Ministry'!H86*EduEnabled+Crises!H86+'Breaking News'!H86+Dilemmas!H86+Startups!H86 -> 20 | I86: =$B86+'Economy Ministry'!I86*EcEnabled+'Environment Ministry'!I86*EnvEnabled+'Defence Ministry'!I86*DefEnabled+'Education Ministry'!I86*EduEnabled+Crises!I86+'Breaking News'!I86+Dilemmas!I86 -> 20 | J86: =$B86+'Economy Ministry'!J86*EcEnabled+'Environment Ministry'!J86*EnvEnabled+'Defence Ministry'!J86*DefEnabled+'Education Ministry'!J86*EduEnabled+Crises!J86+'Breaking News'!J86+Dilemmas!J86 -> 20
A87: CircularityIndex | B87: =(B85+B86)/2 -> 22.5 | C87: =(C85+C86)/2 -> 22.5 | D87: =(D85+D86)/2 -> 22.5 | E87: =(E85+E86)/2 -> 22.5 | F87: =(F85+F86)/2 -> 22.5 | G87: =(G85+G86)/2 -> 22.5 | H87: =(H85+H86)/2 -> 22.5 | I87: =(I85+I86)/2 -> 22.5 | J87: =(J85+J86)/2 -> 22.5
A88: EcosystemIntegrityIndex | B88: 25 | C88: =$B88+'Economy Ministry'!C88*EcEnabled+'Environment Ministry'!C88*EnvEnabled+'Defence Ministry'!C88*DefEnabled+'Education Ministry'!C88*EduEnabled+Crises!C88+'Breaking News'!C88+Dilemmas!C88+Startups!C88 -> 25 | D88: =$B88+'Economy Ministry'!D88*EcEnabled+'Environment Ministry'!D88*EnvEnabled+'Defence Ministry'!D88*DefEnabled+'Education Ministry'!D88*EduEnabled+Crises!D88+'Breaking News'!D88+Dilemmas!D88+Startups!D88 -> 25 | E88: =$B88+'Economy Ministry'!E88*EcEnabled+'Environment Ministry'!E88*EnvEnabled+'Defence Ministry'!E88*DefEnabled+'Education Ministry'!E88*EduEnabled+Crises!E88+'Breaking News'!E88+Dilemmas!E88+Startups!E88 -> 25 | F88: =$B88+'Economy Ministry'!F88*EcEnabled+'Environment Ministry'!F88*EnvEnabled+'Defence Ministry'!F88*DefEnabled+'Education Ministry'!F88*EduEnabled+Crises!F88+'Breaking News'!F88+Dilemmas!F88+Startups!F88 -> 25 | G88: =$B88+'Economy Ministry'!G88*EcEnabled+'Environment Ministry'!G88*EnvEnabled+'Defence Ministry'!G88*DefEnabled+'Education Ministry'!G88*EduEnabled+Crises!G88+'Breaking News'!G88+Dilemmas!G88+Startups!G88 -> 25 | H88: =$B88+'Economy Ministry'!H88*EcEnabled+'Environment Ministry'!H88*EnvEnabled+'Defence Ministry'!H88*DefEnabled+'Education Ministry'!H88*EduEnabled+Crises!H88+'Breaking News'!H88+Dilemmas!H88+Startups!H88 -> 25 | I88: =$B88+'Economy Ministry'!I88*EcEnabled+'Environment Ministry'!I88*EnvEnabled+'Defence Ministry'!I88*DefEnabled+'Education Ministry'!I88*EduEnabled+Crises!I88+'Breaking News'!I88+Dilemmas!I88 -> 25 | J88: =$B88+'Economy Ministry'!J88*EcEnabled+'Environment Ministry'!J88*EnvEnabled+'Defence Ministry'!J88*DefEnabled+'Education Ministry'!J88*EduEnabled+Crises!J88+'Breaking News'!J88+Dilemmas!J88 -> 25
A89: EnvironmentScore | B89: ='Result Targets'!B90 -> 34.722222 | C89: ='Result Targets'!C90 -> 34.722222 | D89: ='Result Targets'!D90 -> 34.722222 | E89: ='Result Targets'!E90 -> 34.722222 | F89: ='Result Targets'!F90 -> 34.722222 | G89: ='Result Targets'!G90 -> 34.722222 | H89: ='Result Targets'!H90 -> 34.722222 | I89: ='Result Targets'!I90 -> 34.722222 | J89: ='Result Targets'!J90 -> 34.722222
A92: Defense
A93: CybersecurityIndex | B93: 35 | C93: =$B93+'Economy Ministry'!C93*EcEnabled+'Environment Ministry'!C93*EnvEnabled+'Defence Ministry'!C93*DefEnabled+'Education Ministry'!C93*EduEnabled+Crises!C93+'Breaking News'!C93+Dilemmas!C93+Startups!C93 -> 35 | D93: =$B93+'Economy Ministry'!D93*EcEnabled+'Environment Ministry'!D93*EnvEnabled+'Defence Ministry'!D93*DefEnabled+'Education Ministry'!D93*EduEnabled+Crises!D93+'Breaking News'!D93+Dilemmas!D93+Startups!D93 -> 35 | E93: =$B93+'Economy Ministry'!E93*EcEnabled+'Environment Ministry'!E93*EnvEnabled+'Defence Ministry'!E93*DefEnabled+'Education Ministry'!E93*EduEnabled+Crises!E93+'Breaking News'!E93+Dilemmas!E93+Startups!E93 -> 35 | F93: =$B93+'Economy Ministry'!F93*EcEnabled+'Environment Ministry'!F93*EnvEnabled+'Defence Ministry'!F93*DefEnabled+'Education Ministry'!F93*EduEnabled+Crises!F93+'Breaking News'!F93+Dilemmas!F93+Startups!F93 -> 35 | G93: =$B93+'Economy Ministry'!G93*EcEnabled+'Environment Ministry'!G93*EnvEnabled+'Defence Ministry'!G93*DefEnabled+'Education Ministry'!G93*EduEnabled+Crises!G93+'Breaking News'!G93+Dilemmas!G93+Startups!G93 -> 35 | H93: =$B93+'Economy Ministry'!H93*EcEnabled+'Environment Ministry'!H93*EnvEnabled+'Defence Ministry'!H93*DefEnabled+'Education Ministry'!H93*EduEnabled+Crises!H93+'Breaking News'!H93+Dilemmas!H93+Startups!H93 -> 35 | I93: =$B93+'Economy Ministry'!I93*EcEnabled+'Environment Ministry'!I93*EnvEnabled+'Defence Ministry'!I93*DefEnabled+'Education Ministry'!I93*EduEnabled+Crises!I93+'Breaking News'!I93+Dilemmas!I93 -> 35 | J93: =$B93+'Economy Ministry'!J93*EcEnabled+'Environment Ministry'!J93*EnvEnabled+'Defence Ministry'!J93*DefEnabled+'Education Ministry'!J93*EduEnabled+Crises!J93+'Breaking News'!J93+Dilemmas!J93 -> 35
A94: AutonomousSystemsSafteyIndex | B94: 40 | C94: =$B94+'Economy Ministry'!C94*EcEnabled+'Environment Ministry'!C94*EnvEnabled+'Defence Ministry'!C94*DefEnabled+'Education Ministry'!C94*EduEnabled+Crises!C94+'Breaking News'!C94+Dilemmas!C94+Startups!C94 -> 40 | D94: =$B94+'Economy Ministry'!D94*EcEnabled+'Environment Ministry'!D94*EnvEnabled+'Defence Ministry'!D94*DefEnabled+'Education Ministry'!D94*EduEnabled+Crises!D94+'Breaking News'!D94+Dilemmas!D94+Startups!D94 -> 39.2 | E94: =$B94+'Economy Ministry'!E94*EcEnabled+'Environment Ministry'!E94*EnvEnabled+'Defence Ministry'!E94*DefEnabled+'Education Ministry'!E94*EduEnabled+Crises!E94+'Breaking News'!E94+Dilemmas!E94+Startups!E94 -> 39.2 | F94: =$B94+'Economy Ministry'!F94*EcEnabled+'Environment Ministry'!F94*EnvEnabled+'Defence Ministry'!F94*DefEnabled+'Education Ministry'!F94*EduEnabled+Crises!F94+'Breaking News'!F94+Dilemmas!F94+Startups!F94 -> 39.2 | G94: =$B94+'Economy Ministry'!G94*EcEnabled+'Environment Ministry'!G94*EnvEnabled+'Defence Ministry'!G94*DefEnabled+'Education Ministry'!G94*EduEnabled+Crises!G94+'Breaking News'!G94+Dilemmas!G94+Startups!G94 -> 39.2 | H94: =$B94+'Economy Ministry'!H94*EcEnabled+'Environment Ministry'!H94*EnvEnabled+'Defence Ministry'!H94*DefEnabled+'Education Ministry'!H94*EduEnabled+Crises!H94+'Breaking News'!H94+Dilemmas!H94+Startups!H94 -> 39.2 | I94: =$B94+'Economy Ministry'!I94*EcEnabled+'Environment Ministry'!I94*EnvEnabled+'Defence Ministry'!I94*DefEnabled+'Education Ministry'!I94*EduEnabled+Crises!I94+'Breaking News'!I94+Dilemmas!I94 -> 39.2 | J94: =$B94+'Economy Ministry'!J94*EcEnabled+'Environment Ministry'!J94*EnvEnabled+'Defence Ministry'!J94*DefEnabled+'Education Ministry'!J94*EduEnabled+Crises!J94+'Breaking News'!J94+Dilemmas!J94 -> 39.2
A95: DefenseExports | B95: 1000000000 | C95: =$B95+'Economy Ministry'!C95*EcEnabled+'Environment Ministry'!C95*EnvEnabled+'Defence Ministry'!C95*DefEnabled+'Education Ministry'!C95*EduEnabled+Crises!C95+'Breaking News'!C95+Dilemmas!C95+Startups!C95 -> 1000000000 | D95: =$B95+'Economy Ministry'!D95*EcEnabled+'Environment Ministry'!D95*EnvEnabled+'Defence Ministry'!D95*DefEnabled+'Education Ministry'!D95*EduEnabled+Crises!D95+'Breaking News'!D95+Dilemmas!D95+Startups!D95 -> 1000000000 | E95: =$B95+'Economy Ministry'!E95*EcEnabled+'Environment Ministry'!E95*EnvEnabled+'Defence Ministry'!E95*DefEnabled+'Education Ministry'!E95*EduEnabled+Crises!E95+'Breaking News'!E95+Dilemmas!E95+Startups!E95 -> 1000000000 | F95: =$B95+'Economy Ministry'!F95*EcEnabled+'Environment Ministry'!F95*EnvEnabled+'Defence Ministry'!F95*DefEnabled+'Education Ministry'!F95*EduEnabled+Crises!F95+'Breaking News'!F95+Dilemmas!F95+Startups!F95 -> 1000000000 | G95: =$B95+'Economy Ministry'!G95*EcEnabled+'Environment Ministry'!G95*EnvEnabled+'Defence Ministry'!G95*DefEnabled+'Education Ministry'!G95*EduEnabled+Crises!G95+'Breaking News'!G95+Dilemmas!G95+Startups!G95 -> 1000000000 | H95: =$B95+'Economy Ministry'!H95*EcEnabled+'Environment Ministry'!H95*EnvEnabled+'Defence Ministry'!H95*DefEnabled+'Education Ministry'!H95*EduEnabled+Crises!H95+'Breaking News'!H95+Dilemmas!H95+Startups!H95 -> 1000000000 | I95: =$B95+'Economy Ministry'!I95*EcEnabled+'Environment Ministry'!I95*EnvEnabled+'Defence Ministry'!I95*DefEnabled+'Education Ministry'!I95*EduEnabled+Crises!I95+'Breaking News'!I95+Dilemmas!I95 -> 1000000000 | J95: =$B95+'Economy Ministry'!J95*EcEnabled+'Environment Ministry'!J95*EnvEnabled+'Defence Ministry'!J95*DefEnabled+'Education Ministry'!J95*EduEnabled+Crises!J95+'Breaking News'!J95+Dilemmas!J95 -> 1000000000
A96: DefenseImports | B96: 1500000000 | C96: =$B96+'Economy Ministry'!C96*EcEnabled+'Environment Ministry'!C96*EnvEnabled+'Defence Ministry'!C96*DefEnabled+'Education Ministry'!C96*EduEnabled+Crises!C96+'Breaking News'!C96+Dilemmas!C96+Startups!C96 -> 1500000000 | D96: =$B96+'Economy Ministry'!D96*EcEnabled+'Environment Ministry'!D96*EnvEnabled+'Defence Ministry'!D96*DefEnabled+'Education Ministry'!D96*EduEnabled+Crises!D96+'Breaking News'!D96+Dilemmas!D96+Startups!D96 -> 1380000000 | E96: =$B96+'Economy Ministry'!E96*EcEnabled+'Environment Ministry'!E96*EnvEnabled+'Defence Ministry'!E96*DefEnabled+'Education Ministry'!E96*EduEnabled+Crises!E96+'Breaking News'!E96+Dilemmas!E96+Startups!E96 -> 1380000000 | F96: =$B96+'Economy Ministry'!F96*EcEnabled+'Environment Ministry'!F96*EnvEnabled+'Defence Ministry'!F96*DefEnabled+'Education Ministry'!F96*EduEnabled+Crises!F96+'Breaking News'!F96+Dilemmas!F96+Startups!F96 -> 1380000000 | G96: =$B96+'Economy Ministry'!G96*EcEnabled+'Environment Ministry'!G96*EnvEnabled+'Defence Ministry'!G96*DefEnabled+'Education Ministry'!G96*EduEnabled+Crises!G96+'Breaking News'!G96+Dilemmas!G96+Startups!G96 -> 1380000000 | H96: =$B96+'Economy Ministry'!H96*EcEnabled+'Environment Ministry'!H96*EnvEnabled+'Defence Ministry'!H96*DefEnabled+'Education Ministry'!H96*EduEnabled+Crises!H96+'Breaking News'!H96+Dilemmas!H96+Startups!H96 -> 1380000000 | I96: =$B96+'Economy Ministry'!I96*EcEnabled+'Environment Ministry'!I96*EnvEnabled+'Defence Ministry'!I96*DefEnabled+'Education Ministry'!I96*EduEnabled+Crises!I96+'Breaking News'!I96+Dilemmas!I96 -> 1380000000 | J96: =$B96+'Economy Ministry'!J96*EcEnabled+'Environment Ministry'!J96*EnvEnabled+'Defence Ministry'!J96*DefEnabled+'Education Ministry'!J96*EduEnabled+Crises!J96+'Breaking News'!J96+Dilemmas!J96 -> 1380000000
A97: MilitaryTechnologyTradeBalance | B97: =B95-B96 -> -500000000 | C97: =C95-C96 -> -500000000 | D97: =D95-D96 -> -380000000 | E97: =E95-E96 -> -380000000 | F97: =F95-F96 -> -380000000 | G97: =G95-G96 -> -380000000 | H97: =H95-H96 -> -380000000 | I97: =I95-I96 -> -380000000 | J97: =J95-J96 -> -380000000
A98: DefenseScore | B98: ='Result Targets'!B98 -> 35.726496 | C98: ='Result Targets'!C98 -> 35.726496 | D98: ='Result Targets'!D98 -> 35.37094 | E98: ='Result Targets'!E98 -> 35.37094 | F98: ='Result Targets'!F98 -> 35.37094 | G98: ='Result Targets'!G98 -> 35.37094 | H98: ='Result Targets'!H98 -> 35.37094 | I98: ='Result Targets'!I98 -> 35.37094 | J98: ='Result Targets'!J98 -> 35.37094
A101: Education & Innovation
A102: AILiteracy | B102: 25 | C102: =$B102+'Economy Ministry'!C102*EcEnabled+'Environment Ministry'!C102*EnvEnabled+'Defence Ministry'!C102*DefEnabled+'Education Ministry'!C102*EduEnabled+Crises!C102+'Breaking News'!C102+Dilemmas!C102+Startups!C102 -> 25 | D102: =$B102+'Economy Ministry'!D102*EcEnabled+'Environment Ministry'!D102*EnvEnabled+'Defence Ministry'!D102*DefEnabled+'Education Ministry'!D102*EduEnabled+Crises!D102+'Breaking News'!D102+Dilemmas!D102+Startups!D102 -> 25 | E102: =$B102+'Economy Ministry'!E102*EcEnabled+'Environment Ministry'!E102*EnvEnabled+'Defence Ministry'!E102*DefEnabled+'Education Ministry'!E102*EduEnabled+Crises!E102+'Breaking News'!E102+Dilemmas!E102+Startups!E102 -> 25 | F102: =$B102+'Economy Ministry'!F102*EcEnabled+'Environment Ministry'!F102*EnvEnabled+'Defence Ministry'!F102*DefEnabled+'Education Ministry'!F102*EduEnabled+Crises!F102+'Breaking News'!F102+Dilemmas!F102+Startups!F102 -> 24.2 | G102: =$B102+'Economy Ministry'!G102*EcEnabled+'Environment Ministry'!G102*EnvEnabled+'Defence Ministry'!G102*DefEnabled+'Education Ministry'!G102*EduEnabled+Crises!G102+'Breaking News'!G102+Dilemmas!G102+Startups!G102 -> 24.2 | H102: =$B102+'Economy Ministry'!H102*EcEnabled+'Environment Ministry'!H102*EnvEnabled+'Defence Ministry'!H102*DefEnabled+'Education Ministry'!H102*EduEnabled+Crises!H102+'Breaking News'!H102+Dilemmas!H102+Startups!H102 -> 24.2 | I102: =$B102+'Economy Ministry'!I102*EcEnabled+'Environment Ministry'!I102*EnvEnabled+'Defence Ministry'!I102*DefEnabled+'Education Ministry'!I102*EduEnabled+Crises!I102+'Breaking News'!I102+Dilemmas!I102 -> 24.2 | J102: =$B102+'Economy Ministry'!J102*EcEnabled+'Environment Ministry'!J102*EnvEnabled+'Defence Ministry'!J102*DefEnabled+'Education Ministry'!J102*EduEnabled+Crises!J102+'Breaking News'!J102+Dilemmas!J102 -> 24.2
A103: InnovationIndex | B103: 30 | C103: =$B103+'Economy Ministry'!C103*EcEnabled+'Environment Ministry'!C103*EnvEnabled+'Defence Ministry'!C103*DefEnabled+'Education Ministry'!C103*EduEnabled+Crises!C103+'Breaking News'!C103+Dilemmas!C103+Startups!C103 -> 30 | D103: =$B103+'Economy Ministry'!D103*EcEnabled+'Environment Ministry'!D103*EnvEnabled+'Defence Ministry'!D103*DefEnabled+'Education Ministry'!D103*EduEnabled+Crises!D103+'Breaking News'!D103+Dilemmas!D103+Startups!D103 -> 30 | E103: =$B103+'Economy Ministry'!E103*EcEnabled+'Environment Ministry'!E103*EnvEnabled+'Defence Ministry'!E103*DefEnabled+'Education Ministry'!E103*EduEnabled+Crises!E103+'Breaking News'!E103+Dilemmas!E103+Startups!E103 -> 29.6 | F103: =$B103+'Economy Ministry'!F103*EcEnabled+'Environment Ministry'!F103*EnvEnabled+'Defence Ministry'!F103*DefEnabled+'Education Ministry'!F103*EduEnabled+Crises!F103+'Breaking News'!F103+Dilemmas!F103+Startups!F103 -> 29.6 | G103: =$B103+'Economy Ministry'!G103*EcEnabled+'Environment Ministry'!G103*EnvEnabled+'Defence Ministry'!G103*DefEnabled+'Education Ministry'!G103*EduEnabled+Crises!G103+'Breaking News'!G103+Dilemmas!G103+Startups!G103 -> 29.6 | H103: =$B103+'Economy Ministry'!H103*EcEnabled+'Environment Ministry'!H103*EnvEnabled+'Defence Ministry'!H103*DefEnabled+'Education Ministry'!H103*EduEnabled+Crises!H103+'Breaking News'!H103+Dilemmas!H103+Startups!H103 -> 30.1 | I103: =$B103+'Economy Ministry'!I103*EcEnabled+'Environment Ministry'!I103*EnvEnabled+'Defence Ministry'!I103*DefEnabled+'Education Ministry'!I103*EduEnabled+Crises!I103+'Breaking News'!I103+Dilemmas!I103 -> 30.1 | J103: =$B103+'Economy Ministry'!J103*EcEnabled+'Environment Ministry'!J103*EnvEnabled+'Defence Ministry'!J103*DefEnabled+'Education Ministry'!J103*EduEnabled+Crises!J103+'Breaking News'!J103+Dilemmas!J103 -> 30.1
A104: InstitutionalAdoptionRate | B104: 20 | C104: =$B104+'Economy Ministry'!C104*EcEnabled+'Environment Ministry'!C104*EnvEnabled+'Defence Ministry'!C104*DefEnabled+'Education Ministry'!C104*EduEnabled+Crises!C104+'Breaking News'!C104+Dilemmas!C104+Startups!C104 -> 20 | D104: =$B104+'Economy Ministry'!D104*EcEnabled+'Environment Ministry'!D104*EnvEnabled+'Defence Ministry'!D104*DefEnabled+'Education Ministry'!D104*EduEnabled+Crises!D104+'Breaking News'!D104+Dilemmas!D104+Startups!D104 -> 20 | E104: =$B104+'Economy Ministry'!E104*EcEnabled+'Environment Ministry'!E104*EnvEnabled+'Defence Ministry'!E104*DefEnabled+'Education Ministry'!E104*EduEnabled+Crises!E104+'Breaking News'!E104+Dilemmas!E104+Startups!E104 -> 20 | F104: =$B104+'Economy Ministry'!F104*EcEnabled+'Environment Ministry'!F104*EnvEnabled+'Defence Ministry'!F104*DefEnabled+'Education Ministry'!F104*EduEnabled+Crises!F104+'Breaking News'!F104+Dilemmas!F104+Startups!F104 -> 20 | G104: =$B104+'Economy Ministry'!G104*EcEnabled+'Environment Ministry'!G104*EnvEnabled+'Defence Ministry'!G104*DefEnabled+'Education Ministry'!G104*EduEnabled+Crises!G104+'Breaking News'!G104+Dilemmas!G104+Startups!G104 -> 20 | H104: =$B104+'Economy Ministry'!H104*EcEnabled+'Environment Ministry'!H104*EnvEnabled+'Defence Ministry'!H104*DefEnabled+'Education Ministry'!H104*EduEnabled+Crises!H104+'Breaking News'!H104+Dilemmas!H104+Startups!H104 -> 20 | I104: =$B104+'Economy Ministry'!I104*EcEnabled+'Environment Ministry'!I104*EnvEnabled+'Defence Ministry'!I104*DefEnabled+'Education Ministry'!I104*EduEnabled+Crises!I104+'Breaking News'!I104+Dilemmas!I104 -> 20 | J104: =$B104+'Economy Ministry'!J104*EcEnabled+'Environment Ministry'!J104*EnvEnabled+'Defence Ministry'!J104*DefEnabled+'Education Ministry'!J104*EduEnabled+Crises!J104+'Breaking News'!J104+Dilemmas!J104 -> 20
A105: EducationScore | B105: ='Result Targets'!B105 -> 40.811966 | C105: ='Result Targets'!C105 -> 40.811966 | D105: ='Result Targets'!D105 -> 40.811966 | E105: ='Result Targets'!E105 -> 40.589744 | F105: ='Result Targets'!F105 -> 40.145299 | G105: ='Result Targets'!G105 -> 40.145299 | H105: ='Result Targets'!H105 -> 40.423077 | I105: ='Result Targets'!I105 -> 40.423077 | J105: ='Result Targets'!J105 -> 40.423077
A108: Weighted Governance
A109: GrowthWellBeing | B109: =B64*'Project Variables'!$E$40 -> 12.5 | C109: =C64*'Project Variables'!$E$40 -> 12.5 | D109: =D64*'Project Variables'!$E$40 -> 12.5 | E109: =E64*'Project Variables'!$E$40 -> 12.5 | F109: =F64*'Project Variables'!$E$40 -> 12.5 | G109: =G64*'Project Variables'!$E$40 -> 12.5 | H109: =H64*'Project Variables'!$E$40 -> 12.5 | I109: =I64*'Project Variables'!$E$40 -> 12.5 | J109: =J64*'Project Variables'!$E$40 -> 12.5
A110: HumanRights | B110: =B65*'Project Variables'!$E$41 -> 13.75 | C110: =C65*'Project Variables'!$E$41 -> 13.75 | D110: =D65*'Project Variables'!$E$41 -> 13.35 | E110: =E65*'Project Variables'!$E$41 -> 13.35 | F110: =F65*'Project Variables'!$E$41 -> 13.35 | G110: =G65*'Project Variables'!$E$41 -> 13.35 | H110: =H65*'Project Variables'!$E$41 -> 13.35 | I110: =I65*'Project Variables'!$E$41 -> 13.35 | J110: =J65*'Project Variables'!$E$41 -> 13.35
A111: PrivacyDataProtection | B111: =B66*'Project Variables'!$E$42 -> 6 | C111: =C66*'Project Variables'!$E$42 -> 6 | D111: =D66*'Project Variables'!$E$42 -> 6 | E111: =E66*'Project Variables'!$E$42 -> 6 | F111: =F66*'Project Variables'!$E$42 -> 6 | G111: =G66*'Project Variables'!$E$42 -> 6 | H111: =H66*'Project Variables'!$E$42 -> 6 | I111: =I66*'Project Variables'!$E$42 -> 6 | J111: =J66*'Project Variables'!$E$42 -> 6
A112: Transparency | B112: =B67*'Project Variables'!$E$43 -> 5.7 | C112: =C67*'Project Variables'!$E$43 -> 5.7 | D112: =D67*'Project Variables'!$E$43 -> 5.46 | E112: =E67*'Project Variables'!$E$43 -> 5.46 | F112: =F67*'Project Variables'!$E$43 -> 5.46 | G112: =G67*'Project Variables'!$E$43 -> 5.46 | H112: =H67*'Project Variables'!$E$43 -> 5.22 | I112: =I67*'Project Variables'!$E$43 -> 5.22 | J112: =J67*'Project Variables'!$E$43 -> 5.22
A113: SecuritySafety | B113: =B68*'Project Variables'!$E$44 -> 4.5 | C113: =C68*'Project Variables'!$E$44 -> 4.5 | D113: =D68*'Project Variables'!$E$44 -> 4.5 | E113: =E68*'Project Variables'!$E$44 -> 4.5 | F113: =F68*'Project Variables'!$E$44 -> 4.5 | G113: =G68*'Project Variables'!$E$44 -> 4.5 | H113: =H68*'Project Variables'!$E$44 -> 4.5 | I113: =I68*'Project Variables'!$E$44 -> 4.5 | J113: =J68*'Project Variables'!$E$44 -> 4.5
A114: Accountability | B114: =B69*'Project Variables'!$E$45 -> 3.8 | C114: =C69*'Project Variables'!$E$45 -> 3.8 | D114: =D69*'Project Variables'!$E$45 -> 3.48 | E114: =E69*'Project Variables'!$E$45 -> 3.48 | F114: =F69*'Project Variables'!$E$45 -> 3.48 | G114: =G69*'Project Variables'!$E$45 -> 3.48 | H114: =H69*'Project Variables'!$E$45 -> 3.16 | I114: =I69*'Project Variables'!$E$45 -> 3.16 | J114: =J69*'Project Variables'!$E$45 -> 3.16
A117: TrustInGovernment | B117: =ROUND(SUM(B109:B114),1) -> 46.3 | C117: =ROUND(SUM(C109:C114),1) -> 46.3 | D117: =ROUND(SUM(D109:D114),1) -> 45.3 | E117: =ROUND(SUM(E109:E114),1) -> 45.3 | F117: =ROUND(SUM(F109:F114),1) -> 45.3 | G117: =ROUND(SUM(G109:G114),1) -> 45.3 | H117: =ROUND(SUM(H109:H114),1) -> 44.7 | I117: =ROUND(SUM(I109:I114),1) -> 44.7 | J117: =ROUND(SUM(J109:J114),1) -> 44.7
A118: AverageMinistryScore | B118: ='Result Targets'!B112 -> 34.065171 | C118: ='Result Targets'!C112 -> 33.576282 | D118: ='Result Targets'!D112 -> 33.487393 | E118: ='Result Targets'!E112 -> 33.298504 | F118: ='Result Targets'!F112 -> 33.187393 | G118: ='Result Targets'!G112 -> 32.920726 | H118: ='Result Targets'!H112 -> 33.267949 | I118: ='Result Targets'!I112 -> 33.267949 | J118: ='Result Targets'!J112 -> 33.267949

Sheet Result Targets
B1: 0 | C1: 1 | D1: 2 | E1: 3 | F1: 4 | G1: 5 | H1: 6 | I1: 7 | J1: 8
A2: Targets
A4: Economy
A5: AIContributionToGDPTarget | B5: =IF(FacilSetsTargets=1,'Target Settings'!B4,'Target Settings'!E4) -> 12 | C5: =B5 -> 12 | D5: =C5 -> 12 | E5: =D5 -> 12 | F5: =E5 -> 12 | G5: =F5 -> 12 | H5: =G5 -> 12 | I5: =H5 -> 12 | J5: =I5 -> 12
A6: AIFDIStockTarget | B6: 100000000000 | C6: =B6 -> 100000000000 | D6: =C6 -> 100000000000 | E6: =D6 -> 100000000000 | F6: =E6 -> 100000000000 | G6: =F6 -> 100000000000 | H6: =G6 -> 100000000000 | I6: =H6 -> 100000000000 | J6: =I6 -> 100000000000
A9: NetJobsFromAITarget | B9: =IF(FacilSetsTargets=1,'Target Settings'!B6,'Target Settings'!E6) -> 500000 | C9: =B9 -> 500000 | D9: =C9 -> 500000 | E9: =D9 -> 500000 | F9: =E9 -> 500000 | G9: =F9 -> 500000 | H9: =G9 -> 500000 | I9: =H9 -> 500000 | J9: =I9 -> 500000
A12: Environment
A15: RenewableEnergyFactorTarget | B15: =IF(FacilSetsTargets=1,'Target Settings'!B10,'Target Settings'!E10) -> 40 | C15: =B15 -> 40 | D15: =C15 -> 40 | E15: =D15 -> 40 | F15: =E15 -> 40 | G15: =F15 -> 40 | H15: =G15 -> 40 | I15: =H15 -> 40 | J15: =I15 -> 40
A18: CircularityIndexTarget | B18: =IF(FacilSetsTargets=1,'Target Settings'!B11,'Target Settings'!E11) -> 60 | C18: =B18 -> 60 | D18: =C18 -> 60 | E18: =D18 -> 60 | F18: =E18 -> 60 | G18: =F18 -> 60 | H18: =G18 -> 60 | I18: =H18 -> 60 | J18: =I18 -> 60
A19: EcosystemIntegrityIndexTarget | B19: =IF(FacilSetsTargets=1,'Target Settings'!B12,'Target Settings'!E12) -> 60 | C19: =B19 -> 60 | D19: =C19 -> 60 | E19: =D19 -> 60 | F19: =E19 -> 60 | G19: =F19 -> 60 | H19: =G19 -> 60 | I19: =H19 -> 60 | J19: =I19 -> 60
A22: Defense
A23: CybersecurityIndexTarget | B23: =IF(FacilSetsTargets=1,'Target Settings'!B16,'Target Settings'!E16) -> 65 | C23: =B23 -> 65 | D23: =C23 -> 65 | E23: =D23 -> 65 | F23: =E23 -> 65 | G23: =F23 -> 65 | H23: =G23 -> 65 | I23: =H23 -> 65 | J23: =I23 -> 65
A24: AutonomousSystemsSafteyIndexTarget | B24: =IF(FacilSetsTargets=1,'Target Settings'!B17,'Target Settings'!E17) -> 75 | C24: =B24 -> 75 | D24: =C24 -> 75 | E24: =D24 -> 75 | F24: =E24 -> 75 | G24: =F24 -> 75 | H24: =G24 -> 75 | I24: =H24 -> 75 | J24: =I24 -> 75
A27: MilitaryTechnologyTradeBalanceTarget | B27: =IF(FacilSetsTargets=1,'Target Settings'!B18,'Target Settings'!E18) -> 2000000000 | C27: =B27 -> 2000000000 | D27: =C27 -> 2000000000 | E27: =D27 -> 2000000000 | F27: =E27 -> 2000000000 | G27: =F27 -> 2000000000 | H27: =G27 -> 2000000000 | I27: =H27 -> 2000000000 | J27: =I27 -> 2000000000
A30: Education & Innovation
A31: AILiteracyTarget | B31: =IF(FacilSetsTargets=1,'Target Settings'!B22,'Target Settings'!E22) -> 60 | C31: =B31 -> 60 | D31: =C31 -> 60 | E31: =D31 -> 60 | F31: =E31 -> 60 | G31: =F31 -> 60 | H31: =G31 -> 60 | I31: =H31 -> 60 | J31: =I31 -> 60
A32: InnovationIndexTarget | B32: =IF(FacilSetsTargets=1,'Target Settings'!B23,'Target Settings'!E23) -> 60 | C32: =B32 -> 60 | D32: =C32 -> 60 | E32: =D32 -> 60 | F32: =E32 -> 60 | G32: =F32 -> 60 | H32: =G32 -> 60 | I32: =H32 -> 60 | J32: =I32 -> 60
A33: InstitutionalAdoptionRateTarget | B33: =IF(FacilSetsTargets=1,'Target Settings'!B24,'Target Settings'!E24) -> 65 | C33: =B33 -> 65 | D33: =C33 -> 65 | E33: =D33 -> 65 | F33: =E33 -> 65 | G33: =F33 -> 65 | H33: =G33 -> 65 | I33: =H33 -> 65 | J33: =I33 -> 65
A70: Percentage of Target Achieved %
A72: Economy
A73: AIContributionToGDPPercOfTargetAchieved | B73: =MAX((Results!B73)/('Result Targets'!B5),0) * 100 -> 25 | C73: =MAX((Results!C73)/('Result Targets'!C5),0) * 100 -> 22.333333 | D73: =MAX((Results!D73)/('Result Targets'!D5),0) * 100 -> 22.333333 | E73: =MAX((Results!E73)/('Result Targets'!E5),0) * 100 -> 22.333333 | F73: =MAX((Results!F73)/('Result Targets'!F5),0) * 100 -> 22.333333 | G73: =MAX((Results!G73)/('Result Targets'!G5),0) * 100 -> 22.333333 | H73: =MAX((Results!H73)/('Result Targets'!H5),0) * 100 -> 25.666667 | I73: =MAX((Results!I73)/('Result Targets'!I5),0) * 100 -> 25.666667 | J73: =MAX((Results!J73)/('Result Targets'!J5),0) * 100 -> 25.666667
A74: AIFDIStockPercOfTargetAchieved | B74: =MAX((Results!B74)/('Result Targets'!B6),0)*100 -> 50 | C74: =MAX((Results!C74)/('Result Targets'!C6),0)*100 -> 46.8 | D74: =MAX((Results!D74)/('Result Targets'!D6),0)*100 -> 46.8 | E74: =MAX((Results!E74)/('Result Targets'!E6),0)*100 -> 45.2 | F74: =MAX((Results!F74)/('Result Targets'!F6),0)*100 -> 45.2 | G74: =MAX((Results!G74)/('Result Targets'!G6),0)*100 -> 42 | H74: =MAX((Results!H74)/('Result Targets'!H6),0)*100 -> 42 | I74: =MAX((Results!I74)/('Result Targets'!I6),0)*100 -> 42 | J74: =MAX((Results!J74)/('Result Targets'!J6),0)*100 -> 42
A77: NetJobsFromAIPercOfTargetAchieved | B77: =MAX((Results!B77)/('Result Targets'!B9),0)*100 -> 0 | C77: =MAX((Results!C77)/('Result Targets'!C9),0)*100 -> 0 | D77: =MAX((Results!D77)/('Result Targets'!D9),0)*100 -> 0 | E77: =MAX((Results!E77)/('Result Targets'!E9),0)*100 -> 0 | F77: =MAX((Results!F77)/('Result Targets'!F9),0)*100 -> 0 | G77: =MAX((Results!G77)/('Result Targets'!G9),0)*100 -> 0 | H77: =MAX((Results!H77)/('Result Targets'!H9),0)*100 -> 0 | I77: =MAX((Results!I77)/('Result Targets'!I9),0)*100 -> 0 | J77: =MAX((Results!J77)/('Result Targets'!J9),0)*100 -> 0
A78: EconomyScore | B78: =AVERAGE(MIN(B73,100),MIN(B74,100),MIN(B77,100)) -> 25 | C78: =AVERAGE(MIN(C73,100),MIN(C74,100),MIN(C77,100)) -> 23.044444 | D78: =AVERAGE(MIN(D73,100),MIN(D74,100),MIN(D77,100)) -> 23.044444 | E78: =AVERAGE(MIN(E73,100),MIN(E74,100),MIN(E77,100)) -> 22.511111 | F78: =AVERAGE(MIN(F73,100),MIN(F74,100),MIN(F77,100)) -> 22.511111 | G78: =AVERAGE(MIN(G73,100),MIN(G74,100),MIN(G77,100)) -> 21.444444 | H78: =AVERAGE(MIN(H73,100),MIN(H74,100),MIN(H77,100)) -> 22.555556 | I78: =AVERAGE(MIN(I73,100),MIN(I74,100),MIN(I77,100)) -> 22.555556 | J78: =AVERAGE(MIN(J73,100),MIN(J74,100),MIN(J77,100)) -> 22.555556
A81: Environment
A84: RenewableEnergyFactorPercOfTargetAchieved | B84: =MAX((Results!B84)/('Result Targets'!B15),0) * 100 -> 25 | C84: =MAX((Results!C84)/('Result Targets'!C15),0) * 100 -> 25 | D84: =MAX((Results!D84)/('Result Targets'!D15),0) * 100 -> 25 | E84: =MAX((Results!E84)/('Result Targets'!E15),0) * 100 -> 25 | F84: =MAX((Results!F84)/('Result Targets'!F15),0) * 100 -> 25 | G84: =MAX((Results!G84)/('Result Targets'!G15),0) * 100 -> 25 | H84: =MAX((Results!H84)/('Result Targets'!H15),0) * 100 -> 25 | I84: =MAX((Results!I84)/('Result Targets'!I15),0) * 100 -> 25 | J84: =MAX((Results!J84)/('Result Targets'!J15),0) * 100 -> 25
A87: CircularityIndexPercOfTargetAchieved | B87: =MAX((Results!B87)/('Result Targets'!B18),0) * 100 -> 37.5 | C87: =MAX((Results!C87)/('Result Targets'!C18),0) * 100 -> 37.5 | D87: =MAX((Results!D87)/('Result Targets'!D18),0) * 100 -> 37.5 | E87: =MAX((Results!E87)/('Result Targets'!E18),0) * 100 -> 37.5 | F87: =MAX((Results!F87)/('Result Targets'!F18),0) * 100 -> 37.5 | G87: =MAX((Results!G87)/('Result Targets'!G18),0) * 100 -> 37.5 | H87: =MAX((Results!H87)/('Result Targets'!H18),0) * 100 -> 37.5 | I87: =MAX((Results!I87)/('Result Targets'!I18),0) * 100 -> 37.5 | J87: =MAX((Results!J87)/('Result Targets'!J18),0) * 100 -> 37.5
A88: EcosystemIntegrityIndexPercOfTargetAchieved | B88: =MAX((Results!B88)/('Result Targets'!B19),0) * 100 -> 41.666667 | C88: =MAX((Results!C88)/('Result Targets'!C19),0) * 100 -> 41.666667 | D88: =MAX((Results!D88)/('Result Targets'!D19),0) * 100 -> 41.666667 | E88: =MAX((Results!E88)/('Result Targets'!E19),0) * 100 -> 41.666667 | F88: =MAX((Results!F88)/('Result Targets'!F19),0) * 100 -> 41.666667 | G88: =MAX((Results!G88)/('Result Targets'!G19),0) * 100 -> 41.666667 | H88: =MAX((Results!H88)/('Result Targets'!H19),0) * 100 -> 41.666667 | I88: =MAX((Results!I88)/('Result Targets'!I19),0) * 100 -> 41.666667 | J88: =MAX((Results!J88)/('Result Targets'!J19),0) * 100 -> 41.666667
A90: EnvironmentScore | B90: =AVERAGE(MIN(B84,100),MIN(B87,100),MIN(B88,100)) -> 34.722222 | C90: =AVERAGE(MIN(C84,100),MIN(C87,100),MIN(C88,100)) -> 34.722222 | D90: =AVERAGE(MIN(D84,100),MIN(D87,100),MIN(D88,100)) -> 34.722222 | E90: =AVERAGE(MIN(E84,100),MIN(E87,100),MIN(E88,100)) -> 34.722222 | F90: =AVERAGE(MIN(F84,100),MIN(F87,100),MIN(F88,100)) -> 34.722222 | G90: =AVERAGE(MIN(G84,100),MIN(G87,100),MIN(G88,100)) -> 34.722222 | H90: =AVERAGE(MIN(H84,100),MIN(H87,100),MIN(H88,100)) -> 34.722222 | I90: =AVERAGE(MIN(I84,100),MIN(I87,100),MIN(I88,100)) -> 34.722222 | J90: =AVERAGE(MIN(J84,100),MIN(J87,100),MIN(J88,100)) -> 34.722222
A92: Defense
A93: CybersecurityIndexPercOfTargetAchieved | B93: =MAX((Results!B93)/('Result Targets'!B23),0)*100 -> 53.846154 | C93: =MAX((Results!C93)/('Result Targets'!C23),0)*100 -> 53.846154 | D93: =MAX((Results!D93)/('Result Targets'!D23),0)*100 -> 53.846154 | E93: =MAX((Results!E93)/('Result Targets'!E23),0)*100 -> 53.846154 | F93: =MAX((Results!F93)/('Result Targets'!F23),0)*100 -> 53.846154 | G93: =MAX((Results!G93)/('Result Targets'!G23),0)*100 -> 53.846154 | H93: =MAX((Results!H93)/('Result Targets'!H23),0)*100 -> 53.846154 | I93: =MAX((Results!I93)/('Result Targets'!I23),0)*100 -> 53.846154 | J93: =MAX((Results!J93)/('Result Targets'!J23),0)*100 -> 53.846154
A94: AutonomousSystemsSafteyIndexPercOfTargetAchieved | B94: =MAX((Results!B94)/('Result Targets'!B24),0)*100 -> 53.333333 | C94: =MAX((Results!C94)/('Result Targets'!C24),0)*100 -> 53.333333 | D94: =MAX((Results!D94)/('Result Targets'!D24),0)*100 -> 52.266667 | E94: =MAX((Results!E94)/('Result Targets'!E24),0)*100 -> 52.266667 | F94: =MAX((Results!F94)/('Result Targets'!F24),0)*100 -> 52.266667 | G94: =MAX((Results!G94)/('Result Targets'!G24),0)*100 -> 52.266667 | H94: =MAX((Results!H94)/('Result Targets'!H24),0)*100 -> 52.266667 | I94: =MAX((Results!I94)/('Result Targets'!I24),0)*100 -> 52.266667 | J94: =MAX((Results!J94)/('Result Targets'!J24),0)*100 -> 52.266667
A97: MilitaryTechnologyTradeBalancePercOfTargetAchieved | B97: =MAX((Results!B97)/('Result Targets'!B27),0)*100 -> 0 | C97: =MAX((Results!C97)/('Result Targets'!C27),0)*100 -> 0 | D97: =MAX((Results!D97)/('Result Targets'!D27),0)*100 -> 0 | E97: =MAX((Results!E97)/('Result Targets'!E27),0)*100 -> 0 | F97: =MAX((Results!F97)/('Result Targets'!F27),0)*100 -> 0 | G97: =MAX((Results!G97)/('Result Targets'!G27),0)*100 -> 0 | H97: =MAX((Results!H97)/('Result Targets'!H27),0)*100 -> 0 | I97: =MAX((Results!I97)/('Result Targets'!I27),0)*100 -> 0 | J97: =MAX((Results!J97)/('Result Targets'!J27),0)*100 -> 0
A98: DefenseScore | B98: =AVERAGE(MIN(B93,100),MIN(B94,100),MIN(B97,100)) -> 35.726496 | C98: =AVERAGE(MIN(C93,100),MIN(C94,100),MIN(C97,100)) -> 35.726496 | D98: =AVERAGE(MIN(D93,100),MIN(D94,100),MIN(D97,100)) -> 35.37094 | E98: =AVERAGE(MIN(E93,100),MIN(E94,100),MIN(E97,100)) -> 35.37094 | F98: =AVERAGE(MIN(F93,100),MIN(F94,100),MIN(F97,100)) -> 35.37094 | G98: =AVERAGE(MIN(G93,100),MIN(G94,100),MIN(G97,100)) -> 35.37094 | H98: =AVERAGE(MIN(H93,100),MIN(H94,100),MIN(H97,100)) -> 35.37094 | I98: =AVERAGE(MIN(I93,100),MIN(I94,100),MIN(I97,100)) -> 35.37094 | J98: =AVERAGE(MIN(J93,100),MIN(J94,100),MIN(J97,100)) -> 35.37094
A101: Education & Innovation
A102: AILiteracyPercOfTargetAchieved | B102: =MAX((Results!B102)/('Result Targets'!B31),0)*100 -> 41.666667 | C102: =MAX((Results!C102)/('Result Targets'!C31),0)*100 -> 41.666667 | D102: =MAX((Results!D102)/('Result Targets'!D31),0)*100 -> 41.666667 | E102: =MAX((Results!E102)/('Result Targets'!E31),0)*100 -> 41.666667 | F102: =MAX((Results!F102)/('Result Targets'!F31),0)*100 -> 40.333333 | G102: =MAX((Results!G102)/('Result Targets'!G31),0)*100 -> 40.333333 | H102: =MAX((Results!H102)/('Result Targets'!H31),0)*100 -> 40.333333 | I102: =MAX((Results!I102)/('Result Targets'!I31),0)*100 -> 40.333333 | J102: =MAX((Results!J102)/('Result Targets'!J31),0)*100 -> 40.333333
A103: InnovationIndexPercOfTargetAchieved | B103: =MAX((Results!B103)/('Result Targets'!B32),0)*100 -> 50 | C103: =MAX((Results!C103)/('Result Targets'!C32),0)*100 -> 50 | D103: =MAX((Results!D103)/('Result Targets'!D32),0)*100 -> 50 | E103: =MAX((Results!E103)/('Result Targets'!E32),0)*100 -> 49.333333 | F103: =MAX((Results!F103)/('Result Targets'!F32),0)*100 -> 49.333333 | G103: =MAX((Results!G103)/('Result Targets'!G32),0)*100 -> 49.333333 | H103: =MAX((Results!H103)/('Result Targets'!H32),0)*100 -> 50.166667 | I103: =MAX((Results!I103)/('Result Targets'!I32),0)*100 -> 50.166667 | J103: =MAX((Results!J103)/('Result Targets'!J32),0)*100 -> 50.166667
A104: InstitutionalAdoptionRatePercOfTargetAchieved | B104: =MAX((Results!B104)/('Result Targets'!B33),0)*100 -> 30.769231 | C104: =MAX((Results!C104)/('Result Targets'!C33),0)*100 -> 30.769231 | D104: =MAX((Results!D104)/('Result Targets'!D33),0)*100 -> 30.769231 | E104: =MAX((Results!E104)/('Result Targets'!E33),0)*100 -> 30.769231 | F104: =MAX((Results!F104)/('Result Targets'!F33),0)*100 -> 30.769231 | G104: =MAX((Results!G104)/('Result Targets'!G33),0)*100 -> 30.769231 | H104: =MAX((Results!H104)/('Result Targets'!H33),0)*100 -> 30.769231 | I104: =MAX((Results!I104)/('Result Targets'!I33),0)*100 -> 30.769231 | J104: =MAX((Results!J104)/('Result Targets'!J33),0)*100 -> 30.769231
A105: EducationScore | B105: =AVERAGE(MIN(B102,100),MIN(B103,100),MIN(B104,100)) -> 40.811966 | C105: =AVERAGE(MIN(C102,100),MIN(C103,100),MIN(C104,100)) -> 40.811966 | D105: =AVERAGE(MIN(D102,100),MIN(D103,100),MIN(D104,100)) -> 40.811966 | E105: =AVERAGE(MIN(E102,100),MIN(E103,100),MIN(E104,100)) -> 40.589744 | F105: =AVERAGE(MIN(F102,100),MIN(F103,100),MIN(F104,100)) -> 40.145299 | G105: =AVERAGE(MIN(G102,100),MIN(G103,100),MIN(G104,100)) -> 40.145299 | H105: =AVERAGE(MIN(H102,100),MIN(H103,100),MIN(H104,100)) -> 40.423077 | I105: =AVERAGE(MIN(I102,100),MIN(I103,100),MIN(I104,100)) -> 40.423077 | J105: =AVERAGE(MIN(J102,100),MIN(J103,100),MIN(J104,100)) -> 40.423077
A108: Numbers
A109: NumTargetsMet | B109: =EcEnabled*COUNTIF(B73:B77,">=100")+EnvEnabled*COUNTIF(B84:B88,">=100")+DefEnabled*COUNTIF(B93:B97,">=100")+EduEnabled*COUNTIF(B102:B104,">=100") -> 0 | C109: =EcEnabled*COUNTIF(C73:C77,">=100")+EnvEnabled*COUNTIF(C84:C88,">=100")+DefEnabled*COUNTIF(C93:C97,">=100")+EduEnabled*COUNTIF(C102:C104,">=100") -> 0 | D109: =EcEnabled*COUNTIF(D73:D77,">=100")+EnvEnabled*COUNTIF(D84:D88,">=100")+DefEnabled*COUNTIF(D93:D97,">=100")+EduEnabled*COUNTIF(D102:D104,">=100") -> 0 | E109: =EcEnabled*COUNTIF(E73:E77,">=100")+EnvEnabled*COUNTIF(E84:E88,">=100")+DefEnabled*COUNTIF(E93:E97,">=100")+EduEnabled*COUNTIF(E102:E104,">=100") -> 0 | F109: =EcEnabled*COUNTIF(F73:F77,">=100")+EnvEnabled*COUNTIF(F84:F88,">=100")+DefEnabled*COUNTIF(F93:F97,">=100")+EduEnabled*COUNTIF(F102:F104,">=100") -> 0 | G109: =EcEnabled*COUNTIF(G73:G77,">=100")+EnvEnabled*COUNTIF(G84:G88,">=100")+DefEnabled*COUNTIF(G93:G97,">=100")+EduEnabled*COUNTIF(G102:G104,">=100") -> 0 | H109: =EcEnabled*COUNTIF(H73:H77,">=100")+EnvEnabled*COUNTIF(H84:H88,">=100")+DefEnabled*COUNTIF(H93:H97,">=100")+EduEnabled*COUNTIF(H102:H104,">=100") -> 0 | I109: =EcEnabled*COUNTIF(I73:I77,">=100")+EnvEnabled*COUNTIF(I84:I88,">=100")+DefEnabled*COUNTIF(I93:I97,">=100")+EduEnabled*COUNTIF(I102:I104,">=100") -> 0 | J109: =EcEnabled*COUNTIF(J73:J77,">=100")+EnvEnabled*COUNTIF(J84:J88,">=100")+DefEnabled*COUNTIF(J93:J97,">=100")+EduEnabled*COUNTIF(J102:J104,">=100") -> 0
A110: NumTargetsAlmostMet | B110: =EcEnabled*COUNTIF(B73:B77,">=80")+EnvEnabled*COUNTIF(B84:B88,">=80")+DefEnabled*COUNTIF(B93:B97,">=80")+EduEnabled*COUNTIF(B102:B104,">=80")-B109 -> 0 | C110: =EcEnabled*COUNTIF(C73:C77,">=80")+EnvEnabled*COUNTIF(C84:C88,">=80")+DefEnabled*COUNTIF(C93:C97,">=80")+EduEnabled*COUNTIF(C102:C104,">=80")-C109 -> 0 | D110: =EcEnabled*COUNTIF(D73:D77,">=80")+EnvEnabled*COUNTIF(D84:D88,">=80")+DefEnabled*COUNTIF(D93:D97,">=80")+EduEnabled*COUNTIF(D102:D104,">=80")-D109 -> 0 | E110: =EcEnabled*COUNTIF(E73:E77,">=80")+EnvEnabled*COUNTIF(E84:E88,">=80")+DefEnabled*COUNTIF(E93:E97,">=80")+EduEnabled*COUNTIF(E102:E104,">=80")-E109 -> 0 | F110: =EcEnabled*COUNTIF(F73:F77,">=80")+EnvEnabled*COUNTIF(F84:F88,">=80")+DefEnabled*COUNTIF(F93:F97,">=80")+EduEnabled*COUNTIF(F102:F104,">=80")-F109 -> 0 | G110: =EcEnabled*COUNTIF(G73:G77,">=80")+EnvEnabled*COUNTIF(G84:G88,">=80")+DefEnabled*COUNTIF(G93:G97,">=80")+EduEnabled*COUNTIF(G102:G104,">=80")-G109 -> 0 | H110: =EcEnabled*COUNTIF(H73:H77,">=80")+EnvEnabled*COUNTIF(H84:H88,">=80")+DefEnabled*COUNTIF(H93:H97,">=80")+EduEnabled*COUNTIF(H102:H104,">=80")-H109 -> 0 | I110: =EcEnabled*COUNTIF(I73:I77,">=80")+EnvEnabled*COUNTIF(I84:I88,">=80")+DefEnabled*COUNTIF(I93:I97,">=80")+EduEnabled*COUNTIF(I102:I104,">=80")-I109 -> 0 | J110: =EcEnabled*COUNTIF(J73:J77,">=80")+EnvEnabled*COUNTIF(J84:J88,">=80")+DefEnabled*COUNTIF(J93:J97,">=80")+EduEnabled*COUNTIF(J102:J104,">=80")-J109 -> 0
A111: NumTargetsNotMet | B111: =EcEnabled*COUNTIF(B73:B77,"<80")+EnvEnabled*COUNTIF(B84:B88,"<80")+DefEnabled*COUNTIF(B93:B97,"<80")+EduEnabled*COUNTIF(B102:B104,"<80") -> 12 | C111: =EcEnabled*COUNTIF(C73:C77,"<80")+EnvEnabled*COUNTIF(C84:C88,"<80")+DefEnabled*COUNTIF(C93:C97,"<80")+EduEnabled*COUNTIF(C102:C104,"<80") -> 12 | D111: =EcEnabled*COUNTIF(D73:D77,"<80")+EnvEnabled*COUNTIF(D84:D88,"<80")+DefEnabled*COUNTIF(D93:D97,"<80")+EduEnabled*COUNTIF(D102:D104,"<80") -> 12 | E111: =EcEnabled*COUNTIF(E73:E77,"<80")+EnvEnabled*COUNTIF(E84:E88,"<80")+DefEnabled*COUNTIF(E93:E97,"<80")+EduEnabled*COUNTIF(E102:E104,"<80") -> 12 | F111: =EcEnabled*COUNTIF(F73:F77,"<80")+EnvEnabled*COUNTIF(F84:F88,"<80")+DefEnabled*COUNTIF(F93:F97,"<80")+EduEnabled*COUNTIF(F102:F104,"<80") -> 12 | G111: =EcEnabled*COUNTIF(G73:G77,"<80")+EnvEnabled*COUNTIF(G84:G88,"<80")+DefEnabled*COUNTIF(G93:G97,"<80")+EduEnabled*COUNTIF(G102:G104,"<80") -> 12 | H111: =EcEnabled*COUNTIF(H73:H77,"<80")+EnvEnabled*COUNTIF(H84:H88,"<80")+DefEnabled*COUNTIF(H93:H97,"<80")+EduEnabled*COUNTIF(H102:H104,"<80") -> 12 | I111: =EcEnabled*COUNTIF(I73:I77,"<80")+EnvEnabled*COUNTIF(I84:I88,"<80")+DefEnabled*COUNTIF(I93:I97,"<80")+EduEnabled*COUNTIF(I102:I104,"<80") -> 12 | J111: =EcEnabled*COUNTIF(J73:J77,"<80")+EnvEnabled*COUNTIF(J84:J88,"<80")+DefEnabled*COUNTIF(J93:J97,"<80")+EduEnabled*COUNTIF(J102:J104,"<80") -> 12
A112: AverageMinistryScore | B112: =(B78*EcEnabled + B90*EnvEnabled + B98*DefEnabled + B105*EduEnabled) / MAX(EcEnabled+EnvEnabled+DefEnabled+EduEnabled, 1) -> 34.065171 | C112: =(C78*EcEnabled + C90*EnvEnabled + C98*DefEnabled + C105*EduEnabled) / MAX(EcEnabled+EnvEnabled+DefEnabled+EduEnabled, 1) -> 33.576282 | D112: =(D78*EcEnabled + D90*EnvEnabled + D98*DefEnabled + D105*EduEnabled) / MAX(EcEnabled+EnvEnabled+DefEnabled+EduEnabled, 1) -> 33.487393 | E112: =(E78*EcEnabled + E90*EnvEnabled + E98*DefEnabled + E105*EduEnabled) / MAX(EcEnabled+EnvEnabled+DefEnabled+EduEnabled, 1) -> 33.298504 | F112: =(F78*EcEnabled + F90*EnvEnabled + F98*DefEnabled + F105*EduEnabled) / MAX(EcEnabled+EnvEnabled+DefEnabled+EduEnabled, 1) -> 33.187393 | G112: =(G78*EcEnabled + G90*EnvEnabled + G98*DefEnabled + G105*EduEnabled) / MAX(EcEnabled+EnvEnabled+DefEnabled+EduEnabled, 1) -> 32.920726 | H112: =(H78*EcEnabled + H90*EnvEnabled + H98*DefEnabled + H105*EduEnabled) / MAX(EcEnabled+EnvEnabled+DefEnabled+EduEnabled, 1) -> 33.267949 | I112: =(I78*EcEnabled + I90*EnvEnabled + I98*DefEnabled + I105*EduEnabled) / MAX(EcEnabled+EnvEnabled+DefEnabled+EduEnabled, 1) -> 33.267949 | J112: =(J78*EcEnabled + J90*EnvEnabled + J98*DefEnabled + J105*EduEnabled) / MAX(EcEnabled+EnvEnabled+DefEnabled+EduEnabled, 1) -> 33.267949 | L112: copied into TotalScore

Sheet KPI Impacts
B1: Policy Impacts | K1: Slider Impacts | S1: Slider Costs
B2: HighNeg | C2: MediumNeg | D2: LowNeg | E2: None | F2: LowPos | G2: MediumPos | H2: HighPos | K2: HighNeg | L2: MediumNeg | M2: LowNeg | N2: None | O2: LowPos | P2: MediumPos | Q2: HighPos | S2: Value | T2: 0 | U2: 1 | V2: 2 | W2: 3
A63: Governance | K63: 0 | L63: 0 | M63: 0 | N63: 0 | O63: 0 | P63: 0 | Q63: 0 | S63: Cost | T63: 0 | U63: 10000000 | V63: 20000000 | W63: 40000000
A64: GrowthWellBeing | B64: =H64*-0.8 -> -2.4 | C64: =G64*-0.8 -> -1.6 | D64: =F64*-0.8 -> -0.8 | E64: 0 | F64: 1 | G64: 2 | H64: 3 | K64: =(Q64*-1)*0.6 -> -0.36 | L64: =(P64*-1)*0.6 -> -0.27 | M64: =(O64*-1)*0.6 -> -0.18 | N64: 0 | O64: 0.3 | P64: 0.45 | Q64: 0.6
A65: HumanRights | B65: =H65*-0.8 -> -2.4 | C65: =G65*-0.8 -> -1.6 | D65: =F65*-0.8 -> -0.8 | E65: 0 | F65: 1 | G65: 2 | H65: 3 | K65: =(Q65*-1)*0.6 -> -0.54 | L65: =(P65*-1)*0.6 -> -0.36 | M65: =(O65*-1)*0.6 -> -0.18 | N65: 0 | O65: 0.3 | P65: 0.6 | Q65: 0.9
A66: PrivacyDataProtection | B66: =H66*-0.8 -> -4.8 | C66: =G66*-0.8 -> -3.2 | D66: =F66*-0.8 -> -1.6 | E66: 0 | F66: 2 | G66: 4 | H66: 6 | K66: =(Q66*-1)*0.6 -> -1.08 | L66: =(P66*-1)*0.6 -> -0.72 | M66: =(O66*-1)*0.6 -> -0.36 | N66: 0 | O66: 0.6 | P66: 1.2 | Q66: 1.8
A67: Transparency | B67: =H67*-0.8 -> -4.8 | C67: =G67*-0.8 -> -3.2 | D67: =F67*-0.8 -> -1.6 | E67: 0 | F67: 2 | G67: 4 | H67: 6 | K67: =(Q67*-1)*0.6 -> -1.08 | L67: =(P67*-1)*0.6 -> -0.72 | M67: =(O67*-1)*0.6 -> -0.36 | N67: 0 | O67: 0.6 | P67: 1.2 | Q67: 1.8
A68: SecuritySafety | B68: =H68*-0.8 -> -4.8 | C68: =G68*-0.8 -> -3.2 | D68: =F68*-0.8 -> -1.6 | E68: 0 | F68: 2 | G68: 4 | H68: 6 | K68: =(Q68*-1)*0.6 -> -0.72 | L68: =(P68*-1)*0.6 -> -0.54 | M68: =(O68*-1)*0.6 -> -0.36 | N68: 0 | O68: 0.6 | P68: 0.9 | Q68: 1.2
A69: Accountability | B69: =H69*-0.8 -> -4.8 | C69: =G69*-0.8 -> -3.2 | D69: =F69*-0.8 -> -1.6 | E69: 0 | F69: 2 | G69: 4 | H69: 6 | K69: =(Q69*-1)*0.6 -> -0.72 | L69: =(P69*-1)*0.6 -> -0.54 | M69: =(O69*-1)*0.6 -> -0.36 | N69: 0 | O69: 0.6 | P69: 0.9 | Q69: 1.2
A72: Economy
A73: AIContributionToGDP | B73: =H73*-0.8 -> -0.8 | C73: =G73*-0.8 -> -0.6 | D73: =F73*-0.8 -> -0.32 | E73: 0 | F73: 0.4 | G73: 0.75 | H73: 1 | K73: =(Q73*-1)*0.6 -> -0.216 | L73: =(P73*-1)*0.6 -> -0.144 | M73: =(O73*-1)*0.6 -> -0.072 | N73: 0 | O73: 0.12 | P73: 0.24 | Q73: 0.36
A74: AIFDIStock | B74: =H74*-0.8 -> -4800000000 | C74: =G74*-0.8 -> -3200000000 | D74: =F74*-0.8 -> -1600000000 | E74: 0 | F74: 2000000000 | G74: 4000000000 | H74: 6000000000 | K74: =(Q74*-1)*0.6 -> -2160000000 | L74: =(P74*-1)*0.6 -> -1440000000 | M74: =(O74*-1)*0.6 -> -720000000 | N74: 0 | O74: 1200000000 | P74: 2400000000 | Q74: 3600000000
A75: JobsCreated | B75: =H75*-0.8 -> -60000 | C75: =G75*-0.8 -> -40000 | D75: =F75*-0.8 -> -20000 | E75: 0 | F75: 25000 | G75: 50000 | H75: 75000 | K75: =(Q75*-1)*0.6 -> -54000 | L75: =(P75*-1)*0.6 -> -54000 | M75: =(O75*-1)*0.6 -> -18000 | N75: 0 | O75: 30000 | P75: 90000 | Q75: 90000
A76: JobsDisplaced | B76: =H76*-0.8 -> -120000 | C76: =G76*-0.8 -> -80000 | D76: =F76*-0.8 -> -40000 | E76: 0 | F76: 50000 | G76: 100000 | H76: 150000 | K76: =(Q76*-1)*0.6 -> -54000 | L76: =(P76*-1)*0.6 -> -36000 | M76: =(O76*-1)*0.6 -> -18000 | N76: 0 | O76: 30000 | P76: 60000 | Q76: 90000
A77: NetJobsFromAI | B77: X | C77: X | D77: X | E77: X | F77: X | G77: X | H77: X | K77: X | L77: X | M77: X | N77: X | O77: X | P77: X | Q77: X
B78: =H78*-1 -> -5 | C78: =G78*-1 -> -3 | D78: =F78*-1 -> -1 | E78: 0 | F78: 1 | G78: 3 | H78: 5 | K78: =(Q78*-1)*0.6 -> -1.8 | L78: =(P78*-1)*0.6 -> -1.08 | M78: =(O78*-1)*0.6 -> -0.36 | N78: 0 | O78: 0.6 | P78: 1.8 | Q78: 3
A81: Environment
A82: EnergyConsumedFromDataCenters | B82: X | C82: X | D82: X | E82: X | F82: X | G82: X | H82: X | K82: X | L82: X | M82: X | N82: X | O82: X | P82: X | Q82: X
A83: CarbonIntensityFromDataCenters | B83: X | C83: X | D83: X | E83: X | F83: X | G83: X | H83: X | K83: X | L83: X | M83: X | N83: X | O83: X | P83: X | Q83: X
A84: RenewableEnergyFactor | B84: =H84*-0.8 -> -3.2 | C84: =G84*-0.8 -> -1.6 | D84: =F84*-0.8 -> -0.8 | E84: 0 | F84: 1 | G84: 2 | H84: 4 | K84: =(Q84*-1)*0.6 -> -1.44 | L84: =(P84*-1)*0.6 -> -0.72 | M84: =(O84*-1)*0.6 -> -0.36 | N84: 0 | O84: 0.6 | P84: 1.2 | Q84: 2.4
A85: WaterCircularityIndex | B85: =H85*-0.8 -> -4.8 | C85: =G85*-0.8 -> -3.2 | D85: =F85*-0.8 -> -1.6 | E85: 0 | F85: 2 | G85: 4 | H85: 6 | K85: =(Q85*-1)*0.6 -> -0.54 | L85: =(P85*-1)*0.6 -> -0.45 | M85: =(O85*-1)*0.6 -> -0.27 | N85: 0 | O85: 0.45 | P85: 0.75 | Q85: 0.9
A86: EwasteCircularityIndex | B86: =H86*-0.8 -> -4.8 | C86: =G86*-0.8 -> -3.2 | D86: =F86*-0.8 -> -1.6 | E86: 0 | F86: 2 | G86: 4 | H86: 6 | K86: =(Q86*-1)*0.6 -> -0.54 | L86: =(P86*-1)*0.6 -> -0.45 | M86: =(O86*-1)*0.6 -> -0.27 | N86: 0 | O86: 0.45 | P86: 0.75 | Q86: 0.9
A87: CircularityIndex | B87: X | C87: X | D87: X | E87: X | F87: X | G87: X | H87: X | K87: X | L87: X | M87: X | N87: X | O87: X | P87: X | Q87: X
A88: EcosystemIntegrityIndex | B88: =H88*-0.8 -> -3.2 | C88: =G88*-0.8 -> -1.6 | D88: =F88*-0.8 -> -0.8 | E88: 0 | F88: 1 | G88: 2 | H88: 4 | K88: =(Q88*-1)*0.6 -> -0.432 | L88: =(P88*-1)*0.6 -> -0.288 | M88: =(O88*-1)*0.6 -> -0.144 | N88: 0 | O88: 0.24 | P88: 0.48 | Q88: 0.72
B89: =H89*-1 -> -5 | C89: =G89*-1 -> -3 | D89: =F89*-1 -> -1 | E89: 0 | F89: 1 | G89: 3 | H89: 5 | K89: =(Q89*-1)*0.6 -> -1.8 | L89: =(P89*-1)*0.6 -> -1.08 | M89: =(O89*-1)*0.6 -> -0.36 | N89: 0 | O89: 0.6 | P89: 1.8 | Q89: 3
A92: Defense
A93: CybersecurityIndex | B93: =H93*-0.8 -> -2 | C93: =G93*-0.8 -> -1.2 | D93: =F93*-0.8 -> -0.8 | E93: 0 | F93: 1 | G93: 1.5 | H93: 2.5 | K93: =(Q93*-1)*0.6 -> -0.54 | L93: =(P93*-1)*0.6 -> -0.36 | M93: =(O93*-1)*0.6 -> -0.18 | N93: 0 | O93: 0.3 | P93: 0.6 | Q93: 0.9
A94: AutonomousSystemsSafteyIndex | B94: =H94*-0.8 -> -2 | C94: =G94*-0.8 -> -1.2 | D94: =F94*-0.8 -> -0.8 | E94: 0 | F94: 1 | G94: 1.5 | H94: 2.5 | K94: =(Q94*-1)*0.6 -> -0.54 | L94: =(P94*-1)*0.6 -> -0.36 | M94: =(O94*-1)*0.6 -> -0.18 | N94: 0 | O94: 0.3 | P94: 0.6 | Q94: 0.9
A95: DefenseExports | B95: =H95*-0.8 -> -1200000000 | C95: =G95*-0.8 -> -800000000 | D95: =F95*-0.8 -> -320000000 | E95: 0 | F95: 400000000 | G95: 1000000000 | H95: 1500000000 | K95: =(Q95*-1)*0.6 -> -270000000 | L95: =(P95*-1)*0.6 -> -144000000 | M95: =(O95*-1)*0.6 -> -54000000 | N95: 0 | O95: 90000000 | P95: 240000000 | Q95: 450000000
A96: DefenseImports | B96: =H96*-0.8 -> -600000000 | C96: =G96*-0.8 -> -320000000 | D96: =F96*-0.8 -> -120000000 | E96: 0 | F96: 150000000 | G96: 400000000 | H96: 750000000 | K96: =(Q96*-1)*0.6 -> -270000000 | L96: =(P96*-1)*0.6 -> -144000000 | M96: =(O96*-1)*0.6 -> -54000000 | N96: 0 | O96: 90000000 | P96: 240000000 | Q96: 450000000
A97: MilitaryTechnologyTradeBalance | B97: X | C97: X | D97: X | E97: X | F97: X | G97: X | H97: X | K97: X | L97: X | M97: X | N97: X | O97: X | P97: X | Q97: X
B98: =H98*-1 -> -5 | C98: =G98*-1 -> -3 | D98: =F98*-1 -> -1 | E98: 0 | F98: 1 | G98: 3 | H98: 5 | K98: =(Q98*-1)*0.6 -> -1.8 | L98: =(P98*-1)*0.6 -> -1.08 | M98: =(O98*-1)*0.6 -> -0.36 | N98: 0 | O98: 0.6 | P98: 1.8 | Q98: 3
A101: Education & Innovation
A102: AILiteracy | B102: =H102*-0.8 -> -3.2 | C102: =G102*-0.8 -> -1.6 | D102: =F102*-0.8 -> -0.8 | E102: 0 | F102: 1 | G102: 2 | H102: 4 | K102: =(Q102*-1)*0.6 -> -1.08 | L102: =(P102*-1)*0.6 -> -0.72 | M102: =(O102*-1)*0.6 -> -0.36 | N102: 0 | O102: 0.6 | P102: 1.2 | Q102: 1.8
A103: InnovationIndex | B103: =H103*-0.8 -> -1.2 | C103: =G103*-0.8 -> -0.8 | D103: =F103*-0.8 -> -0.4 | E103: 0 | F103: 0.5 | G103: 1 | H103: 1.5 | K103: =(Q103*-1)*0.6 -> -0.54 | L103: =(P103*-1)*0.6 -> -0.36 | M103: =(O103*-1)*0.6 -> -0.18 | N103: 0 | O103: 0.3 | P103: 0.6 | Q103: 0.9
A104: InstitutionalAdoptionRate | B104: =H104*-0.8 -> -4.8 | C104: =G104*-0.8 -> -3.2 | D104: =F104*-0.8 -> -1.6 | E104: 0 | F104: 2 | G104: 4 | H104: 6 | K104: =(Q104*-1)*0.6 -> -1.44 | L104: =(P104*-1)*0.6 -> -0.72 | M104: =(O104*-1)*0.6 -> -0.36 | N104: 0 | O104: 0.6 | P104: 1.2 | Q104: 2.4

Sheet Startups
B1: 0 | C1: 1 | D1: 2 | E1: 3 | F1: 4 | G1: 5 | H1: 6 | J1: Cumilative Startup Impact
J2: Level | K2: Impact
A3: Cumilative Startup
A4: CumulativeStartupSpend | B4: ='Economy Ministry'!AQ6*EcEnabled+'Environment Ministry'!AQ6*EnvEnabled+'Defence Ministry'!AQ6*DefEnabled+'Education Ministry'!AQ6*EduEnabled -> 0 | C4: =B4+'Economy Ministry'!AR6*EcEnabled+'Environment Ministry'!AR6*EnvEnabled+'Defence Ministry'!AR6*DefEnabled+'Education Ministry'!AR6*EduEnabled -> 0 | D4: =C4+'Economy Ministry'!AS6*EcEnabled+'Environment Ministry'!AS6*EnvEnabled+'Defence Ministry'!AS6*DefEnabled+'Education Ministry'!AS6*EduEnabled -> 0 | E4: =D4+'Economy Ministry'!AT6*EcEnabled+'Environment Ministry'!AT6*EnvEnabled+'Defence Ministry'!AT6*DefEnabled+'Education Ministry'!AT6*EduEnabled -> 0 | F4: =E4+'Economy Ministry'!AU6*EcEnabled+'Environment Ministry'!AU6*EnvEnabled+'Defence Ministry'!AU6*DefEnabled+'Education Ministry'!AU6*EduEnabled -> 0 | G4: =F4+'Economy Ministry'!AV6*EcEnabled+'Environment Ministry'!AV6*EnvEnabled+'Defence Ministry'!AV6*DefEnabled+'Education Ministry'!AV6*EduEnabled -> 0 | H4: =G4+'Economy Ministry'!AW6*EcEnabled+'Environment Ministry'!AW6*EnvEnabled+'Defence Ministry'!AW6*DefEnabled+'Education Ministry'!AW6*EduEnabled -> 0
A5: CumulativeStartupImpact | B5: =IF(B4>=100000000*(EcEnabled+EnvEnabled+DefEnabled+EduEnabled), 1, 0) -> 0 | C5: =IF(C4>=100000000*(EcEnabled+EnvEnabled+DefEnabled+EduEnabled), 1, 0) -> 0 | D5: =IF(D4>=100000000*(EcEnabled+EnvEnabled+DefEnabled+EduEnabled), 1, 0) -> 0 | E5: =IF(E4>=100000000*(EcEnabled+EnvEnabled+DefEnabled+EduEnabled), 1, 0) -> 0 | F5: =IF(F4>=100000000*(EcEnabled+EnvEnabled+DefEnabled+EduEnabled), 1, 0) -> 0 | G5: =IF(G4>=100000000*(EcEnabled+EnvEnabled+DefEnabled+EduEnabled), 1, 0) -> 0 | H5: =IF(H4>=100000000*(EcEnabled+EnvEnabled+DefEnabled+EduEnabled), 1, 0) -> 0
A6: CumulativeStartupImpactYear | B6: =B5 -> 0 | C6: =IF(AND(C5=1, B5=0), 1, 0) -> 0 | D6: =IF(AND(D5=1, C5=0), 1, 0) -> 0 | E6: =IF(AND(E5=1, D5=0), 1, 0) -> 0 | F6: =IF(AND(F5=1, E5=0), 1, 0) -> 0 | G6: =IF(AND(G5=1, F5=0), 1, 0) -> 0 | H6: =IF(AND(H5=1, G5=0), 1, 0) -> 0
A63: Governance
A64: GrowthWellBeing | B64: =B$5*K64 -> 0 | C64: =C$5*K64 -> 0 | D64: =D$5*K64 -> 0 | E64: =E$5*K64 -> 0 | F64: =F$5*K64 -> 0 | G64: =G$5*K64 -> 0 | H64: =H$5*K64 -> 0 | J64: MediumPos | K64: =_xlfn.XLOOKUP(J64,'KPI Impacts'!$B$2:$H$2,'KPI Impacts'!$B64:$H64) -> 2
A65: HumanRights | B65: =B$5*K65 -> 0 | C65: =C$5*K65 -> 0 | D65: =D$5*K65 -> 0 | E65: =E$5*K65 -> 0 | F65: =F$5*K65 -> 0 | G65: =G$5*K65 -> 0 | H65: =H$5*K65 -> 0 | J65: None | K65: =_xlfn.XLOOKUP(J65,'KPI Impacts'!$B$2:$H$2,'KPI Impacts'!$B65:$H65) -> 0
A66: PrivacyDataProtection | B66: =B$5*K66 -> 0 | C66: =C$5*K66 -> 0 | D66: =D$5*K66 -> 0 | E66: =E$5*K66 -> 0 | F66: =F$5*K66 -> 0 | G66: =G$5*K66 -> 0 | H66: =H$5*K66 -> 0 | J66: MediumNeg | K66: =_xlfn.XLOOKUP(J66,'KPI Impacts'!$B$2:$H$2,'KPI Impacts'!$B66:$H66) -> -3.2
A67: Transparency | B67: =B$5*K67 -> 0 | C67: =C$5*K67 -> 0 | D67: =D$5*K67 -> 0 | E67: =E$5*K67 -> 0 | F67: =F$5*K67 -> 0 | G67: =G$5*K67 -> 0 | H67: =H$5*K67 -> 0 | J67: None | K67: =_xlfn.XLOOKUP(J67,'KPI Impacts'!$B$2:$H$2,'KPI Impacts'!$B67:$H67) -> 0
A68: SecuritySafety | B68: =B$5*K68 -> 0 | C68: =C$5*K68 -> 0 | D68: =D$5*K68 -> 0 | E68: =E$5*K68 -> 0 | F68: =F$5*K68 -> 0 | G68: =G$5*K68 -> 0 | H68: =H$5*K68 -> 0 | J68: None | K68: =_xlfn.XLOOKUP(J68,'KPI Impacts'!$B$2:$H$2,'KPI Impacts'!$B68:$H68) -> 0
A69: Accountability | B69: =B$5*K69 -> 0 | C69: =C$5*K69 -> 0 | D69: =D$5*K69 -> 0 | E69: =E$5*K69 -> 0 | F69: =F$5*K69 -> 0 | G69: =G$5*K69 -> 0 | H69: =H$5*K69 -> 0 | J69: None | K69: =_xlfn.XLOOKUP(J69,'KPI Impacts'!$B$2:$H$2,'KPI Impacts'!$B69:$H69) -> 0
A72: Economy
A73: AIContributionToGDP | B73: =B$5*K73 -> 0 | C73: =C$5*K73 -> 0 | D73: =D$5*K73 -> 0 | E73: =E$5*K73 -> 0 | F73: =F$5*K73 -> 0 | G73: =G$5*K73 -> 0 | H73: =H$5*K73 -> 0 | J73: MediumPos | K73: =_xlfn.XLOOKUP(J73,'KPI Impacts'!$B$2:$H$2,'KPI Impacts'!$B73:$H73) -> 0.75
A74: AIFDIStock | B74: =B$5*K74 -> 0 | C74: =C$5*K74 -> 0 | D74: =D$5*K74 -> 0 | E74: =E$5*K74 -> 0 | F74: =F$5*K74 -> 0 | G74: =G$5*K74 -> 0 | H74: =H$5*K74 -> 0 | J74: MediumPos | K74: =_xlfn.XLOOKUP(J74,'KPI Impacts'!$B$2:$H$2,'KPI Impacts'!$B74:$H74) -> 4000000000
A75: JobsCreated | B75: =B$5*K75 -> 0 | C75: =C$5*K75 -> 0 | D75: =D$5*K75 -> 0 | E75: =E$5*K75 -> 0 | F75: =F$5*K75 -> 0 | G75: =G$5*K75 -> 0 | H75: =H$5*K75 -> 0 | J75: None | K75: =_xlfn.XLOOKUP(J75,'KPI Impacts'!$B$2:$H$2,'KPI Impacts'!$B75:$H75) -> 0
A76: JobsDisplaced | B76: =B$5*K76 -> 0 | C76: =C$5*K76 -> 0 | D76: =D$5*K76 -> 0 | E76: =E$5*K76 -> 0 | F76: =F$5*K76 -> 0 | G76: =G$5*K76 -> 0 | H76: =H$5*K76 -> 0 | J76: None | K76: =_xlfn.XLOOKUP(J76,'KPI Impacts'!$B$2:$H$2,'KPI Impacts'!$B76:$H76) -> 0
A77: NetJobsFromAI
A81: Environment
A82: EnergyConsumedFromDataCenters
A83: CarbonIntensityFromDataCenters
A84: RenewableEnergyFactor | B84: =B$5*K84 -> 0 | C84: =C$5*K84 -> 0 | D84: =D$5*K84 -> 0 | E84: =E$5*K84 -> 0 | F84: =F$5*K84 -> 0 | G84: =G$5*K84 -> 0 | H84: =H$5*K84 -> 0 | J84: LowPos | K84: =_xlfn.XLOOKUP(J84,'KPI Impacts'!$B$2:$H$2,'KPI Impacts'!$B84:$H84) -> 1
A85: WaterCircularityIndex | B85: =B$5*K85 -> 0 | C85: =C$5*K85 -> 0 | D85: =D$5*K85 -> 0 | E85: =E$5*K85 -> 0 | F85: =F$5*K85 -> 0 | G85: =G$5*K85 -> 0 | H85: =H$5*K85 -> 0 | J85: None | K85: =_xlfn.XLOOKUP(J85,'KPI Impacts'!$B$2:$H$2,'KPI Impacts'!$B85:$H85) -> 0
A86: EwasteCircularityIndex | B86: =B$5*K86 -> 0 | C86: =C$5*K86 -> 0 | D86: =D$5*K86 -> 0 | E86: =E$5*K86 -> 0 | F86: =F$5*K86 -> 0 | G86: =G$5*K86 -> 0 | H86: =H$5*K86 -> 0 | J86: MediumPos | K86: =_xlfn.XLOOKUP(J86,'KPI Impacts'!$B$2:$H$2,'KPI Impacts'!$B86:$H86) -> 4
A87: CircularityIndex
A88: EcosystemIntegrityIndex | B88: =B$5*K88 -> 0 | C88: =C$5*K88 -> 0 | D88: =D$5*K88 -> 0 | E88: =E$5*K88 -> 0 | F88: =F$5*K88 -> 0 | G88: =G$5*K88 -> 0 | H88: =H$5*K88 -> 0 | J88: LowPos | K88: =_xlfn.XLOOKUP(J88,'KPI Impacts'!$B$2:$H$2,'KPI Impacts'!$B88:$H88) -> 1
A92: Defense
A93: CybersecurityIndex | B93: =B$5*K93 -> 0 | C93: =C$5*K93 -> 0 | D93: =D$5*K93 -> 0 | E93: =E$5*K93 -> 0 | F93: =F$5*K93 -> 0 | G93: =G$5*K93 -> 0 | H93: =H$5*K93 -> 0 | J93: LowPos | K93: =_xlfn.XLOOKUP(J93,'KPI Impacts'!$B$2:$H$2,'KPI Impacts'!$B93:$H93) -> 1
A94: AutonomousSystemsSafteyIndex | B94: =B$5*K94 -> 0 | C94: =C$5*K94 -> 0 | D94: =D$5*K94 -> 0 | E94: =E$5*K94 -> 0 | F94: =F$5*K94 -> 0 | G94: =G$5*K94 -> 0 | H94: =H$5*K94 -> 0 | J94: None | K94: =_xlfn.XLOOKUP(J94,'KPI Impacts'!$B$2:$H$2,'KPI Impacts'!$B94:$H94) -> 0
A95: DefenseExports | B95: =B$5*K95 -> 0 | C95: =C$5*K95 -> 0 | D95: =D$5*K95 -> 0 | E95: =E$5*K95 -> 0 | F95: =F$5*K95 -> 0 | G95: =G$5*K95 -> 0 | H95: =H$5*K95 -> 0 | J95: MediumPos | K95: =_xlfn.XLOOKUP(J95,'KPI Impacts'!$B$2:$H$2,'KPI Impacts'!$B95:$H95) -> 1000000000
A96: DefenseImports | B96: =B$5*K96 -> 0 | C96: =C$5*K96 -> 0 | D96: =D$5*K96 -> 0 | E96: =E$5*K96 -> 0 | F96: =F$5*K96 -> 0 | G96: =G$5*K96 -> 0 | H96: =H$5*K96 -> 0 | J96: None | K96: =_xlfn.XLOOKUP(J96,'KPI Impacts'!$B$2:$H$2,'KPI Impacts'!$B96:$H96) -> 0
A97: MilitaryTechnologyTradeBalance
A101: Education & Innovation
A102: AILiteracy | B102: =B$5*K102 -> 0 | C102: =C$5*K102 -> 0 | D102: =D$5*K102 -> 0 | E102: =E$5*K102 -> 0 | F102: =F$5*K102 -> 0 | G102: =G$5*K102 -> 0 | H102: =H$5*K102 -> 0 | J102: LowPos | K102: =_xlfn.XLOOKUP(J102,'KPI Impacts'!$B$2:$H$2,'KPI Impacts'!$B102:$H102) -> 1
A103: InnovationIndex | B103: =B$5*K103 -> 0 | C103: =C$5*K103 -> 0 | D103: =D$5*K103 -> 0 | E103: =E$5*K103 -> 0 | F103: =F$5*K103 -> 0 | G103: =G$5*K103 -> 0 | H103: =H$5*K103 -> 0 | J103: MediumPos | K103: =_xlfn.XLOOKUP(J103,'KPI Impacts'!$B$2:$H$2,'KPI Impacts'!$B103:$H103) -> 1
A104: InstitutionalAdoptionRate | B104: =B$5*K104 -> 0 | C104: =C$5*K104 -> 0 | D104: =D$5*K104 -> 0 | E104: =E$5*K104 -> 0 | F104: =F$5*K104 -> 0 | G104: =G$5*K104 -> 0 | H104: =H$5*K104 -> 0 | J104: HighPos | K104: =_xlfn.XLOOKUP(J104,'KPI Impacts'!$B$2:$H$2,'KPI Impacts'!$B104:$H104) -> 6

Sheet Economy Ministry
B1: 0 | C1: 1 | D1: 2 | E1: 3 | F1: 4 | G1: 5 | H1: 6 | I1: 7 | J1: 8 | M1: 0 | N1: 1 | O1: 2 | P1: 3 | Q1: 4 | R1: 5 | S1: 6 | U1: Cumilative RnD Impact | Y1: 0 | Z1: 1 | AA1: 2 | AB1: 3 | AC1: 4 | AD1: 5 | AE1: 6 | AF1: 7 | AG1: 8 | AI1: Low | AK1: Medium | AM1: High | AQ1: 0 | AR1: 1 | AS1: 2 | AT1: 3 | AU1: 4 | AV1: 5 | AW1: 6 | AX1: 7 | AY1: 8 | BA1: Low | BC1: Medium | BE1: High | BI1: 0 | BJ1: 1 | BK1: 2 | BL1: 3 | BM1: 4 | BN1: 5 | BO1: 6 | BP1: 7 | BQ1: 8 | BS1: Year 1 | BU1: Year 2 | BY1: 0 | BZ1: 1 | CA1: 2 | CB1: 3 | CC1: 4 | CD1: 5 | CE1: 6 | CF1: 7 | CG1: 8 | CI1: Year 1 | CK1: Year 2 | CO1: 0 | CP1: 1 | CQ1: 2 | CR1: 3 | CS1: 4 | CT1: 5 | CU1: 6 | CV1: 7 | CW1: 8 | CY1: Year 1 | DA1: Year 2 | DE1: 0 | DF1: 1 | DG1: 2 | DH1: 3 | DI1: 4 | DJ1: 5 | DK1: 6 | DL1: 7 | DM1: 8 | DO1: Year 1 | DQ1: Year 2 | DU1: 0 | DV1: 1 | DW1: 2 | DX1: 3 | DY1: 4 | DZ1: 5 | EA1: 6 | EB1: 7 | EC1: 8 | EE1: Year 1 | EG1: Year 2 | EK1: 0 | EL1: 1 | EM1: 2 | EN1: 3 | EO1: 4 | EP1: 5 | EQ1: 6 | ER1: 7 | ES1: 8 | EU1: Year 1 | EW1: Year 2 | FA1: 0 | FB1: 1 | FC1: 2 | FD1: 3 | FE1: 4 | FF1: 5 | FG1: 6 | FH1: 7 | FI1: 8 | FK1: Year 1 | FM1: Year 2 | FQ1: 0 | FR1: 1 | FS1: 2 | FT1: 3 | FU1: 4 | FV1: 5 | FW1: 6 | FX1: 7 | FY1: 8 | GA1: Year 1 | GC1: Year 2 | GG1: 0 | GH1: 1 | GI1: 2 | GJ1: 3 | GK1: 4 | GL1: 5 | GM1: 6 | GN1: 7 | GO1: 8 | GQ1: Year 1 | GS1: Year 2 | GW1: 0 | GX1: 1 | GY1: 2 | GZ1: 3 | HA1: 4 | HB1: 5 | HC1: 6 | HD1: 7 | HE1: 8 | HG1: Year 1 | HI1: Year 2 | HM1: 0 | HN1: 1 | HO1: 2 | HP1: 3 | HQ1: 4 | HR1: 5 | HS1: 6 | HT1: 7 | HU1: 8 | HW1: Year 1 | HY1: Year 2 | IC1: 0 | ID1: 1 | IE1: 2 | IF1: 3 | IG1: 4 | IH1: 5 | II1: 6 | IJ1: 7 | IK1: 8 | IM1: Year 1 | IO1: Year 2 | IS1: 0 | IT1: 1 | IU1: 2 | IV1: 3 | IW1: 4 | IX1: 5 | IY1: 6 | IZ1: 7 | JA1: 8 | JC1: Year 1 | JE1: Year 2 | JI1: 0 | JJ1: 1 | JK1: 2 | JL1: 3 | JM1: 4 | JN1: 5 | JO1: 6 | JP1: 7 | JQ1: 8 | JS1: Year 1 | JU1: Year 2 | JY1: 0 | JZ1: 1 | KA1: 2 | KB1: 3 | KC1: 4 | KD1: 5 | KE1: 6 | KF1: 7 | KG1: 8 | KI1: Year 1 | KK1: Year 2 | KO1: 0 | KP1: 1 | KQ1: 2 | KR1: 3 | KS1: 4 | KT1: 5 | KU1: 6 | KV1: 7 | KW1: 8 | KY1: Year 1 | LA1: Year 2 | LE1: 0 | LF1: 1 | LG1: 2 | LH1: 3 | LI1: 4 | LJ1: 5 | LK1: 6 | LL1: 7 | LM1: 8 | LO1: Year 1 | LQ1: Year 2 | LU1: 0 | LV1: 1 | LW1: 2 | LX1: 3 | LY1: 4 | LZ1: 5 | MA1: 6 | MB1: 7 | MC1: 8 | ME1: Year 1 | MG1: Year 2 | MK1: 0 | ML1: 1 | MM1: 2 | MN1: 3 | MO1: 4 | MP1: 5 | MQ1: 6 | MR1: 7 | MS1: 8 | MU1: Year 1 | MW1: Year 2 | NA1: 0 | NB1: 1 | NC1: 2 | ND1: 3 | NE1: 4 | NF1: 5 | NG1: 6 | NH1: 7 | NI1: 8 | NK1: Year 1 | NM1: Year 2 | NQ1: 0 | NR1: 1 | NS1: 2 | NT1: 3 | NU1: 4 | NV1: 5 | NW1: 6 | NX1: 7 | NY1: 8 | OA1: Year 1 | OC1: Year 2 | OG1: 0 | OH1: 1 | OI1: 2 | OJ1: 3 | OK1: 4 | OL1: 5 | OM1: 6 | ON1: 7 | OO1: 8 | OQ1: Year 1 | OS1: Year 2
U2: Level | V2: Impact | AI2: Level | AJ2: Impact | AK2: Level | AL2: Impact | AM2: Level | AN2: Impact | BA2: Level | BB2: Impact | BC2: Level | BD2: Impact | BE2: Level | BF2: Impact | BS2: Level | BT2: Impact | BU2: Level | BV2: Impact | CI2: Level | CJ2: Impact | CK2: Level | CL2: Impact | CY2: Level | CZ2: Impact | DA2: Level | DB2: Impact | DO2: Level | DP2: Impact | DQ2: Level | DR2: Impact | EE2: Level | EF2: Impact | EG2: Level | EH2: Impact | EU2: Level | EV2: Impact | EW2: Level | EX2: Impact | FK2: Level | FL2: Impact | FM2: Level | FN2: Impact | GA2: Level | GB2: Impact | GC2: Level | GD2: Impact | GQ2: Level | GR2: Impact | GS2: Level | GT2: Impact | HG2: Level | HH2: Impact | HI2: Level | HJ2: Impact | HW2: Level | HX2: Impact | HY2: Level | HZ2: Impact | IM2: Level | IN2: Impact | IO2: Level | IP2: Impact | JC2: Level | JD2: Impact | JE2: Level | JF2: Impact | JS2: Level | JT2: Impact | JU2: Level | JV2: Impact | KI2: Level | KJ2: Impact | KK2: Level | KL2: Impact | KY2: Level | KZ2: Impact | LA2: Level | LB2: Impact | LO2: Level | LP2: Impact | LQ2: Level | LR2: Impact | ME2: Level | MF2: Impact | MG2: Level | MH2: Impact | MU2: Level | MV2: Impact | MW2: Level | MX2: Impact | NK2: Level | NL2: Impact | NM2: Level | NN2: Impact | OA2: Level | OB2: Impact | OC2: Level | OD2: Impact | OQ2: Level | OR2: Impact | OS2: Level | OT2: Impact
L3: Cumilative RnD | X3: Slider 1 | AP3: Slider 2 | BH3: AI Regulatory Sandbox | BX3: Seal for trustworthy AI | CN3: AI talent visa | DD3: AI provisions in trade agreements | DT3: Robot tax | EJ3: Train ministry staff | EZ3: Standards for AI Interoperability | FP3: Livelihood Protection Policy | GF3: AI Sovereignty Initiative | GV3: Subsidized GPU Access | HL3: Tax Incentives for AI Adoption | IB3: Initiative 12 | IR3: Initiative 13 | JH3: Initiative 14 | JX3: Initiative 15
A4: EcPro | L4: EcCumulativeRnDSpend | M4: =Y6 -> 0 | N4: =M4+Z6 -> 0 | O4: =N4+AA6 -> 0 | P4: =O4+AB6 -> 0 | Q4: =P4+AC6 -> 0 | R4: =Q4+AD6 -> 0 | S4: =R4+AE6 -> 0 | X4: EcSlider1 | Y4: 0 | Z4: 0 | AA4: 0 | AB4: 0 | AC4: 0 | AD4: 0 | AE4: 0 | AF4: 0 | AG4: 0 | AP4: EcSlider2 | AQ4: 0 | AR4: 0 | AS4: 0 | AT4: 0 | AU4: 0 | AV4: 0 | AW4: 0 | AX4: 0 | AY4: 0 | BH4: EcPro3 | BI4: 0 | BJ4: =+BI4 -> 0 | BK4: =+BJ4 -> 0 | BL4: =+BK4 -> 0 | BM4: =+BL4 -> 0 | BN4: =+BM4 -> 0 | BO4: =+BN4 -> 0 | BP4: =+BO4 -> 0 | BQ4: =+BP4 -> 0 | BX4: EcPro4 | BY4: 0 | BZ4: =+BY4 -> 0 | CA4: =+BZ4 -> 0 | CB4: =+CA4 -> 0 | CC4: =+CB4 -> 0 | CD4: =+CC4 -> 0 | CE4: =+CD4 -> 0 | CF4: =+CE4 -> 0 | CG4: =+CF4 -> 0 | CN4: EcPro5 | CO4: 0 | CP4: =+CO4 -> 0 | CQ4: =+CP4 -> 0 | CR4: =+CQ4 -> 0 | CS4: =+CR4 -> 0 | CT4: =+CS4 -> 0 | CU4: =+CT4 -> 0 | CV4: =+CU4 -> 0 | CW4: =+CV4 -> 0 | DD4: EcPro6 | DE4: 0 | DF4: =+DE4 -> 0 | DG4: =+DF4 -> 0 | DH4: =+DG4 -> 0 | DI4: =+DH4 -> 0 | DJ4: =+DI4 -> 0 | DK4: =+DJ4 -> 0 | DL4: =+DK4 -> 0 | DM4: =+DL4 -> 0 | DT4: EcPro7 | DU4: 0 | DV4: =+DU4 -> 0 | DW4: =+DV4 -> 0 | DX4: =+DW4 -> 0 | DY4: =+DX4 -> 0 | DZ4: =+DY4 -> 0 | EA4: =+DZ4 -> 0 | EB4: =+EA4 -> 0 | EC4: =+EB4 -> 0 | EJ4: EcPro8 | EK4: 0 | EL4: =+EK4 -> 0 | EM4: =+EL4 -> 0 | EN4: =+EM4 -> 0 | EO4: =+EN4 -> 0 | EP4: =+EO4 -> 0 | EQ4: =+EP4 -> 0 | ER4: =+EQ4 -> 0 | ES4: =+ER4 -> 0 | EZ4: EcPro9 | FA4: 0 | FB4: =+FA4 -> 0 | FC4: =+FB4 -> 0 | FD4: =+FC4 -> 0 | FE4: =+FD4 -> 0 | FF4: =+FE4 -> 0 | FG4: =+FF4 -> 0 | FH4: =+FG4 -> 0 | FI4: =+FH4 -> 0 | FP4: EcPro10 | FQ4: 0 | FR4: =+FQ4 -> 0 | FS4: =+FR4 -> 0 | FT4: =+FS4 -> 0 | FU4: =+FT4 -> 0 | FV4: =+FU4 -> 0 | FW4: =+FV4 -> 0 | FX4: =+FW4 -> 0 | FY4: =+FX4 -> 0 | GF4: EcPro11 | GG4: 0 | GH4: =+GG4 -> 0 | GI4: =+GH4 -> 0 | GJ4: =+GI4 -> 0 | GK4: =+GJ4 -> 0 | GL4: =+GK4 -> 0 | GM4: =+GL4 -> 0 | GN4: =+GM4 -> 0 | GO4: =+GN4 -> 0 | GV4: EcPro12 | GW4: 0 | GX4: =+GW4 -> 0 | GY4: =+GX4 -> 0 | GZ4: =+GY4 -> 0 | HA4: =+GZ4 -> 0 | HB4: =+HA4 -> 0 | HC4: =+HB4 -> 0 | HD4: =+HC4 -> 0 | HE4: =+HD4 -> 0 | HL4: EcPro13 | HM4: 0 | HN4: =+HM4 -> 0 | HO4: =+HN4 -> 0 | HP4: =+HO4 -> 0 | HQ4: =+HP4 -> 0 | HR4: =+HQ4 -> 0 | HS4: =+HR4 -> 0 | HT4: =+HS4 -> 0 | HU4: =+HT4 -> 0 | IB4: EcPro14 | IC4: 0 | ID4: =+IC4 -> 0 | IE4: =+ID4 -> 0 | IF4: =+IE4 -> 0 | IG4: =+IF4 -> 0 | IH4: =+IG4 -> 0 | II4: =+IH4 -> 0 | IJ4: =+II4 -> 0 | IK4: =+IJ4 -> 0 | IR4: EcPro15 | IS4: 0 | IT4: =+IS4 -> 0 | IU4: =+IT4 -> 0 | IV4: =+IU4 -> 0 | IW4: =+IV4 -> 0 | IX4: =+IW4 -> 0 | IY4: =+IX4 -> 0 | IZ4: =+IY4 -> 0 | JA4: =+IZ4 -> 0 | JH4: EcPro16 | JI4: 0 | JJ4: =+JI4 -> 0 | JK4: =+JJ4 -> 0 | JL4: =+JK4 -> 0 | JM4: =+JL4 -> 0 | JN4: =+JM4 -> 0 | JO4: =+JN4 -> 0 | JP4: =+JO4 -> 0 | JQ4: =+JP4 -> 0 | JX4: EcPro17 | JY4: 0 | JZ4: =+JY4 -> 0 | KA4: =+JZ4 -> 0 | KB4: =+KA4 -> 0 | KC4: =+KB4 -> 0 | KD4: =+KC4 -> 0 | KE4: =+KD4 -> 0 | KF4: =+KE4 -> 0 | KG4: =+KF4 -> 0 | KN4: EcPro18 | KO4: 0 | KP4: =+KO4 -> 0 | KQ4: =+KP4 -> 0 | KR4: =+KQ4 -> 0 | KS4: =+KR4 -> 0 | KT4: =+KS4 -> 0 | KU4: =+KT4 -> 0 | KV4: =+KU4 -> 0 | KW4: =+KV4 -> 0 | LD4: EcPro19 | LE4: 0 | LF4: =+LE4 -> 0 | LG4: =+LF4 -> 0 | LH4: =+LG4 -> 0 | LI4: =+LH4 -> 0 | LJ4: =+LI4 -> 0 | LK4: =+LJ4 -> 0 | LL4: =+LK4 -> 0 | LM4: =+LL4 -> 0 | LT4: EcPro20 | LU4: 0 | LV4: =+LU4 -> 0 | LW4: =+LV4 -> 0 | LX4: =+LW4 -> 0 | LY4: =+LX4 -> 0 | LZ4: =+LY4 -> 0 | MA4: =+LZ4 -> 0 | MB4: =+MA4 -> 0 | MC4: =+MB4 -> 0 | MJ4: EcPro21 | MK4: 0 | ML4: =+MK4 -> 0 | MM4: =+ML4 -> 0 | MN4: =+MM4 -> 0 | MO4: =+MN4 -> 0 | MP4: =+MO4 -> 0 | MQ4: =+MP4 -> 0 | MR4: =+MQ4 -> 0 | MS4: =+MR4 -> 0 | MZ4: EcPro22 | NA4: 0 | NB4: =+NA4 -> 0 | NC4: =+NB4 -> 0 | ND4: =+NC4 -> 0 | NE4: =+ND4 -> 0 | NF4: =+NE4 -> 0 | NG4: =+NF4 -> 0 | NH4: =+NG4 -> 0 | NI4: =+NH4 -> 0 | NP4: EcPro23 | NQ4: 0 | NR4: =+NQ4 -> 0 | NS4: =+NR4 -> 0 | NT4: =+NS4 -> 0 | NU4: =+NT4 -> 0 | NV4: =+NU4 -> 0 | NW4: =+NV4 -> 0 | NX4: =+NW4 -> 0 | NY4: =+NX4 -> 0 | OF4: EcPro24 | OG4: 0 | OH4: =+OG4 -> 0 | OI4: =+OH4 -> 0 | OJ4: =+OI4 -> 0 | OK4: =+OJ4 -> 0 | OL4: =+OK4 -> 0 | OM4: =+OL4 -> 0 | ON4: =+OM4 -> 0 | OO4: =+ON4 -> 0
A5: EcProDone | L5: EcCumulativeRnDImpact | M5: =IF(M4>=100000000, 1, 0) -> 0 | N5: =IF(N4>=100000000, 1, 0) -> 0 | O5: =IF(O4>=100000000, 1, 0) -> 0 | P5: =IF(P4>=100000000, 1, 0) -> 0 | Q5: =IF(Q4>=100000000, 1, 0) -> 0 | R5: =IF(R4>=100000000, 1, 0) -> 0 | S5: =IF(S4>=100000000, 1, 0) -> 0 | X5: EcSlider1LastYear | Y5: 0 | Z5: =Y4 -> 0 | AA5: =Z4 -> 0 | AB5: =AA4 -> 0 | AC5: =AB4 -> 0 | AD5: =AC4 -> 0 | AE5: =AD4 -> 0 | AF5: =AE4 -> 0 | AG5: =AF4 -> 0 | AP5: EcSlider2LastYear | AQ5: 0 | AR5: =AQ4 -> 0 | AS5: =AR4 -> 0 | AT5: =AS4 -> 0 | AU5: =AT4 -> 0 | AV5: =AU4 -> 0 | AW5: =AV4 -> 0 | AX5: =AW4 -> 0 | AY5: =AX4 -> 0 | BH5: EcPro3Done | BI5: =BI4 -> 0 | BJ5: =IF(BI5=1,1,BJ4) -> 0 | BK5: =IF(BJ5=1,1,BK4) -> 0 | BL5: =IF(BK5=1,1,BL4) -> 0 | BM5: =IF(BL5=1,1,BM4) -> 0 | BN5: =IF(BM5=1,1,BN4) -> 0 | BO5: =IF(BN5=1,1,BO4) -> 0 | BP5: =IF(BO5=1,1,BP4) -> 0 | BQ5: =IF(BP5=1,1,BQ4) -> 0 | BX5: EcPro4Done | BY5: =BY4 -> 0 | BZ5: =IF(BY5=1,1,BZ4) -> 0 | CA5: =IF(BZ5=1,1,CA4) -> 0 | CB5: =IF(CA5=1,1,CB4) -> 0 | CC5: =IF(CB5=1,1,CC4) -> 0 | CD5: =IF(CC5=1,1,CD4) -> 0 | CE5: =IF(CD5=1,1,CE4) -> 0 | CF5: =IF(CE5=1,1,CF4) -> 0 | CG5: =IF(CF5=1,1,CG4) -> 0 | CN5: EcPro5Done | CO5: =CO4 -> 0 | CP5: =IF(CO5=1,1,CP4) -> 0 | CQ5: =IF(CP5=1,1,CQ4) -> 0 | CR5: =IF(CQ5=1,1,CR4) -> 0 | CS5: =IF(CR5=1,1,CS4) -> 0 | CT5: =IF(CS5=1,1,CT4) -> 0 | CU5: =IF(CT5=1,1,CU4) -> 0 | CV5: =IF(CU5=1,1,CV4) -> 0 | CW5: =IF(CV5=1,1,CW4) -> 0 | DD5: EcPro6Done | DE5: =DE4 -> 0 | DF5: =IF(DE5=1,1,DF4) -> 0 | DG5: =IF(DF5=1,1,DG4) -> 0 | DH5: =IF(DG5=1,1,DH4) -> 0 | DI5: =IF(DH5=1,1,DI4) -> 0 | DJ5: =IF(DI5=1,1,DJ4) -> 0 | DK5: =IF(DJ5=1,1,DK4) -> 0 | DL5: =IF(DK5=1,1,DL4) -> 0 | DM5: =IF(DL5=1,1,DM4) -> 0 | DT5: EcPro7Done | DU5: =DU4 -> 0 | DV5: =IF(DU5=1,1,DV4) -> 0 | DW5: =IF(DV5=1,1,DW4) -> 0 | DX5: =IF(DW5=1,1,DX4) -> 0 | DY5: =IF(DX5=1,1,DY4) -> 0 | DZ5: =IF(DY5=1,1,DZ4) -> 0 | EA5: =IF(DZ5=1,1,EA4) -> 0 | EB5: =IF(EA5=1,1,EB4) -> 0 | EC5: =IF(EB5=1,1,EC4) -> 0 | EJ5: EcPro8Done | EK5: =EK4 -> 0 | EL5: =IF(EK5=1,1,EL4) -> 0 | EM5: =IF(EL5=1,1,EM4) -> 0 | EN5: =IF(EM5=1,1,EN4) -> 0 | EO5: =IF(EN5=1,1,EO4) -> 0 | EP5: =IF(EO5=1,1,EP4) -> 0 | EQ5: =IF(EP5=1,1,EQ4) -> 0 | ER5: =IF(EQ5=1,1,ER4) -> 0 | ES5: =IF(ER5=1,1,ES4) -> 0 | EZ5: EcPro9Done | FA5: =FA4 -> 0 | FB5: =IF(FA5=1,1,FB4) -> 0 | FC5: =IF(FB5=1,1,FC4) -> 0 | FD5: =IF(FC5=1,1,FD4) -> 0 | FE5: =IF(FD5=1,1,FE4) -> 0 | FF5: =IF(FE5=1,1,FF4) -> 0 | FG5: =IF(FF5=1,1,FG4) -> 0 | FH5: =IF(FG5=1,1,FH4) -> 0 | FI5: =IF(FH5=1,1,FI4) -> 0 | FP5: EcPro10Done | FQ5: =FQ4 -> 0 | FR5: =IF(FQ5=1,1,FR4) -> 0 | FS5: =IF(FR5=1,1,FS4) -> 0 | FT5: =IF(FS5=1,1,FT4) -> 0 | FU5: =IF(FT5=1,1,FU4) -> 0 | FV5: =IF(FU5=1,1,FV4) -> 0 | FW5: =IF(FV5=1,1,FW4) -> 0 | FX5: =IF(FW5=1,1,FX4) -> 0 | FY5: =IF(FX5=1,1,FY4) -> 0 | GF5: EcPro11Done | GG5: =GG4 -> 0 | GH5: =IF(GG5=1,1,GH4) -> 0 | GI5: =IF(GH5=1,1,GI4) -> 0 | GJ5: =IF(GI5=1,1,GJ4) -> 0 | GK5: =IF(GJ5=1,1,GK4) -> 0 | GL5: =IF(GK5=1,1,GL4) -> 0 | GM5: =IF(GL5=1,1,GM4) -> 0 | GN5: =IF(GM5=1,1,GN4) -> 0 | GO5: =IF(GN5=1,1,GO4) -> 0 | GV5: EcPro12Done | GW5: =GW4 -> 0 | GX5: =IF(GW5=1,1,GX4) -> 0 | GY5: =IF(GX5=1,1,GY4) -> 0 | GZ5: =IF(GY5=1,1,GZ4) -> 0 | HA5: =IF(GZ5=1,1,HA4) -> 0 | HB5: =IF(HA5=1,1,HB4) -> 0 | HC5: =IF(HB5=1,1,HC4) -> 0 | HD5: =IF(HC5=1,1,HD4) -> 0 | HE5: =IF(HD5=1,1,HE4) -> 0 | HL5: EcPro13Done | HM5: =HM4 -> 0 | HN5: =IF(HM5=1,1,HN4) -> 0 | HO5: =IF(HN5=1,1,HO4) -> 0 | HP5: =IF(HO5=1,1,HP4) -> 0 | HQ5: =IF(HP5=1,1,HQ4) -> 0 | HR5: =IF(HQ5=1,1,HR4) -> 0 | HS5: =IF(HR5=1,1,HS4) -> 0 | HT5: =IF(HS5=1,1,HT4) -> 0 | HU5: =IF(HT5=1,1,HU4) -> 0 | IB5: EcPro14Done | IC5: =IC4 -> 0 | ID5: =IF(IC5=1,1,ID4) -> 0 | IE5: =IF(ID5=1,1,IE4) -> 0 | IF5: =IF(IE5=1,1,IF4) -> 0 | IG5: =IF(IF5=1,1,IG4) -> 0 | IH5: =IF(IG5=1,1,IH4) -> 0 | II5: =IF(IH5=1,1,II4) -> 0 | IJ5: =IF(II5=1,1,IJ4) -> 0 | IK5: =IF(IJ5=1,1,IK4) -> 0 | IR5: EcPro15Done | IS5: =IS4 -> 0 | IT5: =IF(IS5=1,1,IT4) -> 0 | IU5: =IF(IT5=1,1,IU4) -> 0 | IV5: =IF(IU5=1,1,IV4) -> 0 | IW5: =IF(IV5=1,1,IW4) -> 0 | IX5: =IF(IW5=1,1,IX4) -> 0 | IY5: =IF(IX5=1,1,IY4) -> 0 | IZ5: =IF(IY5=1,1,IZ4) -> 0 | JA5: =IF(IZ5=1,1,JA4) -> 0 | JH5: EcPro16Done | JI5: =JI4 -> 0 | JJ5: =IF(JI5=1,1,JJ4) -> 0 | JK5: =IF(JJ5=1,1,JK4) -> 0 | JL5: =IF(JK5=1,1,JL4) -> 0 | JM5: =IF(JL5=1,1,JM4) -> 0 | JN5: =IF(JM5=1,1,JN4) -> 0 | JO5: =IF(JN5=1,1,JO4) -> 0 | JP5: =IF(JO5=1,1,JP4) -> 0 | JQ5: =IF(JP5=1,1,JQ4) -> 0 | JX5: EcPro17Done | JY5: =JY4 -> 0 | JZ5: =IF(JY5=1,1,JZ4) -> 0 | KA5: =IF(JZ5=1,1,KA4) -> 0 | KB5: =IF(KA5=1,1,KB4) -> 0 | KC5: =IF(KB5=1,1,KC4) -> 0 | KD5: =IF(KC5=1,1,KD4) -> 0 | KE5: =IF(KD5=1,1,KE4) -> 0 | KF5: =IF(KE5=1,1,KF4) -> 0 | KG5: =IF(KF5=1,1,KG4) -> 0 | KN5: EcPro18Done | KO5: =KO4 -> 0 | KP5: =IF(KO5=1,1,KP4) -> 0 | KQ5: =IF(KP5=1,1,KQ4) -> 0 | KR5: =IF(KQ5=1,1,KR4) -> 0 | KS5: =IF(KR5=1,1,KS4) -> 0 | KT5: =IF(KS5=1,1,KT4) -> 0 | KU5: =IF(KT5=1,1,KU4) -> 0 | KV5: =IF(KU5=1,1,KV4) -> 0 | KW5: =IF(KV5=1,1,KW4) -> 0 | LD5: EcPro19Done | LE5: =LE4 -> 0 | LF5: =IF(LE5=1,1,LF4) -> 0 | LG5: =IF(LF5=1,1,LG4) -> 0 | LH5: =IF(LG5=1,1,LH4) -> 0 | LI5: =IF(LH5=1,1,LI4) -> 0 | LJ5: =IF(LI5=1,1,LJ4) -> 0 | LK5: =IF(LJ5=1,1,LK4) -> 0 | LL5: =IF(LK5=1,1,LL4) -> 0 | LM5: =IF(LL5=1,1,LM4) -> 0 | LT5: EcPro20Done | LU5: =LU4 -> 0 | LV5: =IF(LU5=1,1,LV4) -> 0 | LW5: =IF(LV5=1,1,LW4) -> 0 | LX5: =IF(LW5=1,1,LX4) -> 0 | LY5: =IF(LX5=1,1,LY4) -> 0 | LZ5: =IF(LY5=1,1,LZ4) -> 0 | MA5: =IF(LZ5=1,1,MA4) -> 0 | MB5: =IF(MA5=1,1,MB4) -> 0 | MC5: =IF(MB5=1,1,MC4) -> 0 | MJ5: EcPro21Done | MK5: =MK4 -> 0 | ML5: =IF(MK5=1,1,ML4) -> 0 | MM5: =IF(ML5=1,1,MM4) -> 0 | MN5: =IF(MM5=1,1,MN4) -> 0 | MO5: =IF(MN5=1,1,MO4) -> 0 | MP5: =IF(MO5=1,1,MP4) -> 0 | MQ5: =IF(MP5=1,1,MQ4) -> 0 | MR5: =IF(MQ5=1,1,MR4) -> 0 | MS5: =IF(MR5=1,1,MS4) -> 0 | MZ5: EcPro22Done | NA5: =NA4 -> 0 | NB5: =IF(NA5=1,1,NB4) -> 0 | NC5: =IF(NB5=1,1,NC4) -> 0 | ND5: =IF(NC5=1,1,ND4) -> 0 | NE5: =IF(ND5=1,1,NE4) -> 0 | NF5: =IF(NE5=1,1,NF4) -> 0 | NG5: =IF(NF5=1,1,NG4) -> 0 | NH5: =IF(NG5=1,1,NH4) -> 0 | NI5: =IF(NH5=1,1,NI4) -> 0 | NP5: EcPro23Done | NQ5: =NQ4 -> 0 | NR5: =IF(NQ5=1,1,NR4) -> 0 | NS5: =IF(NR5=1,1,NS4) -> 0 | NT5: =IF(NS5=1,1,NT4) -> 0 | NU5: =IF(NT5=1,1,NU4) -> 0 | NV5: =IF(NU5=1,1,NV4) -> 0 | NW5: =IF(NV5=1,1,NW4) -> 0 | NX5: =IF(NW5=1,1,NX4) -> 0 | NY5: =IF(NX5=1,1,NY4) -> 0 | OF5: EcPro24Done | OG5: =OG4 -> 0 | OH5: =IF(OG5=1,1,OH4) -> 0 | OI5: =IF(OH5=1,1,OI4) -> 0 | OJ5: =IF(OI5=1,1,OJ4) -> 0 | OK5: =IF(OJ5=1,1,OK4) -> 0 | OL5: =IF(OK5=1,1,OL4) -> 0 | OM5: =IF(OL5=1,1,OM4) -> 0 | ON5: =IF(OM5=1,1,ON4) -> 0 | OO5: =IF(ON5=1,1,OO4) -> 0
A6: EcProShow | L6: EcCumulativeRnDImpactYear | M6: =M5 -> 0 | N6: =IF(AND(N5=1, M5=0), 1, 0) -> 0 | O6: =IF(AND(O5=1, N5=0), 1, 0) -> 0 | P6: =IF(AND(P5=1, O5=0), 1, 0) -> 0 | Q6: =IF(AND(Q5=1, P5=0), 1, 0) -> 0 | R6: =IF(AND(R5=1, Q5=0), 1, 0) -> 0 | S6: =IF(AND(S5=1, R5=0), 1, 0) -> 0 | X6: EcSlider1Cost | Y6: =_xlfn.XLOOKUP(Y4,'KPI Impacts'!$T$2:$W$2,'KPI Impacts'!$T$63:$W$63) -> 0 | Z6: =_xlfn.XLOOKUP(Z4,'KPI Impacts'!$T$2:$W$2,'KPI Impacts'!$T$63:$W$63) -> 0 | AA6: =_xlfn.XLOOKUP(AA4,'KPI Impacts'!$T$2:$W$2,'KPI Impacts'!$T$63:$W$63) -> 0 | AB6: =_xlfn.XLOOKUP(AB4,'KPI Impacts'!$T$2:$W$2,'KPI Impacts'!$T$63:$W$63) -> 0 | AC6: =_xlfn.XLOOKUP(AC4,'KPI Impacts'!$T$2:$W$2,'KPI Impacts'!$T$63:$W$63) -> 0 | AD6: =_xlfn.XLOOKUP(AD4,'KPI Impacts'!$T$2:$W$2,'KPI Impacts'!$T$63:$W$63) -> 0 | AE6: =_xlfn.XLOOKUP(AE4,'KPI Impacts'!$T$2:$W$2,'KPI Impacts'!$T$63:$W$63) -> 0 | AF6: =_xlfn.XLOOKUP(AF4,'KPI Impacts'!$T$2:$W$2,'KPI Impacts'!$T$63:$W$63) -> 0 | AG6: =_xlfn.XLOOKUP(AG4,'KPI Impacts'!$T$2:$W$2,'KPI Impacts'!$T$63:$W$63) -> 0 | AP6: EcSlider2Cost | AQ6: =_xlfn.XLOOKUP(AQ4,'KPI Impacts'!$T$2:$W$2,'KPI Impacts'!$T$63:$W$63) -> 0 | AR6: =_xlfn.XLOOKUP(AR4,'KPI Impacts'!$T$2:$W$2,'KPI Impacts'!$T$63:$W$63) -> 0 | AS6: =_xlfn.XLOOKUP(AS4,'KPI Impacts'!$T$2:$W$2,'KPI Impacts'!$T$63:$W$63) -> 0 | AT6: =_xlfn.XLOOKUP(AT4,'KPI Impacts'!$T$2:$W$2,'KPI Impacts'!$T$63:$W$63) -> 0 | AU6: =_xlfn.XLOOKUP(AU4,'KPI Impacts'!$T$2:$W$2,'KPI Impacts'!$T$63:$W$63) -> 0 | AV6: =_xlfn.XLOOKUP(AV4,'KPI Impacts'!$T$2:$W$2,'KPI Impacts'!$T$63:$W$63) -> 0 | AW6: =_xlfn.XLOOKUP(AW4,'KPI Impacts'!$T$2:$W$2,'KPI Impacts'!$T$63:$W$63) -> 0 | AX6: =_xlfn.XLOOKUP(AX4,'KPI Impacts'!$T$2:$W$2,'KPI Impacts'!$T$63:$W$63) -> 0 | AY6: =_xlfn.XLOOKUP(AY4,'KPI Impacts'!$T$2:$W$2,'KPI Impacts'!$T$63:$W$63) -> 0 | BH6: EcPro3Show | BI6: 0 | BJ6: =IF(AND(BI4=1,BI5=1),1,IF(AND(BI4=0,BI5=1),3,0)) -> 0 | BK6: =IF(AND(BJ4=1,BJ5=1),1,IF(AND(BJ4=0,BJ5=1),3,0)) -> 0 | BL6: =IF(AND(BK4=1,BK5=1),1,IF(AND(BK4=0,BK5=1),3,0)) -> 0 | BM6: =IF(AND(BL4=1,BL5=1),1,IF(AND(BL4=0,BL5=1),3,0)) -> 0 | BN6: =IF(AND(BM4=1,BM5=1),1,IF(AND(BM4=0,BM5=1),3,0)) -> 0 | BO6: =IF(AND(BN4=1,BN5=1),1,IF(AND(BN4=0,BN5=1),3,0)) -> 0 | BP6: =IF(AND(BO4=1,BO5=1),1,IF(AND(BO4=0,BO5=1),3,0)) -> 0 | BQ6: =IF(AND(BP4=1,BP5=1),1,IF(AND(BP4=0,BP5=1),3,0)) -> 0 | BX6: EcPro4Show | BY6: 0 | BZ6: =IF(AND(BY4=1,BY5=1),1,IF(AND(BY4=0,BY5=1),3,0)) -> 0 | CA6: =IF(AND(BZ4=1,BZ5=1),1,IF(AND(BZ4=0,BZ5=1),3,0)) -> 0 | CB6: =IF(AND(CA4=1,CA5=1),1,IF(AND(CA4=0,CA5=1),3,0)) -> 0 | CC6: =IF(AND(CB4=1,CB5=1),1,IF(AND(CB4=0,CB5=1),3,0)) -> 0 | CD6: =IF(AND(CC4=1,CC5=1),1,IF(AND(CC4=0,CC5=1),3,0)) -> 0 | CE6: =IF(AND(CD4=1,CD5=1),1,IF(AND(CD4=0,CD5=1),3,0)) -> 0 | CF6: =IF(AND(CE4=1,CE5=1),1,IF(AND(CE4=0,CE5=1),3,0)) -> 0 | CG6: =IF(AND(CF4=1,CF5=1),1,IF(AND(CF4=0,CF5=1),3,0)) -> 0 | CN6: EcPro5Show | CO6: 0 | CP6: =IF(AND(CO4=1,CO5=1),1,IF(AND(CO4=0,CO5=1),3,0)) -> 0 | CQ6: =IF(AND(CP4=1,CP5=1),1,IF(AND(CP4=0,CP5=1),3,0)) -> 0 | CR6: =IF(AND(CQ4=1,CQ5=1),1,IF(AND(CQ4=0,CQ5=1),3,0)) -> 0 | CS6: =IF(AND(CR4=1,CR5=1),1,IF(AND(CR4=0,CR5=1),3,0)) -> 0 | CT6: =IF(AND(CS4=1,CS5=1),1,IF(AND(CS4=0,CS5=1),3,0)) -> 0 | CU6: =IF(AND(CT4=1,CT5=1),1,IF(AND(CT4=0,CT5=1),3,0)) -> 0 | CV6: =IF(AND(CU4=1,CU5=1),1,IF(AND(CU4=0,CU5=1),3,0)) -> 0 | CW6: =IF(AND(CV4=1,CV5=1),1,IF(AND(CV4=0,CV5=1),3,0)) -> 0 | DD6: EcPro6Show | DE6: 0 | DF6: =IF(AND(DE4=1,DE5=1),1,IF(AND(DE4=0,DE5=1),3,0)) -> 0 | DG6: =IF(AND(DF4=1,DF5=1),1,IF(AND(DF4=0,DF5=1),3,0)) -> 0 | DH6: =IF(AND(DG4=1,DG5=1),1,IF(AND(DG4=0,DG5=1),3,0)) -> 0 | DI6: =IF(AND(DH4=1,DH5=1),1,IF(AND(DH4=0,DH5=1),3,0)) -> 0 | DJ6: =IF(AND(DI4=1,DI5=1),1,IF(AND(DI4=0,DI5=1),3,0)) -> 0 | DK6: =IF(AND(DJ4=1,DJ5=1),1,IF(AND(DJ4=0,DJ5=1),3,0)) -> 0 | DL6: =IF(AND(DK4=1,DK5=1),1,IF(AND(DK4=0,DK5=1),3,0)) -> 0 | DM6: =IF(AND(DL4=1,DL5=1),1,IF(AND(DL4=0,DL5=1),3,0)) -> 0 | DT6: EcPro7Show | DU6: 2 | DV6: 2 | DW6: =IF(AND(DV4=1,DV5=1),1,IF(AND(DV4=0,DV5=1),3,0)) -> 0 | DX6: =IF(AND(DW4=1,DW5=1),1,IF(AND(DW4=0,DW5=1),3,0)) -> 0 | DY6: =IF(AND(DX4=1,DX5=1),1,IF(AND(DX4=0,DX5=1),3,0)) -> 0 | DZ6: =IF(AND(DY4=1,DY5=1),1,IF(AND(DY4=0,DY5=1),3,0)) -> 0 | EA6: =IF(AND(DZ4=1,DZ5=1),1,IF(AND(DZ4=0,DZ5=1),3,0)) -> 0 | EB6: =IF(AND(EA4=1,EA5=1),1,IF(AND(EA4=0,EA5=1),3,0)) -> 0 | EC6: =IF(AND(EB4=1,EB5=1),1,IF(AND(EB4=0,EB5=1),3,0)) -> 0 | EJ6: EcPro8Show | EK6: 2 | EL6: 2 | EM6: =IF(AND(EL4=1,EL5=1),1,IF(AND(EL4=0,EL5=1),3,0)) -> 0 | EN6: =IF(AND(EM4=1,EM5=1),1,IF(AND(EM4=0,EM5=1),3,0)) -> 0 | EO6: =IF(AND(EN4=1,EN5=1),1,IF(AND(EN4=0,EN5=1),3,0)) -> 0 | EP6: =IF(AND(EO4=1,EO5=1),1,IF(AND(EO4=0,EO5=1),3,0)) -> 0 | EQ6: =IF(AND(EP4=1,EP5=1),1,IF(AND(EP4=0,EP5=1),3,0)) -> 0 | ER6: =IF(AND(EQ4=1,EQ5=1),1,IF(AND(EQ4=0,EQ5=1),3,0)) -> 0 | ES6: =IF(AND(ER4=1,ER5=1),1,IF(AND(ER4=0,ER5=1),3,0)) -> 0 | EZ6: EcPro9Show | FA6: 2 | FB6: 2 | FC6: 2 | FD6: =IF(AND(FC4=1,FC5=1),1,IF(AND(FC4=0,FC5=1),3,0)) -> 0 | FE6: =IF(AND(FD4=1,FD5=1),1,IF(AND(FD4=0,FD5=1),3,0)) -> 0 | FF6: =IF(AND(FE4=1,FE5=1),1,IF(AND(FE4=0,FE5=1),3,0)) -> 0 | FG6: =IF(AND(FF4=1,FF5=1),1,IF(AND(FF4=0,FF5=1),3,0)) -> 0 | FH6: =IF(AND(FG4=1,FG5=1),1,IF(AND(FG4=0,FG5=1),3,0)) -> 0 | FI6: =IF(AND(FH4=1,FH5=1),1,IF(AND(FH4=0,FH5=1),3,0)) -> 0 | FP6: EcPro10Show | FQ6: 2 | FR6: 2 | FS6: 2 | FT6: =IF(AND(FS4=1,FS5=1),1,IF(AND(FS4=0,FS5=1),3,0)) -> 0 | FU6: =IF(AND(FT4=1,FT5=1),1,IF(AND(FT4=0,FT5=1),3,0)) -> 0 | FV6: =IF(AND(FU4=1,FU5=1),1,IF(AND(FU4=0,FU5=1),3,0)) -> 0 | FW6: =IF(AND(FV4=1,FV5=1),1,IF(AND(FV4=0,FV5=1),3,0)) -> 0 | FX6: =IF(AND(FW4=1,FW5=1),1,IF(AND(FW4=0,FW5=1),3,0)) -> 0 | FY6: =IF(AND(FX4=1,FX5=1),1,IF(AND(FX4=0,FX5=1),3,0)) -> 0 | GF6: EcPro11Show | GG6: 2 | GH6: 2 | GI6: 2 | GJ6: 2 | GK6: =IF(AND(GJ4=1,GJ5=1),1,IF(AND(GJ4=0,GJ5=1),3,0)) -> 0 | GL6: =IF(AND(GK4=1,GK5=1),1,IF(AND(GK4=0,GK5=1),3,0)) -> 0 | GM6: =IF(AND(GL4=1,GL5=1),1,IF(AND(GL4=0,GL5=1),3,0)) -> 0 | GN6: =IF(AND(GM4=1,GM5=1),1,IF(AND(GM4=0,GM5=1),3,0)) -> 0 | GO6: =IF(AND(GN4=1,GN5=1),1,IF(AND(GN4=0,GN5=1),3,0)) -> 0 | GV6: EcPro12Show | GW6: 2 | GX6: 2 | GY6: 2 | GZ6: 2 | HA6: =IF(AND(GZ4=1,GZ5=1),1,IF(AND(GZ4=0,GZ5=1),3,0)) -> 0 | HB6: =IF(AND(HA4=1,HA5=1),1,IF(AND(HA4=0,HA5=1),3,0)) -> 0 | HC6: =IF(AND(HB4=1,HB5=1),1,IF(AND(HB4=0,HB5=1),3,0)) -> 0 | HD6: =IF(AND(HC4=1,HC5=1),1,IF(AND(HC4=0,HC5=1),3,0)) -> 0 | HE6: =IF(AND(HD4=1,HD5=1),1,IF(AND(HD4=0,HD5=1),3,0)) -> 0 | HL6: EcPro13Show | HM6: 2 | HN6: 2 | HO6: 2 | HP6: 2 | HQ6: 2 | HR6: =IF(AND(HQ4=1,HQ5=1),1,IF(AND(HQ4=0,HQ5=1),3,0)) -> 0 | HS6: =IF(AND(HR4=1,HR5=1),1,IF(AND(HR4=0,HR5=1),3,0)) -> 0 | HT6: =IF(AND(HS4=1,HS5=1),1,IF(AND(HS4=0,HS5=1),3,0)) -> 0 | HU6: =IF(AND(HT4=1,HT5=1),1,IF(AND(HT4=0,HT5=1),3,0)) -> 0 | IB6: EcPro14Show | IC6: 2 | ID6: 2 | IE6: 2 | IF6: =IF(AND(IE4=1,IE5=1),1,IF(AND(IE4=0,IE5=1),3,0)) -> 0 | IG6: =IF(AND(IF4=1,IF5=1),1,IF(AND(IF4=0,IF5=1),3,0)) -> 0 | IH6: =IF(AND(IG4=1,IG5=1),1,IF(AND(IG4=0,IG5=1),3,0)) -> 0 | II6: =IF(AND(IH4=1,IH5=1),1,IF(AND(IH4=0,IH5=1),3,0)) -> 0 | IJ6: =IF(AND(II4=1,II5=1),1,IF(AND(II4=0,II5=1),3,0)) -> 0 | IK6: =IF(AND(IJ4=1,IJ5=1),1,IF(AND(IJ4=0,IJ5=1),3,0)) -> 0 | IR6: EcPro15Show | IS6: 2 | IT6: 2 | IU6: 2 | IV6: =IF(AND(IU4=1,IU5=1),1,IF(AND(IU4=0,IU5=1),3,0)) -> 0 | IW6: =IF(AND(IV4=1,IV5=1),1,IF(AND(IV4=0,IV5=1),3,0)) -> 0 | IX6: =IF(AND(IW4=1,IW5=1),1,IF(AND(IW4=0,IW5=1),3,0)) -> 0 | IY6: =IF(AND(IX4=1,IX5=1),1,IF(AND(IX4=0,IX5=1),3,0)) -> 0 | IZ6: =IF(AND(IY4=1,IY5=1),1,IF(AND(IY4=0,IY5=1),3,0)) -> 0 | JA6: =IF(AND(IZ4=1,IZ5=1),1,IF(AND(IZ4=0,IZ5=1),3,0)) -> 0 | JH6: EcPro16Show | JI6: 2 | JJ6: 2 | JK6: 2 | JL6: 2 | JM6: =IF(AND(JL4=1,JL5=1),1,IF(AND(JL4=0,JL5=1),3,0)) -> 0 | JN6: =IF(AND(JM4=1,JM5=1),1,IF(AND(JM4=0,JM5=1),3,0)) -> 0 | JO6: =IF(AND(JN4=1,JN5=1),1,IF(AND(JN4=0,JN5=1),3,0)) -> 0 | JP6: =IF(AND(JO4=1,JO5=1),1,IF(AND(JO4=0,JO5=1),3,0)) -> 0 | JQ6: =IF(AND(JP4=1,JP5=1),1,IF(AND(JP4=0,JP5=1),3,0)) -> 0 | JX6: EcPro17Show | JY6: 2 | JZ6: 2 | KA6: 2 | KB6: 2 | KC6: =IF(AND(KB4=1,KB5=1),1,IF(AND(KB4=0,KB5=1),3,0)) -> 0 | KD6: =IF(AND(KC4=1,KC5=1),1,IF(AND(KC4=0,KC5=1),3,0)) -> 0 | KE6: =IF(AND(KD4=1,KD5=1),1,IF(AND(KD4=0,KD5=1),3,0)) -> 0 | KF6: =IF(AND(KE4=1,KE5=1),1,IF(AND(KE4=0,KE5=1),3,0)) -> 0 | KG6: =IF(AND(KF4=1,KF5=1),1,IF(AND(KF4=0,KF5=1),3,0)) -> 0 | KN6: EcPro18Show | KO6: 0 | KP6: =IF(AND(KO4=1,KO5=1),1,IF(AND(KO4=0,KO5=1),3,0)) -> 0 | KQ6: =IF(AND(KP4=1,KP5=1),1,IF(AND(KP4=0,KP5=1),3,0)) -> 0 | KR6: =IF(AND(KQ4=1,KQ5=1),1,IF(AND(KQ4=0,KQ5=1),3,0)) -> 0 | KS6: =IF(AND(KR4=1,KR5=1),1,IF(AND(KR4=0,KR5=1),3,0)) -> 0 | KT6: =IF(AND(KS4=1,KS5=1),1,IF(AND(KS4=0,KS5=1),3,0)) -> 0 | KU6: =IF(AND(KT4=1,KT5=1),1,IF(AND(KT4=0,KT5=1),3,0)) -> 0 | KV6: =IF(AND(KU4=1,KU5=1),1,IF(AND(KU4=0,KU5=1),3,0)) -> 0 | KW6: =IF(AND(KV4=1,KV5=1),1,IF(AND(KV4=0,KV5=1),3,0)) -> 0 | LD6: EcPro19Show | LE6: 0 | LF6: =IF(AND(LE4=1,LE5=1),1,IF(AND(LE4=0,LE5=1),3,0)) -> 0 | LG6: =IF(AND(LF4=1,LF5=1),1,IF(AND(LF4=0,LF5=1),3,0)) -> 0 | LH6: =IF(AND(LG4=1,LG5=1),1,IF(AND(LG4=0,LG5=1),3,0)) -> 0 | LI6: =IF(AND(LH4=1,LH5=1),1,IF(AND(LH4=0,LH5=1),3,0)) -> 0 | LJ6: =IF(AND(LI4=1,LI5=1),1,IF(AND(LI4=0,LI5=1),3,0)) -> 0 | LK6: =IF(AND(LJ4=1,LJ5=1),1,IF(AND(LJ4=0,LJ5=1),3,0)) -> 0 | LL6: =IF(AND(LK4=1,LK5=1),1,IF(AND(LK4=0,LK5=1),3,0)) -> 0 | LM6: =IF(AND(LL4=1,LL5=1),1,IF(AND(LL4=0,LL5=1),3,0)) -> 0 | LT6: EcPro20Show | LU6: 0 | LV6: =IF(AND(LU4=1,LU5=1),1,IF(AND(LU4=0,LU5=1),3,0)) -> 0 | LW6: =IF(AND(LV4=1,LV5=1),1,IF(AND(LV4=0,LV5=1),3,0)) -> 0 | LX6: =IF(AND(LW4=1,LW5=1),1,IF(AND(LW4=0,LW5=1),3,0)) -> 0 | LY6: =IF(AND(LX4=1,LX5=1),1,IF(AND(LX4=0,LX5=1),3,0)) -> 0 | LZ6: =IF(AND(LY4=1,LY5=1),1,IF(AND(LY4=0,LY5=1),3,0)) -> 0 | MA6: =IF(AND(LZ4=1,LZ5=1),1,IF(AND(LZ4=0,LZ5=1),3,0)) -> 0 | MB6: =IF(AND(MA4=1,MA5=1),1,IF(AND(MA4=0,MA5=1),3,0)) -> 0 | MC6: =IF(AND(MB4=1,MB5=1),1,IF(AND(MB4=0,MB5=1),3,0)) -> 0 | MJ6: EcPro21Show | MK6: 0 | ML6: =IF(AND(MK4=1,MK5=1),1,IF(AND(MK4=0,MK5=1),3,0)) -> 0 | MM6: =IF(AND(ML4=1,ML5=1),1,IF(AND(ML4=0,ML5=1),3,0)) -> 0 | MN6: =IF(AND(MM4=1,MM5=1),1,IF(AND(MM4=0,MM5=1),3,0)) -> 0 | MO6: =IF(AND(MN4=1,MN5=1),1,IF(AND(MN4=0,MN5=1),3,0)) -> 0 | MP6: =IF(AND(MO4=1,MO5=1),1,IF(AND(MO4=0,MO5=1),3,0)) -> 0 | MQ6: =IF(AND(MP4=1,MP5=1),1,IF(AND(MP4=0,MP5=1),3,0)) -> 0 | MR6: =IF(AND(MQ4=1,MQ5=1),1,IF(AND(MQ4=0,MQ5=1),3,0)) -> 0 | MS6: =IF(AND(MR4=1,MR5=1),1,IF(AND(MR4=0,MR5=1),3,0)) -> 0 | MZ6: EcPro22Show | NA6: 0 | NB6: =IF(AND(NA4=1,NA5=1),1,IF(AND(NA4=0,NA5=1),3,0)) -> 0 | NC6: =IF(AND(NB4=1,NB5=1),1,IF(AND(NB4=0,NB5=1),3,0)) -> 0 | ND6: =IF(AND(NC4=1,NC5=1),1,IF(AND(NC4=0,NC5=1),3,0)) -> 0 | NE6: =IF(AND(ND4=1,ND5=1),1,IF(AND(ND4=0,ND5=1),3,0)) -> 0 | NF6: =IF(AND(NE4=1,NE5=1),1,IF(AND(NE4=0,NE5=1),3,0)) -> 0 | NG6: =IF(AND(NF4=1,NF5=1),1,IF(AND(NF4=0,NF5=1),3,0)) -> 0 | NH6: =IF(AND(NG4=1,NG5=1),1,IF(AND(NG4=0,NG5=1),3,0)) -> 0 | NI6: =IF(AND(NH4=1,NH5=1),1,IF(AND(NH4=0,NH5=1),3,0)) -> 0 | NP6: EcPro23Show | NQ6: 0 | NR6: =IF(AND(NQ4=1,NQ5=1),1,IF(AND(NQ4=0,NQ5=1),3,0)) -> 0 | NS6: =IF(AND(NR4=1,NR5=1),1,IF(AND(NR4=0,NR5=1),3,0)) -> 0 | NT6: =IF(AND(NS4=1,NS5=1),1,IF(AND(NS4=0,NS5=1),3,0)) -> 0 | NU6: =IF(AND(NT4=1,NT5=1),1,IF(AND(NT4=0,NT5=1),3,0)) -> 0 | NV6: =IF(AND(NU4=1,NU5=1),1,IF(AND(NU4=0,NU5=1),3,0)) -> 0 | NW6: =IF(AND(NV4=1,NV5=1),1,IF(AND(NV4=0,NV5=1),3,0)) -> 0 | NX6: =IF(AND(NW4=1,NW5=1),1,IF(AND(NW4=0,NW5=1),3,0)) -> 0 | NY6: =IF(AND(NX4=1,NX5=1),1,IF(AND(NX4=0,NX5=1),3,0)) -> 0 | OF6: EcPro24Show | OG6: 0 | OH6: =IF(AND(OG4=1,OG5=1),1,IF(AND(OG4=0,OG5=1),3,0)) -> 0 | OI6: =IF(AND(OH4=1,OH5=1),1,IF(AND(OH4=0,OH5=1),3,0)) -> 0 | OJ6: =IF(AND(OI4=1,OI5=1),1,IF(AND(OI4=0,OI5=1),3,0)) -> 0 | OK6: =IF(AND(OJ4=1,OJ5=1),1,IF(AND(OJ4=0,OJ5=1),3,0)) -> 0 | OL6: =IF(AND(OK4=1,OK5=1),1,IF(AND(OK4=0,OK5=1),3,0)) -> 0 | OM6: =IF(AND(OL4=1,OL5=1),1,IF(AND(OL4=0,OL5=1),3,0)) -> 0 | ON6: =IF(AND(OM4=1,OM5=1),1,IF(AND(OM4=0,OM5=1),3,0)) -> 0 | OO6: =IF(AND(ON4=1,ON5=1),1,IF(AND(ON4=0,ON5=1),3,0)) -> 0
A7: EcProNew | BH7: EcPro3New | BI7: 0 | BJ7: =IF(AND(BI6=2,BJ6<>2),1,0) -> 0 | BK7: =IF(AND(BJ6=2,BK6<>2),1,0) -> 0 | BL7: =IF(AND(BK6=2,BL6<>2),1,0) -> 0 | BM7: =IF(AND(BL6=2,BM6<>2),1,0) -> 0 | BN7: =IF(AND(BM6=2,BN6<>2),1,0) -> 0 | BO7: =IF(AND(BN6=2,BO6<>2),1,0) -> 0 | BP7: =IF(AND(BO6=2,BP6<>2),1,0) -> 0 | BQ7: =IF(AND(BP6=2,BQ6<>2),1,0) -> 0 | BX7: EcPro4New | BY7: 0 | BZ7: =IF(AND(BY6=2,BZ6<>2),1,0) -> 0 | CA7: =IF(AND(BZ6=2,CA6<>2),1,0) -> 0 | CB7: =IF(AND(CA6=2,CB6<>2),1,0) -> 0 | CC7: =IF(AND(CB6=2,CC6<>2),1,0) -> 0 | CD7: =IF(AND(CC6=2,CD6<>2),1,0) -> 0 | CE7: =IF(AND(CD6=2,CE6<>2),1,0) -> 0 | CF7: =IF(AND(CE6=2,CF6<>2),1,0) -> 0 | CG7: =IF(AND(CF6=2,CG6<>2),1,0) -> 0 | CN7: EcPro5New | CO7: 0 | CP7: =IF(AND(CO6=2,CP6<>2),1,0) -> 0 | CQ7: =IF(AND(CP6=2,CQ6<>2),1,0) -> 0 | CR7: =IF(AND(CQ6=2,CR6<>2),1,0) -> 0 | CS7: =IF(AND(CR6=2,CS6<>2),1,0) -> 0 | CT7: =IF(AND(CS6=2,CT6<>2),1,0) -> 0 | CU7: =IF(AND(CT6=2,CU6<>2),1,0) -> 0 | CV7: =IF(AND(CU6=2,CV6<>2),1,0) -> 0 | CW7: =IF(AND(CV6=2,CW6<>2),1,0) -> 0 | DD7: EcPro6New | DE7: 0 | DF7: =IF(AND(DE6=2,DF6<>2),1,0) -> 0 | DG7: =IF(AND(DF6=2,DG6<>2),1,0) -> 0 | DH7: =IF(AND(DG6=2,DH6<>2),1,0) -> 0 | DI7: =IF(AND(DH6=2,DI6<>2),1,0) -> 0 | DJ7: =IF(AND(DI6=2,DJ6<>2),1,0) -> 0 | DK7: =IF(AND(DJ6=2,DK6<>2),1,0) -> 0 | DL7: =IF(AND(DK6=2,DL6<>2),1,0) -> 0 | DM7: =IF(AND(DL6=2,DM6<>2),1,0) -> 0 | DT7: EcPro7New | DU7: 0 | DV7: =IF(AND(DU6=2,DV6<>2),1,0) -> 0 | DW7: =IF(AND(DV6=2,DW6<>2),1,0) -> 1 | DX7: =IF(AND(DW6=2,DX6<>2),1,0) -> 0 | DY7: =IF(AND(DX6=2,DY6<>2),1,0) -> 0 | DZ7: =IF(AND(DY6=2,DZ6<>2),1,0) -> 0 | EA7: =IF(AND(DZ6=2,EA6<>2),1,0) -> 0 | EB7: =IF(AND(EA6=2,EB6<>2),1,0) -> 0 | EC7: =IF(AND(EB6=2,EC6<>2),1,0) -> 0 | EJ7: EcPro8New | EK7: 0 | EL7: =IF(AND(EK6=2,EL6<>2),1,0) -> 0 | EM7: =IF(AND(EL6=2,EM6<>2),1,0) -> 1 | EN7: =IF(AND(EM6=2,EN6<>2),1,0) -> 0 | EO7: =IF(AND(EN6=2,EO6<>2),1,0) -> 0 | EP7: =IF(AND(EO6=2,EP6<>2),1,0) -> 0 | EQ7: =IF(AND(EP6=2,EQ6<>2),1,0) -> 0 | ER7: =IF(AND(EQ6=2,ER6<>2),1,0) -> 0 | ES7: =IF(AND(ER6=2,ES6<>2),1,0) -> 0 | EZ7: EcPro9New | FA7: 0 | FB7: =IF(AND(FA6=2,FB6<>2),1,0) -> 0 | FC7: =IF(AND(FB6=2,FC6<>2),1,0) -> 0 | FD7: =IF(AND(FC6=2,FD6<>2),1,0) -> 1 | FE7: =IF(AND(FD6=2,FE6<>2),1,0) -> 0 | FF7: =IF(AND(FE6=2,FF6<>2),1,0) -> 0 | FG7: =IF(AND(FF6=2,FG6<>2),1,0) -> 0 | FH7: =IF(AND(FG6=2,FH6<>2),1,0) -> 0 | FI7: =IF(AND(FH6=2,FI6<>2),1,0) -> 0 | FP7: EcPro10New | FQ7: 0 | FR7: =IF(AND(FQ6=2,FR6<>2),1,0) -> 0 | FS7: =IF(AND(FR6=2,FS6<>2),1,0) -> 0 | FT7: =IF(AND(FS6=2,FT6<>2),1,0) -> 1 | FU7: =IF(AND(FT6=2,FU6<>2),1,0) -> 0 | FV7: =IF(AND(FU6=2,FV6<>2),1,0) -> 0 | FW7: =IF(AND(FV6=2,FW6<>2),1,0) -> 0 | FX7: =IF(AND(FW6=2,FX6<>2),1,0) -> 0 | FY7: =IF(AND(FX6=2,FY6<>2),1,0) -> 0 | GF7: EcPro11New | GG7: 0 | GH7: =IF(AND(GG6=2,GH6<>2),1,0) -> 0 | GI7: =IF(AND(GH6=2,GI6<>2),1,0) -> 0 | GJ7: =IF(AND(GI6=2,GJ6<>2),1,0) -> 0 | GK7: =IF(AND(GJ6=2,GK6<>2),1,0) -> 1 | GL7: =IF(AND(GK6=2,GL6<>2),1,0) -> 0 | GM7: =IF(AND(GL6=2,GM6<>2),1,0) -> 0 | GN7: =IF(AND(GM6=2,GN6<>2),1,0) -> 0 | GO7: =IF(AND(GN6=2,GO6<>2),1,0) -> 0 | GV7: EcPro12New | GW7: 0 | GX7: =IF(AND(GW6=2,GX6<>2),1,0) -> 0 | GY7: =IF(AND(GX6=2,GY6<>2),1,0) -> 0 | GZ7: =IF(AND(GY6=2,GZ6<>2),1,0) -> 0 | HA7: =IF(AND(GZ6=2,HA6<>2),1,0) -> 1 | HB7: =IF(AND(HA6=2,HB6<>2),1,0) -> 0 | HC7: =IF(AND(HB6=2,HC6<>2),1,0) -> 0 | HD7: =IF(AND(HC6=2,HD6<>2),1,0) -> 0 | HE7: =IF(AND(HD6=2,HE6<>2),1,0) -> 0 | HL7: EcPro13New | HM7: 0 | HN7: =IF(AND(HM6=2,HN6<>2),1,0) -> 0 | HO7: =IF(AND(HN6=2,HO6<>2),1,0) -> 0 | HP7: =IF(AND(HO6=2,HP6<>2),1,0) -> 0 | HQ7: =IF(AND(HP6=2,HQ6<>2),1,0) -> 0 | HR7: =IF(AND(HQ6=2,HR6<>2),1,0) -> 1 | HS7: =IF(AND(HR6=2,HS6<>2),1,0) -> 0 | HT7: =IF(AND(HS6=2,HT6<>2),1,0) -> 0 | HU7: =IF(AND(HT6=2,HU6<>2),1,0) -> 0 | IB7: EcPro14New | IC7: 0 | ID7: =IF(AND(IC6=2,ID6<>2),1,0) -> 0 | IE7: =IF(AND(ID6=2,IE6<>2),1,0) -> 0 | IF7: =IF(AND(IE6=2,IF6<>2),1,0) -> 1 | IG7: =IF(AND(IF6=2,IG6<>2),1,0) -> 0 | IH7: =IF(AND(IG6=2,IH6<>2),1,0) -> 0 | II7: =IF(AND(IH6=2,II6<>2),1,0) -> 0 | IJ7: =IF(AND(II6=2,IJ6<>2),1,0) -> 0 | IK7: =IF(AND(IJ6=2,IK6<>2),1,0) -> 0 | IR7: EcPro15New | IS7: 0 | IT7: =IF(AND(IS6=2,IT6<>2),1,0) -> 0 | IU7: =IF(AND(IT6=2,IU6<>2),1,0) -> 0 | IV7: =IF(AND(IU6=2,IV6<>2),1,0) -> 1 | IW7: =IF(AND(IV6=2,IW6<>2),1,0) -> 0 | IX7: =IF(AND(IW6=2,IX6<>2),1,0) -> 0 | IY7: =IF(AND(IX6=2,IY6<>2),1,0) -> 0 | IZ7: =IF(AND(IY6=2,IZ6<>2),1,0) -> 0 | JA7: =IF(AND(IZ6=2,JA6<>2),1,0) -> 0 | JH7: EcPro16New | JI7: 0 | JJ7: =IF(AND(JI6=2,JJ6<>2),1,0) -> 0 | JK7: =IF(AND(JJ6=2,JK6<>2),1,0) -> 0 | JL7: =IF(AND(JK6=2,JL6<>2),1,0) -> 0 | JM7: =IF(AND(JL6=2,JM6<>2),1,0) -> 1 | JN7: =IF(AND(JM6=2,JN6<>2),1,0) -> 0 | JO7: =IF(AND(JN6=2,JO6<>2),1,0) -> 0 | JP7: =IF(AND(JO6=2,JP6<>2),1,0) -> 0 | JQ7: =IF(AND(JP6=2,JQ6<>2),1,0) -> 0 | JX7: EcPro17New | JY7: 0 | JZ7: =IF(AND(JY6=2,JZ6<>2),1,0) -> 0 | KA7: =IF(AND(JZ6=2,KA6<>2),1,0) -> 0 | KB7: =IF(AND(KA6=2,KB6<>2),1,0) -> 0 | KC7: =IF(AND(KB6=2,KC6<>2),1,0) -> 1 | KD7: =IF(AND(KC6=2,KD6<>2),1,0) -> 0 | KE7: =IF(AND(KD6=2,KE6<>2),1,0) -> 0 | KF7: =IF(AND(KE6=2,KF6<>2),1,0) -> 0 | KG7: =IF(AND(KF6=2,KG6<>2),1,0) -> 0 | KN7: EcPro18New | KO7: 0 | KP7: =IF(AND(KO6=2,KP6<>2),1,0) -> 0 | KQ7: =IF(AND(KP6=2,KQ6<>2),1,0) -> 0 | KR7: =IF(AND(KQ6=2,KR6<>2),1,0) -> 0 | KS7: =IF(AND(KR6=2,KS6<>2),1,0) -> 0 | KT7: =IF(AND(KS6=2,KT6<>2),1,0) -> 0 | KU7: =IF(AND(KT6=2,KU6<>2),1,0) -> 0 | KV7: =IF(AND(KU6=2,KV6<>2),1,0) -> 0 | KW7: =IF(AND(KV6=2,KW6<>2),1,0) -> 0 | LD7: EcPro19New | LE7: 0 | LF7: =IF(AND(LE6=2,LF6<>2),1,0) -> 0 | LG7: =IF(AND(LF6=2,LG6<>2),1,0) -> 0 | LH7: =IF(AND(LG6=2,LH6<>2),1,0) -> 0 | LI7: =IF(AND(LH6=2,LI6<>2),1,0) -> 0 | LJ7: =IF(AND(LI6=2,LJ6<>2),1,0) -> 0 | LK7: =IF(AND(LJ6=2,LK6<>2),1,0) -> 0 | LL7: =IF(AND(LK6=2,LL6<>2),1,0) -> 0 | LM7: =IF(AND(LL6=2,LM6<>2),1,0) -> 0 | LT7: EcPro20New | LU7: 0 | LV7: =IF(AND(LU6=2,LV6<>2),1,0) -> 0 | LW7: =IF(AND(LV6=2,LW6<>2),1,0) -> 0 | LX7: =IF(AND(LW6=2,LX6<>2),1,0) -> 0 | LY7: =IF(AND(LX6=2,LY6<>2),1,0) -> 0 | LZ7: =IF(AND(LY6=2,LZ6<>2),1,0) -> 0 | MA7: =IF(AND(LZ6=2,MA6<>2),1,0) -> 0 | MB7: =IF(AND(MA6=2,MB6<>2),1,0) -> 0 | MC7: =IF(AND(MB6=2,MC6<>2),1,0) -> 0 | MJ7: EcPro21New | MK7: 0 | ML7: =IF(AND(MK6=2,ML6<>2),1,0) -> 0 | MM7: =IF(AND(ML6=2,MM6<>2),1,0) -> 0 | MN7: =IF(AND(MM6=2,MN6<>2),1,0) -> 0 | MO7: =IF(AND(MN6=2,MO6<>2),1,0) -> 0 | MP7: =IF(AND(MO6=2,MP6<>2),1,0) -> 0 | MQ7: =IF(AND(MP6=2,MQ6<>2),1,0) -> 0 | MR7: =IF(AND(MQ6=2,MR6<>2),1,0) -> 0 | MS7: =IF(AND(MR6=2,MS6<>2),1,0) -> 0 | MZ7: EcPro22New | NA7: 0 | NB7: =IF(AND(NA6=2,NB6<>2),1,0) -> 0 | NC7: =IF(AND(NB6=2,NC6<>2),1,0) -> 0 | ND7: =IF(AND(NC6=2,ND6<>2),1,0) -> 0 | NE7: =IF(AND(ND6=2,NE6<>2),1,0) -> 0 | NF7: =IF(AND(NE6=2,NF6<>2),1,0) -> 0 | NG7: =IF(AND(NF6=2,NG6<>2),1,0) -> 0 | NH7: =IF(AND(NG6=2,NH6<>2),1,0) -> 0 | NI7: =IF(AND(NH6=2,NI6<>2),1,0) -> 0 | NP7: EcPro23New | NQ7: 0 | NR7: =IF(AND(NQ6=2,NR6<>2),1,0) -> 0 | NS7: =IF(AND(NR6=2,NS6<>2),1,0) -> 0 | NT7: =IF(AND(NS6=2,NT6<>2),1,0) -> 0 | NU7: =IF(AND(NT6=2,NU6<>2),1,0) -> 0 | NV7: =IF(AND(NU6=2,NV6<>2),1,0) -> 0 | NW7: =IF(AND(NV6=2,NW6<>2),1,0) -> 0 | NX7: =IF(AND(NW6=2,NX6<>2),1,0) -> 0 | NY7: =IF(AND(NX6=2,NY6<>2),1,0) -> 0 | OF7: EcPro24New | OG7: 0 | OH7: =IF(AND(OG6=2,OH6<>2),1,0) -> 0 | OI7: =IF(AND(OH6=2,OI6<>2),1,0) -> 0 | OJ7: =IF(AND(OI6=2,OJ6<>2),1,0) -> 0 | OK7: =IF(AND(OJ6=2,OK6<>2),1,0) -> 0 | OL7: =IF(AND(OK6=2,OL6<>2),1,0) -> 0 | OM7: =IF(AND(OL6=2,OM6<>2),1,0) -> 0 | ON7: =IF(AND(OM6=2,ON6<>2),1,0) -> 0 | OO7: =IF(AND(ON6=2,OO6<>2),1,0) -> 0
A8: EcProSort | BH8: EcPro3Sort | BI8: 0 | BJ8: =IF(BJ7=1,Results!C5+1,BI8) -> 0 | BK8: =IF(BK7=1,Results!D5+1,BJ8) -> 0 | BL8: =IF(BL7=1,Results!E5+1,BK8) -> 0 | BM8: =IF(BM7=1,Results!F5+1,BL8) -> 0 | BN8: =IF(BN7=1,Results!G5+1,BM8) -> 0 | BO8: =IF(BO7=1,Results!H5+1,BN8) -> 0 | BP8: =IF(BP7=1,Results!I5+1,BO8) -> 0 | BQ8: =IF(BQ7=1,Results!J5+1,BP8) -> 0 | BX8: EcPro4Sort | BY8: 0 | BZ8: =IF(BZ7=1,Results!C5+1,BY8) -> 0 | CA8: =IF(CA7=1,Results!D5+1,BZ8) -> 0 | CB8: =IF(CB7=1,Results!E5+1,CA8) -> 0 | CC8: =IF(CC7=1,Results!F5+1,CB8) -> 0 | CD8: =IF(CD7=1,Results!G5+1,CC8) -> 0 | CE8: =IF(CE7=1,Results!H5+1,CD8) -> 0 | CF8: =IF(CF7=1,Results!I5+1,CE8) -> 0 | CG8: =IF(CG7=1,Results!J5+1,CF8) -> 0 | CN8: EcPro5Sort | CO8: 0 | CP8: =IF(CP7=1,Results!C5+1,CO8) -> 0 | CQ8: =IF(CQ7=1,Results!D5+1,CP8) -> 0 | CR8: =IF(CR7=1,Results!E5+1,CQ8) -> 0 | CS8: =IF(CS7=1,Results!F5+1,CR8) -> 0 | CT8: =IF(CT7=1,Results!G5+1,CS8) -> 0 | CU8: =IF(CU7=1,Results!H5+1,CT8) -> 0 | CV8: =IF(CV7=1,Results!I5+1,CU8) -> 0 | CW8: =IF(CW7=1,Results!J5+1,CV8) -> 0 | DD8: EcPro6Sort | DE8: 0 | DF8: =IF(DF7=1,Results!C5+1,DE8) -> 0 | DG8: =IF(DG7=1,Results!D5+1,DF8) -> 0 | DH8: =IF(DH7=1,Results!E5+1,DG8) -> 0 | DI8: =IF(DI7=1,Results!F5+1,DH8) -> 0 | DJ8: =IF(DJ7=1,Results!G5+1,DI8) -> 0 | DK8: =IF(DK7=1,Results!H5+1,DJ8) -> 0 | DL8: =IF(DL7=1,Results!I5+1,DK8) -> 0 | DM8: =IF(DM7=1,Results!J5+1,DL8) -> 0 | DT8: EcPro7Sort | DU8: 0 | DV8: =IF(DV7=1,Results!C5+1,DU8) -> 0 | DW8: =IF(DW7=1,Results!D5+1,DV8) -> 3 | DX8: =IF(DX7=1,Results!E5+1,DW8) -> 3 | DY8: =IF(DY7=1,Results!F5+1,DX8) -> 3 | DZ8: =IF(DZ7=1,Results!G5+1,DY8) -> 3 | EA8: =IF(EA7=1,Results!H5+1,DZ8) -> 3 | EB8: =IF(EB7=1,Results!I5+1,EA8) -> 3 | EC8: =IF(EC7=1,Results!J5+1,EB8) -> 3 | EJ8: EcPro8Sort | EK8: 0 | EL8: =IF(EL7=1,Results!C5+1,EK8) -> 0 | EM8: =IF(EM7=1,Results!D5+1,EL8) -> 3 | EN8: =IF(EN7=1,Results!E5+1,EM8) -> 3 | EO8: =IF(EO7=1,Results!F5+1,EN8) -> 3 | EP8: =IF(EP7=1,Results!G5+1,EO8) -> 3 | EQ8: =IF(EQ7=1,Results!H5+1,EP8) -> 3 | ER8: =IF(ER7=1,Results!I5+1,EQ8) -> 3 | ES8: =IF(ES7=1,Results!J5+1,ER8) -> 3 | EZ8: EcPro9Sort | FA8: 0 | FB8: =IF(FB7=1,Results!C5+1,FA8) -> 0 | FC8: =IF(FC7=1,Results!D5+1,FB8) -> 0 | FD8: =IF(FD7=1,Results!E5+1,FC8) -> 4 | FE8: =IF(FE7=1,Results!F5+1,FD8) -> 4 | FF8: =IF(FF7=1,Results!G5+1,FE8) -> 4 | FG8: =IF(FG7=1,Results!H5+1,FF8) -> 4 | FH8: =IF(FH7=1,Results!I5+1,FG8) -> 4 | FI8: =IF(FI7=1,Results!J5+1,FH8) -> 4 | FP8: EcPro10Sort | FQ8: 0 | FR8: =IF(FR7=1,Results!C5+1,FQ8) -> 0 | FS8: =IF(FS7=1,Results!D5+1,FR8) -> 0 | FT8: =IF(FT7=1,Results!E5+1,FS8) -> 4 | FU8: =IF(FU7=1,Results!F5+1,FT8) -> 4 | FV8: =IF(FV7=1,Results!G5+1,FU8) -> 4 | FW8: =IF(FW7=1,Results!H5+1,FV8) -> 4 | FX8: =IF(FX7=1,Results!I5+1,FW8) -> 4 | FY8: =IF(FY7=1,Results!J5+1,FX8) -> 4 | GF8: EcPro11Sort | GG8: 0 | GH8: =IF(GH7=1,Results!C5+1,GG8) -> 0 | GI8: =IF(GI7=1,Results!D5+1,GH8) -> 0 | GJ8: =IF(GJ7=1,Results!E5+1,GI8) -> 0 | GK8: =IF(GK7=1,Results!F5+1,GJ8) -> 5 | GL8: =IF(GL7=1,Results!G5+1,GK8) -> 5 | GM8: =IF(GM7=1,Results!H5+1,GL8) -> 5 | GN8: =IF(GN7=1,Results!I5+1,GM8) -> 5 | GO8: =IF(GO7=1,Results!J5+1,GN8) -> 5 | GV8: EcPro12Sort | GW8: 0 | GX8: =IF(GX7=1,Results!C5+1,GW8) -> 0 | GY8: =IF(GY7=1,Results!D5+1,GX8) -> 0 | GZ8: =IF(GZ7=1,Results!E5+1,GY8) -> 0 | HA8: =IF(HA7=1,Results!F5+1,GZ8) -> 5 | HB8: =IF(HB7=1,Results!G5+1,HA8) -> 5 | HC8: =IF(HC7=1,Results!H5+1,HB8) -> 5 | HD8: =IF(HD7=1,Results!I5+1,HC8) -> 5 | HE8: =IF(HE7=1,Results!J5+1,HD8) -> 5 | HL8: EcPro13Sort | HM8: 0 | HN8: =IF(HN7=1,Results!C5+1,HM8) -> 0 | HO8: =IF(HO7=1,Results!D5+1,HN8) -> 0 | HP8: =IF(HP7=1,Results!E5+1,HO8) -> 0 | HQ8: =IF(HQ7=1,Results!F5+1,HP8) -> 0 | HR8: =IF(HR7=1,Results!G5+1,HQ8) -> 6 | HS8: =IF(HS7=1,Results!H5+1,HR8) -> 6 | HT8: =IF(HT7=1,Results!I5+1,HS8) -> 6 | HU8: =IF(HU7=1,Results!J5+1,HT8) -> 6 | IB8: EcPro14Sort | IC8: 0 | ID8: =IF(ID7=1,Results!C5+1,IC8) -> 0 | IE8: =IF(IE7=1,Results!D5+1,ID8) -> 0 | IF8: =IF(IF7=1,Results!E5+1,IE8) -> 4 | IG8: =IF(IG7=1,Results!F5+1,IF8) -> 4 | IH8: =IF(IH7=1,Results!G5+1,IG8) -> 4 | II8: =IF(II7=1,Results!H5+1,IH8) -> 4 | IJ8: =IF(IJ7=1,Results!I5+1,II8) -> 4 | IK8: =IF(IK7=1,Results!J5+1,IJ8) -> 4 | IR8: EcPro15Sort | IS8: 0 | IT8: =IF(IT7=1,Results!$C5+1,IS8) -> 0 | IU8: =IF(IU7=1,Results!$D5+1,IT8) -> 0 | IV8: =IF(IV7=1,Results!$E5+1,IU8) -> 4 | IW8: =IF(IW7=1,Results!$F5+1,IV8) -> 4 | IX8: =IF(IX7=1,Results!$G5+1,IW8) -> 4 | IY8: =IF(IY7=1,Results!$H5+1,IX8) -> 4 | IZ8: =IF(IZ7=1,Results!$I5+1,IY8) -> 4 | JA8: =IF(JA7=1,Results!$J5+1,IZ8) -> 4 | JH8: EcPro16Sort | JI8: 0 | JJ8: =IF(JJ7=1,Results!$C5+1,JI8) -> 0 | JK8: =IF(JK7=1,Results!$D5+1,JJ8) -> 0 | JL8: =IF(JL7=1,Results!$E5+1,JK8) -> 0 | JM8: =IF(JM7=1,Results!$F5+1,JL8) -> 5 | JN8: =IF(JN7=1,Results!$G5+1,JM8) -> 5 | JO8: =IF(JO7=1,Results!$H5+1,JN8) -> 5 | JP8: =IF(JP7=1,Results!$I5+1,JO8) -> 5 | JQ8: =IF(JQ7=1,Results!$J5+1,JP8) -> 5 | JX8: EcPro17Sort | JY8: 0 | JZ8: =IF(JZ7=1,Results!$C5+1,JY8) -> 0 | KA8: =IF(KA7=1,Results!$D5+1,JZ8) -> 0 | KB8: =IF(KB7=1,Results!$E5+1,KA8) -> 0 | KC8: =IF(KC7=1,Results!$F5+1,KB8) -> 5 | KD8: =IF(KD7=1,Results!$G5+1,KC8) -> 5 | KE8: =IF(KE7=1,Results!$H5+1,KD8) -> 5 | KF8: =IF(KF7=1,Results!$I5+1,KE8) -> 5 | KG8: =IF(KG7=1,Results!$J5+1,KF8) -> 5 | KN8: EcPro18Sort | KO8: 0 | KP8: =IF(KP7=1,Results!C5+1,KO8) -> 0 | KQ8: =IF(KQ7=1,Results!D5+1,KP8) -> 0 | KR8: =IF(KR7=1,Results!E5+1,KQ8) -> 0 | KS8: =IF(KS7=1,Results!F5+1,KR8) -> 0 | KT8: =IF(KT7=1,Results!G5+1,KS8) -> 0 | KU8: =IF(KU7=1,Results!H5+1,KT8) -> 0 | KV8: =IF(KV7=1,Results!I5+1,KU8) -> 0 | KW8: =IF(KW7=1,Results!J5+1,KV8) -> 0 | LD8: EcPro19Sort | LE8: 0 | LF8: =IF(LF7=1,Results!C5+1,LE8) -> 0 | LG8: =IF(LG7=1,Results!D5+1,LF8) -> 0 | LH8: =IF(LH7=1,Results!E5+1,LG8) -> 0 | LI8: =IF(LI7=1,Results!F5+1,LH8) -> 0 | LJ8: =IF(LJ7=1,Results!G5+1,LI8) -> 0 | LK8: =IF(LK7=1,Results!H5+1,LJ8) -> 0 | LL8: =IF(LL7=1,Results!I5+1,LK8) -> 0 | LM8: =IF(LM7=1,Results!J5+1,LL8) -> 0 | LT8: EcPro20Sort | LU8: 0 | LV8: =IF(LV7=1,Results!C5+1,LU8) -> 0 | LW8: =IF(LW7=1,Results!D5+1,LV8) -> 0 | LX8: =IF(LX7=1,Results!E5+1,LW8) -> 0 | LY8: =IF(LY7=1,Results!F5+1,LX8) -> 0 | LZ8: =IF(LZ7=1,Results!G5+1,LY8) -> 0 | MA8: =IF(MA7=1,Results!H5+1,LZ8) -> 0 | MB8: =IF(MB7=1,Results!I5+1,MA8) -> 0 | MC8: =IF(MC7=1,Results!J5+1,MB8) -> 0 | MJ8: EcPro21Sort | MK8: 0 | ML8: =IF(ML7=1,Results!C5+1,MK8) -> 0 | MM8: =IF(MM7=1,Results!D5+1,ML8) -> 0 | MN8: =IF(MN7=1,Results!E5+1,MM8) -> 0 | MO8: =IF(MO7=1,Results!F5+1,MN8) -> 0 | MP8: =IF(MP7=1,Results!G5+1,MO8) -> 0 | MQ8: =IF(MQ7=1,Results!H5+1,MP8) -> 0 | MR8: =IF(MR7=1,Results!I5+1,MQ8) -> 0 | MS8: =IF(MS7=1,Results!J5+1,MR8) -> 0 | MZ8: EcPro22Sort | NA8: 0 | NB8: =IF(NB7=1,Results!C5+1,NA8) -> 0 | NC8: =IF(NC7=1,Results!D5+1,NB8) -> 0 | ND8: =IF(ND7=1,Results!E5+1,NC8) -> 0 | NE8: =IF(NE7=1,Results!F5+1,ND8) -> 0 | NF8: =IF(NF7=1,Results!G5+1,NE8) -> 0 | NG8: =IF(NG7=1,Results!H5+1,NF8) -> 0 | NH8: =IF(NH7=1,Results!I5+1,NG8) -> 0 | NI8: =IF(NI7=1,Results!J5+1,NH8) -> 0 | NP8: EcPro23Sort | NQ8: 0 | NR8: =IF(NR7=1,Results!C5+1,NQ8) -> 0 | NS8: =IF(NS7=1,Results!D5+1,NR8) -> 0 | NT8: =IF(NT7=1,Results!E5+1,NS8) -> 0 | NU8: =IF(NU7=1,Results!F5+1,NT8) -> 0 | NV8: =IF(NV7=1,Results!G5+1,NU8) -> 0 | NW8: =IF(NW7=1,Results!H5+1,NV8) -> 0 | NX8: =IF(NX7=1,Results!I5+1,NW8) -> 0 | NY8: =IF(NY7=1,Results!J5+1,NX8) -> 0 | OF8: EcPro24Sort | OG8: 0 | OH8: =IF(OH7=1,Results!C5+1,OG8) -> 0 | OI8: =IF(OI7=1,Results!D5+1,OH8) -> 0 | OJ8: =IF(OJ7=1,Results!E5+1,OI8) -> 0 | OK8: =IF(OK7=1,Results!F5+1,OJ8) -> 0 | OL8: =IF(OL7=1,Results!G5+1,OK8) -> 0 | OM8: =IF(OM7=1,Results!H5+1,OL8) -> 0 | ON8: =IF(ON7=1,Results!I5+1,OM8) -> 0 | OO8: =IF(OO7=1,Results!J5+1,ON8) -> 0
A9: EcProDecidedlastyr | BH9: EcPro3Decidedlastyr | BI9: 0 | BJ9: =+BI4 -> 0 | BK9: =+BJ4-BI4 -> 0 | BL9: =+BK4-BJ4 -> 0 | BM9: =+BL4-BK4 -> 0 | BN9: =+BM4-BL4 -> 0 | BO9: =+BN4-BM4 -> 0 | BP9: =+BO4-BN4 -> 0 | BQ9: =+BP4-BO4 -> 0 | BX9: EcPro4Decidedlastyr | BY9: 0 | BZ9: =+BY4 -> 0 | CA9: =+BZ4-BY4 -> 0 | CB9: =+CA4-BZ4 -> 0 | CC9: =+CB4-CA4 -> 0 | CD9: =+CC4-CB4 -> 0 | CE9: =+CD4-CC4 -> 0 | CF9: =+CE4-CD4 -> 0 | CG9: =+CF4-CE4 -> 0 | CN9: EcPro5Decidedlastyr | CO9: 0 | CP9: =+CO4 -> 0 | CQ9: =+CP4-CO4 -> 0 | CR9: =+CQ4-CP4 -> 0 | CS9: =+CR4-CQ4 -> 0 | CT9: =+CS4-CR4 -> 0 | CU9: =+CT4-CS4 -> 0 | CV9: =+CU4-CT4 -> 0 | CW9: =+CV4-CU4 -> 0 | DD9: EcPro6Decidedlastyr | DE9: 0 | DF9: =+DE4 -> 0 | DG9: =+DF4-DE4 -> 0 | DH9: =+DG4-DF4 -> 0 | DI9: =+DH4-DG4 -> 0 | DJ9: =+DI4-DH4 -> 0 | DK9: =+DJ4-DI4 -> 0 | DL9: =+DK4-DJ4 -> 0 | DM9: =+DL4-DK4 -> 0 | DT9: EcPro7Decidedlastyr | DU9: 0 | DV9: =+DU4 -> 0 | DW9: =+DV4-DU4 -> 0 | DX9: =+DW4-DV4 -> 0 | DY9: =+DX4-DW4 -> 0 | DZ9: =+DY4-DX4 -> 0 | EA9: =+DZ4-DY4 -> 0 | EB9: =+EA4-DZ4 -> 0 | EC9: =+EB4-EA4 -> 0 | EJ9: EcPro8Decidedlastyr | EK9: 0 | EL9: =+EK4 -> 0 | EM9: =+EL4-EK4 -> 0 | EN9: =+EM4-EL4 -> 0 | EO9: =+EN4-EM4 -> 0 | EP9: =+EO4-EN4 -> 0 | EQ9: =+EP4-EO4 -> 0 | ER9: =+EQ4-EP4 -> 0 | ES9: =+ER4-EQ4 -> 0 | EZ9: EcPro9Decidedlastyr | FA9: 0 | FB9: =+FA4 -> 0 | FC9: =+FB4-FA4 -> 0 | FD9: =+FC4-FB4 -> 0 | FE9: =+FD4-FC4 -> 0 | FF9: =+FE4-FD4 -> 0 | FG9: =+FF4-FE4 -> 0 | FH9: =+FG4-FF4 -> 0 | FI9: =+FH4-FG4 -> 0 | FP9: EcPro10Decidedlastyr | FQ9: 0 | FR9: =+FQ4 -> 0 | FS9: =+FR4-FQ4 -> 0 | FT9: =+FS4-FR4 -> 0 | FU9: =+FT4-FS4 -> 0 | FV9: =+FU4-FT4 -> 0 | FW9: =+FV4-FU4 -> 0 | FX9: =+FW4-FV4 -> 0 | FY9: =+FX4-FW4 -> 0 | GF9: EcPro11Decidedlastyr | GG9: 0 | GH9: =+GG4 -> 0 | GI9: =+GH4-GG4 -> 0 | GJ9: =+GI4-GH4 -> 0 | GK9: =+GJ4-GI4 -> 0 | GL9: =+GK4-GJ4 -> 0 | GM9: =+GL4-GK4 -> 0 | GN9: =+GM4-GL4 -> 0 | GO9: =+GN4-GM4 -> 0 | GV9: EcPro12Decidedlastyr | GW9: 0 | GX9: =+GW4 -> 0 | GY9: =+GX4-GW4 -> 0 | GZ9: =+GY4-GX4 -> 0 | HA9: =+GZ4-GY4 -> 0 | HB9: =+HA4-GZ4 -> 0 | HC9: =+HB4-HA4 -> 0 | HD9: =+HC4-HB4 -> 0 | HE9: =+HD4-HC4 -> 0 | HL9: EcPro13Decidedlastyr | HM9: 0 | HN9: =+HM4 -> 0 | HO9: =+HN4-HM4 -> 0 | HP9: =+HO4-HN4 -> 0 | HQ9: =+HP4-HO4 -> 0 | HR9: =+HQ4-HP4 -> 0 | HS9: =+HR4-HQ4 -> 0 | HT9: =+HS4-HR4 -> 0 | HU9: =+HT4-HS4 -> 0 | IB9: EcPro14Decidedlastyr | IC9: 0 | ID9: =+IC4 -> 0 | IE9: =+ID4-IC4 -> 0 | IF9: =+IE4-ID4 -> 0 | IG9: =+IF4-IE4 -> 0 | IH9: =+IG4-IF4 -> 0 | II9: =+IH4-IG4 -> 0 | IJ9: =+II4-IH4 -> 0 | IK9: =+IJ4-II4 -> 0 | IR9: EcPro15Decidedlastyr | IS9: 0 | IT9: =+IS4 -> 0 | IU9: =+IT4-IS4 -> 0 | IV9: =+IU4-IT4 -> 0 | IW9: =+IV4-IU4 -> 0 | IX9: =+IW4-IV4 -> 0 | IY9: =+IX4-IW4 -> 0 | IZ9: =+IY4-IX4 -> 0 | JA9: =+IZ4-IY4 -> 0 | JH9: EcPro16Decidedlastyr | JI9: 0 | JJ9: =+JI4 -> 0 | JK9: =+JJ4-JI4 -> 0 | JL9: =+JK4-JJ4 -> 0 | JM9: =+JL4-JK4 -> 0 | JN9: =+JM4-JL4 -> 0 | JO9: =+JN4-JM4 -> 0 | JP9: =+JO4-JN4 -> 0 | JQ9: =+JP4-JO4 -> 0 | JX9: EcPro17Decidedlastyr | JY9: 0 | JZ9: =+JY4 -> 0 | KA9: =+JZ4-JY4 -> 0 | KB9: =+KA4-JZ4 -> 0 | KC9: =+KB4-KA4 -> 0 | KD9: =+KC4-KB4 -> 0 | KE9: =+KD4-KC4 -> 0 | KF9: =+KE4-KD4 -> 0 | KG9: =+KF4-KE4 -> 0 | KN9: EcPro18Decidedlastyr | KO9: 0 | KP9: =+KO4 -> 0 | KQ9: =+KP4-KO4 -> 0 | KR9: =+KQ4-KP4 -> 0 | KS9: =+KR4-KQ4 -> 0 | KT9: =+KS4-KR4 -> 0 | KU9: =+KT4-KS4 -> 0 | KV9: =+KU4-KT4 -> 0 | KW9: =+KV4-KU4 -> 0 | LD9: EcPro19Decidedlastyr | LE9: 0 | LF9: =+LE4 -> 0 | LG9: =+LF4-LE4 -> 0 | LH9: =+LG4-LF4 -> 0 | LI9: =+LH4-LG4 -> 0 | LJ9: =+LI4-LH4 -> 0 | LK9: =+LJ4-LI4 -> 0 | LL9: =+LK4-LJ4 -> 0 | LM9: =+LL4-LK4 -> 0 | LT9: EcPro20Decidedlastyr | LU9: 0 | LV9: =+LU4 -> 0 | LW9: =+LV4-LU4 -> 0 | LX9: =+LW4-LV4 -> 0 | LY9: =+LX4-LW4 -> 0 | LZ9: =+LY4-LX4 -> 0 | MA9: =+LZ4-LY4 -> 0 | MB9: =+MA4-LZ4 -> 0 | MC9: =+MB4-MA4 -> 0 | MJ9: EcPro21Decidedlastyr | MK9: 0 | ML9: =+MK4 -> 0 | MM9: =+ML4-MK4 -> 0 | MN9: =+MM4-ML4 -> 0 | MO9: =+MN4-MM4 -> 0 | MP9: =+MO4-MN4 -> 0 | MQ9: =+MP4-MO4 -> 0 | MR9: =+MQ4-MP4 -> 0 | MS9: =+MR4-MQ4 -> 0 | MZ9: EcPro22Decidedlastyr | NA9: 0 | NB9: =+NA4 -> 0 | NC9: =+NB4-NA4 -> 0 | ND9: =+NC4-NB4 -> 0 | NE9: =+ND4-NC4 -> 0 | NF9: =+NE4-ND4 -> 0 | NG9: =+NF4-NE4 -> 0 | NH9: =+NG4-NF4 -> 0 | NI9: =+NH4-NG4 -> 0 | NP9: EcPro23Decidedlastyr | NQ9: 0 | NR9: =+NQ4 -> 0 | NS9: =+NR4-NQ4 -> 0 | NT9: =+NS4-NR4 -> 0 | NU9: =+NT4-NS4 -> 0 | NV9: =+NU4-NT4 -> 0 | NW9: =+NV4-NU4 -> 0 | NX9: =+NW4-NV4 -> 0 | NY9: =+NX4-NW4 -> 0 | OF9: EcPro24Decidedlastyr | OG9: 0 | OH9: =+OG4 -> 0 | OI9: =+OH4-OG4 -> 0 | OJ9: =+OI4-OH4 -> 0 | OK9: =+OJ4-OI4 -> 0 | OL9: =+OK4-OJ4 -> 0 | OM9: =+OL4-OK4 -> 0 | ON9: =+OM4-OL4 -> 0 | OO9: =+ON4-OM4 -> 0
A10: EcProDecided2yrsago | BH10: EcPro3Decided2yrsago | BI10: 0 | BJ10: =BI9 -> 0 | BK10: =BJ9 -> 0 | BL10: =BK9 -> 0 | BM10: =BL9 -> 0 | BN10: =BM9 -> 0 | BO10: =BN9 -> 0 | BP10: =BO9 -> 0 | BQ10: =BP9 -> 0 | BX10: EcPro4Decided2yrsago | BY10: 0 | BZ10: =BY9 -> 0 | CA10: =BZ9 -> 0 | CB10: =CA9 -> 0 | CC10: =CB9 -> 0 | CD10: =CC9 -> 0 | CE10: =CD9 -> 0 | CF10: =CE9 -> 0 | CG10: =CF9 -> 0 | CN10: EcPro5Decided2yrsago | CO10: 0 | CP10: =CO9 -> 0 | CQ10: =CP9 -> 0 | CR10: =CQ9 -> 0 | CS10: =CR9 -> 0 | CT10: =CS9 -> 0 | CU10: =CT9 -> 0 | CV10: =CU9 -> 0 | CW10: =CV9 -> 0 | DD10: EcPro6Decided2yrsago | DE10: 0 | DF10: =DE9 -> 0 | DG10: =DF9 -> 0 | DH10: =DG9 -> 0 | DI10: =DH9 -> 0 | DJ10: =DI9 -> 0 | DK10: =DJ9 -> 0 | DL10: =DK9 -> 0 | DM10: =DL9 -> 0 | DT10: EcPro7Decided2yrsago | DU10: 0 | DV10: =DU9 -> 0 | DW10: =DV9 -> 0 | DX10: =DW9 -> 0 | DY10: =DX9 -> 0 | DZ10: =DY9 -> 0 | EA10: =DZ9 -> 0 | EB10: =EA9 -> 0 | EC10: =EB9 -> 0 | EJ10: EcPro8Decided2yrsago | EK10: 0 | EL10: =EK9 -> 0 | EM10: =EL9 -> 0 | EN10: =EM9 -> 0 | EO10: =EN9 -> 0 | EP10: =EO9 -> 0 | EQ10: =EP9 -> 0 | ER10: =EQ9 -> 0 | ES10: =ER9 -> 0 | EZ10: EcPro9Decided2yrsago | FA10: 0 | FB10: =FA9 -> 0 | FC10: =FB9 -> 0 | FD10: =FC9 -> 0 | FE10: =FD9 -> 0 | FF10: =FE9 -> 0 | FG10: =FF9 -> 0 | FH10: =FG9 -> 0 | FI10: =FH9 -> 0 | FP10: EcPro10Decided2yrsago | FQ10: 0 | FR10: =FQ9 -> 0 | FS10: =FR9 -> 0 | FT10: =FS9 -> 0 | FU10: =FT9 -> 0 | FV10: =FU9 -> 0 | FW10: =FV9 -> 0 | FX10: =FW9 -> 0 | FY10: =FX9 -> 0 | GF10: EcPro11Decided2yrsago | GG10: 0 | GH10: =GG9 -> 0 | GI10: =GH9 -> 0 | GJ10: =GI9 -> 0 | GK10: =GJ9 -> 0 | GL10: =GK9 -> 0 | GM10: =GL9 -> 0 | GN10: =GM9 -> 0 | GO10: =GN9 -> 0 | GV10: EcPro12Decided2yrsago | GW10: 0 | GX10: =GW9 -> 0 | GY10: =GX9 -> 0 | GZ10: =GY9 -> 0 | HA10: =GZ9 -> 0 | HB10: =HA9 -> 0 | HC10: =HB9 -> 0 | HD10: =HC9 -> 0 | HE10: =HD9 -> 0 | HL10: EcPro13Decided2yrsago | HM10: 0 | HN10: =HM9 -> 0 | HO10: =HN9 -> 0 | HP10: =HO9 -> 0 | HQ10: =HP9 -> 0 | HR10: =HQ9 -> 0 | HS10: =HR9 -> 0 | HT10: =HS9 -> 0 | HU10: =HT9 -> 0 | IB10: EcPro14Decided2yrsago | IC10: 0 | ID10: =IC9 -> 0 | IE10: =ID9 -> 0 | IF10: =IE9 -> 0 | IG10: =IF9 -> 0 | IH10: =IG9 -> 0 | II10: =IH9 -> 0 | IJ10: =II9 -> 0 | IK10: =IJ9 -> 0 | IR10: EcPro15Decided2yrsago | IS10: 0 | IT10: =IS9 -> 0 | IU10: =IT9 -> 0 | IV10: =IU9 -> 0 | IW10: =IV9 -> 0 | IX10: =IW9 -> 0 | IY10: =IX9 -> 0 | IZ10: =IY9 -> 0 | JA10: =IZ9 -> 0 | JH10: EcPro16Decided2yrsago | JI10: 0 | JJ10: =JI9 -> 0 | JK10: =JJ9 -> 0 | JL10: =JK9 -> 0 | JM10: =JL9 -> 0 | JN10: =JM9 -> 0 | JO10: =JN9 -> 0 | JP10: =JO9 -> 0 | JQ10: =JP9 -> 0 | JX10: EcPro17Decided2yrsago | JY10: 0 | JZ10: =JY9 -> 0 | KA10: =JZ9 -> 0 | KB10: =KA9 -> 0 | KC10: =KB9 -> 0 | KD10: =KC9 -> 0 | KE10: =KD9 -> 0 | KF10: =KE9 -> 0 | KG10: =KF9 -> 0 | KN10: EcPro18Decided2yrsago | KO10: 0 | KP10: =KO9 -> 0 | KQ10: =KP9 -> 0 | KR10: =KQ9 -> 0 | KS10: =KR9 -> 0 | KT10: =KS9 -> 0 | KU10: =KT9 -> 0 | KV10: =KU9 -> 0 | KW10: =KV9 -> 0 | LD10: EcPro19Decided2yrsago | LE10: 0 | LF10: =LE9 -> 0 | LG10: =LF9 -> 0 | LH10: =LG9 -> 0 | LI10: =LH9 -> 0 | LJ10: =LI9 -> 0 | LK10: =LJ9 -> 0 | LL10: =LK9 -> 0 | LM10: =LL9 -> 0 | LT10: EcPro20Decided2yrsago | LU10: 0 | LV10: =LU9 -> 0 | LW10: =LV9 -> 0 | LX10: =LW9 -> 0 | LY10: =LX9 -> 0 | LZ10: =LY9 -> 0 | MA10: =LZ9 -> 0 | MB10: =MA9 -> 0 | MC10: =MB9 -> 0 | MJ10: EcPro21Decided2yrsago | MK10: 0 | ML10: =MK9 -> 0 | MM10: =ML9 -> 0 | MN10: =MM9 -> 0 | MO10: =MN9 -> 0 | MP10: =MO9 -> 0 | MQ10: =MP9 -> 0 | MR10: =MQ9 -> 0 | MS10: =MR9 -> 0 | MZ10: EcPro22Decided2yrsago | NA10: 0 | NB10: =NA9 -> 0 | NC10: =NB9 -> 0 | ND10: =NC9 -> 0 | NE10: =ND9 -> 0 | NF10: =NE9 -> 0 | NG10: =NF9 -> 0 | NH10: =NG9 -> 0 | NI10: =NH9 -> 0 | NP10: EcPro23Decided2yrsago | NQ10: 0 | NR10: =NQ9 -> 0 | NS10: =NR9 -> 0 | NT10: =NS9 -> 0 | NU10: =NT9 -> 0 | NV10: =NU9 -> 0 | NW10: =NV9 -> 0 | NX10: =NW9 -> 0 | NY10: =NX9 -> 0 | OF10: EcPro24Decided2yrsago | OG10: 0 | OH10: =OG9 -> 0 | OI10: =OH9 -> 0 | OJ10: =OI9 -> 0 | OK10: =OJ9 -> 0 | OL10: =OK9 -> 0 | OM10: =OL9 -> 0 | ON10: =OM9 -> 0 | OO10: =ON9 -> 0
A11: EcProCost | BH11: EcPro3Cost | BI11: =IF(BI18=1,MAX((BI4-BI6)*BI12,0),MAX((BI4-BI6),0)) -> 0 | BJ11: =IF(BI18=1,MAX((BJ4-BJ6)*BI12,0),MAX((BJ4-BJ6),0)) -> 0 | BK11: =IF(BI18=1,MAX((BK4-BK6)*BI12,0),MAX((BK4-BK6),0)) -> 0 | BL11: =IF(BI18=1,MAX((BL4-BL6)*BI12,0),MAX((BL4-BL6),0)) -> 0 | BM11: =IF(BI18=1,MAX((BM4-BM6)*BI12,0),MAX((BM4-BM6),0)) -> 0 | BN11: =IF(BI18=1,MAX((BN4-BN6)*BI12,0),MAX((BN4-BN6),0)) -> 0 | BO11: =IF(BI18=1,MAX((BO4-BO6)*BI12,0),MAX((BO4-BO6),0)) -> 0 | BP11: =IF(BI18=1,MAX((BP4-BP6)*BI12,0),MAX((BP4-BP6),0)) -> 0 | BQ11: =IF(BI18=1,MAX((BQ4-BQ6)*BI12,0),MAX((BQ4-BQ6),0)) -> 0 | BX11: EcPro4Cost | BY11: =IF(BY18=1,MAX((BY4-BY6)*BY12,0),MAX((BY4-BY6),0)) -> 0 | BZ11: =IF(BY18=1,MAX((BZ4-BZ6)*BY12,0),MAX((BZ4-BZ6),0)) -> 0 | CA11: =IF(BY18=1,MAX((CA4-CA6)*BY12,0),MAX((CA4-CA6),0)) -> 0 | CB11: =IF(BY18=1,MAX((CB4-CB6)*BY12,0),MAX((CB4-CB6),0)) -> 0 | CC11: =IF(BY18=1,MAX((CC4-CC6)*BY12,0),MAX((CC4-CC6),0)) -> 0 | CD11: =IF(BY18=1,MAX((CD4-CD6)*BY12,0),MAX((CD4-CD6),0)) -> 0 | CE11: =IF(BY18=1,MAX((CE4-CE6)*BY12,0),MAX((CE4-CE6),0)) -> 0 | CF11: =IF(BY18=1,MAX((CF4-CF6)*BY12,0),MAX((CF4-CF6),0)) -> 0 | CG11: =IF(BY18=1,MAX((CG4-CG6)*BY12,0),MAX((CG4-CG6),0)) -> 0 | CN11: EcPro5Cost | CO11: =IF(CO18=1,MAX((CO4-CO6)*CO12,0),MAX((CO4-CO6),0)) -> 0 | CP11: =IF(CO18=1,MAX((CP4-CP6)*CO12,0),MAX((CP4-CP6),0)) -> 0 | CQ11: =IF(CO18=1,MAX((CQ4-CQ6)*CO12,0),MAX((CQ4-CQ6),0)) -> 0 | CR11: =IF(CO18=1,MAX((CR4-CR6)*CO12,0),MAX((CR4-CR6),0)) -> 0 | CS11: =IF(CO18=1,MAX((CS4-CS6)*CO12,0),MAX((CS4-CS6),0)) -> 0 | CT11: =IF(CO18=1,MAX((CT4-CT6)*CO12,0),MAX((CT4-CT6),0)) -> 0 | CU11: =IF(CO18=1,MAX((CU4-CU6)*CO12,0),MAX((CU4-CU6),0)) -> 0 | CV11: =IF(CO18=1,MAX((CV4-CV6)*CO12,0),MAX((CV4-CV6),0)) -> 0 | CW11: =IF(CO18=1,MAX((CW4-CW6)*CO12,0),MAX((CW4-CW6),0)) -> 0 | DD11: EcPro6Cost | DE11: =IF(DE18=1,MAX((DE4-DE6)*DE12,0),MAX((DE4-DE6),0)) -> 0 | DF11: =IF(DE18=1,MAX((DF4-DF6)*DE12,0),MAX((DF4-DF6),0)) -> 0 | DG11: =IF(DE18=1,MAX((DG4-DG6)*DE12,0),MAX((DG4-DG6),0)) -> 0 | DH11: =IF(DE18=1,MAX((DH4-DH6)*DE12,0),MAX((DH4-DH6),0)) -> 0 | DI11: =IF(DE18=1,MAX((DI4-DI6)*DE12,0),MAX((DI4-DI6),0)) -> 0 | DJ11: =IF(DE18=1,MAX((DJ4-DJ6)*DE12,0),MAX((DJ4-DJ6),0)) -> 0 | DK11: =IF(DE18=1,MAX((DK4-DK6)*DE12,0),MAX((DK4-DK6),0)) -> 0 | DL11: =IF(DE18=1,MAX((DL4-DL6)*DE12,0),MAX((DL4-DL6),0)) -> 0 | DM11: =IF(DE18=1,MAX((DM4-DM6)*DE12,0),MAX((DM4-DM6),0)) -> 0 | DT11: EcPro7Cost | DU11: =IF(DU18=1,MAX((DU4-DU6)*DU12,0),MAX((DU4-DU6),0)) -> 0 | DV11: =IF(DU18=1,MAX((DV4-DV6)*DU12,0),MAX((DV4-DV6),0)) -> 0 | DW11: =IF(DU18=1,MAX((DW4-DW6)*DU12,0),MAX((DW4-DW6),0)) -> 0 | DX11: =IF(DU18=1,MAX((DX4-DX6)*DU12,0),MAX((DX4-DX6),0)) -> 0 | DY11: =IF(DU18=1,MAX((DY4-DY6)*DU12,0),MAX((DY4-DY6),0)) -> 0 | DZ11: =IF(DU18=1,MAX((DZ4-DZ6)*DU12,0),MAX((DZ4-DZ6),0)) -> 0 | EA11: =IF(DU18=1,MAX((EA4-EA6)*DU12,0),MAX((EA4-EA6),0)) -> 0 | EB11: =IF(DU18=1,MAX((EB4-EB6)*DU12,0),MAX((EB4-EB6),0)) -> 0 | EC11: =IF(DU18=1,MAX((EC4-EC6)*DU12,0),MAX((EC4-EC6),0)) -> 0 | EJ11: EcPro8Cost | EK11: =IF(EK18=1,MAX((EK4-EK6)*EK12,0),MAX((EK4-EK6),0)) -> 0 | EL11: =IF(EK18=1,MAX((EL4-EL6)*EK12,0),MAX((EL4-EL6),0)) -> 0 | EM11: =IF(EK18=1,MAX((EM4-EM6)*EK12,0),MAX((EM4-EM6),0)) -> 0 | EN11: =IF(EK18=1,MAX((EN4-EN6)*EK12,0),MAX((EN4-EN6),0)) -> 0 | EO11: =IF(EK18=1,MAX((EO4-EO6)*EK12,0),MAX((EO4-EO6),0)) -> 0 | EP11: =IF(EK18=1,MAX((EP4-EP6)*EK12,0),MAX((EP4-EP6),0)) -> 0 | EQ11: =IF(EK18=1,MAX((EQ4-EQ6)*EK12,0),MAX((EQ4-EQ6),0)) -> 0 | ER11: =IF(EK18=1,MAX((ER4-ER6)*EK12,0),MAX((ER4-ER6),0)) -> 0 | ES11: =IF(EK18=1,MAX((ES4-ES6)*EK12,0),MAX((ES4-ES6),0)) -> 0 | EZ11: EcPro9Cost | FA11: =IF(FA18=1,MAX((FA4-FA6)*FA12,0),MAX((FA4-FA6),0)) -> 0 | FB11: =IF(FA18=1,MAX((FB4-FB6)*FA12,0),MAX((FB4-FB6),0)) -> 0 | FC11: =IF(FA18=1,MAX((FC4-FC6)*FA12,0),MAX((FC4-FC6),0)) -> 0 | FD11: =IF(FA18=1,MAX((FD4-FD6)*FA12,0),MAX((FD4-FD6),0)) -> 0 | FE11: =IF(FA18=1,MAX((FE4-FE6)*FA12,0),MAX((FE4-FE6),0)) -> 0 | FF11: =IF(FA18=1,MAX((FF4-FF6)*FA12,0),MAX((FF4-FF6),0)) -> 0 | FG11: =IF(FA18=1,MAX((FG4-FG6)*FA12,0),MAX((FG4-FG6),0)) -> 0 | FH11: =IF(FA18=1,MAX((FH4-FH6)*FA12,0),MAX((FH4-FH6),0)) -> 0 | FI11: =IF(FA18=1,MAX((FI4-FI6)*FA12,0),MAX((FI4-FI6),0)) -> 0 | FP11: EcPro10Cost | FQ11: =IF(FQ18=1,MAX((FQ4-FQ6)*FQ12,0),MAX((FQ4-FQ6),0)) -> 0 | FR11: =IF(FQ18=1,MAX((FR4-FR6)*FQ12,0),MAX((FR4-FR6),0)) -> 0 | FS11: =IF(FQ18=1,MAX((FS4-FS6)*FQ12,0),MAX((FS4-FS6),0)) -> 0 | FT11: =IF(FQ18=1,MAX((FT4-FT6)*FQ12,0),MAX((FT4-FT6),0)) -> 0 | FU11: =IF(FQ18=1,MAX((FU4-FU6)*FQ12,0),MAX((FU4-FU6),0)) -> 0 | FV11: =IF(FQ18=1,MAX((FV4-FV6)*FQ12,0),MAX((FV4-FV6),0)) -> 0 | FW11: =IF(FQ18=1,MAX((FW4-FW6)*FQ12,0),MAX((FW4-FW6),0)) -> 0 | FX11: =IF(FQ18=1,MAX((FX4-FX6)*FQ12,0),MAX((FX4-FX6),0)) -> 0 | FY11: =IF(FQ18=1,MAX((FY4-FY6)*FQ12,0),MAX((FY4-FY6),0)) -> 0 | GF11: EcPro11Cost | GG11: =IF(GG18=1,MAX((GG4-GG6)*GG12,0),MAX((GG4-GG6),0)) -> 0 | GH11: =IF(GG18=1,MAX((GH4-GH6)*GG12,0),MAX((GH4-GH6),0)) -> 0 | GI11: =IF(GG18=1,MAX((GI4-GI6)*GG12,0),MAX((GI4-GI6),0)) -> 0 | GJ11: =IF(GG18=1,MAX((GJ4-GJ6)*GG12,0),MAX((GJ4-GJ6),0)) -> 0 | GK11: =IF(GG18=1,MAX((GK4-GK6)*GG12,0),MAX((GK4-GK6),0)) -> 0 | GL11: =IF(GG18=1,MAX((GL4-GL6)*GG12,0),MAX((GL4-GL6),0)) -> 0 | GM11: =IF(GG18=1,MAX((GM4-GM6)*GG12,0),MAX((GM4-GM6),0)) -> 0 | GN11: =IF(GG18=1,MAX((GN4-GN6)*GG12,0),MAX((GN4-GN6),0)) -> 0 | GO11: =IF(GG18=1,MAX((GO4-GO6)*GG12,0),MAX((GO4-GO6),0)) -> 0 | GV11: EcPro12Cost | GW11: =IF(GW18=1,MAX((GW4-GW6)*GW12,0),MAX((GW4-GW6),0)) -> 0 | GX11: =IF(GW18=1,MAX((GX4-GX6)*GW12,0),MAX((GX4-GX6),0)) -> 0 | GY11: =IF(GW18=1,MAX((GY4-GY6)*GW12,0),MAX((GY4-GY6),0)) -> 0 | GZ11: =IF(GW18=1,MAX((GZ4-GZ6)*GW12,0),MAX((GZ4-GZ6),0)) -> 0 | HA11: =IF(GW18=1,MAX((HA4-HA6)*GW12,0),MAX((HA4-HA6),0)) -> 0 | HB11: =IF(GW18=1,MAX((HB4-HB6)*GW12,0),MAX((HB4-HB6),0)) -> 0 | HC11: =IF(GW18=1,MAX((HC4-HC6)*GW12,0),MAX((HC4-HC6),0)) -> 0 | HD11: =IF(GW18=1,MAX((HD4-HD6)*GW12,0),MAX((HD4-HD6),0)) -> 0 | HE11: =IF(GW18=1,MAX((HE4-HE6)*GW12,0),MAX((HE4-HE6),0)) -> 0 | HL11: EcPro13Cost | HM11: =IF(HM18=1,MAX((HM4-HM6)*HM12,0),MAX((HM4-HM6),0)) -> 0 | HN11: =IF(HM18=1,MAX((HN4-HN6)*HM12,0),MAX((HN4-HN6),0)) -> 0 | HO11: =IF(HM18=1,MAX((HO4-HO6)*HM12,0),MAX((HO4-HO6),0)) -> 0 | HP11: =IF(HM18=1,MAX((HP4-HP6)*HM12,0),MAX((HP4-HP6),0)) -> 0 | HQ11: =IF(HM18=1,MAX((HQ4-HQ6)*HM12,0),MAX((HQ4-HQ6),0)) -> 0 | HR11: =IF(HM18=1,MAX((HR4-HR6)*HM12,0),MAX((HR4-HR6),0)) -> 0 | HS11: =IF(HM18=1,MAX((HS4-HS6)*HM12,0),MAX((HS4-HS6),0)) -> 0 | HT11: =IF(HM18=1,MAX((HT4-HT6)*HM12,0),MAX((HT4-HT6),0)) -> 0 | HU11: =IF(HM18=1,MAX((HU4-HU6)*HM12,0),MAX((HU4-HU6),0)) -> 0 | IB11: EcPro14Cost | IC11: =IF(IC18=1,MAX((IC4-IC6)*IC12,0),MAX((IC4-IC6),0)) -> 0 | ID11: =IF(IC18=1,MAX((ID4-ID6)*IC12,0),MAX((ID4-ID6),0)) -> 0 | IE11: =IF(IC18=1,MAX((IE4-IE6)*IC12,0),MAX((IE4-IE6),0)) -> 0 | IF11: =IF(IC18=1,MAX((IF4-IF6)*IC12,0),MAX((IF4-IF6),0)) -> 0 | IG11: =IF(IC18=1,MAX((IG4-IG6)*IC12,0),MAX((IG4-IG6),0)) -> 0 | IH11: =IF(IC18=1,MAX((IH4-IH6)*IC12,0),MAX((IH4-IH6),0)) -> 0 | II11: =IF(IC18=1,MAX((II4-II6)*IC12,0),MAX((II4-II6),0)) -> 0 | IJ11: =IF(IC18=1,MAX((IJ4-IJ6)*IC12,0),MAX((IJ4-IJ6),0)) -> 0 | IK11: =IF(IC18=1,MAX((IK4-IK6)*IC12,0),MAX((IK4-IK6),0)) -> 0 | IR11: EcPro15Cost | IS11: =IF(IS18=1,MAX((IS4-IS6)*IS12,0),MAX((IS4-IS6),0)) -> 0 | IT11: =IF(IS18=1,MAX((IT4-IT6)*IS12,0),MAX((IT4-IT6),0)) -> 0 | IU11: =IF(IS18=1,MAX((IU4-IU6)*IS12,0),MAX((IU4-IU6),0)) -> 0 | IV11: =IF(IS18=1,MAX((IV4-IV6)*IS12,0),MAX((IV4-IV6),0)) -> 0 | IW11: =IF(IS18=1,MAX((IW4-IW6)*IS12,0),MAX((IW4-IW6),0)) -> 0 | IX11: =IF(IS18=1,MAX((IX4-IX6)*IS12,0),MAX((IX4-IX6),0)) -> 0 | IY11: =IF(IS18=1,MAX((IY4-IY6)*IS12,0),MAX((IY4-IY6),0)) -> 0 | IZ11: =IF(IS18=1,MAX((IZ4-IZ6)*IS12,0),MAX((IZ4-IZ6),0)) -> 0 | JA11: =IF(IS18=1,MAX((JA4-JA6)*IS12,0),MAX((JA4-JA6),0)) -> 0 | JH11: EcPro16Cost | JI11: =IF(JI18=1,MAX((JI4-JI6)*JI12,0),MAX((JI4-JI6),0)) -> 0 | JJ11: =IF(JI18=1,MAX((JJ4-JJ6)*JI12,0),MAX((JJ4-JJ6),0)) -> 0 | JK11: =IF(JI18=1,MAX((JK4-JK6)*JI12,0),MAX((JK4-JK6),0)) -> 0 | JL11: =IF(JI18=1,MAX((JL4-JL6)*JI12,0),MAX((JL4-JL6),0)) -> 0 | JM11: =IF(JI18=1,MAX((JM4-JM6)*JI12,0),MAX((JM4-JM6),0)) -> 0 | JN11: =IF(JI18=1,MAX((JN4-JN6)*JI12,0),MAX((JN4-JN6),0)) -> 0 | JO11: =IF(JI18=1,MAX((JO4-JO6)*JI12,0),MAX((JO4-JO6),0)) -> 0 | JP11: =IF(JI18=1,MAX((JP4-JP6)*JI12,0),MAX((JP4-JP6),0)) -> 0 | JQ11: =IF(JI18=1,MAX((JQ4-JQ6)*JI12,0),MAX((JQ4-JQ6),0)) -> 0 | JX11: EcPro17Cost | JY11: =IF(JY18=1,MAX((JY4-JY6)*JY12,0),MAX((JY4-JY6),0)) -> 0 | JZ11: =IF(JY18=1,MAX((JZ4-JZ6)*JY12,0),MAX((JZ4-JZ6),0)) -> 0 | KA11: =IF(JY18=1,MAX((KA4-KA6)*JY12,0),MAX((KA4-KA6),0)) -> 0 | KB11: =IF(JY18=1,MAX((KB4-KB6)*JY12,0),MAX((KB4-KB6),0)) -> 0 | KC11: =IF(JY18=1,MAX((KC4-KC6)*JY12,0),MAX((KC4-KC6),0)) -> 0 | KD11: =IF(JY18=1,MAX((KD4-KD6)*JY12,0),MAX((KD4-KD6),0)) -> 0 | KE11: =IF(JY18=1,MAX((KE4-KE6)*JY12,0),MAX((KE4-KE6),0)) -> 0 | KF11: =IF(JY18=1,MAX((KF4-KF6)*JY12,0),MAX((KF4-KF6),0)) -> 0 | KG11: =IF(JY18=1,MAX((KG4-KG6)*JY12,0),MAX((KG4-KG6),0)) -> 0 | KN11: EcPro18Cost | KO11: =+MAX((KO4-KO6)*$KO12,0) -> 0 | KP11: =+MAX((KP4-KP6)*$KO12,0) -> 0 | KQ11: =+MAX((KQ4-KQ6)*$KO12,0) -> 0 | KR11: =+MAX((KR4-KR6)*$KO12,0) -> 0 | KS11: =+MAX((KS4-KS6)*$KO12,0) -> 0 | KT11: =+MAX((KT4-KT6)*$KO12,0) -> 0 | KU11: =+MAX((KU4-KU6)*$KO12,0) -> 0 | KV11: =+MAX((KV4-KV6)*$KO12,0) -> 0 | KW11: =+MAX((KW4-KW6)*$KO12,0) -> 0 | LD11: EcPro19Cost | LE11: =+MAX((LE4-LE6)*$LE12,0) -> 0 | LF11: =+MAX((LF4-LF6)*$LE12,0) -> 0 | LG11: =+MAX((LG4-LG6)*$LE12,0) -> 0 | LH11: =+MAX((LH4-LH6)*$LE12,0) -> 0 | LI11: =+MAX((LI4-LI6)*$LE12,0) -> 0 | LJ11: =+MAX((LJ4-LJ6)*$LE12,0) -> 0 | LK11: =+MAX((LK4-LK6)*$LE12,0) -> 0 | LL11: =+MAX((LL4-LL6)*$LE12,0) -> 0 | LM11: =+MAX((LM4-LM6)*$LE12,0) -> 0 | LT11: EcPro20Cost | LU11: =+MAX((LU4-LU6)*$LU12,0) -> 0 | LV11: =+MAX((LV4-LV6)*$LU12,0) -> 0 | LW11: =+MAX((LW4-LW6)*$LU12,0) -> 0 | LX11: =+MAX((LX4-LX6)*$LU12,0) -> 0 | LY11: =+MAX((LY4-LY6)*$LU12,0) -> 0 | LZ11: =+MAX((LZ4-LZ6)*$LU12,0) -> 0 | MA11: =+MAX((MA4-MA6)*$LU12,0) -> 0 | MB11: =+MAX((MB4-MB6)*$LU12,0) -> 0 | MC11: =+MAX((MC4-MC6)*$LU12,0) -> 0 | MJ11: EcPro21Cost | MK11: =+MAX((MK4-MK6)*$MK12,0) -> 0 | ML11: =+MAX((ML4-ML6)*$MK12,0) -> 0 | MM11: =+MAX((MM4-MM6)*$MK12,0) -> 0 | MN11: =+MAX((MN4-MN6)*$MK12,0) -> 0 | MO11: =+MAX((MO4-MO6)*$MK12,0) -> 0 | MP11: =+MAX((MP4-MP6)*$MK12,0) -> 0 | MQ11: =+MAX((MQ4-MQ6)*$MK12,0) -> 0 | MR11: =+MAX((MR4-MR6)*$MK12,0) -> 0 | MS11: =+MAX((MS4-MS6)*$MK12,0) -> 0 | MZ11: EcPro22Cost | NA11: =+MAX((NA4-NA6)*$NA12,0) -> 0 | NB11: =+MAX((NB4-NB6)*$NA12,0) -> 0 | NC11: =+MAX((NC4-NC6)*$NA12,0) -> 0 | ND11: =+MAX((ND4-ND6)*$NA12,0) -> 0 | NE11: =+MAX((NE4-NE6)*$NA12,0) -> 0 | NF11: =+MAX((NF4-NF6)*$NA12,0) -> 0 | NG11: =+MAX((NG4-NG6)*$NA12,0) -> 0 | NH11: =+MAX((NH4-NH6)*$NA12,0) -> 0 | NI11: =+MAX((NI4-NI6)*$NA12,0) -> 0 | NP11: EcPro23Cost | NQ11: =+MAX((NQ4-NQ6)*$NQ12,0) -> 0 | NR11: =+MAX((NR4-NR6)*$NQ12,0) -> 0 | NS11: =+MAX((NS4-NS6)*$NQ12,0) -> 0 | NT11: =+MAX((NT4-NT6)*$NQ12,0) -> 0 | NU11: =+MAX((NU4-NU6)*$NQ12,0) -> 0 | NV11: =+MAX((NV4-NV6)*$NQ12,0) -> 0 | NW11: =+MAX((NW4-NW6)*$NQ12,0) -> 0 | NX11: =+MAX((NX4-NX6)*$NQ12,0) -> 0 | NY11: =+MAX((NY4-NY6)*$NQ12,0) -> 0 | OF11: EcPro24Cost | OG11: =+MAX((OG4-OG6)*$OG12,0) -> 0 | OH11: =+MAX((OH4-OH6)*$OG12,0) -> 0 | OI11: =+MAX((OI4-OI6)*$OG12,0) -> 0 | OJ11: =+MAX((OJ4-OJ6)*$OG12,0) -> 0 | OK11: =+MAX((OK4-OK6)*$OG12,0) -> 0 | OL11: =+MAX((OL4-OL6)*$OG12,0) -> 0 | OM11: =+MAX((OM4-OM6)*$OG12,0) -> 0 | ON11: =+MAX((ON4-ON6)*$OG12,0) -> 0 | OO11: =+MAX((OO4-OO6)*$OG12,0) -> 0
A12: EcProCostInitial | BH12: EcPro3CostValue | BI12: 20000000 | BX12: EcPro4CostValue | BY12: 10000000 | CN12: EcPro5CostValue | CO12: 20000000 | DD12: EcPro6CostValue | DE12: 40000000 | DT12: EcPro7CostValue | DU12: 20000000 | EJ12: EcPro8CostValue | EK12: 20000000 | EZ12: EcPro9CostValue | FA12: 40000000 | FP12: EcPro10CostValue | FQ12: 10000000 | GF12: EcPro11CostValue | GG12: 10000000 | GV12: EcPro12CostValue | GW12: 40000000 | HL12: EcPro13CostValue | HM12: 40000000 | IB12: EcPro14CostValue | IC12: 20000000 | IR12: EcPro15CostValue | IS12: 20000000 | JH12: EcPro16CostValue | JI12: 20000000 | JX12: EcPro17CostValue | JY12: 20000000 | KN12: EcPro18CostValue | KO12: 20000000 | LD12: EcPro19CostValue | LE12: 20000000 | LT12: EcPro20CostValue | LU12: 20000000 | MJ12: EcPro21CostValue | MK12: 20000000 | MZ12: EcPro22CostValue | NA12: 20000000 | NP12: EcPro23CostValue | NQ12: 20000000 | OF12: EcPro24CostValue | OG12: 20000000
A13: EcProCostRecurring | BH13: EcPro3CostRecurring | BI13: =IF(AND(BI6=1,BI4=1),$BI$14,0) -> 0 | BJ13: =IF(AND(BJ6=1,BJ4=1),$BI$14,0) -> 0 | BK13: =IF(AND(BK6=1,BK4=1),$BI$14,0) -> 0 | BL13: =IF(AND(BL6=1,BL4=1),$BI$14,0) -> 0 | BM13: =IF(AND(BM6=1,BM4=1),$BI$14,0) -> 0 | BN13: =IF(AND(BN6=1,BN4=1),$BI$14,0) -> 0 | BO13: =IF(AND(BO6=1,BO4=1),$BI$14,0) -> 0 | BP13: =IF(AND(BP6=1,BP4=1),$BI$14,0) -> 0 | BQ13: =IF(AND(BQ6=1,BQ4=1),$BI$14,0) -> 0 | BX13: EcPro4CostRecurring | BY13: =IF(AND(BY6=1,BY4=1),$BY$14,0) -> 0 | BZ13: =IF(AND(BZ6=1,BZ4=1),$BY$14,0) -> 0 | CA13: =IF(AND(CA6=1,CA4=1),$BY$14,0) -> 0 | CB13: =IF(AND(CB6=1,CB4=1),$BY$14,0) -> 0 | CC13: =IF(AND(CC6=1,CC4=1),$BY$14,0) -> 0 | CD13: =IF(AND(CD6=1,CD4=1),$BY$14,0) -> 0 | CE13: =IF(AND(CE6=1,CE4=1),$BY$14,0) -> 0 | CF13: =IF(AND(CF6=1,CF4=1),$BY$14,0) -> 0 | CG13: =IF(AND(CG6=1,CG4=1),$BY$14,0) -> 0 | CN13: EcPro5CostRecurring | CO13: =IF(AND(CO6=1,CO4=1),$CO$14,0) -> 0 | CP13: =IF(AND(CP6=1,CP4=1),$CO$14,0) -> 0 | CQ13: =IF(AND(CQ6=1,CQ4=1),$CO$14,0) -> 0 | CR13: =IF(AND(CR6=1,CR4=1),$CO$14,0) -> 0 | CS13: =IF(AND(CS6=1,CS4=1),$CO$14,0) -> 0 | CT13: =IF(AND(CT6=1,CT4=1),$CO$14,0) -> 0 | CU13: =IF(AND(CU6=1,CU4=1),$CO$14,0) -> 0 | CV13: =IF(AND(CV6=1,CV4=1),$CO$14,0) -> 0 | CW13: =IF(AND(CW6=1,CW4=1),$CO$14,0) -> 0 | DD13: EcPro6CostRecurring | DE13: =IF(AND(DE6=1,DE4=1),$DE$14,0) -> 0 | DF13: =IF(AND(DF6=1,DF4=1),$DE$14,0) -> 0 | DG13: =IF(AND(DG6=1,DG4=1),$DE$14,0) -> 0 | DH13: =IF(AND(DH6=1,DH4=1),$DE$14,0) -> 0 | DI13: =IF(AND(DI6=1,DI4=1),$DE$14,0) -> 0 | DJ13: =IF(AND(DJ6=1,DJ4=1),$DE$14,0) -> 0 | DK13: =IF(AND(DK6=1,DK4=1),$DE$14,0) -> 0 | DL13: =IF(AND(DL6=1,DL4=1),$DE$14,0) -> 0 | DM13: =IF(AND(DM6=1,DM4=1),$DE$14,0) -> 0 | DT13: EcPro7CostRecurring | DU13: =IF(AND(DU6=1,DU4=1),$DU$14,0) -> 0 | DV13: =IF(AND(DV6=1,DV4=1),$DU$14,0) -> 0 | DW13: =IF(AND(DW6=1,DW4=1),$DU$14,0) -> 0 | DX13: =IF(AND(DX6=1,DX4=1),$DU$14,0) -> 0 | DY13: =IF(AND(DY6=1,DY4=1),$DU$14,0) -> 0 | DZ13: =IF(AND(DZ6=1,DZ4=1),$DU$14,0) -> 0 | EA13: =IF(AND(EA6=1,EA4=1),$DU$14,0) -> 0 | EB13: =IF(AND(EB6=1,EB4=1),$DU$14,0) -> 0 | EC13: =IF(AND(EC6=1,EC4=1),$DU$14,0) -> 0 | EJ13: EcPro8CostRecurring | EK13: =IF(AND(EK6=1,EK4=1),$EK$14,0) -> 0 | EL13: =IF(AND(EL6=1,EL4=1),$EK$14,0) -> 0 | EM13: =IF(AND(EM6=1,EM4=1),$EK$14,0) -> 0 | EN13: =IF(AND(EN6=1,EN4=1),$EK$14,0) -> 0 | EO13: =IF(AND(EO6=1,EO4=1),$EK$14,0) -> 0 | EP13: =IF(AND(EP6=1,EP4=1),$EK$14,0) -> 0 | EQ13: =IF(AND(EQ6=1,EQ4=1),$EK$14,0) -> 0 | ER13: =IF(AND(ER6=1,ER4=1),$EK$14,0) -> 0 | ES13: =IF(AND(ES6=1,ES4=1),$EK$14,0) -> 0 | EZ13: EcPro9CostRecurring | FA13: =IF(AND(FA6=1,FA4=1),$FA$14,0) -> 0 | FB13: =IF(AND(FB6=1,FB4=1),$FA$14,0) -> 0 | FC13: =IF(AND(FC6=1,FC4=1),$FA$14,0) -> 0 | FD13: =IF(AND(FD6=1,FD4=1),$FA$14,0) -> 0 | FE13: =IF(AND(FE6=1,FE4=1),$FA$14,0) -> 0 | FF13: =IF(AND(FF6=1,FF4=1),$FA$14,0) -> 0 | FG13: =IF(AND(FG6=1,FG4=1),$FA$14,0) -> 0 | FH13: =IF(AND(FH6=1,FH4=1),$FA$14,0) -> 0 | FI13: =IF(AND(FI6=1,FI4=1),$FA$14,0) -> 0 | FP13: EcPro10CostRecurring | FQ13: =IF(AND(FQ6=1,FQ4=1),$FQ$14,0) -> 0 | FR13: =IF(AND(FR6=1,FR4=1),$FQ$14,0) -> 0 | FS13: =IF(AND(FS6=1,FS4=1),$FQ$14,0) -> 0 | FT13: =IF(AND(FT6=1,FT4=1),$FQ$14,0) -> 0 | FU13: =IF(AND(FU6=1,FU4=1),$FQ$14,0) -> 0 | FV13: =IF(AND(FV6=1,FV4=1),$FQ$14,0) -> 0 | FW13: =IF(AND(FW6=1,FW4=1),$FQ$14,0) -> 0 | FX13: =IF(AND(FX6=1,FX4=1),$FQ$14,0) -> 0 | FY13: =IF(AND(FY6=1,FY4=1),$FQ$14,0) -> 0 | GF13: EcPro11CostRecurring | GG13: =IF(AND(GG6=1,GG4=1),$GG$14,0) -> 0 | GH13: =IF(AND(GH6=1,GH4=1),$GG$14,0) -> 0 | GI13: =IF(AND(GI6=1,GI4=1),$GG$14,0) -> 0 | GJ13: =IF(AND(GJ6=1,GJ4=1),$GG$14,0) -> 0 | GK13: =IF(AND(GK6=1,GK4=1),$GG$14,0) -> 0 | GL13: =IF(AND(GL6=1,GL4=1),$GG$14,0) -> 0 | GM13: =IF(AND(GM6=1,GM4=1),$GG$14,0) -> 0 | GN13: =IF(AND(GN6=1,GN4=1),$GG$14,0) -> 0 | GO13: =IF(AND(GO6=1,GO4=1),$GG$14,0) -> 0 | GV13: EcPro12CostRecurring | GW13: =IF(AND(GW6=1,GW4=1),$GW$14,0) -> 0 | GX13: =IF(AND(GX6=1,GX4=1),$GW$14,0) -> 0 | GY13: =IF(AND(GY6=1,GY4=1),$GW$14,0) -> 0 | GZ13: =IF(AND(GZ6=1,GZ4=1),$GW$14,0) -> 0 | HA13: =IF(AND(HA6=1,HA4=1),$GW$14,0) -> 0 | HB13: =IF(AND(HB6=1,HB4=1),$GW$14,0) -> 0 | HC13: =IF(AND(HC6=1,HC4=1),$GW$14,0) -> 0 | HD13: =IF(AND(HD6=1,HD4=1),$GW$14,0) -> 0 | HE13: =IF(AND(HE6=1,HE4=1),$GW$14,0) -> 0 | HL13: EcPro13CostRecurring | HM13: =IF(AND(HM6=1,HM4=1),$HM$14,0) -> 0 | HN13: =IF(AND(HN6=1,HN4=1),$HM$14,0) -> 0 | HO13: =IF(AND(HO6=1,HO4=1),$HM$14,0) -> 0 | HP13: =IF(AND(HP6=1,HP4=1),$HM$14,0) -> 0 | HQ13: =IF(AND(HQ6=1,HQ4=1),$HM$14,0) -> 0 | HR13: =IF(AND(HR6=1,HR4=1),$HM$14,0) -> 0 | HS13: =IF(AND(HS6=1,HS4=1),$HM$14,0) -> 0 | HT13: =IF(AND(HT6=1,HT4=1),$HM$14,0) -> 0 | HU13: =IF(AND(HU6=1,HU4=1),$HM$14,0) -> 0 | IB13: EcPro14CostRecurring | IC13: =IF(AND(IC6=1,IC4=1),$IC$14,0) -> 0 | ID13: =IF(AND(ID6=1,ID4=1),$IC$14,0) -> 0 | IE13: =IF(AND(IE6=1,IE4=1),$IC$14,0) -> 0 | IF13: =IF(AND(IF6=1,IF4=1),$IC$14,0) -> 0 | IG13: =IF(AND(IG6=1,IG4=1),$IC$14,0) -> 0 | IH13: =IF(AND(IH6=1,IH4=1),$IC$14,0) -> 0 | II13: =IF(AND(II6=1,II4=1),$IC$14,0) -> 0 | IJ13: =IF(AND(IJ6=1,IJ4=1),$IC$14,0) -> 0 | IK13: =IF(AND(IK6=1,IK4=1),$IC$14,0) -> 0 | IR13: EcPro15CostRecurring | IS13: =IF(AND(IS6=1,IS4=1),$IS$14,0) -> 0 | IT13: =IF(AND(IT6=1,IT4=1),$IS$14,0) -> 0 | IU13: =IF(AND(IU6=1,IU4=1),$IS$14,0) -> 0 | IV13: =IF(AND(IV6=1,IV4=1),$IS$14,0) -> 0 | IW13: =IF(AND(IW6=1,IW4=1),$IS$14,0) -> 0 | IX13: =IF(AND(IX6=1,IX4=1),$IS$14,0) -> 0 | IY13: =IF(AND(IY6=1,IY4=1),$IS$14,0) -> 0 | IZ13: =IF(AND(IZ6=1,IZ4=1),$IS$14,0) -> 0 | JA13: =IF(AND(JA6=1,JA4=1),$IS$14,0) -> 0 | JH13: EcPro16CostRecurring | JI13: =IF(AND(JI6=1,JI4=1),$JI$14,0) -> 0 | JJ13: =IF(AND(JJ6=1,JJ4=1),$JI$14,0) -> 0 | JK13: =IF(AND(JK6=1,JK4=1),$JI$14,0) -> 0 | JL13: =IF(AND(JL6=1,JL4=1),$JI$14,0) -> 0 | JM13: =IF(AND(JM6=1,JM4=1),$JI$14,0) -> 0 | JN13: =IF(AND(JN6=1,JN4=1),$JI$14,0) -> 0 | JO13: =IF(AND(JO6=1,JO4=1),$JI$14,0) -> 0 | JP13: =IF(AND(JP6=1,JP4=1),$JI$14,0) -> 0 | JQ13: =IF(AND(JQ6=1,JQ4=1),$JI$14,0) -> 0 | JX13: EcPro17CostRecurring | JY13: =IF(AND(JY6=1,JY4=1),$JY$14,0) -> 0 | JZ13: =IF(AND(JZ6=1,JZ4=1),$JY$14,0) -> 0 | KA13: =IF(AND(KA6=1,KA4=1),$JY$14,0) -> 0 | KB13: =IF(AND(KB6=1,KB4=1),$JY$14,0) -> 0 | KC13: =IF(AND(KC6=1,KC4=1),$JY$14,0) -> 0 | KD13: =IF(AND(KD6=1,KD4=1),$JY$14,0) -> 0 | KE13: =IF(AND(KE6=1,KE4=1),$JY$14,0) -> 0 | KF13: =IF(AND(KF6=1,KF4=1),$JY$14,0) -> 0 | KG13: =IF(AND(KG6=1,KG4=1),$JY$14,0) -> 0 | KN13: EcPro18CostRecurring | KO13: =IF(AND(KO6=1,KO4=1),$KO$14,0) -> 0 | KP13: =IF(AND(KP6=1,KP4=1),$KO$14,0) -> 0 | KQ13: =IF(AND(KQ6=1,KQ4=1),$KO$14,0) -> 0 | KR13: =IF(AND(KR6=1,KR4=1),$KO$14,0) -> 0 | KS13: =IF(AND(KS6=1,KS4=1),$KO$14,0) -> 0 | KT13: =IF(AND(KT6=1,KT4=1),$KO$14,0) -> 0 | KU13: =IF(AND(KU6=1,KU4=1),$KO$14,0) -> 0 | KV13: =IF(AND(KV6=1,KV4=1),$KO$14,0) -> 0 | KW13: =IF(AND(KW6=1,KW4=1),$KO$14,0) -> 0 | LD13: EcPro19CostRecurring | LE13: =IF(AND(LE6=1,LE4=1),$LE$14,0) -> 0 | LF13: =IF(AND(LF6=1,LF4=1),$LE$14,0) -> 0 | LG13: =IF(AND(LG6=1,LG4=1),$LE$14,0) -> 0 | LH13: =IF(AND(LH6=1,LH4=1),$LE$14,0) -> 0 | LI13: =IF(AND(LI6=1,LI4=1),$LE$14,0) -> 0 | LJ13: =IF(AND(LJ6=1,LJ4=1),$LE$14,0) -> 0 | LK13: =IF(AND(LK6=1,LK4=1),$LE$14,0) -> 0 | LL13: =IF(AND(LL6=1,LL4=1),$LE$14,0) -> 0 | LM13: =IF(AND(LM6=1,LM4=1),$LE$14,0) -> 0 | LT13: EcPro20CostRecurring | LU13: =IF(AND(LU6=1,LU4=1),$LU$14,0) -> 0 | LV13: =IF(AND(LV6=1,LV4=1),$LU$14,0) -> 0 | LW13: =IF(AND(LW6=1,LW4=1),$LU$14,0) -> 0 | LX13: =IF(AND(LX6=1,LX4=1),$LU$14,0) -> 0 | LY13: =IF(AND(LY6=1,LY4=1),$LU$14,0) -> 0 | LZ13: =IF(AND(LZ6=1,LZ4=1),$LU$14,0) -> 0 | MA13: =IF(AND(MA6=1,MA4=1),$LU$14,0) -> 0 | MB13: =IF(AND(MB6=1,MB4=1),$LU$14,0) -> 0 | MC13: =IF(AND(MC6=1,MC4=1),$LU$14,0) -> 0 | MJ13: EcPro21CostRecurring | MK13: =IF(AND(MK6=1,MK4=1),$MK$14,0) -> 0 | ML13: =IF(AND(ML6=1,ML4=1),$MK$14,0) -> 0 | MM13: =IF(AND(MM6=1,MM4=1),$MK$14,0) -> 0 | MN13: =IF(AND(MN6=1,MN4=1),$MK$14,0) -> 0 | MO13: =IF(AND(MO6=1,MO4=1),$MK$14,0) -> 0 | MP13: =IF(AND(MP6=1,MP4=1),$MK$14,0) -> 0 | MQ13: =IF(AND(MQ6=1,MQ4=1),$MK$14,0) -> 0 | MR13: =IF(AND(MR6=1,MR4=1),$MK$14,0) -> 0 | MS13: =IF(AND(MS6=1,MS4=1),$MK$14,0) -> 0 | MZ13: EcPro22CostRecurring | NA13: =IF(AND(NA6=1,NA4=1),$NA$14,0) -> 0 | NB13: =IF(AND(NB6=1,NB4=1),$NA$14,0) -> 0 | NC13: =IF(AND(NC6=1,NC4=1),$NA$14,0) -> 0 | ND13: =IF(AND(ND6=1,ND4=1),$NA$14,0) -> 0 | NE13: =IF(AND(NE6=1,NE4=1),$NA$14,0) -> 0 | NF13: =IF(AND(NF6=1,NF4=1),$NA$14,0) -> 0 | NG13: =IF(AND(NG6=1,NG4=1),$NA$14,0) -> 0 | NH13: =IF(AND(NH6=1,NH4=1),$NA$14,0) -> 0 | NI13: =IF(AND(NI6=1,NI4=1),$NA$14,0) -> 0 | NP13: EcPro23CostRecurring | NQ13: =IF(AND(NQ6=1,NQ4=1),$NQ$14,0) -> 0 | NR13: =IF(AND(NR6=1,NR4=1),$NQ$14,0) -> 0 | NS13: =IF(AND(NS6=1,NS4=1),$NQ$14,0) -> 0 | NT13: =IF(AND(NT6=1,NT4=1),$NQ$14,0) -> 0 | NU13: =IF(AND(NU6=1,NU4=1),$NQ$14,0) -> 0 | NV13: =IF(AND(NV6=1,NV4=1),$NQ$14,0) -> 0 | NW13: =IF(AND(NW6=1,NW4=1),$NQ$14,0) -> 0 | NX13: =IF(AND(NX6=1,NX4=1),$NQ$14,0) -> 0 | NY13: =IF(AND(NY6=1,NY4=1),$NQ$14,0) -> 0 | OF13: EcPro24CostRecurring | OG13: =IF(AND(OG6=1,OG4=1),$OG$14,0) -> 0 | OH13: =IF(AND(OH6=1,OH4=1),$OG$14,0) -> 0 | OI13: =IF(AND(OI6=1,OI4=1),$OG$14,0) -> 0 | OJ13: =IF(AND(OJ6=1,OJ4=1),$OG$14,0) -> 0 | OK13: =IF(AND(OK6=1,OK4=1),$OG$14,0) -> 0 | OL13: =IF(AND(OL6=1,OL4=1),$OG$14,0) -> 0 | OM13: =IF(AND(OM6=1,OM4=1),$OG$14,0) -> 0 | ON13: =IF(AND(ON6=1,ON4=1),$OG$14,0) -> 0 | OO13: =IF(AND(OO6=1,OO4=1),$OG$14,0) -> 0
A14: EcProCostRecurringValue | BH14: EcPro3CostRecurringValue | BI14: =BI12/5 -> 4000000 | BX14: EcPro4CostRecurringValue | BY14: =BY12/5 -> 2000000 | CN14: EcPro5CostRecurringValue | CO14: =CO12/5 -> 4000000 | DD14: EcPro6CostRecurringValue | DE14: =DE12/5 -> 8000000 | DT14: EcPro7CostRecurringValue | DU14: =DU12/5 -> 4000000 | EJ14: EcPro8CostRecurringValue | EK14: =EK12/5 -> 4000000 | EZ14: EcPro9CostRecurringValue | FA14: =FA12/5 -> 8000000 | FP14: EcPro10CostRecurringValue | FQ14: =FQ12/5 -> 2000000 | GF14: EcPro11CostRecurringValue | GG14: =GG12/5 -> 2000000 | GV14: EcPro12CostRecurringValue | GW14: =GW12/5 -> 8000000 | HL14: EcPro13CostRecurringValue | HM14: =HM12/5 -> 8000000 | IB14: EcPro14CostRecurringValue | IC14: =IC12/5 -> 4000000 | IR14: EcPro15CostRecurringValue | IS14: =IS12/5 -> 4000000 | JH14: EcPro16CostRecurringValue | JI14: =JI12/5 -> 4000000 | JX14: EcPro17CostRecurringValue | JY14: =JY12/5 -> 4000000 | KN14: EcPro18CostRecurringValue | KO14: =KO12/5 -> 4000000 | LD14: EcPro19CostRecurringValue | LE14: =LE12/5 -> 4000000 | LT14: EcPro20CostRecurringValue | LU14: =LU12/5 -> 4000000 | MJ14: EcPro21CostRecurringValue | MK14: =MK12/5 -> 4000000 | MZ14: EcPro22CostRecurringValue | NA14: =NA12/5 -> 4000000 | NP14: EcPro23CostRecurringValue | NQ14: =NQ12/5 -> 4000000 | OF14: EcPro24CostRecurringValue | OG14: =OG12/5 -> 4000000
A15: EcProReasoning | BH15: EcPro3Reasoning | BX15: EcPro4Reasoning | CN15: EcPro5Reasoning | DD15: EcPro6Reasoning | DT15: EcPro7Reasoning | EJ15: EcPro8Reasoning | EZ15: EcPro9Reasoning | FP15: EcPro10Reasoning | GF15: EcPro11Reasoning | GV15: EcPro12Reasoning | HL15: EcPro13Reasoning | IB15: EcPro14Reasoning | IR15: EcPro15Reasoning | JH15: EcPro16Reasoning | JX15: EcPro17Reasoning | KN15: EcPro18Reasoning | LD15: EcPro19Reasoning | LT15: EcPro20Reasoning | MJ15: EcPro21Reasoning | MZ15: EcPro22Reasoning | NP15: EcPro23Reasoning | OF15: EcPro24Reasoning
A16: EcProResponse | BH16: EcPro3Response | BX16: EcPro4Response | CN16: EcPro5Response | DD16: EcPro6Response | DT16: EcPro7Response | EJ16: EcPro8Response | EZ16: EcPro9Response | FP16: EcPro10Response | GF16: EcPro11Response | GV16: EcPro12Response | HL16: EcPro13Response | IB16: EcPro14Response | IR16: EcPro15Response | JH16: EcPro16Response | JX16: EcPro17Response | KN16: EcPro18Response | LD16: EcPro19Response | LT16: EcPro20Response | MJ16: EcPro21Response | MZ16: EcPro22Response | NP16: EcPro23Response | OF16: EcPro24Response
A17: EcProYearSelected | BH17: EcPro3YearSelected | BI17: =IF(BI4=1,1,IF(AND(BI4=0,BJ4=1),2,IF(AND(BJ4=0,BK4=1),3,IF(AND(BK4=0,BL4=1),4,IF(AND(BL4=0,BM4=1),5,IF(AND(BM4=0,BN4=1),6,IF(AND(BN4=0,BO4=1),7,IF(AND(BO4=0,BP4=1),8,-1)))))))) -> -1 | BX17: EcPro4YearSelected | BY17: =IF(BY4=1,1,IF(AND(BY4=0,BZ4=1),2,IF(AND(BZ4=0,CA4=1),3,IF(AND(CA4=0,CB4=1),4,IF(AND(CB4=0,CC4=1),5,IF(AND(CC4=0,CD4=1),6,IF(AND(CD4=0,CE4=1),7,IF(AND(CE4=0,CF4=1),8,-1)))))))) -> -1 | CN17: EcPro5YearSelected | CO17: =IF(CO4=1,1,IF(AND(CO4=0,CP4=1),2,IF(AND(CP4=0,CQ4=1),3,IF(AND(CQ4=0,CR4=1),4,IF(AND(CR4=0,CS4=1),5,IF(AND(CS4=0,CT4=1),6,IF(AND(CT4=0,CU4=1),7,IF(AND(CU4=0,CV4=1),8,-1)))))))) -> -1 | DD17: EcPro6YearSelected | DE17: =IF(DE4=1,1,IF(AND(DE4=0,DF4=1),2,IF(AND(DF4=0,DG4=1),3,IF(AND(DG4=0,DH4=1),4,IF(AND(DH4=0,DI4=1),5,IF(AND(DI4=0,DJ4=1),6,IF(AND(DJ4=0,DK4=1),7,IF(AND(DK4=0,DL4=1),8,-1)))))))) -> -1 | DT17: EcPro7YearSelected | DU17: =IF(DU4=1,1,IF(AND(DU4=0,DV4=1),2,IF(AND(DV4=0,DW4=1),3,IF(AND(DW4=0,DX4=1),4,IF(AND(DX4=0,DY4=1),5,IF(AND(DY4=0,DZ4=1),6,IF(AND(DZ4=0,EA4=1),7,IF(AND(EA4=0,EB4=1),8,-1)))))))) -> -1 | EJ17: EcPro8YearSelected | EK17: =IF(EK4=1,1,IF(AND(EK4=0,EL4=1),2,IF(AND(EL4=0,EM4=1),3,IF(AND(EM4=0,EN4=1),4,IF(AND(EN4=0,EO4=1),5,IF(AND(EO4=0,EP4=1),6,IF(AND(EP4=0,EQ4=1),7,IF(AND(EQ4=0,ER4=1),8,-1)))))))) -> -1 | EZ17: EcPro9YearSelected | FA17: =IF(FA4=1,1,IF(AND(FA4=0,FB4=1),2,IF(AND(FB4=0,FC4=1),3,IF(AND(FC4=0,FD4=1),4,IF(AND(FD4=0,FE4=1),5,IF(AND(FE4=0,FF4=1),6,IF(AND(FF4=0,FG4=1),7,IF(AND(FG4=0,FH4=1),8,-1)))))))) -> -1 | FP17: EcPro10YearSelected | FQ17: =IF(FQ4=1,1,IF(AND(FQ4=0,FR4=1),2,IF(AND(FR4=0,FS4=1),3,IF(AND(FS4=0,FT4=1),4,IF(AND(FT4=0,FU4=1),5,IF(AND(FU4=0,FV4=1),6,IF(AND(FV4=0,FW4=1),7,IF(AND(FW4=0,FX4=1),8,-1)))))))) -> -1 | GF17: EcPro11YearSelected | GG17: =IF(GG4=1,1,IF(AND(GG4=0,GH4=1),2,IF(AND(GH4=0,GI4=1),3,IF(AND(GI4=0,GJ4=1),4,IF(AND(GJ4=0,GK4=1),5,IF(AND(GK4=0,GL4=1),6,IF(AND(GL4=0,GM4=1),7,IF(AND(GM4=0,GN4=1),8,-1)))))))) -> -1 | GV17: EcPro12YearSelected | GW17: =IF(GW4=1,1,IF(AND(GW4=0,GX4=1),2,IF(AND(GX4=0,GY4=1),3,IF(AND(GY4=0,GZ4=1),4,IF(AND(GZ4=0,HA4=1),5,IF(AND(HA4=0,HB4=1),6,IF(AND(HB4=0,HC4=1),7,IF(AND(HC4=0,HD4=1),8,-1)))))))) -> -1 | HL17: EcPro13YearSelected | HM17: =IF(HM4=1,1,IF(AND(HM4=0,HN4=1),2,IF(AND(HN4=0,HO4=1),3,IF(AND(HO4=0,HP4=1),4,IF(AND(HP4=0,HQ4=1),5,IF(AND(HQ4=0,HR4=1),6,IF(AND(HR4=0,HS4=1),7,IF(AND(HS4=0,HT4=1),8,-1)))))))) -> -1 | IB17: EcPro14YearSelected | IC17: =IF(IC4=1,1,IF(AND(IC4=0,ID4=1),2,IF(AND(ID4=0,IE4=1),3,IF(AND(IE4=0,IF4=1),4,IF(AND(IF4=0,IG4=1),5,IF(AND(IG4=0,IH4=1),6,IF(AND(IH4=0,II4=1),7,IF(AND(II4=0,IJ4=1),8,-1)))))))) -> -1 | IR17: EcPro15YearSelected | IS17: =IF(IS4=1,1,IF(AND(IS4=0,IT4=1),2,IF(AND(IT4=0,IU4=1),3,IF(AND(IU4=0,IV4=1),4,IF(AND(IV4=0,IW4=1),5,IF(AND(IW4=0,IX4=1),6,IF(AND(IX4=0,IY4=1),7,IF(AND(IY4=0,IZ4=1),8,-1)))))))) -> -1 | JH17: EcPro16YearSelected | JI17: =IF(JI4=1,1,IF(AND(JI4=0,JJ4=1),2,IF(AND(JJ4=0,JK4=1),3,IF(AND(JK4=0,JL4=1),4,IF(AND(JL4=0,JM4=1),5,IF(AND(JM4=0,JN4=1),6,IF(AND(JN4=0,JO4=1),7,IF(AND(JO4=0,JP4=1),8,-1)))))))) -> -1 | JX17: EcPro17YearSelected | JY17: =IF(JY4=1,1,IF(AND(JY4=0,JZ4=1),2,IF(AND(JZ4=0,KA4=1),3,IF(AND(KA4=0,KB4=1),4,IF(AND(KB4=0,KC4=1),5,IF(AND(KC4=0,KD4=1),6,IF(AND(KD4=0,KE4=1),7,IF(AND(KE4=0,KF4=1),8,-1)))))))) -> -1 | KN17: EcPro18YearSelected | KO17: =IF(KO4=1,1,IF(AND(KO4=0,KP4=1),2,IF(AND(KP4=0,KQ4=1),3,IF(AND(KQ4=0,KR4=1),4,IF(AND(KR4=0,KS4=1),5,IF(AND(KS4=0,KT4=1),6,IF(AND(KT4=0,KU4=1),7,IF(AND(KU4=0,KV4=1),8,-1)))))))) -> -1 | LD17: EcPro19YearSelected | LE17: =IF(LE4=1,1,IF(AND(LE4=0,LF4=1),2,IF(AND(LF4=0,LG4=1),3,IF(AND(LG4=0,LH4=1),4,IF(AND(LH4=0,LI4=1),5,IF(AND(LI4=0,LJ4=1),6,IF(AND(LJ4=0,LK4=1),7,IF(AND(LK4=0,LL4=1),8,-1)))))))) -> -1 | LT17: EcPro20YearSelected | LU17: =IF(LU4=1,1,IF(AND(LU4=0,LV4=1),2,IF(AND(LV4=0,LW4=1),3,IF(AND(LW4=0,LX4=1),4,IF(AND(LX4=0,LY4=1),5,IF(AND(LY4=0,LZ4=1),6,IF(AND(LZ4=0,MA4=1),7,IF(AND(MA4=0,MB4=1),8,-1)))))))) -> -1 | MJ17: EcPro21YearSelected | MK17: =IF(MK4=1,1,IF(AND(MK4=0,ML4=1),2,IF(AND(ML4=0,MM4=1),3,IF(AND(MM4=0,MN4=1),4,IF(AND(MN4=0,MO4=1),5,IF(AND(MO4=0,MP4=1),6,IF(AND(MP4=0,MQ4=1),7,IF(AND(MQ4=0,MR4=1),8,-1)))))))) -> -1 | MZ17: EcPro22YearSelected | NA17: =IF(NA4=1,1,IF(AND(NA4=0,NB4=1),2,IF(AND(NB4=0,NC4=1),3,IF(AND(NC4=0,ND4=1),4,IF(AND(ND4=0,NE4=1),5,IF(AND(NE4=0,NF4=1),6,IF(AND(NF4=0,NG4=1),7,IF(AND(NG4=0,NH4=1),8,-1)))))))) -> -1 | NP17: EcPro23YearSelected | NQ17: =IF(NQ4=1,1,IF(AND(NQ4=0,NR4=1),2,IF(AND(NR4=0,NS4=1),3,IF(AND(NS4=0,NT4=1),4,IF(AND(NT4=0,NU4=1),5,IF(AND(NU4=0,NV4=1),6,IF(AND(NV4=0,NW4=1),7,IF(AND(NW4=0,NX4=1),8,-1)))))))) -> -1 | OF17: EcPro24YearSelected | OG17: =IF(OG4=1,1,IF(AND(OG4=0,OH4=1),2,IF(AND(OH4=0,OI4=1),3,IF(AND(OI4=0,OJ4=1),4,IF(AND(OJ4=0,OK4=1),5,IF(AND(OK4=0,OL4=1),6,IF(AND(OL4=0,OM4=1),7,IF(AND(OM4=0,ON4=1),8,-1)))))))) -> -1
A18: EcProType | BH18: EcPro3Type | BI18: 1 | BX18: EcPro4Type | BY18: 1 | CN18: EcPro5Type | CO18: 1 | DD18: EcPro6Type | DE18: 1 | DT18: EcPro7Type | DU18: 1 | EJ18: EcPro8Type | EK18: 1 | EZ18: EcPro9Type | FA18: 1 | FP18: EcPro10Type | FQ18: 1 | GF18: EcPro11Type | GG18: 1 | GV18: EcPro12Type | GW18: 1 | HL18: EcPro13Type | HM18: 1 | IB18: EcPro14Type | IC18: 1 | IR18: EcPro15Type | IS18: 1 | JH18: EcPro16Type | JI18: 1 | JX18: EcPro17Type | JY18: 1
A19: EcProCanCancel | BH19: EcPro3CanCancel | BI19: 1 | BX19: EcPro4CanCancel | BY19: 1 | CN19: EcPro5CanCancel | CO19: 1 | DD19: EcPro6CanCancel | DE19: 0 | DT19: EcPro7CanCancel | DU19: 1 | EJ19: EcPro8CanCancel | EK19: 1 | EZ19: EcPro9CanCancel | FA19: 1 | FP19: EcPro10CanCancel | FQ19: 1 | GF19: EcPro11CanCancel | GG19: 1 | GV19: EcPro12CanCancel | GW19: 0 | HL19: EcPro13CanCancel | HM19: 1 | IB19: EcPro14CanCancel | IC19: 0 | IR19: EcPro15CanCancel | IS19: 1 | JH19: EcPro16CanCancel | JI19: 0 | JX19: EcPro17CanCancel | JY19: 1 | KN19: EcPro18CanCancel | KO19: 1 | LD19: EcPro19CanCancel | LE19: 1 | LT19: EcPro20CanCancel | LU19: 1 | MJ19: EcPro21CanCancel | MK19: 1 | MZ19: EcPro22CanCancel | NA19: 1 | NP19: EcPro23CanCancel | NQ19: 1 | OF19: EcPro24CanCancel | OG19: 1
A20: EcProYear2Impact | BH20: EcPro3Year2Impact | BI20: 1 | BX20: EcPro4Year2Impact | BY20: 0 | CN20: EcPro5Year2Impact | CO20: 0 | DD20: EcPro6Year2Impact | DE20: 0 | DT20: EcPro7Year2Impact | DU20: 0 | EJ20: EcPro8Year2Impact | EK20: 0 | EZ20: EcPro9Year2Impact | FA20: 1 | FP20: EcPro10Year2Impact | FQ20: 0 | GF20: EcPro11Year2Impact | GG20: 0 | GV20: EcPro12Year2Impact | GW20: 0 | HL20: EcPro13Year2Impact | HM20: 0 | IB20: EcPro14Year2Impact | IC20: 0 | IR20: EcPro15Year2Impact | IS20: 0 | JH20: EcPro16Year2Impact | JI20: 0 | JX20: EcPro17Year2Impact | JY20: 0 | KN20: EcPro18Year2Impact | KO20: 0 | LD20: EcPro19Year2Impact | LE20: 0 | LT20: EcPro20Year2Impact | LU20: 0 | MJ20: EcPro21Year2Impact | MK20: 0 | MZ20: EcPro22Year2Impact | NA20: 0 | NP20: EcPro23Year2Impact | NQ20: 0 | OF20: EcPro24Year2Impact | OG20: 0
A21: EcProCancelledModifier | BH21: EcPro3CancelledModifier | BI21: 0.25 | BX21: EcPro4CancelledModifier | BY21: 0 | CN21: EcPro5CancelledModifier | CO21: 0.25 | DD21: EcPro6CancelledModifier | DE21: 0 | DT21: EcPro7CancelledModifier | DU21: 0 | EJ21: EcPro8CancelledModifier | EK21: 0.25 | EZ21: EcPro9CancelledModifier | FA21: 0.25 | FP21: EcPro10CancelledModifier | FQ21: 0.25 | GF21: EcPro11CancelledModifier | GG21: 0.25 | GV21: EcPro12CancelledModifier | GW21: 0 | HL21: EcPro13CancelledModifier | HM21: 0 | IB21: EcPro14CancelledModifier | IC21: 0.25 | IR21: EcPro15CancelledModifier | IS21: 0.25 | JH21: EcPro16CancelledModifier | JI21: 0.25 | JX21: EcPro17CancelledModifier | JY21: 0.25 | KN21: EcPro18CancelledModifier | KO21: 0.25 | LD21: EcPro19CancelledModifier | LE21: 0.25 | LT21: EcPro20CancelledModifier | LU21: 0.25 | MJ21: EcPro21CancelledModifier | MK21: 0.25 | MZ21: EcPro22CancelledModifier | NA21: 0.25 | NP21: EcPro23CancelledModifier | NQ21: 0.25 | OF21: EcPro24CancelledModifier | OG21: 0.25
A22: EcProWeight | BH22: EcPro3Weight | BI22: =IF(BI4=1, 1, IF(BI5=1, BI21, 0)) -> 0 | BJ22: =IF(BJ4=1, 1, IF(BJ5=1, BI21, 0)) -> 0 | BK22: =IF(BK4=1, 1, IF(BK5=1, BI21, 0)) -> 0 | BL22: =IF(BL4=1, 1, IF(BL5=1, BI21, 0)) -> 0 | BM22: =IF(BM4=1, 1, IF(BM5=1, BI21, 0)) -> 0 | BN22: =IF(BN4=1, 1, IF(BN5=1, BI21, 0)) -> 0 | BO22: =IF(BO4=1, 1, IF(BO5=1, BI21, 0)) -> 0 | BP22: =IF(BP4=1, 1, IF(BP5=1, BI21, 0)) -> 0 | BQ22: =IF(BQ4=1, 1, IF(BQ5=1, BI21, 0)) -> 0 | BX22: EcPro4Weight | BY22: =IF(BY4=1, 1, IF(BY5=1, BY21, 0)) -> 0 | BZ22: =IF(BZ4=1, 1, IF(BZ5=1, BY21, 0)) -> 0 | CA22: =IF(CA4=1, 1, IF(CA5=1, BY21, 0)) -> 0 | CB22: =IF(CB4=1, 1, IF(CB5=1, BY21, 0)) -> 0 | CC22: =IF(CC4=1, 1, IF(CC5=1, BY21, 0)) -> 0 | CD22: =IF(CD4=1, 1, IF(CD5=1, BY21, 0)) -> 0 | CE22: =IF(CE4=1, 1, IF(CE5=1, BY21, 0)) -> 0 | CF22: =IF(CF4=1, 1, IF(CF5=1, BY21, 0)) -> 0 | CG22: =IF(CG4=1, 1, IF(CG5=1, BY21, 0)) -> 0 | CN22: EcPro5Weight | CO22: =IF(CO4=1, 1, IF(CO5=1, CO21, 0)) -> 0 | CP22: =IF(CP4=1, 1, IF(CP5=1, CO21, 0)) -> 0 | CQ22: =IF(CQ4=1, 1, IF(CQ5=1, CO21, 0)) -> 0 | CR22: =IF(CR4=1, 1, IF(CR5=1, CO21, 0)) -> 0 | CS22: =IF(CS4=1, 1, IF(CS5=1, CO21, 0)) -> 0 | CT22: =IF(CT4=1, 1, IF(CT5=1, CO21, 0)) -> 0 | CU22: =IF(CU4=1, 1, IF(CU5=1, CO21, 0)) -> 0 | CV22: =IF(CV4=1, 1, IF(CV5=1, CO21, 0)) -> 0 | CW22: =IF(CW4=1, 1, IF(CW5=1, CO21, 0)) -> 0 | DD22: EcPro6Weight | DE22: =IF(DE4=1, 1, IF(DE5=1, DE21, 0)) -> 0 | DF22: =IF(DF4=1, 1, IF(DF5=1, DE21, 0)) -> 0 | DG22: =IF(DG4=1, 1, IF(DG5=1, DE21, 0)) -> 0 | DH22: =IF(DH4=1, 1, IF(DH5=1, DE21, 0)) -> 0 | DI22: =IF(DI4=1, 1, IF(DI5=1, DE21, 0)) -> 0 | DJ22: =IF(DJ4=1, 1, IF(DJ5=1, DE21, 0)) -> 0 | DK22: =IF(DK4=1, 1, IF(DK5=1, DE21, 0)) -> 0 | DL22: =IF(DL4=1, 1, IF(DL5=1, DE21, 0)) -> 0 | DM22: =IF(DM4=1, 1, IF(DM5=1, DE21, 0)) -> 0 | DT22: EcPro7Weight | DU22: =IF(DU4=1, 1, IF(DU5=1, DU21, 0)) -> 0 | DV22: =IF(DV4=1, 1, IF(DV5=1, DU21, 0)) -> 0 | DW22: =IF(DW4=1, 1, IF(DW5=1, DU21, 0)) -> 0 | DX22: =IF(DX4=1, 1, IF(DX5=1, DU21, 0)) -> 0 | DY22: =IF(DY4=1, 1, IF(DY5=1, DU21, 0)) -> 0 | DZ22: =IF(DZ4=1, 1, IF(DZ5=1, DU21, 0)) -> 0 | EA22: =IF(EA4=1, 1, IF(EA5=1, DU21, 0)) -> 0 | EB22: =IF(EB4=1, 1, IF(EB5=1, DU21, 0)) -> 0 | EC22: =IF(EC4=1, 1, IF(EC5=1, DU21, 0)) -> 0 | EJ22: EcPro8Weight | EK22: =IF(EK4=1, 1, IF(EK5=1, EK21, 0)) -> 0 | EL22: =IF(EL4=1, 1, IF(EL5=1, EK21, 0)) -> 0 | EM22: =IF(EM4=1, 1, IF(EM5=1, EK21, 0)) -> 0 | EN22: =IF(EN4=1, 1, IF(EN5=1, EK21, 0)) -> 0 | EO22: =IF(EO4=1, 1, IF(EO5=1, EK21, 0)) -> 0 | EP22: =IF(EP4=1, 1, IF(EP5=1, EK21, 0)) -> 0 | EQ22: =IF(EQ4=1, 1, IF(EQ5=1, EK21, 0)) -> 0 | ER22: =IF(ER4=1, 1, IF(ER5=1, EK21, 0)) -> 0 | ES22: =IF(ES4=1, 1, IF(ES5=1, EK21, 0)) -> 0 | EZ22: EcPro9Weight | FA22: =IF(FA4=1, 1, IF(FA5=1, FA21, 0)) -> 0 | FB22: =IF(FB4=1, 1, IF(FB5=1, FA21, 0)) -> 0 | FC22: =IF(FC4=1, 1, IF(FC5=1, FA21, 0)) -> 0 | FD22: =IF(FD4=1, 1, IF(FD5=1, FA21, 0)) -> 0 | FE22: =IF(FE4=1, 1, IF(FE5=1, FA21, 0)) -> 0 | FF22: =IF(FF4=1, 1, IF(FF5=1, FA21, 0)) -> 0 | FG22: =IF(FG4=1, 1, IF(FG5=1, FA21, 0)) -> 0 | FH22: =IF(FH4=1, 1, IF(FH5=1, FA21, 0)) -> 0 | FI22: =IF(FI4=1, 1, IF(FI5=1, FA21, 0)) -> 0 | FP22: EcPro10Weight | FQ22: =IF(FQ4=1, 1, IF(FQ5=1, FQ21, 0)) -> 0 | FR22: =IF(FR4=1, 1, IF(FR5=1, FQ21, 0)) -> 0 | FS22: =IF(FS4=1, 1, IF(FS5=1, FQ21, 0)) -> 0 | FT22: =IF(FT4=1, 1, IF(FT5=1, FQ21, 0)) -> 0 | FU22: =IF(FU4=1, 1, IF(FU5=1, FQ21, 0)) -> 0 | FV22: =IF(FV4=1, 1, IF(FV5=1, FQ21, 0)) -> 0 | FW22: =IF(FW4=1, 1, IF(FW5=1, FQ21, 0)) -> 0 | FX22: =IF(FX4=1, 1, IF(FX5=1, FQ21, 0)) -> 0 | FY22: =IF(FY4=1, 1, IF(FY5=1, FQ21, 0)) -> 0 | GF22: EcPro11Weight | GG22: =IF(GG4=1, 1, IF(GG5=1, GG21, 0)) -> 0 | GH22: =IF(GH4=1, 1, IF(GH5=1, GG21, 0)) -> 0 | GI22: =IF(GI4=1, 1, IF(GI5=1, GG21, 0)) -> 0 | GJ22: =IF(GJ4=1, 1, IF(GJ5=1, GG21, 0)) -> 0 | GK22: =IF(GK4=1, 1, IF(GK5=1, GG21, 0)) -> 0 | GL22: =IF(GL4=1, 1, IF(GL5=1, GG21, 0)) -> 0 | GM22: =IF(GM4=1, 1, IF(GM5=1, GG21, 0)) -> 0 | GN22: =IF(GN4=1, 1, IF(GN5=1, GG21, 0)) -> 0 | GO22: =IF(GO4=1, 1, IF(GO5=1, GG21, 0)) -> 0 | GV22: EcPro12Weight | GW22: =IF(GW4=1, 1, IF(GW5=1, GW21, 0)) -> 0 | GX22: =IF(GX4=1, 1, IF(GX5=1, GW21, 0)) -> 0 | GY22: =IF(GY4=1, 1, IF(GY5=1, GW21, 0)) -> 0 | GZ22: =IF(GZ4=1, 1, IF(GZ5=1, GW21, 0)) -> 0 | HA22: =IF(HA4=1, 1, IF(HA5=1, GW21, 0)) -> 0 | HB22: =IF(HB4=1, 1, IF(HB5=1, GW21, 0)) -> 0 | HC22: =IF(HC4=1, 1, IF(HC5=1, GW21, 0)) -> 0 | HD22: =IF(HD4=1, 1, IF(HD5=1, GW21, 0)) -> 0 | HE22: =IF(HE4=1, 1, IF(HE5=1, GW21, 0)) -> 0 | HL22: EcPro13Weight | HM22: =IF(HM4=1, 1, IF(HM5=1, HM21, 0)) -> 0 | HN22: =IF(HN4=1, 1, IF(HN5=1, HM21, 0)) -> 0 | HO22: =IF(HO4=1, 1, IF(HO5=1, HM21, 0)) -> 0 | HP22: =IF(HP4=1, 1, IF(HP5=1, HM21, 0)) -> 0 | HQ22: =IF(HQ4=1, 1, IF(HQ5=1, HM21, 0)) -> 0 | HR22: =IF(HR4=1, 1, IF(HR5=1, HM21, 0)) -> 0 | HS22: =IF(HS4=1, 1, IF(HS5=1, HM21, 0)) -> 0 | HT22: =IF(HT4=1, 1, IF(HT5=1, HM21, 0)) -> 0 | HU22: =IF(HU4=1, 1, IF(HU5=1, HM21, 0)) -> 0 | IB22: EcPro14Weight | IC22: =IF(IC4=1, 1, IF(IC5=1, IC21, 0)) -> 0 | ID22: =IF(ID4=1, 1, IF(ID5=1, IC21, 0)) -> 0 | IE22: =IF(IE4=1, 1, IF(IE5=1, IC21, 0)) -> 0 | IF22: =IF(IF4=1, 1, IF(IF5=1, IC21, 0)) -> 0 | IG22: =IF(IG4=1, 1, IF(IG5=1, IC21, 0)) -> 0 | IH22: =IF(IH4=1, 1, IF(IH5=1, IC21, 0)) -> 0 | II22: =IF(II4=1, 1, IF(II5=1, IC21, 0)) -> 0 | IJ22: =IF(IJ4=1, 1, IF(IJ5=1, IC21, 0)) -> 0 | IK22: =IF(IK4=1, 1, IF(IK5=1, IC21, 0)) -> 0 | IR22: EcPro15Weight | IS22: =IF(IS4=1, 1, IF(IS5=1, IS21, 0)) -> 0 | IT22: =IF(IT4=1, 1, IF(IT5=1, IS21, 0)) -> 0 | IU22: =IF(IU4=1, 1, IF(IU5=1, IS21, 0)) -> 0 | IV22: =IF(IV4=1, 1, IF(IV5=1, IS21, 0)) -> 0 | IW22: =IF(IW4=1, 1, IF(IW5=1, IS21, 0)) -> 0 | IX22: =IF(IX4=1, 1, IF(IX5=1, IS21, 0)) -> 0 | IY22: =IF(IY4=1, 1, IF(IY5=1, IS21, 0)) -> 0 | IZ22: =IF(IZ4=1, 1, IF(IZ5=1, IS21, 0)) -> 0 | JA22: =IF(JA4=1, 1, IF(JA5=1, IS21, 0)) -> 0 | JH22: EcPro16Weight | JI22: =IF(JI4=1, 1, IF(JI5=1, JI21, 0)) -> 0 | JJ22: =IF(JJ4=1, 1, IF(JJ5=1, JI21, 0)) -> 0 | JK22: =IF(JK4=1, 1, IF(JK5=1, JI21, 0)) -> 0 | JL22: =IF(JL4=1, 1, IF(JL5=1, JI21, 0)) -> 0 | JM22: =IF(JM4=1, 1, IF(JM5=1, JI21, 0)) -> 0 | JN22: =IF(JN4=1, 1, IF(JN5=1, JI21, 0)) -> 0 | JO22: =IF(JO4=1, 1, IF(JO5=1, JI21, 0)) -> 0 | JP22: =IF(JP4=1, 1, IF(JP5=1, JI21, 0)) -> 0 | JQ22: =IF(JQ4=1, 1, IF(JQ5=1, JI21, 0)) -> 0 | JX22: EcPro17Weight | JY22: =IF(JY4=1, 1, IF(JY5=1, JY21, 0)) -> 0 | JZ22: =IF(JZ4=1, 1, IF(JZ5=1, JY21, 0)) -> 0 | KA22: =IF(KA4=1, 1, IF(KA5=1, JY21, 0)) -> 0 | KB22: =IF(KB4=1, 1, IF(KB5=1, JY21, 0)) -> 0 | KC22: =IF(KC4=1, 1, IF(KC5=1, JY21, 0)) -> 0 | KD22: =IF(KD4=1, 1, IF(KD5=1, JY21, 0)) -> 0 | KE22: =IF(KE4=1, 1, IF(KE5=1, JY21, 0)) -> 0 | KF22: =IF(KF4=1, 1, IF(KF5=1, JY21, 0)) -> 0 | KG22: =IF(KG4=1, 1, IF(KG5=1, JY21, 0)) -> 0 | KN22: EcPro18Weight | KO22: =IF(KO4=1, 1, IF(KO5=1, KO21, 0)) -> 0 | KP22: =IF(KP4=1, 1, IF(KP5=1, KO21, 0)) -> 0 | KQ22: =IF(KQ4=1, 1, IF(KQ5=1, KO21, 0)) -> 0 | KR22: =IF(KR4=1, 1, IF(KR5=1, KO21, 0)) -> 0 | KS22: =IF(KS4=1, 1, IF(KS5=1, KO21, 0)) -> 0 | KT22: =IF(KT4=1, 1, IF(KT5=1, KO21, 0)) -> 0 | KU22: =IF(KU4=1, 1, IF(KU5=1, KO21, 0)) -> 0 | KV22: =IF(KV4=1, 1, IF(KV5=1, KO21, 0)) -> 0 | KW22: =IF(KW4=1, 1, IF(KW5=1, KO21, 0)) -> 0 | LD22: EcPro19Weight | LE22: =IF(LE4=1, 1, IF(LE5=1, LE21, 0)) -> 0 | LF22: =IF(LF4=1, 1, IF(LF5=1, LE21, 0)) -> 0 | LG22: =IF(LG4=1, 1, IF(LG5=1, LE21, 0)) -> 0 | LH22: =IF(LH4=1, 1, IF(LH5=1, LE21, 0)) -> 0 | LI22: =IF(LI4=1, 1, IF(LI5=1, LE21, 0)) -> 0 | LJ22: =IF(LJ4=1, 1, IF(LJ5=1, LE21, 0)) -> 0 | LK22: =IF(LK4=1, 1, IF(LK5=1, LE21, 0)) -> 0 | LL22: =IF(LL4=1, 1, IF(LL5=1, LE21, 0)) -> 0 | LM22: =IF(LM4=1, 1, IF(LM5=1, LE21, 0)) -> 0 | LT22: EcPro20Weight | LU22: =IF(LU4=1, 1, IF(LU5=1, LU21, 0)) -> 0 | LV22: =IF(LV4=1, 1, IF(LV5=1, LU21, 0)) -> 0 | LW22: =IF(LW4=1, 1, IF(LW5=1, LU21, 0)) -> 0 | LX22: =IF(LX4=1, 1, IF(LX5=1, LU21, 0)) -> 0 | LY22: =IF(LY4=1, 1, IF(LY5=1, LU21, 0)) -> 0 | LZ22: =IF(LZ4=1, 1, IF(LZ5=1, LU21, 0)) -> 0 | MA22: =IF(MA4=1, 1, IF(MA5=1, LU21, 0)) -> 0 | MB22: =IF(MB4=1, 1, IF(MB5=1, LU21, 0)) -> 0 | MC22: =IF(MC4=1, 1, IF(MC5=1, LU21, 0)) -> 0 | MJ22: EcPro21Weight | MK22: =IF(MK4=1, 1, IF(MK5=1, MK21, 0)) -> 0 | ML22: =IF(ML4=1, 1, IF(ML5=1, MK21, 0)) -> 0 | MM22: =IF(MM4=1, 1, IF(MM5=1, MK21, 0)) -> 0 | MN22: =IF(MN4=1, 1, IF(MN5=1, MK21, 0)) -> 0 | MO22: =IF(MO4=1, 1, IF(MO5=1, MK21, 0)) -> 0 | MP22: =IF(MP4=1, 1, IF(MP5=1, MK21, 0)) -> 0 | MQ22: =IF(MQ4=1, 1, IF(MQ5=1, MK21, 0)) -> 0 | MR22: =IF(MR4=1, 1, IF(MR5=1, MK21, 0)) -> 0 | MS22: =IF(MS4=1, 1, IF(MS5=1, MK21, 0)) -> 0 | MZ22: EcPro22Weight | NA22: =IF(NA4=1, 1, IF(NA5=1, NA21, 0)) -> 0 | NB22: =IF(NB4=1, 1, IF(NB5=1, NA21, 0)) -> 0 | NC22: =IF(NC4=1, 1, IF(NC5=1, NA21, 0)) -> 0 | ND22: =IF(ND4=1, 1, IF(ND5=1, NA21, 0)) -> 0 | NE22: =IF(NE4=1, 1, IF(NE5=1, NA21, 0)) -> 0 | NF22: =IF(NF4=1, 1, IF(NF5=1, NA21, 0)) -> 0 | NG22: =IF(NG4=1, 1, IF(NG5=1, NA21, 0)) -> 0 | NH22: =IF(NH4=1, 1, IF(NH5=1, NA21, 0)) -> 0 | NI22: =IF(NI4=1, 1, IF(NI5=1, NA21, 0)) -> 0 | NP22: EcPro23Weight | NQ22: =IF(NQ4=1, 1, IF(NQ5=1, NQ21, 0)) -> 0 | NR22: =IF(NR4=1, 1, IF(NR5=1, NQ21, 0)) -> 0 | NS22: =IF(NS4=1, 1, IF(NS5=1, NQ21, 0)) -> 0 | NT22: =IF(NT4=1, 1, IF(NT5=1, NQ21, 0)) -> 0 | NU22: =IF(NU4=1, 1, IF(NU5=1, NQ21, 0)) -> 0 | NV22: =IF(NV4=1, 1, IF(NV5=1, NQ21, 0)) -> 0 | NW22: =IF(NW4=1, 1, IF(NW5=1, NQ21, 0)) -> 0 | NX22: =IF(NX4=1, 1, IF(NX5=1, NQ21, 0)) -> 0 | NY22: =IF(NY4=1, 1, IF(NY5=1, NQ21, 0)) -> 0 | OF22: EcPro24Weight | OG22: =IF(OG4=1, 1, IF(OG5=1, OG21, 0)) -> 0 | OH22: =IF(OH4=1, 1, IF(OH5=1, OG21, 0)) -> 0 | OI22: =IF(OI4=1, 1, IF(OI5=1, OG21, 0)) -> 0 | OJ22: =IF(OJ4=1, 1, IF(OJ5=1, OG21, 0)) -> 0 | OK22: =IF(OK4=1, 1, IF(OK5=1, OG21, 0)) -> 0 | OL22: =IF(OL4=1, 1, IF(OL5=1, OG21, 0)) -> 0 | OM22: =IF(OM4=1, 1, IF(OM5=1, OG21, 0)) -> 0 | ON22: =IF(ON4=1, 1, IF(ON5=1, OG21, 0)) -> 0 | OO22: =IF(OO4=1, 1, IF(OO5=1, OG21, 0)) -> 0
A63: Governance
A64: GrowthWellBeing | B64: =M64+Y64+AQ64+BI64+BY64+CO64+DE64+DU64+EK64+FA64+FQ64+GG64+GW64+HM64+IC64+IS64+JI64+JY64+KO64+LE64+LU64+MK64+NA64+NQ64+OG64 -> 0 | C64: =N64+Z64+AR64+BJ64+BZ64+CP64+DF64+DV64+EL64+FB64+FR64+GH64+GX64+HN64+ID64+IT64+JJ64+JZ64+KP64+LF64+LV64+ML64+NB64+NR64+OH64 -> 0 | D64: =O64+AA64+AS64+BK64+CA64+CQ64+DG64+DW64+EM64+FC64+FS64+GI64+GY64+HO64+IE64+IU64+JK64+KA64+KQ64+LG64+LW64+MM64+NC64+NS64+OI64 -> 0 | E64: =P64+AB64+AT64+BL64+CB64+CR64+DH64+DX64+EN64+FD64+FT64+GJ64+GZ64+HP64+IF64+IV64+JL64+KB64+KR64+LH64+LX64+MN64+ND64+NT64+OJ64 -> 0 | F64: =Q64+AC64+AU64+BM64+CC64+CS64+DI64+DY64+EO64+FE64+FU64+GK64+HA64+HQ64+IG64+IW64+JM64+KC64+KS64+LI64+LY64+MO64+NE64+NU64+OK64 -> 0 | G64: =R64+AD64+AV64+BN64+CD64+CT64+DJ64+DZ64+EP64+FF64+FV64+GL64+HB64+HR64+IH64+IX64+JN64+KD64+KT64+LJ64+LZ64+MP64+NF64+NV64+OL64 -> 0 | H64: =S64+AE64+AW64+BO64+CE64+CU64+DK64+EA64+EQ64+FG64+FW64+GM64+HC64+HS64+II64+IY64+JO64+KE64+KU64+LK64+MA64+MQ64+NG64+NW64+OM64 -> 0 | I64: =AF64+AX64+BP64+CF64+CV64+DL64+EB64+ER64+FH64+FX64+GN64+HD64+HT64+IJ64+IZ64+JP64+KF64+KV64+LL64+MB64+MR64+NH64+NX64+ON64 -> 0 | J64: =AG64+AY64+BQ64+CG64+CW64+DM64+EC64+ES64+FI64+FY64+GO64+HE64+HU64+IK64+JA64+JQ64+KG64+KW64+LM64+MC64+MS64+NI64+NY64+OO64 -> 0 | M64: =M$5*V64 -> 0 | N64: =N$5*V64 -> 0 | O64: =O$5*V64 -> 0 | P64: =P$5*V64 -> 0 | Q64: =Q$5*V64 -> 0 | R64: =R$5*V64 -> 0 | S64: =S$5*V64 -> 0 | U64: LowPos | V64: =_xlfn.XLOOKUP(U64,'KPI Impacts'!$B$2:$H$2,'KPI Impacts'!$B64:$H64) -> 1 | Y64: {=_xlfn.SWITCH(Y$4, 0,0, 1, AJ64,2,AL64,3,AN64,0)} -> 0 | Z64: {=_xlfn.SWITCH(Z$4, 0,0, 1, AJ64,2,AL64,3,AN64,0)+Y64} -> 0 | AA64: {=_xlfn.SWITCH(AA$4, 0,0, 1, AJ64,2,AL64,3,AN64,0)+Z64} -> 0 | AB64: {=_xlfn.SWITCH(AB$4, 0,0, 1, AJ64,2,AL64,3,AN64,0)+AA64} -> 0 | AC64: {=_xlfn.SWITCH(AC$4, 0,0, 1, AJ64,2,AL64,3,AN64,0)+AB64} -> 0 | AD64: {=_xlfn.SWITCH(AD$4, 0,0, 1, AJ64,2,AL64,3,AN64,0)+AC64} -> 0 | AE64: {=_xlfn.SWITCH(AE$4, 0,0, 1, AJ64,2,AL64,3,AN64,0)+AD64} -> 0 | AF64: {=_xlfn.SWITCH(AF$4, 0,0, 1, AJ64,2,AL64,3,AN64,0)+AE64} -> 0 | AG64: {=_xlfn.SWITCH(AG$4, 0,0, 1, AJ64,2,AL64,3,AN64,0)+AF64} -> 0 | AI64: None | AJ64: =_xlfn.XLOOKUP(AI64,'KPI Impacts'!$K$2:$Q$2,'KPI Impacts'!$K64:$Q64) -> 0 | AK64: None | AL64: =_xlfn.XLOOKUP(AK64,'KPI Impacts'!$K$2:$Q$2,'KPI Impacts'!$K64:$Q64) -> 0 | AM64: None | AN64: =_xlfn.XLOOKUP(AM64,'KPI Impacts'!$K$2:$Q$2,'KPI Impacts'!$K64:$Q64) -> 0 | AQ64: {=_xlfn.SWITCH(AQ$4, 0,0, 1, BB64,2,BD64,3,BF64,0)} -> 0 | AR64: {=_xlfn.SWITCH(AR$4, 0,0, 1, BB64,2,BD64,3,BF64,0)+AQ64} -> 0 | AS64: {=_xlfn.SWITCH(AS$4, 0,0, 1, BB64,2,BD64,3,BF64,0)+AR64} -> 0 | AT64: {=_xlfn.SWITCH(AT$4, 0,0, 1, BB64,2,BD64,3,BF64,0)+AS64} -> 0 | AU64: {=_xlfn.SWITCH(AU$4, 0,0, 1, BB64,2,BD64,3,BF64,0)+AT64} -> 0 | AV64: {=_xlfn.SWITCH(AV$4, 0,0, 1, BB64,2,BD64,3,BF64,0)+AU64} -> 0 | AW64: {=_xlfn.SWITCH(AW$4, 0,0, 1, BB64,2,BD64,3,BF64,0)+AV64} -> 0 | AX64: {=_xlfn.SWITCH(AX$4, 0,0, 1, BB64,2,BD64,3,BF64,0)+AW64} -> 0 | AY64: {=_xlfn.SWITCH(AY$4, 0,0, 1, BB64,2,BD64,3,BF64,0)+AX64} -> 0 | BA64: LowPos | BB64: =_xlfn.XLOOKUP(BA64,'KPI Impacts'!$K$2:$Q$2,'KPI Impacts'!$K64:$Q64) -> 0.3 | BC64: MediumPos | BD64: =_xlfn.XLOOKUP(BC64,'KPI Impacts'!$K$2:$Q$2,'KPI Impacts'!$K64:$Q64) -> 0.45 | BE64: HighPos | BF64: =_xlfn.XLOOKUP(BE64,'KPI Impacts'!$K$2:$Q$2,'KPI Impacts'!$K64:$Q64) -> 0.6 | BI64: =BI$22*BT64 -> 0 | BJ64: =BJ$22 * IF(AND(BI$5=1,BI$20=1), BV64, BT64) -> 0 | BK64: =BK$22 * IF(AND(BJ$5=1,BI$20=1), BV64, BT64) -> 0 | BL64: =BL$22 * IF(AND(BK$5=1,BI$20=1), BV64, BT64) -> 0 | BM64: =BM$22 * IF(AND(BL$5=1,BI$20=1), BV64, BT64) -> 0 | BN64: =BN$22 * IF(AND(BM$5=1,BI$20=1), BV64, BT64) -> 0 | BO64: =BO$22 * IF(AND(BN$5=1,BI$20=1), BV64, BT64) -> 0 | BP64: =BP$22 * IF(AND(BO$5=1,BI$20=1), BV64, BT64) -> 0 | BQ64: =BQ$22 * IF(AND(BP$5=1,BI$20=1), BV64, BT64) -> 0 | BS64: None | BT64: =_xlfn.XLOOKUP(BS64,'KPI Impacts'!$B$2:$H$2,'KPI Impacts'!$B64:$H64) -> 0 | BU64: None | BV64: =_xlfn.XLOOKUP(BU64,'KPI Impacts'!$B$2:$H$2,'KPI Impacts'!$B64:$H64) -> 0 | BY64: =BY$22*CJ64 -> 0 | BZ64: =BZ$22 * IF(AND(BY$5=1,BY$20=1), CL64, CJ64) -> 0 | CA64: =CA$22 * IF(AND(BZ$5=1,BY$20=1), CL64, CJ64) -> 0 | CB64: =CB$22 * IF(AND(CA$5=1,BY$20=1), CL64, CJ64) -> 0 | CC64: =CC$22 * IF(AND(CB$5=1,BY$20=1), CL64, CJ64) -> 0 | CD64: =CD$22 * IF(AND(CC$5=1,BY$20=1), CL64, CJ64) -> 0 | CE64: =CE$22 * IF(AND(CD$5=1,BY$20=1), CL64, CJ64) -> 0 | CF64: =CF$22 * IF(AND(CE$5=1,BY$20=1), CL64, CJ64) -> 0 | CG64: =CG$22 * IF(AND(CF$5=1,BY$20=1), CL64, CJ64) -> 0 | CI64: None | CJ64: =_xlfn.XLOOKUP(CI64,'KPI Impacts'!$B$2:$H$2,'KPI Impacts'!$B64:$H64) -> 0 | CK64: None | CL64: =_xlfn.XLOOKUP(CK64,'KPI Impacts'!$B$2:$H$2,'KPI Impacts'!$B64:$H64) -> 0 | CO64: =CO$22*CZ64 -> 0 | CP64: =CP$22 * IF(AND(CO$5=1,CO$20=1), DB64, CZ64) -> 0 | CQ64: =CQ$22 * IF(AND(CP$5=1,CO$20=1), DB64, CZ64) -> 0 | CR64: =CR$22 * IF(AND(CQ$5=1,CO$20=1), DB64, CZ64) -> 0 | CS64: =CS$22 * IF(AND(CR$5=1,CO$20=1), DB64, CZ64) -> 0 | CT64: =CT$22 * IF(AND(CS$5=1,CO$20=1), DB64, CZ64) -> 0 | CU64: =CU$22 * IF(AND(CT$5=1,CO$20=1), DB64, CZ64) -> 0 | CV64: =CV$22 * IF(AND(CU$5=1,CO$20=1), DB64, CZ64) -> 0 | CW64: =CW$22 * IF(AND(CV$5=1,CO$20=1), DB64, CZ64) -> 0 | CY64: LowPos | CZ64: =_xlfn.XLOOKUP(CY64,'KPI Impacts'!$B$2:$H$2,'KPI Impacts'!$B64:$H64) -> 1 | DA64: None | DB64: =_xlfn.XLOOKUP(DA64,'KPI Impacts'!$B$2:$H$2,'KPI Impacts'!$B64:$H64) -> 0 | DE64: =DE$22*DP64 -> 0 | DF64: =DF$22 * IF(AND(DE$5=1,DE$20=1), DR64, DP64) -> 0 | DG64: =DG$22 * IF(AND(DF$5=1,DE$20=1), DR64, DP64) -> 0 | DH64: =DH$22 * IF(AND(DG$5=1,DE$20=1), DR64, DP64) -> 0 | DI64: =DI$22 * IF(AND(DH$5=1,DE$20=1), DR64, DP64) -> 0 | DJ64: =DJ$22 * IF(AND(DI$5=1,DE$20=1), DR64, DP64) -> 0 | DK64: =DK$22 * IF(AND(DJ$5=1,DE$20=1), DR64, DP64) -> 0 | DL64: =DL$22 * IF(AND(DK$5=1,DE$20=1), DR64, DP64) -> 0 | DM64: =DM$22 * IF(AND(DL$5=1,DE$20=1), DR64, DP64) -> 0 | DO64: LowPos | DP64: =_xlfn.XLOOKUP(DO64,'KPI Impacts'!$B$2:$H$2,'KPI Impacts'!$B64:$H64) -> 1 | DQ64: None | DR64: =_xlfn.XLOOKUP(DQ64,'KPI Impacts'!$B$2:$H$2,'KPI Impacts'!$B64:$H64) -> 0 | DU64: =DU$22*EF64 -> 0 | DV64: =DV$22 * IF(AND(DU$5=1,DU$20=1), EH64, EF64) -> 0 | DW64: =DW$22 * IF(AND(DV$5=1,DU$20=1), EH64, EF64) -> 0 | DX64: =DX$22 * IF(AND(DW$5=1,DU$20=1), EH64, EF64) -> 0 | DY64: =DY$22 * IF(AND(DX$5=1,DU$20=1), EH64, EF64) -> 0 | DZ64: =DZ$22 * IF(AND(DY$5=1,DU$20=1), EH64, EF64) -> 0 | EA64: =EA$22 * IF(AND(DZ$5=1,DU$20=1), EH64, EF64) -> 0 | EB64: =EB$22 * IF(AND(EA$5=1,DU$20=1), EH64, EF64) -> 0 | EC64: =EC$22 * IF(AND(EB$5=1,DU$20=1), EH64, EF64) -> 0 | EE64: LowPos | EF64: =_xlfn.XLOOKUP(EE64,'KPI Impacts'!$B$2:$H$2,'KPI Impacts'!$B64:$H64) -> 1 | EG64: None | EH64: =_xlfn.XLOOKUP(EG64,'KPI Impacts'!$B$2:$H$2,'KPI Impacts'!$B64:$H64) -> 0 | EK64: =EK$22*EV64 -> 0 | EL64: =EL$22 * IF(AND(EK$5=1,EK$20=1), EX64, EV64) -> 0 | EM64: =EM$22 * IF(AND(EL$5=1,EK$20=1), EX64, EV64) -> 0 | EN64: =EN$22 * IF(AND(EM$5=1,EK$20=1), EX64, EV64) -> 0 | EO64: =EO$22 * IF(AND(EN$5=1,EK$20=1), EX64, EV64) -> 0 | EP64: =EP$22 * IF(AND(EO$5=1,EK$20=1), EX64, EV64) -> 0 | EQ64: =EQ$22 * IF(AND(EP$5=1,EK$20=1), EX64, EV64) -> 0 | ER64: =ER$22 * IF(AND(EQ$5=1,EK$20=1), EX64, EV64) -> 0 | ES64: =ES$22 * IF(AND(ER$5=1,EK$20=1), EX64, EV64) -> 0 | EU64: LowPos | EV64: =_xlfn.XLOOKUP(EU64,'KPI Impacts'!$B$2:$H$2,'KPI Impacts'!$B64:$H64) -> 1 | EW64: None | EX64: =_xlfn.XLOOKUP(EW64,'KPI Impacts'!$B$2:$H$2,'KPI Impacts'!$B64:$H64) -> 0 | FA64: =FA$22*FL64 -> 0 | FB64: =FB$22 * IF(AND(FA$5=1,FA$20=1), FN64, FL64) -> 0 | FC64: =FC$22 * IF(AND(FB$5=1,FA$20=1), FN64, FL64) -> 0 | FD64: =FD$22 * IF(AND(FC$5=1,FA$20=1), FN64, FL64) -> 0 | FE64: =FE$22 * IF(AND(FD$5=1,FA$20=1), FN64, FL64) -> 0 | FF64: =FF$22 * IF(AND(FE$5=1,FA$20=1), FN64, FL64) -> 0 | FG64: =FG$22 * IF(AND(FF$5=1,FA$20=1), FN64, FL64) -> 0 | FH64: =FH$22 * IF(AND(FG$5=1,FA$20=1), FN64, FL64) -> 0 | FI64: =FI$22 * IF(AND(FH$5=1,FA$20=1), FN64, FL64) -> 0 | FK64: LowPos | FL64: =_xlfn.XLOOKUP(FK64,'KPI Impacts'!$B$2:$H$2,'KPI Impacts'!$B64:$H64) -> 1 | FM64: LowPos | FN64: =_xlfn.XLOOKUP(FM64,'KPI Impacts'!$B$2:$H$2,'KPI Impacts'!$B64:$H64) -> 1 | FQ64: =FQ$22*GB64 -> 0 | FR64: =FR$22 * IF(AND(FQ$5=1,FQ$20=1), GD64, GB64) -> 0 | FS64: =FS$22 * IF(AND(FR$5=1,FQ$20=1), GD64, GB64) -> 0 | FT64: =FT$22 * IF(AND(FS$5=1,FQ$20=1), GD64, GB64) -> 0 | FU64: =FU$22 * IF(AND(FT$5=1,FQ$20=1), GD64, GB64) -> 0 | FV64: =FV$22 * IF(AND(FU$5=1,FQ$20=1), GD64, GB64) -> 0 | FW64: =FW$22 * IF(AND(FV$5=1,FQ$20=1), GD64, GB64) -> 0 | FX64: =FX$22 * IF(AND(FW$5=1,FQ$20=1), GD64, GB64) -> 0 | FY64: =FY$22 * IF(AND(FX$5=1,FQ$20=1), GD64, GB64) -> 0 | GA64: HighPos | GB64: =_xlfn.XLOOKUP(GA64,'KPI Impacts'!$B$2:$H$2,'KPI Impacts'!$B64:$H64) -> 3 | GC64: None | GD64: =_xlfn.XLOOKUP(GC64,'KPI Impacts'!$B$2:$H$2,'KPI Impacts'!$B64:$H64) -> 0 | GG64: =GG$22*GR64 -> 0 | GH64: =GH$22 * IF(AND(GG$5=1,GG$20=1), GT64, GR64) -> 0 | GI64: =GI$22 * IF(AND(GH$5=1,GG$20=1), GT64, GR64) -> 0 | GJ64: =GJ$22 * IF(AND(GI$5=1,GG$20=1), GT64, GR64) -> 0 | GK64: =GK$22 * IF(AND(GJ$5=1,GG$20=1), GT64, GR64) -> 0 | GL64: =GL$22 * IF(AND(GK$5=1,GG$20=1), GT64, GR64) -> 0 | GM64: =GM$22 * IF(AND(GL$5=1,GG$20=1), GT64, GR64) -> 0 | GN64: =GN$22 * IF(AND(GM$5=1,GG$20=1), GT64, GR64) -> 0 | GO64: =GO$22 * IF(AND(GN$5=1,GG$20=1), GT64, GR64) -> 0 | GQ64: LowPos | GR64: =_xlfn.XLOOKUP(GQ64,'KPI Impacts'!$B$2:$H$2,'KPI Impacts'!$B64:$H64) -> 1 | GS64: None | GT64: =_xlfn.XLOOKUP(GS64,'KPI Impacts'!$B$2:$H$2,'KPI Impacts'!$B64:$H64) -> 0 | GW64: =GW$22*HH64 -> 0 | GX64: =GX$22 * IF(AND(GW$5=1,GW$20=1), HJ64, HH64) -> 0 | GY64: =GY$22 * IF(AND(GX$5=1,GW$20=1), HJ64, HH64) -> 0 | GZ64: =GZ$22 * IF(AND(GY$5=1,GW$20=1), HJ64, HH64) -> 0 | HA64: =HA$22 * IF(AND(GZ$5=1,GW$20=1), HJ64, HH64) -> 0 | HB64: =HB$22 * IF(AND(HA$5=1,GW$20=1), HJ64, HH64) -> 0 | HC64: =HC$22 * IF(AND(HB$5=1,GW$20=1), HJ64, HH64) -> 0 | HD64: =HD$22 * IF(AND(HC$5=1,GW$20=1), HJ64, HH64) -> 0 | HE64: =HE$22 * IF(AND(HD$5=1,GW$20=1), HJ64, HH64) -> 0 | HG64: LowPos | HH64: =_xlfn.XLOOKUP(HG64,'KPI Impacts'!$B$2:$H$2,'KPI Impacts'!$B64:$H64) -> 1 | HI64: None | HJ64: =_xlfn.XLOOKUP(HI64,'KPI Impacts'!$B$2:$H$2,'KPI Impacts'!$B64:$H64) -> 0 | HM64: =HM$22*HX64 -> 0 | HN64: =HN$22 * IF(AND(HM$5=1,HM$20=1), HZ64, HX64) -> 0 | HO64: =HO$22 * IF(AND(HN$5=1,HM$20=1), HZ64, HX64) -> 0 | HP64: =HP$22 * IF(AND(HO$5=1,HM$20=1), HZ64, HX64) -> 0 | HQ64: =HQ$22 * IF(AND(HP$5=1,HM$20=1), HZ64, HX64) -> 0 | HR64: =HR$22 * IF(AND(HQ$5=1,HM$20=1), HZ64, HX64) -> 0 | HS64: =HS$22 * IF(AND(HR$5=1,HM$20=1), HZ64, HX64) -> 0 | HT64: =HT$22 * IF(AND(HS$5=1,HM$20=1), HZ64, HX64) -> 0 | HU64: =HU$22 * IF(AND(HT$5=1,HM$20=1), HZ64, HX64) -> 0 | HW64: None | HX64: =_xlfn.XLOOKUP(HW64,'KPI Impacts'!$B$2:$H$2,'KPI Impacts'!$B64:$H64) -> 0 | HY64: None | HZ64: =_xlfn.XLOOKUP(HY64,'KPI Impacts'!$B$2:$H$2,'KPI Impacts'!$B64:$H64) -> 0 | IC64: =IC$22*IN64 -> 0 | ID64: =ID$22 * IF(AND(IC$5=1,IC$20=1), IP64, IN64) -> 0 | IE64: =IE$22 * IF(AND(ID$5=1,IC$20=1), IP64, IN64) -> 0 | IF64: =IF$22 * IF(AND(IE$5=1,IC$20=1), IP64, IN64) -> 0 | IG64: =IG$22 * IF(AND(IF$5=1,IC$20=1), IP64, IN64) -> 0 | IH64: =IH$22 * IF(AND(IG$5=1,IC$20=1), IP64, IN64) -> 0 | II64: =II$22 * IF(AND(IH$5=1,IC$20=1), IP64, IN64) -> 0 | IJ64: =IJ$22 * IF(AND(II$5=1,IC$20=1), IP64, IN64) -> 0 | IK64: =IK$22 * IF(AND(IJ$5=1,IC$20=1), IP64, IN64) -> 0 | IM64: None | IN64: =_xlfn.XLOOKUP(IM64,'KPI Impacts'!$B$2:$H$2,'KPI Impacts'!$B64:$H64) -> 0 | IO64: None | IP64: =_xlfn.XLOOKUP(IO64,'KPI Impacts'!$B$2:$H$2,'KPI Impacts'!$B64:$H64) -> 0 | IS64: =IS$22*JD64 -> 0 | IT64: =IT$22 * IF(AND(IS$5=1,IS$20=1), JF64, JD64) -> 0 | IU64: =IU$22 * IF(AND(IT$5=1,IS$20=1), JF64, JD64) -> 0 | IV64: =IV$22 * IF(AND(IU$5=1,IS$20=1), JF64, JD64) -> 0 | IW64: =IW$22 * IF(AND(IV$5=1,IS$20=1), JF64, JD64) -> 0 | IX64: =IX$22 * IF(AND(IW$5=1,IS$20=1), JF64, JD64) -> 0 | IY64: =IY$22 * IF(AND(IX$5=1,IS$20=1), JF64, JD64) -> 0 | IZ64: =IZ$22 * IF(AND(IY$5=1,IS$20=1), JF64, JD64) -> 0 | JA64: =JA$22 * IF(AND(IZ$5=1,IS$20=1), JF64, JD64) -> 0 | JC64: None | JD64: =_xlfn.XLOOKUP(JC64,'KPI Impacts'!$B$2:$H$2,'KPI Impacts'!$B64:$H64) -> 0 | JE64: None | JF64: =_xlfn.XLOOKUP(JE64,'KPI Impacts'!$B$2:$H$2,'KPI Impacts'!$B64:$H64) -> 0 | JI64: =JI$22*JT64 -> 0 | JJ64: =JJ$22 * IF(AND(JI$5=1,JI$20=1), JV64, JT64) -> 0 | JK64: =JK$22 * IF(AND(JJ$5=1,JI$20=1), JV64, JT64) -> 0 | JL64: =JL$22 * IF(AND(JK$5=1,JI$20=1), JV64, JT64) -> 0 | JM64: =JM$22 * IF(AND(JL$5=1,JI$20=1), JV64, JT64) -> 0 | JN64: =JN$22 * IF(AND(JM$5=1,JI$20=1), JV64, JT64) -> 0 | JO64: =JO$22 * IF(AND(JN$5=1,JI$20=1), JV64, JT64) -> 0 | JP64: =JP$22 * IF(AND(JO$5=1,JI$20=1), JV64, JT64) -> 0 | JQ64: =JQ$22 * IF(AND(JP$5=1,JI$20=1), JV64, JT64) -> 0 | JS64: None | JT64: =_xlfn.XLOOKUP(JS64,'KPI Impacts'!$B$2:$H$2,'KPI Impacts'!$B64:$H64) -> 0 | JU64: None | JV64: =_xlfn.XLOOKUP(JU64,'KPI Impacts'!$B$2:$H$2,'KPI Impacts'!$B64:$H64) -> 0 | JY64: =JY$22*KJ64 -> 0 | JZ64: =JZ$22 * IF(AND(JY$5=1,JY$20=1), KL64, KJ64) -> 0 | KA64: =KA$22 * IF(AND(JZ$5=1,JY$20=1), KL64, KJ64) -> 0 | KB64: =KB$22 * IF(AND(KA$5=1,JY$20=1), KL64, KJ64) -> 0 | KC64: =KC$22 * IF(AND(KB$5=1,JY$20=1), KL64, KJ64) -> 0 | KD64: =KD$22 * IF(AND(KC$5=1,JY$20=1), KL64, KJ64) -> 0 | KE64: =KE$22 * IF(AND(KD$5=1,JY$20=1), KL64, KJ64) -> 0 | KF64: =KF$22 * IF(AND(KE$5=1,JY$20=1), KL64, KJ64) -> 0 | KG64: =KG$22 * IF(AND(KF$5=1,JY$20=1), KL64, KJ64) -> 0 | KI64: None | KJ64: =_xlfn.XLOOKUP(KI64,'KPI Impacts'!$B$2:$H$2,'KPI Impacts'!$B64:$H64) -> 0 | KK64: None | KL64: =_xlfn.XLOOKUP(KK64,'KPI Impacts'!$B$2:$H$2,'KPI Impacts'!$B64:$H64) -> 0 | KO64: =KO$22*KZ64 -> 0 | KP64: =KP$22 * IF(AND(KO$5=1,KO$20=1), LB64, KZ64) -> 0 | KQ64: =KQ$22 * IF(AND(KP$5=1,KO$20=1), LB64, KZ64) -> 0 | KR64: =KR$22 * IF(AND(KQ$5=1,KO$20=1), LB64, KZ64) -> 0 | KS64: =KS$22 * IF(AND(KR$5=1,KO$20=1), LB64, KZ64) -> 0 | KT64: =KT$22 * IF(AND(KS$5=1,KO$20=1), LB64, KZ64) -> 0 | KU64: =KU$22 * IF(AND(KT$5=1,KO$20=1), LB64, KZ64) -> 0 | KV64: =KV$22 * IF(AND(KU$5=1,KO$20=1), LB64, KZ64) -> 0 | KW64: =KW$22 * IF(AND(KV$5=1,KO$20=1), LB64, KZ64) -> 0 | KY64: None | KZ64: =_xlfn.XLOOKUP(KY64,'KPI Impacts'!$B$2:$H$2,'KPI Impacts'!$B64:$H64) -> 0 | LA64: None | LB64: =_xlfn.XLOOKUP(LA64,'KPI Impacts'!$B$2:$H$2,'KPI Impacts'!$B64:$H64) -> 0 | LE64: =LE$22*LP64 -> 0 | LF64: =LF$22 * IF(AND(LE$5=1,LE$20=1), LR64, LP64) -> 0 | LG64: =LG$22 * IF(AND(LF$5=1,LE$20=1), LR64, LP64) -> 0 | LH64: =LH$22 * IF(AND(LG$5=1,LE$20=1), LR64, LP64) -> 0 | LI64: =LI$22 * IF(AND(LH$5=1,LE$20=1), LR64, LP64) -> 0 | LJ64: =LJ$22 * IF(AND(LI$5=1,LE$20=1), LR64, LP64) -> 0 | LK64: =LK$22 * IF(AND(LJ$5=1,LE$20=1), LR64, LP64) -> 0 | LL64: =LL$22 * IF(AND(LK$5=1,LE$20=1), LR64, LP64) -> 0 | LM64: =LM$22 * IF(AND(LL$5=1,LE$20=1), LR64, LP64) -> 0 | LO64: None | LP64: =_xlfn.XLOOKUP(LO64,'KPI Impacts'!$B$2:$H$2,'KPI Impacts'!$B64:$H64) -> 0 | LQ64: None | LR64: =_xlfn.XLOOKUP(LQ64,'KPI Impacts'!$B$2:$H$2,'KPI Impacts'!$B64:$H64) -> 0 | LU64: =LU$22*MF64 -> 0 | LV64: =LV$22 * IF(AND(LU$5=1,LU$20=1), MH64, MF64) -> 0 | LW64: =LW$22 * IF(AND(LV$5=1,LU$20=1), MH64, MF64) -> 0 | LX64: =LX$22 * IF(AND(LW$5=1,LU$20=1), MH64, MF64) -> 0 | LY64: =LY$22 * IF(AND(LX$5=1,LU$20=1), MH64, MF64) -> 0 | LZ64: =LZ$22 * IF(AND(LY$5=1,LU$20=1), MH64, MF64) -> 0 | MA64: =MA$22 * IF(AND(LZ$5=1,LU$20=1), MH64, MF64) -> 0 | MB64: =MB$22 * IF(AND(MA$5=1,LU$20=1), MH64, MF64) -> 0 | MC64: =MC$22 * IF(AND(MB$5=1,LU$20=1), MH64, MF64) -> 0 | ME64: None | MF64: =_xlfn.XLOOKUP(ME64,'KPI Impacts'!$B$2:$H$2,'KPI Impacts'!$B64:$H64) -> 0 | MG64: None | MH64: =_xlfn.XLOOKUP(MG64,'KPI Impacts'!$B$2:$H$2,'KPI Impacts'!$B64:$H64) -> 0 | MK64: =MK$22*MV64 -> 0 | ML64: =ML$22 * IF(AND(MK$5=1,MK$20=1), MX64, MV64) -> 0 | MM64: =MM$22 * IF(AND(ML$5=1,MK$20=1), MX64, MV64) -> 0 | MN64: =MN$22 * IF(AND(MM$5=1,MK$20=1), MX64, MV64) -> 0 | MO64: =MO$22 * IF(AND(MN$5=1,MK$20=1), MX64, MV64) -> 0 | MP64: =MP$22 * IF(AND(MO$5=1,MK$20=1), MX64, MV64) -> 0 | MQ64: =MQ$22 * IF(AND(MP$5=1,MK$20=1), MX64, MV64) -> 0 | MR64: =MR$22 * IF(AND(MQ$5=1,MK$20=1), MX64, MV64) -> 0 | MS64: =MS$22 * IF(AND(MR$5=1,MK$20=1), MX64, MV64) -> 0 | MU64: None | MV64: =_xlfn.XLOOKUP(MU64,'KPI Impacts'!$B$2:$H$2,'KPI Impacts'!$B64:$H64) -> 0 | MW64: None | MX64: =_xlfn.XLOOKUP(MW64,'KPI Impacts'!$B$2:$H$2,'KPI Impacts'!$B64:$H64) -> 0 | NA64: =NA$22*NL64 -> 0 | NB64: =NB$22 * IF(AND(NA$5=1,NA$20=1), NN64, NL64) -> 0 | NC64: =NC$22 * IF(AND(NB$5=1,NA$20=1), NN64, NL64) -> 0 | ND64: =ND$22 * IF(AND(NC$5=1,NA$20=1), NN64, NL64) -> 0 | NE64: =NE$22 * IF(AND(ND$5=1,NA$20=1), NN64, NL64) -> 0 | NF64: =NF$22 * IF(AND(NE$5=1,NA$20=1), NN64, NL64) -> 0 | NG64: =NG$22 * IF(AND(NF$5=1,NA$20=1), NN64, NL64) -> 0 | NH64: =NH$22 * IF(AND(NG$5=1,NA$20=1), NN64, NL64) -> 0 | NI64: =NI$22 * IF(AND(NH$5=1,NA$20=1), NN64, NL64) -> 0 | NK64: None | NL64: =_xlfn.XLOOKUP(NK64,'KPI Impacts'!$B$2:$H$2,'KPI Impacts'!$B64:$H64) -> 0 | NM64: None | NN64: =_xlfn.XLOOKUP(NM64,'KPI Impacts'!$B$2:$H$2,'KPI Impacts'!$B64:$H64) -> 0 | NQ64: =NQ$22*OB64 -> 0 | NR64: =NR$22 * IF(AND(NQ$5=1,NQ$20=1), OD64, OB64) -> 0 | NS64: =NS$22 * IF(AND(NR$5=1,NQ$20=1), OD64, OB64) -> 0 | NT64: =NT$22 * IF(AND(NS$5=1,NQ$20=1), OD64, OB64) -> 0 | NU64: =NU$22 * IF(AND(NT$5=1,NQ$20=1), OD64, OB64) -> 0 | NV64: =NV$22 * IF(AND(NU$5=1,NQ$20=1), OD64, OB64) -> 0 | NW64: =NW$22 * IF(AND(NV$5=1,NQ$20=1), OD64, OB64) -> 0 | NX64: =NX$22 * IF(AND(NW$5=1,NQ$20=1), OD64, OB64) -> 0 | NY64: =NY$22 * IF(AND(NX$5=1,NQ$20=1), OD64, OB64) -> 0 | OA64: None | OB64: =_xlfn.XLOOKUP(OA64,'KPI Impacts'!$B$2:$H$2,'KPI Impacts'!$B64:$H64) -> 0 | OC64: None | OD64: =_xlfn.XLOOKUP(OC64,'KPI Impacts'!$B$2:$H$2,'KPI Impacts'!$B64:$H64) -> 0 | OG64: =OG$22*OR64 -> 0 | OH64: =OH$22 * IF(AND(OG$5=1,OG$20=1), OT64, OR64) -> 0 | OI64: =OI$22 * IF(AND(OH$5=1,OG$20=1), OT64, OR64) -> 0 | OJ64: =OJ$22 * IF(AND(OI$5=1,OG$20=1), OT64, OR64) -> 0 | OK64: =OK$22 * IF(AND(OJ$5=1,OG$20=1), OT64, OR64) -> 0 | OL64: =OL$22 * IF(AND(OK$5=1,OG$20=1), OT64, OR64) -> 0 | OM64: =OM$22 * IF(AND(OL$5=1,OG$20=1), OT64, OR64) -> 0 | ON64: =ON$22 * IF(AND(OM$5=1,OG$20=1), OT64, OR64) -> 0 | OO64: =OO$22 * IF(AND(ON$5=1,OG$20=1), OT64, OR64) -> 0 | OQ64: None | OR64: =_xlfn.XLOOKUP(OQ64,'KPI Impacts'!$B$2:$H$2,'KPI Impacts'!$B64:$H64) -> 0 | OS64: None | OT64: =_xlfn.XLOOKUP(OS64,'KPI Impacts'!$B$2:$H$2,'KPI Impacts'!$B64:$H64) -> 0
